Workbook

Sheet Diagrama de clases

Sheet Clases
A1: Clase | B1: Estereotipo | C1: Descripción
A2: UnidadMedida | B2: class | C2: Representa las unidades utilizadas por la pizzería para cuantificar los ingredientes, productos y demás elementos que requieren control de cantidades.
A3: TipoProducto | B3: class | C3: Representa la clasificación de cada producto que ofrece la pizzería, indicando si corresponde a una pizza, una bebida o una adición.
A4: ClaseMovimiento | B4: class | C4: Representa la clase de cada movimiento de inventario, indicando si corresponde a una entrada o a una salida de existencias.
A5: CategoriaOrigen | B5: class | C5: Representa la categoría de origen de la operación que genera un movimiento de inventario: una compra, una venta o un cambio de producto.
A6: TipoMovimiento | B6: class | C6: Representa el código de una operación concreta que mueve el inventario (cada detalle de compra, consumo de venta o cambio tiene el suyo); pertenece a una categoría de origen y lo comparten la operación y los movimientos que genera.
A7: Tamano | B7: class | C7: Representa las distintas presentaciones de tamaño en las que la pizzería puede ofrecer un producto; los productos que no son pizza usan "No aplica".
A8: Proveedor | B8: class | C8: Representa a las personas o empresas que suministran a la pizzería los insumos y productos necesarios para su operación.
A9: ProductoInterno | B9: class | C9: Representa cada insumo o producto que la pizzería compra y almacena en su inventario, ya sea que se consuma dentro de una receta o se venda directamente al cliente.
A10: Producto | B10: class | C10: Representa los artículos que la pizzería comercializa y que pueden ser vendidos al cliente, sirviendo como referencia para identificar y gestionar su oferta comercial.
A11: DetalleReceta | B11: class | C11: Representa cada uno de los ingredientes necesarios para elaborar una receta, indicando la cantidad requerida y la unidad de medida utilizada.
A12: Inventario | B12: class | C12: Representa las existencias disponibles de los insumos y productos que la pizzería necesita para operar y atender sus ventas.
... A23: Usuario | B23: class | C23: Representa a la persona que puede ingresar a la aplicación; solo los usuarios activos con rol Administrador pueden iniciar sesión.

Sheet Valores
A1: Estereotipo | B1: Relación | C1: Tipo relación | D1: Modificador acceso clase top level | E1: Tipo estructura | F1: Modificador acceso clase top level | G1: Tipo de dato | H1: Tipo acceso | I1: Tipo constructor | J1: Tipo parámetro | K1: Tipo método accesor | L1: Tipo de dato retorno método
A2: class | B2: Necesita de | C2: Asociación | D2: public | E2: final | F2: private | G2: byte/Byte | H2: static | I2: Defecto | J2: Por valor | K2: getter | L2: void
A3: abstract class | B3: Es usada por | C3: Agregación | D3: default | E3: no final | F3: protected | G3: short/Short | H3: no static | I3: Parametrizado | J3: Por referencia | K3: setter | L3: byte/Byte
A4: interface | C4: Composición | F4: default | G4: int/Integer | L4: short/Short
A5: enum | C5: Dependencia | F5: public | G5: long/Long | L5: int/Integer
A6: record | C6: Herencia | G6: float/Float | L6: long/Long
C7: Realización | G7: double/Double | L7: float/Float
G8: char/Character | L8: double/Double
G9: boolean/Boolean | L9: char/Character
G10: String | L10: boolean/Boolean
G11: Date | L11: String
G12: Otro | L12: Date
L13: Otro

Sheet UnidadMedida
A1: <-Volver al inicio
A2: =Clases!$A$1 -> Clase | B2: =Clases!A2 -> UnidadMedida
A3: =Clases!$B$1 -> Estereotipo | B3: =Clases!B2 -> class
A4: =Clases!$C$1 -> Descripción | B4: =Clases!C2 -> Representa las unidades utilizadas por la pizzería para cuantificar los ingredientes, productos y demás elementos que requieren control de cantidades.
A5: Modificador acceso: | B5: public
A6: Tipo clase: | B6: no final
A7: Relaciones
A8: Relación | B8: Tipo relación | E8: Estructura
A9: Es usada por | B9: Asociación | E9: ProductoInterno
A10: Es usada por | B10: Asociación | E10: DetalleReceta
A11: Es usada por | B11: Asociación | E11: Inventario
A12: Es usada por | B12: Asociación | E12: Lote
A13: Es usada por | B13: Asociación | E13: DetalleCompra
A14: Es usada por | B14: Asociación | E14: ConsumoVenta
A15: Es usada por | B15: Asociación | E15: Cambio
A17: Atributos
A18: Modificador de acceso | B18: Nombre | C18: Tipo de dato | E18: Tipo modificación atributo | F18: Tipo acceso atributo | G18: Valor por defecto | J18: Descripción atributo
C19: Tipo de dato | D19: ¿Cuál?
A20: private | B20: id | C20: Otro | D20: UUID | E20: no final | F20: no static | G20: 00000000-0000-0000-0000-000000000000 | J20: Identificador único de la unidad de medida.
A21: private | B21: unidadMedida | C21: String | E21: no final | F21: no static | G21: "" (cadena vacía) | J21: Símbolo o nombre corto de la unidad de medida (por ejemplo: g, kg, ml, l, und).
A22: private | B22: tipoMedida | C22: String | E22: no final | F22: no static | G22: "" (cadena vacía) | J22: Tipo de magnitud al que corresponde la unidad (peso, volumen o unidades).
A24: Constructores
A25: Modificador de acceso | B25: Nombre | C25: Tipo constructor | D25: Descripción | E25: Parámetros | M25: Excepciones
E26: Nombre | F26: Tipo de dato | G26: ¿Cuál? | H26: Tipo parámetro | I26: Tipo modificación atributo | J26: Descripción
A27: private | B27: =B2 -> UnidadMedida | C27: Parametrizado | D27: Constructor privado: crea la instancia de UnidadMedida copiando los valores ya saneados que reunió el Builder. Solo se invoca desde Builder.build(). | E27: builder | F27: Otro | G27: Builder | H27: Por valor | I27: no final | J27: Builder con los valores de los atributos de la clase.
A29: Métodos accesores
A30: Modificador de acceso | B30: Nombre | C30: Tipo método accesor | D30: Tipo modificación método | E30: Descripción | F30: Parámetros | L30: Tipo dato de retorno | N30: Excepciones
F31: Nombre | G31: Tipo de dato | H31: ¿Cuál? | I31: Tipo parámetro | J31: Tipo modificación atributo | K31: Descripción | L31: Tipo de dato | M31: ¿Cuál?
A32: public | B32: getId | C32: getter | D32: no final | E32: Método encargado de obtener el valor del atributo id. | L32: Otro | M32: UUID
A33: public | B33: getUnidadMedida | C33: getter | D33: no final | E33: Método encargado de obtener el valor del atributo unidadMedida. | L33: String
A34: public | B34: getTipoMedida | C34: getter | D34: no final | E34: Método encargado de obtener el valor del atributo tipoMedida. | L34: String
A36: Métodos
A37: Modificador de acceso | B37: Nombre | C37: Tipo acceso método | D37: Tipo modificación método | E37: Descripción | F37: Parámetros | L37: Tipo dato de retorno | N37: Excepciones
F38: Nombre | G38: Tipo de dato | H38: ¿Cuál? | I38: Tipo parámetro | J38: Tipo modificación atributo | K38: Descripción | L38: Tipo de dato | M38: ¿Cuál?
A39: public | B39: consultarUnidadesDeMedidaDisponibles | C39: static | D39: final | E39: Permite consultar las unidades de medida precargadas en el sistema para seleccionar la unidad adecuada al registrar cantidades de productos, ingredientes, compras, recetas o movimientos de inventario. | F39: unidadMedida | G39: Otro | H39: UnidadMedida | I39: Por valor | J39: no final | K39: Criterios necesarios para realizar la consulta de las unidades de medida disponibles. | L39: Otro | M39: List<UnidadMedida> | N39: No existen unidades de medida registradas en el catálogo. No existe una unidad de medida asociada al identificador indicado.
A40: public | B40: eliminarUnidadDeMedida | C40: no static | D40: no final | E40: Permite eliminar una unidad de medida que no esté siendo utilizada por ningún otro registro de la pizzería. | F40: id | G40: Otro | H40: UUID | I40: Por valor | J40: no final | K40: Identificador de la unidad de medida que se desea eliminar. | L40: void | N40: La unidad de medida que se desea eliminar no existe. La unidad de medida está siendo utilizada por un producto interno, un lote o un registro de inventario. La unidad de medida está siendo utilizada por un detalle de receta, un detalle de compra, un cambio o un consumo de venta.
A42: Builder (clase interna public static)
A43: Modificador de acceso | B43: Nombre | C43: Tipo acceso método | D43: Tipo modificación método | E43: Descripción | F43: Parámetros | L43: Tipo dato de retorno | N43: Excepciones
F44: Nombre | G44: Tipo de dato | H44: ¿Cuál? | I44: Tipo parámetro | J44: Tipo modificación atributo | K44: Descripción | L44: Tipo de dato | M44: ¿Cuál?
A45: public | B45: Builder | C45: no static | D45: no final | E45: Constructor del Builder: asigna a cada atributo su valor por defecto.
A46: public | B46: id | C46: no static | D46: no final | E46: Asigna el identificador recibido; si es nulo, asigna el identificador por defecto (00000000-0000-0000-0000-000000000000). | F46: id | G46: Otro | H46: UUID | I46: Por valor | J46: no final | K46: Valor que se desea asignar al atributo id. | L46: Otro | M46: Builder
A47: public | B47: unidadMedida | C47: no static | D47: no final | E47: Asigna el texto recibido sin espacios en blanco al inicio y al final; si es nulo, asigna una cadena vacía. | F47: unidadMedida | G47: String | I47: Por valor | J47: no final | K47: Valor que se desea asignar al atributo unidadMedida. | L47: Otro | M47: Builder
A48: public | B48: tipoMedida | C48: no static | D48: no final | E48: Asigna el texto recibido sin espacios en blanco al inicio y al final, con la primera letra en mayúscula y el resto en minúscula; si es nulo o vacío, asigna una cadena vacía. | F48: tipoMedida | G48: String | I48: Por valor | J48: no final | K48: Valor que se desea asignar al atributo tipoMedida. | L48: Otro | M48: Builder
A49: public | B49: build | C49: no static | D49: no final | E49: Crea la instancia de UnidadMedida con los valores reunidos en el Builder, usando su constructor privado. | L49: Otro | M49: UnidadMedida

Sheet TipoProducto
A1: <-Volver al inicio
A2: =Clases!$A$1 -> Clase | B2: =Clases!A3 -> TipoProducto
A3: =Clases!$B$1 -> Estereotipo | B3: =Clases!B3 -> class
A4: =Clases!$C$1 -> Descripción | B4: =Clases!C3 -> Representa la clasificación de cada producto que ofrece la pizzería, indicando si corresponde a una pizza, una bebida o una adición.
A5: Modificador acceso: | B5: public
A6: Tipo clase: | B6: no final
A7: Relaciones
A8: Relación | B8: Tipo relación | E8: Estructura
A9: Es usada por | B9: Asociación | E9: Producto
A11: Atributos
A12: Modificador de acceso | B12: Nombre | C12: Tipo de dato | E12: Tipo modificación atributo | F12: Tipo acceso atributo | G12: Valor por defecto | J12: Descripción atributo
C13: Tipo de dato | D13: ¿Cuál?
A14: private | B14: id | C14: Otro | D14: UUID | E14: no final | F14: no static | G14: 00000000-0000-0000-0000-000000000000 | J14: Identificador único del tipo de producto.
A15: private | B15: nombre | C15: String | E15: no final | F15: no static | G15: "" (cadena vacía) | J15: Nombre de la clasificación del producto (Pizza, Bebida o Adición).
A17: Constructores
A18: Modificador de acceso | B18: Nombre | C18: Tipo constructor | D18: Descripción | E18: Parámetros | M18: Excepciones
E19: Nombre | F19: Tipo de dato | G19: ¿Cuál? | H19: Tipo parámetro | I19: Tipo modificación atributo | J19: Descripción
A20: private | B20: =B2 -> TipoProducto | C20: Parametrizado | D20: Constructor privado: crea la instancia de TipoProducto copiando los valores ya saneados que reunió el Builder. Solo se invoca desde Builder.build(). | E20: builder | F20: Otro | G20: Builder | H20: Por valor | I20: no final | J20: Builder con los valores de los atributos de la clase.
A22: Métodos accesores
A23: Modificador de acceso | B23: Nombre | C23: Tipo método accesor | D23: Tipo modificación método | E23: Descripción | F23: Parámetros | L23: Tipo dato de retorno | N23: Excepciones
F24: Nombre | G24: Tipo de dato | H24: ¿Cuál? | I24: Tipo parámetro | J24: Tipo modificación atributo | K24: Descripción | L24: Tipo de dato | M24: ¿Cuál?
A25: public | B25: getId | C25: getter | D25: no final | E25: Método encargado de obtener el valor del atributo id. | L25: Otro | M25: UUID
A26: public | B26: getNombre | C26: getter | D26: no final | E26: Método encargado de obtener el valor del atributo nombre. | L26: String
A28: Métodos
A29: Modificador de acceso | B29: Nombre | C29: Tipo acceso método | D29: Tipo modificación método | E29: Descripción | F29: Parámetros | L29: Tipo dato de retorno | N29: Excepciones
F30: Nombre | G30: Tipo de dato | H30: ¿Cuál? | I30: Tipo parámetro | J30: Tipo modificación atributo | K30: Descripción | L30: Tipo de dato | M30: ¿Cuál?
A31: public | B31: consultarTiposDeProductoDisponibles | C31: static | D31: final | E31: Permite consultar los tipos de producto disponibles en el sistema para clasificar un producto. | L31: Otro | M31: List<TipoProducto> | N31: No existen tipos de producto disponibles.
A32: public | B32: registrarTipoDeProducto | C32: no static | D32: no final | E32: Permite agregar un nuevo tipo de producto al catálogo, para cuando la pizzería empiece a manejar una categoría de producto que no exista todavía. | F32: tipoProducto | G32: Otro | H32: TipoProducto | I32: Por valor | J32: no final | K32: Nombre del nuevo tipo de producto que se desea registrar. | L32: Otro | M32: TipoProducto | N32: El dato ingresado no es válido según el tipo de dato, la obligatoriedad o el formato esperado. Ya existe otro tipo de producto registrado con el mismo Nombre.
A33: public | B33: actualizarTipoDeProducto | C33: no static | D33: no final | E33: Permite modificar el nombre de un tipo de producto que ya existe. | F33: tipoProducto | G33: Otro | H33: TipoProducto | I33: Por valor | J33: no final | K33: Identificador del tipo de producto que se desea modificar, junto con el nuevo nombre. | L33: Otro | M33: TipoProducto | N33: El tipo de producto no existe en el sistema. El nuevo dato ingresado no es válido según el tipo de dato, la obligatoriedad o el formato esperado.
A34: public | B34: eliminarTipoDeProducto | C34: no static | D34: no final | E34: Permite eliminar un tipo de producto que no tenga productos asociados que deban conservarse. | F34: id | G34: Otro | H34: UUID | I34: Por valor | J34: no final | K34: Identificador del tipo de producto que se desea eliminar. | L34: void | N34: El tipo de producto tiene productos asociados que deben conservarse. El tipo de producto no existe en el sistema.
A36: Builder (clase interna public static)
A37: Modificador de acceso | B37: Nombre | C37: Tipo acceso método | D37: Tipo modificación método | E37: Descripción | F37: Parámetros | L37: Tipo dato de retorno | N37: Excepciones
F38: Nombre | G38: Tipo de dato | H38: ¿Cuál? | I38: Tipo parámetro | J38: Tipo modificación atributo | K38: Descripción | L38: Tipo de dato | M38: ¿Cuál?
A39: public | B39: Builder | C39: no static | D39: no final | E39: Constructor del Builder: asigna a cada atributo su valor por defecto.
A40: public | B40: id | C40: no static | D40: no final | E40: Asigna el identificador recibido; si es nulo, asigna el identificador por defecto (00000000-0000-0000-0000-000000000000). | F40: id | G40: Otro | H40: UUID | I40: Por valor | J40: no final | K40: Valor que se desea asignar al atributo id. | L40: Otro | M40: Builder
A41: public | B41: nombre | C41: no static | D41: no final | E41: Asigna el texto recibido sin espacios en blanco al inicio y al final, con la primera letra en mayúscula y el resto en minúscula; si es nulo o vacío, asigna una cadena vacía. | F41: nombre | G41: String | I41: Por valor | J41: no final | K41: Valor que se desea asignar al atributo nombre. | L41: Otro | M41: Builder
A42: public | B42: build | C42: no static | D42: no final | E42: Crea la instancia de TipoProducto con los valores reunidos en el Builder, usando su constructor privado. | L42: Otro | M42: TipoProducto

Sheet ClaseMovimiento
A1: <-Volver al inicio
A2: =Clases!$A$1 -> Clase | B2: =Clases!A4 -> ClaseMovimiento
A3: =Clases!$B$1 -> Estereotipo | B3: =Clases!B4 -> class
A4: =Clases!$C$1 -> Descripción | B4: =Clases!C4 -> Representa la clase de cada movimiento de inventario, indicando si corresponde a una entrada o a una salida de existencias.
A5: Modificador acceso: | B5: public
A6: Tipo clase: | B6: no final
A7: Relaciones
A8: Relación | B8: Tipo relación | E8: Estructura
A9: Es usada por | B9: Asociación | E9: MovimientoInventario
A11: Atributos
A12: Modificador de acceso | B12: Nombre | C12: Tipo de dato | E12: Tipo modificación atributo | F12: Tipo acceso atributo | G12: Valor por defecto | J12: Descripción atributo
C13: Tipo de dato | D13: ¿Cuál?
A14: private | B14: id | C14: Otro | D14: UUID | E14: no final | F14: no static | G14: 00000000-0000-0000-0000-000000000000 | J14: Identificador único de la clase de movimiento.
A15: private | B15: nombre | C15: String | E15: no final | F15: no static | G15: "" (cadena vacía) | J15: Nombre de la clase de movimiento (Entrada o Salida): indica si el movimiento suma o resta inventario.
A17: Constructores
A18: Modificador de acceso | B18: Nombre | C18: Tipo constructor | D18: Descripción | E18: Parámetros | M18: Excepciones
E19: Nombre | F19: Tipo de dato | G19: ¿Cuál? | H19: Tipo parámetro | I19: Tipo modificación atributo | J19: Descripción
A20: private | B20: =B2 -> ClaseMovimiento | C20: Parametrizado | D20: Constructor privado: crea la instancia de ClaseMovimiento copiando los valores ya saneados que reunió el Builder. Solo se invoca desde Builder.build(). | E20: builder | F20: Otro | G20: Builder | H20: Por valor | I20: no final | J20: Builder con los valores de los atributos de la clase.
A22: Métodos accesores
A23: Modificador de acceso | B23: Nombre | C23: Tipo método accesor | D23: Tipo modificación método | E23: Descripción | F23: Parámetros | L23: Tipo dato de retorno | N23: Excepciones
F24: Nombre | G24: Tipo de dato | H24: ¿Cuál? | I24: Tipo parámetro | J24: Tipo modificación atributo | K24: Descripción | L24: Tipo de dato | M24: ¿Cuál?
A25: public | B25: getId | C25: getter | D25: no final | E25: Método encargado de obtener el valor del atributo id. | L25: Otro | M25: UUID
A26: public | B26: getNombre | C26: getter | D26: no final | E26: Método encargado de obtener el valor del atributo nombre. | L26: String
A28: Métodos
A29: Modificador de acceso | B29: Nombre | C29: Tipo acceso método | D29: Tipo modificación método | E29: Descripción | F29: Parámetros | L29: Tipo dato de retorno | N29: Excepciones
F30: Nombre | G30: Tipo de dato | H30: ¿Cuál? | I30: Tipo parámetro | J30: Tipo modificación atributo | K30: Descripción | L30: Tipo de dato | M30: ¿Cuál?
A31: public | B31: consultarClasesDeMovimientoDisponibles | C31: static | D31: final | E31: Permite consultar las clases de movimiento (Entrada o Salida) disponibles para clasificar un movimiento de inventario. | L31: Otro | M31: List<ClaseMovimiento> | N31: No existen clases de movimiento disponibles.
A33: Builder (clase interna public static)
A34: Modificador de acceso | B34: Nombre | C34: Tipo acceso método | D34: Tipo modificación método | E34: Descripción | F34: Parámetros | L34: Tipo dato de retorno | N34: Excepciones
F35: Nombre | G35: Tipo de dato | H35: ¿Cuál? | I35: Tipo parámetro | J35: Tipo modificación atributo | K35: Descripción | L35: Tipo de dato | M35: ¿Cuál?
A36: public | B36: Builder | C36: no static | D36: no final | E36: Constructor del Builder: asigna a cada atributo su valor por defecto.
A37: public | B37: id | C37: no static | D37: no final | E37: Asigna el identificador recibido; si es nulo, asigna el identificador por defecto (00000000-0000-0000-0000-000000000000). | F37: id | G37: Otro | H37: UUID | I37: Por valor | J37: no final | K37: Valor que se desea asignar al atributo id. | L37: Otro | M37: Builder
A38: public | B38: nombre | C38: no static | D38: no final | E38: Asigna el texto recibido sin espacios en blanco al inicio y al final, con la primera letra en mayúscula y el resto en minúscula; si es nulo o vacío, asigna una cadena vacía. | F38: nombre | G38: String | I38: Por valor | J38: no final | K38: Valor que se desea asignar al atributo nombre. | L38: Otro | M38: Builder
A39: public | B39: build | C39: no static | D39: no final | E39: Crea la instancia de ClaseMovimiento con los valores reunidos en el Builder, usando su constructor privado. | L39: Otro | M39: ClaseMovimiento

Sheet CategoriaOrigen
A1: <-Volver al inicio
A2: =Clases!$A$1 -> Clase | B2: =Clases!A5 -> CategoriaOrigen
A3: =Clases!$B$1 -> Estereotipo | B3: =Clases!B5 -> class
A4: =Clases!$C$1 -> Descripción | B4: =Clases!C5 -> Representa la categoría de origen de la operación que genera un movimiento de inventario: una compra, una venta o un cambio de producto.
A5: Modificador acceso: | B5: public
A6: Tipo clase: | B6: no final
A7: Relaciones
A8: Relación | B8: Tipo relación | E8: Estructura
A9: Es usada por | B9: Asociación | E9: TipoMovimiento
A11: Atributos
A12: Modificador de acceso | B12: Nombre | C12: Tipo de dato | E12: Tipo modificación atributo | F12: Tipo acceso atributo | G12: Valor por defecto | J12: Descripción atributo
C13: Tipo de dato | D13: ¿Cuál?
A14: private | B14: id | C14: Otro | D14: UUID | E14: no final | F14: no static | G14: 00000000-0000-0000-0000-000000000000 | J14: Identificador único de la categoría de origen.
A15: private | B15: nombre | C15: String | E15: no final | F15: no static | G15: "" (cadena vacía) | J15: Nombre de la categoría de origen de la operación que mueve el inventario (Compra, Venta o Cambio).
A17: Constructores
A18: Modificador de acceso | B18: Nombre | C18: Tipo constructor | D18: Descripción | E18: Parámetros | M18: Excepciones
E19: Nombre | F19: Tipo de dato | G19: ¿Cuál? | H19: Tipo parámetro | I19: Tipo modificación atributo | J19: Descripción
A20: private | B20: =B2 -> CategoriaOrigen | C20: Parametrizado | D20: Constructor privado: crea la instancia de CategoriaOrigen copiando los valores ya saneados que reunió el Builder. Solo se invoca desde Builder.build(). | E20: builder | F20: Otro | G20: Builder | H20: Por valor | I20: no final | J20: Builder con los valores de los atributos de la clase.
A22: Métodos accesores
A23: Modificador de acceso | B23: Nombre | C23: Tipo método accesor | D23: Tipo modificación método | E23: Descripción | F23: Parámetros | L23: Tipo dato de retorno | N23: Excepciones
F24: Nombre | G24: Tipo de dato | H24: ¿Cuál? | I24: Tipo parámetro | J24: Tipo modificación atributo | K24: Descripción | L24: Tipo de dato | M24: ¿Cuál?
A25: public | B25: getId | C25: getter | D25: no final | E25: Método encargado de obtener el valor del atributo id. | L25: Otro | M25: UUID
A26: public | B26: getNombre | C26: getter | D26: no final | E26: Método encargado de obtener el valor del atributo nombre. | L26: String
A28: Métodos
A29: Modificador de acceso | B29: Nombre | C29: Tipo acceso método | D29: Tipo modificación método | E29: Descripción | F29: Parámetros | L29: Tipo dato de retorno | N29: Excepciones
F30: Nombre | G30: Tipo de dato | H30: ¿Cuál? | I30: Tipo parámetro | J30: Tipo modificación atributo | K30: Descripción | L30: Tipo de dato | M30: ¿Cuál?
A31: public | B31: consultarCategoriasDeOrigenDisponibles | C31: static | D31: final | E31: Permite consultar las categorías de origen (Compra, Venta o Cambio) que indican que operación generó un movimiento de inventario. | L31: Otro | M31: List<CategoriaOrigen> | N31: No existen categorías de origen disponibles.
A33: Builder (clase interna public static)
A34: Modificador de acceso | B34: Nombre | C34: Tipo acceso método | D34: Tipo modificación método | E34: Descripción | F34: Parámetros | L34: Tipo dato de retorno | N34: Excepciones
F35: Nombre | G35: Tipo de dato | H35: ¿Cuál? | I35: Tipo parámetro | J35: Tipo modificación atributo | K35: Descripción | L35: Tipo de dato | M35: ¿Cuál?
A36: public | B36: Builder | C36: no static | D36: no final | E36: Constructor del Builder: asigna a cada atributo su valor por defecto.
A37: public | B37: id | C37: no static | D37: no final | E37: Asigna el identificador recibido; si es nulo, asigna el identificador por defecto (00000000-0000-0000-0000-000000000000). | F37: id | G37: Otro | H37: UUID | I37: Por valor | J37: no final | K37: Valor que se desea asignar al atributo id. | L37: Otro | M37: Builder
A38: public | B38: nombre | C38: no static | D38: no final | E38: Asigna el texto recibido sin espacios en blanco al inicio y al final, con la primera letra en mayúscula y el resto en minúscula; si es nulo o vacío, asigna una cadena vacía. | F38: nombre | G38: String | I38: Por valor | J38: no final | K38: Valor que se desea asignar al atributo nombre. | L38: Otro | M38: Builder
A39: public | B39: build | C39: no static | D39: no final | E39: Crea la instancia de CategoriaOrigen con los valores reunidos en el Builder, usando su constructor privado. | L39: Otro | M39: CategoriaOrigen

Sheet TipoMovimiento
A1: <-Volver al inicio
A2: =Clases!$A$1 -> Clase | B2: =Clases!A6 -> TipoMovimiento
A3: =Clases!$B$1 -> Estereotipo | B3: =Clases!B6 -> class
A4: =Clases!$C$1 -> Descripción | B4: =Clases!C6 -> Representa el código de una operación concreta que mueve el inventario (cada detalle de compra, consumo de venta o cambio tiene el suyo); pertenece a una categoría de origen y lo comparten la operación y los movimientos que genera.
A5: Modificador acceso: | B5: public
A6: Tipo clase: | B6: no final
A7: Relaciones
A8: Relación | B8: Tipo relación | E8: Estructura
A9: Necesita de | B9: Asociación | E9: CategoriaOrigen
A10: Es usada por | B10: Asociación | E10: DetalleCompra
A11: Es usada por | B11: Asociación | E11: ConsumoVenta
A12: Es usada por | B12: Asociación | E12: Cambio
A13: Es usada por | B13: Asociación | E13: MovimientoInventario
A15: Atributos
A16: Modificador de acceso | B16: Nombre | C16: Tipo de dato | E16: Tipo modificación atributo | F16: Tipo acceso atributo | G16: Valor por defecto | J16: Descripción atributo
C17: Tipo de dato | D17: ¿Cuál?
A18: private | B18: id | C18: Otro | D18: UUID | E18: no final | F18: no static | G18: 00000000-0000-0000-0000-000000000000 | J18: Código único de la operación concreta que genera movimientos de inventario (cada detalle de compra, consumo de venta o cambio tiene el suyo).
A19: private | B19: categoriaOrigen | C19: Otro | D19: CategoriaOrigen | E19: no final | F19: no static | G19: Instancia por defecto de CategoriaOrigen | J19: Categoría de origen a la que pertenece la operación (Compra, Venta o Cambio).
A21: Constructores
A22: Modificador de acceso | B22: Nombre | C22: Tipo constructor | D22: Descripción | E22: Parámetros | M22: Excepciones
E23: Nombre | F23: Tipo de dato | G23: ¿Cuál? | H23: Tipo parámetro | I23: Tipo modificación atributo | J23: Descripción
A24: private | B24: =B2 -> TipoMovimiento | C24: Parametrizado | D24: Constructor privado: crea la instancia de TipoMovimiento copiando los valores ya saneados que reunió el Builder. Solo se invoca desde Builder.build(). | E24: builder | F24: Otro | G24: Builder | H24: Por valor | I24: no final | J24: Builder con los valores de los atributos de la clase.
A26: Métodos accesores
A27: Modificador de acceso | B27: Nombre | C27: Tipo método accesor | D27: Tipo modificación método | E27: Descripción | F27: Parámetros | L27: Tipo dato de retorno | N27: Excepciones
F28: Nombre | G28: Tipo de dato | H28: ¿Cuál? | I28: Tipo parámetro | J28: Tipo modificación atributo | K28: Descripción | L28: Tipo de dato | M28: ¿Cuál?
A29: public | B29: getId | C29: getter | D29: no final | E29: Método encargado de obtener el valor del atributo id. | L29: Otro | M29: UUID
A30: public | B30: getCategoriaOrigen | C30: getter | D30: no final | E30: Método encargado de obtener el valor del atributo categoriaOrigen. | L30: Otro | M30: CategoriaOrigen
A32: Métodos
A33: Modificador de acceso | B33: Nombre | C33: Tipo acceso método | D33: Tipo modificación método | E33: Descripción | F33: Parámetros | L33: Tipo dato de retorno | N33: Excepciones
F34: Nombre | G34: Tipo de dato | H34: ¿Cuál? | I34: Tipo parámetro | J34: Tipo modificación atributo | K34: Descripción | L34: Tipo de dato | M34: ¿Cuál?
A35: public | B35: generarTipoDeMovimiento | C35: no static | D35: no final | E35: Genera un nuevo código de operación con su categoría de origen cada vez que se registra un detalle de compra, un consumo de venta o un cambio. | F35: categoriaOrigen | G35: Otro | H35: CategoriaOrigen | I35: Por valor | J35: no final | K35: Categoría de origen de la operación que genera el código. | L35: Otro | M35: TipoMovimiento | N35: La categoría de origen no existe. El identificador generado ya está siendo utilizado.
A36: public | B36: consultarTipoDeMovimiento | C36: static | D36: final | E36: Permite consultar un tipo de movimiento para conocer la categoría de origen de la operación. | F36: id | G36: Otro | H36: UUID | I36: Por valor | J36: no final | K36: Identificador del tipo de movimiento que se desea consultar. | L36: Otro | M36: TipoMovimiento | N36: No existe un tipo de movimiento con el identificador indicado.
A38: Builder (clase interna public static)
A39: Modificador de acceso | B39: Nombre | C39: Tipo acceso método | D39: Tipo modificación método | E39: Descripción | F39: Parámetros | L39: Tipo dato de retorno | N39: Excepciones
F40: Nombre | G40: Tipo de dato | H40: ¿Cuál? | I40: Tipo parámetro | J40: Tipo modificación atributo | K40: Descripción | L40: Tipo de dato | M40: ¿Cuál?
A41: public | B41: Builder | C41: no static | D41: no final | E41: Constructor del Builder: asigna a cada atributo su valor por defecto.
A42: public | B42: id | C42: no static | D42: no final | E42: Asigna el identificador recibido; si es nulo, asigna el identificador por defecto (00000000-0000-0000-0000-000000000000). | F42: id | G42: Otro | H42: UUID | I42: Por valor | J42: no final | K42: Valor que se desea asignar al atributo id. | L42: Otro | M42: Builder
A43: public | B43: categoriaOrigen | C43: no static | D43: no final | E43: Asigna el valor recibido; si es nulo, asigna la instancia por defecto de CategoriaOrigen. | F43: categoriaOrigen | G43: Otro | H43: CategoriaOrigen | I43: Por valor | J43: no final | K43: Valor que se desea asignar al atributo categoriaOrigen. | L43: Otro | M43: Builder
A44: public | B44: build | C44: no static | D44: no final | E44: Crea la instancia de TipoMovimiento con los valores reunidos en el Builder, usando su constructor privado. | L44: Otro | M44: TipoMovimiento

Sheet Tamano
A1: <-Volver al inicio
A2: =Clases!$A$1 -> Clase | B2: =Clases!A7 -> Tamano
A3: =Clases!$B$1 -> Estereotipo | B3: =Clases!B7 -> class
A4: =Clases!$C$1 -> Descripción | B4: =Clases!C7 -> Representa las distintas presentaciones de tamaño en las que la pizzería puede ofrecer un producto; los productos que no son pizza usan "No aplica".
A5: Modificador acceso: | B5: public
A6: Tipo clase: | B6: no final
A7: Relaciones
A8: Relación | B8: Tipo relación | E8: Estructura
A9: Es usada por | B9: Asociación | E9: Producto
A11: Atributos
A12: Modificador de acceso | B12: Nombre | C12: Tipo de dato | E12: Tipo modificación atributo | F12: Tipo acceso atributo | G12: Valor por defecto | J12: Descripción atributo
C13: Tipo de dato | D13: ¿Cuál?
A14: private | B14: id | C14: Otro | D14: UUID | E14: no final | F14: no static | G14: 00000000-0000-0000-0000-000000000000 | J14: Identificador único del tamaño.
A15: private | B15: tamano | C15: String | E15: no final | F15: no static | G15: "" (cadena vacía) | J15: Nombre de la presentación de tamaño (Grande, Mediana, Pequeña o No aplica).
A17: Constructores
A18: Modificador de acceso | B18: Nombre | C18: Tipo constructor | D18: Descripción | E18: Parámetros | M18: Excepciones
E19: Nombre | F19: Tipo de dato | G19: ¿Cuál? | H19: Tipo parámetro | I19: Tipo modificación atributo | J19: Descripción
A20: private | B20: =B2 -> Tamano | C20: Parametrizado | D20: Constructor privado: crea la instancia de Tamano copiando los valores ya saneados que reunió el Builder. Solo se invoca desde Builder.build(). | E20: builder | F20: Otro | G20: Builder | H20: Por valor | I20: no final | J20: Builder con los valores de los atributos de la clase.
A22: Métodos accesores
A23: Modificador de acceso | B23: Nombre | C23: Tipo método accesor | D23: Tipo modificación método | E23: Descripción | F23: Parámetros | L23: Tipo dato de retorno | N23: Excepciones
F24: Nombre | G24: Tipo de dato | H24: ¿Cuál? | I24: Tipo parámetro | J24: Tipo modificación atributo | K24: Descripción | L24: Tipo de dato | M24: ¿Cuál?
A25: public | B25: getId | C25: getter | D25: no final | E25: Método encargado de obtener el valor del atributo id. | L25: Otro | M25: UUID
A26: public | B26: getTamano | C26: getter | D26: no final | E26: Método encargado de obtener el valor del atributo tamano. | L26: String
A28: Métodos
A29: Modificador de acceso | B29: Nombre | C29: Tipo acceso método | D29: Tipo modificación método | E29: Descripción | F29: Parámetros | L29: Tipo dato de retorno | N29: Excepciones
F30: Nombre | G30: Tipo de dato | H30: ¿Cuál? | I30: Tipo parámetro | J30: Tipo modificación atributo | K30: Descripción | L30: Tipo de dato | M30: ¿Cuál?
A31: public | B31: consultarTamanosDisponibles | C31: static | D31: final | E31: Permite consultar los tamaños disponibles en el sistema para definir el tamaño de un producto. | L31: Otro | M31: List<Tamano> | N31: No existen tamaños disponibles.
A32: public | B32: registrarTamano | C32: no static | D32: no final | E32: Permite agregar un nuevo tamaño al catálogo, para cuando la pizzería empiece a ofrecer una presentación que no exista todavía. | F32: tamano | G32: Otro | H32: Tamano | I32: Por valor | J32: no final | K32: Nombre del nuevo tamaño que se desea registrar. | L32: Otro | M32: Tamano | N32: El dato ingresado no es válido según el tipo de dato, la obligatoriedad o el formato esperado. Ya existe otro tamaño registrado con el mismo Nombre.
A33: public | B33: actualizarTamano | C33: no static | D33: no final | E33: Permite modificar el nombre de un tamaño que ya existe. | F33: tamano | G33: Otro | H33: Tamano | I33: Por valor | J33: no final | K33: Identificador del tamaño que se desea modificar, junto con el nuevo nombre. | L33: Otro | M33: Tamano | N33: El tamaño no existe en el sistema. El nuevo dato ingresado no es válido según el tipo de dato, la obligatoriedad o el formato esperado.
A34: public | B34: eliminarTamano | C34: no static | D34: no final | E34: Permite eliminar un tamaño que no tenga productos asociados que deban conservarse. | F34: id | G34: Otro | H34: UUID | I34: Por valor | J34: no final | K34: Identificador del tamaño que se desea eliminar. | L34: void | N34: El tamaño tiene productos asociados que deben conservarse. El tamaño no existe en el sistema.
A36: Builder (clase interna public static)
A37: Modificador de acceso | B37: Nombre | C37: Tipo acceso método | D37: Tipo modificación método | E37: Descripción | F37: Parámetros | L37: Tipo dato de retorno | N37: Excepciones
F38: Nombre | G38: Tipo de dato | H38: ¿Cuál? | I38: Tipo parámetro | J38: Tipo modificación atributo | K38: Descripción | L38: Tipo de dato | M38: ¿Cuál?
A39: public | B39: Builder | C39: no static | D39: no final | E39: Constructor del Builder: asigna a cada atributo su valor por defecto.
A40: public | B40: id | C40: no static | D40: no final | E40: Asigna el identificador recibido; si es nulo, asigna el identificador por defecto (00000000-0000-0000-0000-000000000000). | F40: id | G40: Otro | H40: UUID | I40: Por valor | J40: no final | K40: Valor que se desea asignar al atributo id. | L40: Otro | M40: Builder
A41: public | B41: tamano | C41: no static | D41: no final | E41: Asigna el texto recibido sin espacios en blanco al inicio y al final, con la primera letra en mayúscula y el resto en minúscula; si es nulo o vacío, asigna una cadena vacía. | F41: tamano | G41: String | I41: Por valor | J41: no final | K41: Valor que se desea asignar al atributo tamano. | L41: Otro | M41: Builder
A42: public | B42: build | C42: no static | D42: no final | E42: Crea la instancia de Tamano con los valores reunidos en el Builder, usando su constructor privado. | L42: Otro | M42: Tamano

Sheet Proveedor
A1: <-Volver al inicio
A2: =Clases!$A$1 -> Clase | B2: =Clases!A8 -> Proveedor
A3: =Clases!$B$1 -> Estereotipo | B3: =Clases!B8 -> class
A4: =Clases!$C$1 -> Descripción | B4: =Clases!C8 -> Representa a las personas o empresas que suministran a la pizzería los insumos y productos necesarios para su operación.
A5: Modificador acceso: | B5: public
A6: Tipo clase: | B6: no final
A7: Relaciones
A8: Relación | B8: Tipo relación | E8: Estructura
A9: Es usada por | B9: Asociación | E9: Compra
A11: Atributos
A12: Modificador de acceso | B12: Nombre | C12: Tipo de dato | E12: Tipo modificación atributo | F12: Tipo acceso atributo | G12: Valor por defecto | J12: Descripción atributo
C13: Tipo de dato | D13: ¿Cuál?
A14: private | B14: id | C14: Otro | D14: UUID | E14: no final | F14: no static | G14: 00000000-0000-0000-0000-000000000000 | J14: Identificador único del proveedor.
A15: private | B15: nombreEmpresa | C15: String | E15: no final | F15: no static | G15: "" (cadena vacía) | J15: Nombre de la empresa a la que pertenece el proveedor.
A16: private | B16: nit | C16: String | E16: no final | F16: no static | G16: "" (cadena vacía) | J16: Número de identificación tributaria (NIT) del proveedor; no se puede repetir entre proveedores.
A17: private | B17: contacto | C17: String | E17: no final | F17: no static | G17: "" (cadena vacía) | J17: Forma de comunicación directa con el proveedor.
A18: private | B18: activo | C18: boolean/Boolean | E18: no final | F18: no static | G18: true | J18: Indica si el proveedor está activo y disponible para nuevas compras.
A20: Constructores
A21: Modificador de acceso | B21: Nombre | C21: Tipo constructor | D21: Descripción | E21: Parámetros | M21: Excepciones
E22: Nombre | F22: Tipo de dato | G22: ¿Cuál? | H22: Tipo parámetro | I22: Tipo modificación atributo | J22: Descripción
A23: private | B23: =B2 -> Proveedor | C23: Parametrizado | D23: Constructor privado: crea la instancia de Proveedor copiando los valores ya saneados que reunió el Builder. Solo se invoca desde Builder.build(). | E23: builder | F23: Otro | G23: Builder | H23: Por valor | I23: no final | J23: Builder con los valores de los atributos de la clase.
A25: Métodos accesores
A26: Modificador de acceso | B26: Nombre | C26: Tipo método accesor | D26: Tipo modificación método | E26: Descripción | F26: Parámetros | L26: Tipo dato de retorno | N26: Excepciones
F27: Nombre | G27: Tipo de dato | H27: ¿Cuál? | I27: Tipo parámetro | J27: Tipo modificación atributo | K27: Descripción | L27: Tipo de dato | M27: ¿Cuál?
A28: public | B28: getId | C28: getter | D28: no final | E28: Método encargado de obtener el valor del atributo id. | L28: Otro | M28: UUID
A29: public | B29: getNombreEmpresa | C29: getter | D29: no final | E29: Método encargado de obtener el valor del atributo nombreEmpresa. | L29: String
A30: public | B30: getNit | C30: getter | D30: no final | E30: Método encargado de obtener el valor del atributo nit. | L30: String
A31: public | B31: getContacto | C31: getter | D31: no final | E31: Método encargado de obtener el valor del atributo contacto. | L31: String
A32: public | B32: isActivo | C32: getter | D32: no final | E32: Método encargado de obtener el valor del atributo activo. | L32: boolean/Boolean
A34: Métodos
A35: Modificador de acceso | B35: Nombre | C35: Tipo acceso método | D35: Tipo modificación método | E35: Descripción | F35: Parámetros | L35: Tipo dato de retorno | N35: Excepciones
F36: Nombre | G36: Tipo de dato | H36: ¿Cuál? | I36: Tipo parámetro | J36: Tipo modificación atributo | K36: Descripción | L36: Tipo de dato | M36: ¿Cuál?
A37: public | B37: registrarProveedor | C37: no static | D37: no final | E37: Permite incorporar un nuevo proveedor al sistema. | F37: proveedor | G37: Otro | H37: Proveedor | I37: Por valor | J37: no final | K37: Información necesaria para registrar e identificar al proveedor. | L37: Otro | M37: Proveedor | N37: Los datos ingresados para registrar el proveedor no son válidos. El identificador generado ya está siendo utilizado por otro proveedor. Ya existe otro proveedor registrado con el mismo NIT. Ya existe otro proveedor registrado con el mismo nombre de empresa.
A38: public | B38: modificarProveedor | C38: no static | D38: no final | E38: Actualizar la información de un proveedor existente sin afectar la trazabilidad de las compras históricas asociadas a este. | F38: proveedor | G38: Otro | H38: Proveedor | I38: Por valor | J38: no final | K38: Identificador del proveedor y datos que se desean modificar. | L38: Otro | M38: Proveedor | N38: El proveedor que se desea actualizar no existe. Los nuevos datos del proveedor no son válidos. La información modificada genera duplicidad con otro proveedor registrado.
A39: public | B39: retirarProveedor | C39: no static | D39: no final | E39: Permite retirar un proveedor con el que la pizzería ya no trabaja: queda inactivo y no se puede usar en nuevas compras, pero se conservan sus compras. | F39: id | G39: Otro | H39: UUID | I39: Por valor | J39: no final | K39: Identificador del proveedor que se desea retirar. | L39: Otro | M39: Proveedor | N39: El proveedor que se desea retirar no existe. El proveedor ya se encuentra retirado. El proveedor tiene compras registradas.
A40: public | B40: consultarProveedoresActivos | C40: static | D40: final | E40: Permite consultar los proveedores activos, ordenados por nombre de empresa, para seleccionarlos al registrar una compra. | L40: Otro | M40: List<Proveedor> | N40: No existen proveedores activos.
A42: Builder (clase interna public static)
A43: Modificador de acceso | B43: Nombre | C43: Tipo acceso método | D43: Tipo modificación método | E43: Descripción | F43: Parámetros | L43: Tipo dato de retorno | N43: Excepciones
F44: Nombre | G44: Tipo de dato | H44: ¿Cuál? | I44: Tipo parámetro | J44: Tipo modificación atributo | K44: Descripción | L44: Tipo de dato | M44: ¿Cuál?
A45: public | B45: Builder | C45: no static | D45: no final | E45: Constructor del Builder: asigna a cada atributo su valor por defecto.
A46: public | B46: id | C46: no static | D46: no final | E46: Asigna el identificador recibido; si es nulo, asigna el identificador por defecto (00000000-0000-0000-0000-000000000000). | F46: id | G46: Otro | H46: UUID | I46: Por valor | J46: no final | K46: Valor que se desea asignar al atributo id. | L46: Otro | M46: Builder
A47: public | B47: nombreEmpresa | C47: no static | D47: no final | E47: Asigna el texto recibido sin espacios en blanco al inicio y al final; si es nulo, asigna una cadena vacía. | F47: nombreEmpresa | G47: String | I47: Por valor | J47: no final | K47: Valor que se desea asignar al atributo nombreEmpresa. | L47: Otro | M47: Builder
A48: public | B48: nit | C48: no static | D48: no final | E48: Asigna el texto recibido sin espacios en blanco al inicio y al final; si es nulo, asigna una cadena vacía. | F48: nit | G48: String | I48: Por valor | J48: no final | K48: Valor que se desea asignar al atributo nit. | L48: Otro | M48: Builder
A49: public | B49: contacto | C49: no static | D49: no final | E49: Asigna el texto recibido sin espacios en blanco al inicio y al final; si es nulo, asigna una cadena vacía. | F49: contacto | G49: String | I49: Por valor | J49: no final | K49: Valor que se desea asignar al atributo contacto. | L49: Otro | M49: Builder
A50: public | B50: activo | C50: no static | D50: no final | E50: Asigna el valor recibido. | F50: activo | G50: boolean/Boolean | I50: Por valor | J50: no final | K50: Valor que se desea asignar al atributo activo. | L50: Otro | M50: Builder
A51: public | B51: build | C51: no static | D51: no final | E51: Crea la instancia de Proveedor con los valores reunidos en el Builder, usando su constructor privado. | L51: Otro | M51: Proveedor

Sheet ProductoInterno
A1: <-Volver al inicio
A2: =Clases!$A$1 -> Clase | B2: =Clases!A9 -> ProductoInterno
A3: =Clases!$B$1 -> Estereotipo | B3: =Clases!B9 -> class
A4: =Clases!$C$1 -> Descripción | B4: =Clases!C9 -> Representa cada insumo o producto que la pizzería compra y almacena en su inventario, ya sea que se consuma dentro de una receta o se venda directamente al cliente.
A5: Modificador acceso: | B5: public
A6: Tipo clase: | B6: no final
A7: Relaciones
A8: Relación | B8: Tipo relación | E8: Estructura
A9: Necesita de | B9: Asociación | E9: UnidadMedida
A10: Es usada por | B10: Asociación | E10: Producto
A11: Es usada por | B11: Asociación | E11: DetalleReceta
A12: Es usada por | B12: Asociación | E12: Inventario
A13: Es usada por | B13: Asociación | E13: Lote
A14: Es usada por | B14: Asociación | E14: DetalleCompra
A15: Es usada por | B15: Asociación | E15: ConsumoVenta
A16: Es usada por | B16: Asociación | E16: Cambio
A18: Atributos
A19: Modificador de acceso | B19: Nombre | C19: Tipo de dato | E19: Tipo modificación atributo | F19: Tipo acceso atributo | G19: Valor por defecto | J19: Descripción atributo
C20: Tipo de dato | D20: ¿Cuál?
A21: private | B21: id | C21: Otro | D21: UUID | E21: no final | F21: no static | G21: 00000000-0000-0000-0000-000000000000 | J21: Identificador único del producto interno.
A22: private | B22: nombre | C22: String | E22: no final | F22: no static | G22: "" (cadena vacía) | J22: Nombre del producto interno (ingrediente o bebida almacenada).
A23: private | B23: perecedero | C23: boolean/Boolean | E23: no final | F23: no static | G23: false | J23: Indica si el producto interno es perecedero.
A24: private | B24: vidaUtil | C24: int/Integer | E24: no final | F24: no static | G24: 0 | J24: Vida útil del producto interno en días: de 1 a 400 si es perecedero y 0 si no lo es.
A25: private | B25: tipoMedida | C25: Otro | D25: UnidadMedida | E25: no final | F25: no static | G25: Instancia por defecto de UnidadMedida | J25: Unidad de medida en la que se maneja el producto interno; su tipo (Peso, Volumen o Unidad) define la unidad de las recetas.
A26: private | B26: activo | C26: boolean/Boolean | E26: no final | F26: no static | G26: true | J26: Indica si el producto interno está activo y disponible para usarse en recetas y compras.
A28: Constructores
A29: Modificador de acceso | B29: Nombre | C29: Tipo constructor | D29: Descripción | E29: Parámetros | M29: Excepciones
E30: Nombre | F30: Tipo de dato | G30: ¿Cuál? | H30: Tipo parámetro | I30: Tipo modificación atributo | J30: Descripción
A31: private | B31: =B2 -> ProductoInterno | C31: Parametrizado | D31: Constructor privado: crea la instancia de ProductoInterno copiando los valores ya saneados que reunió el Builder. Solo se invoca desde Builder.build(). | E31: builder | F31: Otro | G31: Builder | H31: Por valor | I31: no final | J31: Builder con los valores de los atributos de la clase.
A33: Métodos accesores
A34: Modificador de acceso | B34: Nombre | C34: Tipo método accesor | D34: Tipo modificación método | E34: Descripción | F34: Parámetros | L34: Tipo dato de retorno | N34: Excepciones
F35: Nombre | G35: Tipo de dato | H35: ¿Cuál? | I35: Tipo parámetro | J35: Tipo modificación atributo | K35: Descripción | L35: Tipo de dato | M35: ¿Cuál?
A36: public | B36: getId | C36: getter | D36: no final | E36: Método encargado de obtener el valor del atributo id. | L36: Otro | M36: UUID
A37: public | B37: getNombre | C37: getter | D37: no final | E37: Método encargado de obtener el valor del atributo nombre. | L37: String
A38: public | B38: isPerecedero | C38: getter | D38: no final | E38: Método encargado de obtener el valor del atributo perecedero. | L38: boolean/Boolean
A39: public | B39: getVidaUtil | C39: getter | D39: no final | E39: Método encargado de obtener el valor del atributo vidaUtil. | L39: int/Integer
A40: public | B40: getTipoMedida | C40: getter | D40: no final | E40: Método encargado de obtener el valor del atributo tipoMedida. | L40: Otro | M40: UnidadMedida
A41: public | B41: isActivo | C41: getter | D41: no final | E41: Método encargado de obtener el valor del atributo activo. | L41: boolean/Boolean
A43: Métodos
A44: Modificador de acceso | B44: Nombre | C44: Tipo acceso método | D44: Tipo modificación método | E44: Descripción | F44: Parámetros | L44: Tipo dato de retorno | N44: Excepciones
F45: Nombre | G45: Tipo de dato | H45: ¿Cuál? | I45: Tipo parámetro | J45: Tipo modificación atributo | K45: Descripción | L45: Tipo de dato | M45: ¿Cuál?
A46: public | B46: registrarProductoInterno | C46: no static | D46: no final | E46: Permite incorporar un nuevo producto interno (ingrediente o bebida almacenada) al inventario de la pizzería. | F46: productoInterno | G46: Otro | H46: ProductoInterno | I46: Por valor | J46: no final | K46: Información propia necesaria para registrar el producto interno. | L46: Otro | M46: ProductoInterno | N46: Los datos ingresados para registrar el producto interno no son válidos. Ya existe otro producto interno registrado con el mismo Nombre. La vida útil no está entre 1 y 400 días para un producto perecedero, o no es 0 para uno no perecedero. La TipoMedida indicada no corresponde a una unidad de medida existente. No fue posible crear el registro de inventario del producto interno.
A47: public | B47: actualizarProductoInterno | C47: no static | D47: no final | E47: Permite modificar la información de un producto interno existente. | F47: productoInterno | G47: Otro | H47: ProductoInterno | I47: Por valor | J47: no final | K47: Identificador del producto interno y datos que se desean actualizar. | L47: Otro | M47: ProductoInterno | N47: El producto interno no existe en el sistema. Se intentó modificar el registro "Sin insumo". Los nuevos datos del producto interno no son válidos. El nuevo Nombre ya lo tiene otro producto interno. La nueva vida útil no corresponde a si el producto es perecedero o no.
A48: public | B48: inactivarProductoInterno | C48: no static | D48: no final | E48: Permite inactivar un producto interno que la pizzería ya no usa: no se puede usar en nuevas recetas ni compras, pero se conserva su historial. | F48: id | G48: Otro | H48: UUID | I48: Por valor | J48: no final | K48: Identificador del producto interno que se desea inactivar. | L48: Otro | M48: ProductoInterno | N48: El producto interno que se desea inactivar no existe. El producto interno ya se encuentra inactivo. Se intentó inactivar el registro "Sin insumo". El producto interno tiene lotes, compras o recetas registradas.
A49: public | B49: consultarProductosInternosActivos | C49: static | D49: final | E49: Permite consultar los productos internos activos, por ejemplo para escoger los ingredientes de una receta. | L49: Otro | M49: List<ProductoInterno> | N49: No existen productos internos activos.
A51: Builder (clase interna public static)
A52: Modificador de acceso | B52: Nombre | C52: Tipo acceso método | D52: Tipo modificación método | E52: Descripción | F52: Parámetros | L52: Tipo dato de retorno | N52: Excepciones
F53: Nombre | G53: Tipo de dato | H53: ¿Cuál? | I53: Tipo parámetro | J53: Tipo modificación atributo | K53: Descripción | L53: Tipo de dato | M53: ¿Cuál?
A54: public | B54: Builder | C54: no static | D54: no final | E54: Constructor del Builder: asigna a cada atributo su valor por defecto.
A55: public | B55: id | C55: no static | D55: no final | E55: Asigna el identificador recibido; si es nulo, asigna el identificador por defecto (00000000-0000-0000-0000-000000000000). | F55: id | G55: Otro | H55: UUID | I55: Por valor | J55: no final | K55: Valor que se desea asignar al atributo id. | L55: Otro | M55: Builder
A56: public | B56: nombre | C56: no static | D56: no final | E56: Asigna el texto recibido sin espacios en blanco al inicio y al final; si es nulo, asigna una cadena vacía. | F56: nombre | G56: String | I56: Por valor | J56: no final | K56: Valor que se desea asignar al atributo nombre. | L56: Otro | M56: Builder
A57: public | B57: perecedero | C57: no static | D57: no final | E57: Asigna el valor recibido. | F57: perecedero | G57: boolean/Boolean | I57: Por valor | J57: no final | K57: Valor que se desea asignar al atributo perecedero. | L57: Otro | M57: Builder
A58: public | B58: vidaUtil | C58: no static | D58: no final | E58: Asigna el valor recibido; si es nulo, asigna 0. | F58: vidaUtil | G58: int/Integer | I58: Por valor | J58: no final | K58: Valor que se desea asignar al atributo vidaUtil. | L58: Otro | M58: Builder
A59: public | B59: tipoMedida | C59: no static | D59: no final | E59: Asigna el valor recibido; si es nulo, asigna la instancia por defecto de UnidadMedida. | F59: tipoMedida | G59: Otro | H59: UnidadMedida | I59: Por valor | J59: no final | K59: Valor que se desea asignar al atributo tipoMedida. | L59: Otro | M59: Builder
A60: public | B60: activo | C60: no static | D60: no final | E60: Asigna el valor recibido. | F60: activo | G60: boolean/Boolean | I60: Por valor | J60: no final | K60: Valor que se desea asignar al atributo activo. | L60: Otro | M60: Builder
A61: public | B61: build | C61: no static | D61: no final | E61: Crea la instancia de ProductoInterno con los valores reunidos en el Builder, usando su constructor privado. | L61: Otro | M61: ProductoInterno

Sheet Producto
A1: <-Volver al inicio
A2: =Clases!$A$1 -> Clase | B2: =Clases!A10 -> Producto
A3: =Clases!$B$1 -> Estereotipo | B3: =Clases!B10 -> class
A4: =Clases!$C$1 -> Descripción | B4: =Clases!C10 -> Representa los artículos que la pizzería comercializa y que pueden ser vendidos al cliente, sirviendo como referencia para identificar y gestionar su oferta comercial.
A5: Modificador acceso: | B5: public
A6: Tipo clase: | B6: no final
A7: Relaciones
A8: Relación | B8: Tipo relación | E8: Estructura
A9: Necesita de | B9: Asociación | E9: TipoProducto
A10: Necesita de | B10: Asociación | E10: Tamano
A11: Necesita de | B11: Asociación | E11: ProductoInterno
A12: Es usada por | B12: Composición | E12: DetalleReceta
A13: Es usada por | B13: Asociación | E13: DetalleVenta
A14: Es usada por | B14: Asociación | E14: HistoricoPrecio
A16: Atributos
A17: Modificador de acceso | B17: Nombre | C17: Tipo de dato | E17: Tipo modificación atributo | F17: Tipo acceso atributo | G17: Valor por defecto | J17: Descripción atributo
C18: Tipo de dato | D18: ¿Cuál?
A19: private | B19: id | C19: Otro | D19: UUID | E19: no final | F19: no static | G19: 00000000-0000-0000-0000-000000000000 | J19: Identificador único del producto.
A20: private | B20: nombre | C20: String | E20: no final | F20: no static | G20: "" (cadena vacía) | J20: Nombre del producto que ofrece la pizzería.
A21: private | B21: tipoProducto | C21: Otro | D21: TipoProducto | E21: no final | F21: no static | G21: Instancia por defecto de TipoProducto | J21: Clasificación a la que pertenece el producto (Pizza, Bebida o Adición).
A22: private | B22: tamano | C22: Otro | D22: Tamano | E22: no final | F22: no static | G22: Instancia por defecto de Tamano | J22: Presentación de tamaño del producto; los productos que no son pizza usan "No aplica".
A23: private | B23: productoInterno | C23: boolean/Boolean | E23: no final | F23: no static | G23: false | J23: Indica si el producto se vende directamente desde el inventario, sin necesidad de receta.
A24: private | B24: productoInternoAsociado | C24: Otro | D24: ProductoInterno | E24: no final | F24: no static | G24: Instancia por defecto de ProductoInterno | J24: Producto interno asociado: si el producto se vende directamente desde el inventario es el producto interno con el mismo nombre; si no, es el registro "Sin insumo".
A25: private | B25: precio | C25: Otro | D25: BigDecimal | E25: no final | F25: no static | G25: 0 | J25: Precio de venta al público del producto; coincide con el precio vigente en el histórico de precios.
A26: private | B26: activo | C26: boolean/Boolean | E26: no final | F26: no static | G26: true | J26: Indica si el producto está activo y disponible para la venta.
A28: Constructores
A29: Modificador de acceso | B29: Nombre | C29: Tipo constructor | D29: Descripción | E29: Parámetros | M29: Excepciones
E30: Nombre | F30: Tipo de dato | G30: ¿Cuál? | H30: Tipo parámetro | I30: Tipo modificación atributo | J30: Descripción
A31: private | B31: =B2 -> Producto | C31: Parametrizado | D31: Constructor privado: crea la instancia de Producto copiando los valores ya saneados que reunió el Builder. Solo se invoca desde Builder.build(). | E31: builder | F31: Otro | G31: Builder | H31: Por valor | I31: no final | J31: Builder con los valores de los atributos de la clase.
A33: Métodos accesores
A34: Modificador de acceso | B34: Nombre | C34: Tipo método accesor | D34: Tipo modificación método | E34: Descripción | F34: Parámetros | L34: Tipo dato de retorno | N34: Excepciones
F35: Nombre | G35: Tipo de dato | H35: ¿Cuál? | I35: Tipo parámetro | J35: Tipo modificación atributo | K35: Descripción | L35: Tipo de dato | M35: ¿Cuál?
A36: public | B36: getId | C36: getter | D36: no final | E36: Método encargado de obtener el valor del atributo id. | L36: Otro | M36: UUID
A37: public | B37: getNombre | C37: getter | D37: no final | E37: Método encargado de obtener el valor del atributo nombre. | L37: String
A38: public | B38: getTipoProducto | C38: getter | D38: no final | E38: Método encargado de obtener el valor del atributo tipoProducto. | L38: Otro | M38: TipoProducto
A39: public | B39: getTamano | C39: getter | D39: no final | E39: Método encargado de obtener el valor del atributo tamano. | L39: Otro | M39: Tamano
A40: public | B40: isProductoInterno | C40: getter | D40: no final | E40: Método encargado de obtener el valor del atributo productoInterno. | L40: boolean/Boolean
A41: public | B41: getProductoInternoAsociado | C41: getter | D41: no final | E41: Método encargado de obtener el valor del atributo productoInternoAsociado. | L41: Otro | M41: ProductoInterno
A42: public | B42: getPrecio | C42: getter | D42: no final | E42: Método encargado de obtener el valor del atributo precio. | L42: Otro | M42: BigDecimal
A43: public | B43: isActivo | C43: getter | D43: no final | E43: Método encargado de obtener el valor del atributo activo. | L43: boolean/Boolean
A45: Métodos
A46: Modificador de acceso | B46: Nombre | C46: Tipo acceso método | D46: Tipo modificación método | E46: Descripción | F46: Parámetros | L46: Tipo dato de retorno | N46: Excepciones
F47: Nombre | G47: Tipo de dato | H47: ¿Cuál? | I47: Tipo parámetro | J47: Tipo modificación atributo | K47: Descripción | L47: Tipo de dato | M47: ¿Cuál?
A48: public | B48: registrarProducto | C48: no static | D48: no final | E48: Permite incorporar un nuevo producto a la oferta comercial de la pizzería, definiendo la información necesaria para su identificación y comercialización. | F48: producto | G48: Otro | H48: Producto | I48: Por valor | J48: no final | K48: Información propia necesaria para registrar el producto. | L48: Otro | M48: Producto | N48: Los datos ingresados para registrar el producto no cumplen las reglas establecidas. El identificador generado ya está siendo utilizado por otro producto. Ya existe otro producto con el mismo Nombre y el mismo Tamaño. El tipo de producto utilizado no corresponde a un tipo válido definido por la pizzería. No existe un producto interno con el mismo nombre del producto. El tamaño utilizado no corresponde a un tamaño válido definido por la pizzería. No fue posible registrar el precio inicial en el histórico de precios.
A49: public | B49: inactivarProducto | C49: no static | D49: no final | E49: Permite inactivar un producto que la pizzería ya no ofrece: no se puede vender, pero se conserva su historial de precios, ventas y recetas. | F49: id | G49: Otro | H49: UUID | I49: Por valor | J49: no final | K49: Identificador del producto que se desea inactivar. | L49: Otro | M49: Producto | N49: El producto no existe con el identificador indicado. El producto ya se encuentra inactivo. El producto tiene precios, ventas o recetas registradas.
A50: public | B50: consultarProductosActivos | C50: static | D50: final | E50: Permite consultar los productos activos que la pizzería ofrece, por ejemplo para registrar una venta o armar una receta. | L50: Otro | M50: List<Producto> | N50: No existen productos activos.
A52: Builder (clase interna public static)
A53: Modificador de acceso | B53: Nombre | C53: Tipo acceso método | D53: Tipo modificación método | E53: Descripción | F53: Parámetros | L53: Tipo dato de retorno | N53: Excepciones
F54: Nombre | G54: Tipo de dato | H54: ¿Cuál? | I54: Tipo parámetro | J54: Tipo modificación atributo | K54: Descripción | L54: Tipo de dato | M54: ¿Cuál?
A55: public | B55: Builder | C55: no static | D55: no final | E55: Constructor del Builder: asigna a cada atributo su valor por defecto.
A56: public | B56: id | C56: no static | D56: no final | E56: Asigna el identificador recibido; si es nulo, asigna el identificador por defecto (00000000-0000-0000-0000-000000000000). | F56: id | G56: Otro | H56: UUID | I56: Por valor | J56: no final | K56: Valor que se desea asignar al atributo id. | L56: Otro | M56: Builder
A57: public | B57: nombre | C57: no static | D57: no final | E57: Asigna el texto recibido sin espacios en blanco al inicio y al final; si es nulo, asigna una cadena vacía. | F57: nombre | G57: String | I57: Por valor | J57: no final | K57: Valor que se desea asignar al atributo nombre. | L57: Otro | M57: Builder
A58: public | B58: tipoProducto | C58: no static | D58: no final | E58: Asigna el valor recibido; si es nulo, asigna la instancia por defecto de TipoProducto. | F58: tipoProducto | G58: Otro | H58: TipoProducto | I58: Por valor | J58: no final | K58: Valor que se desea asignar al atributo tipoProducto. | L58: Otro | M58: Builder
A59: public | B59: tamano | C59: no static | D59: no final | E59: Asigna el valor recibido; si es nulo, asigna la instancia por defecto de Tamano. | F59: tamano | G59: Otro | H59: Tamano | I59: Por valor | J59: no final | K59: Valor que se desea asignar al atributo tamano. | L59: Otro | M59: Builder
A60: public | B60: productoInterno | C60: no static | D60: no final | E60: Asigna el valor recibido. | F60: productoInterno | G60: boolean/Boolean | I60: Por valor | J60: no final | K60: Valor que se desea asignar al atributo productoInterno. | L60: Otro | M60: Builder
A61: public | B61: productoInternoAsociado | C61: no static | D61: no final | E61: Asigna el valor recibido; si es nulo, asigna la instancia por defecto de ProductoInterno. | F61: productoInternoAsociado | G61: Otro | H61: ProductoInterno | I61: Por valor | J61: no final | K61: Valor que se desea asignar al atributo productoInternoAsociado. | L61: Otro | M61: Builder
A62: public | B62: precio | C62: no static | D62: no final | E62: Asigna el valor recibido; si es nulo o negativo, asigna 0. | F62: precio | G62: Otro | H62: BigDecimal | I62: Por valor | J62: no final | K62: Valor que se desea asignar al atributo precio. | L62: Otro | M62: Builder
A63: public | B63: activo | C63: no static | D63: no final | E63: Asigna el valor recibido. | F63: activo | G63: boolean/Boolean | I63: Por valor | J63: no final | K63: Valor que se desea asignar al atributo activo. | L63: Otro | M63: Builder
A64: public | B64: build | C64: no static | D64: no final | E64: Crea la instancia de Producto con los valores reunidos en el Builder, usando su constructor privado. | L64: Otro | M64: Producto

Sheet DetalleReceta
A1: <-Volver al inicio
A2: =Clases!$A$1 -> Clase | B2: =Clases!A11 -> DetalleReceta
A3: =Clases!$B$1 -> Estereotipo | B3: =Clases!B11 -> class
A4: =Clases!$C$1 -> Descripción | B4: =Clases!C11 -> Representa cada uno de los ingredientes necesarios para elaborar una receta, indicando la cantidad requerida y la unidad de medida utilizada.
A5: Modificador acceso: | B5: public
A6: Tipo clase: | B6: no final
A7: Relaciones
A8: Relación | B8: Tipo relación | E8: Estructura
A9: Necesita de | B9: Asociación | E9: ProductoInterno
A10: Necesita de | B10: Asociación | E10: UnidadMedida
A11: Necesita de | B11: Composición | E11: Producto
A13: Atributos
A14: Modificador de acceso | B14: Nombre | C14: Tipo de dato | E14: Tipo modificación atributo | F14: Tipo acceso atributo | G14: Valor por defecto | J14: Descripción atributo
C15: Tipo de dato | D15: ¿Cuál?
A16: private | B16: id | C16: Otro | D16: UUID | E16: no final | F16: no static | G16: 00000000-0000-0000-0000-000000000000 | J16: Identificador único del detalle de receta.
A17: private | B17: productoInterno | C17: Otro | D17: ProductoInterno | E17: no final | F17: no static | G17: Instancia por defecto de ProductoInterno | J17: Producto interno (ingrediente) que se utiliza en la receta.
A18: private | B18: cantidad | C18: Otro | D18: BigDecimal | E18: no final | F18: no static | G18: 0 | J18: Cantidad requerida del ingrediente para elaborar el producto.
A19: private | B19: unidadMedida | C19: Otro | D19: UnidadMedida | E19: no final | F19: no static | G19: Instancia por defecto de UnidadMedida | J19: Unidad de medida de la cantidad del ingrediente; se asigna automáticamente según el tipo de medida del producto interno (g, ml o und).
A20: private | B20: producto | C20: Otro | D20: Producto | E20: no final | F20: no static | G20: Instancia por defecto de Producto | J20: Producto (pizza o adición) al que pertenece esta línea de receta.
A22: Constructores
A23: Modificador de acceso | B23: Nombre | C23: Tipo constructor | D23: Descripción | E23: Parámetros | M23: Excepciones
E24: Nombre | F24: Tipo de dato | G24: ¿Cuál? | H24: Tipo parámetro | I24: Tipo modificación atributo | J24: Descripción
A25: private | B25: =B2 -> DetalleReceta | C25: Parametrizado | D25: Constructor privado: crea la instancia de DetalleReceta copiando los valores ya saneados que reunió el Builder. Solo se invoca desde Builder.build(). | E25: builder | F25: Otro | G25: Builder | H25: Por valor | I25: no final | J25: Builder con los valores de los atributos de la clase.
A27: Métodos accesores
A28: Modificador de acceso | B28: Nombre | C28: Tipo método accesor | D28: Tipo modificación método | E28: Descripción | F28: Parámetros | L28: Tipo dato de retorno | N28: Excepciones
F29: Nombre | G29: Tipo de dato | H29: ¿Cuál? | I29: Tipo parámetro | J29: Tipo modificación atributo | K29: Descripción | L29: Tipo de dato | M29: ¿Cuál?
A30: public | B30: getId | C30: getter | D30: no final | E30: Método encargado de obtener el valor del atributo id. | L30: Otro | M30: UUID
A31: public | B31: getProductoInterno | C31: getter | D31: no final | E31: Método encargado de obtener el valor del atributo productoInterno. | L31: Otro | M31: ProductoInterno
A32: public | B32: getCantidad | C32: getter | D32: no final | E32: Método encargado de obtener el valor del atributo cantidad. | L32: Otro | M32: BigDecimal
A33: public | B33: getUnidadMedida | C33: getter | D33: no final | E33: Método encargado de obtener el valor del atributo unidadMedida. | L33: Otro | M33: UnidadMedida
A34: public | B34: getProducto | C34: getter | D34: no final | E34: Método encargado de obtener el valor del atributo producto. | L34: Otro | M34: Producto
A36: Métodos
A37: Modificador de acceso | B37: Nombre | C37: Tipo acceso método | D37: Tipo modificación método | E37: Descripción | F37: Parámetros | L37: Tipo dato de retorno | N37: Excepciones
F38: Nombre | G38: Tipo de dato | H38: ¿Cuál? | I38: Tipo parámetro | J38: Tipo modificación atributo | K38: Descripción | L38: Tipo de dato | M38: ¿Cuál?
A39: public | B39: agregarIngredienteAReceta | C39: no static | D39: no final | E39: Permite incorporar un ingrediente a la composición de una receta indicando la cantidad necesaria para su elaboración. | F39: detalleReceta | G39: Otro | H39: DetalleReceta | I39: Por valor | J39: no final | K39: Información necesaria para incorporar el ingrediente a la receta. | L39: Otro | M39: DetalleReceta | N39: Los datos ingresados para registrar el detalle de receta no son válidos. El producto (pizza o adición) al que pertenece el detalle de receta no existe. El producto se encuentra inactivo. El producto asociado al detalle de receta no es una pizza ni una adición. El producto interno que se quiere asociar al detalle de receta no existe. El producto interno se encuentra inactivo. La cantidad no es mayor que cero o supera 10.000. No fue posible determinar la unidad de medida a partir del producto interno. El producto interno ya se encuentra registrado dentro de la misma receta. El identificador generado ya está siendo utilizado.
A40: public | B40: modificarCantidadDeIngrediente | C40: no static | D40: no final | E40: Permite ajustar la cantidad de un ingrediente requerida para la elaboración de una receta. | F40: detalleReceta | G40: Otro | H40: DetalleReceta | I40: Por valor | J40: no final | K40: Identificador del detalle y nueva información necesaria para modificar la cantidad. | L40: Otro | M40: DetalleReceta | N40: El detalle de receta que se desea actualizar no existe. La nueva cantidad no es mayor que cero o supera 10.000.
A41: public | B41: retirarIngredienteDeReceta | C41: no static | D41: no final | E41: Permite retirar un ingrediente de la composición de una receta cuando deja de ser requerido para su elaboración. | F41: id | G41: Otro | H41: UUID | I41: Por valor | J41: no final | K41: Identificador del detalle de receta que se desea retirar. | L41: void | N41: El detalle de receta no existe con el identificador indicado.
A42: public | B42: consultarIngredientesPorFiltro | C42: static | D42: final | E42: Permite consultar los ingredientes de recetas que cumplan con los criterios indicados, por ejemplo todos los ingredientes de un producto. | F42: filtro | G42: Otro | H42: DetalleReceta | I42: Por valor | J42: no final | K42: Criterios de búsqueda. | L42: Otro | M42: List<DetalleReceta> | N42: No existen ingredientes que cumplan con el filtro.
A43: public | B43: consultarRecetasDeProductosActivos | C43: static | D43: final | E43: Permite consultar las recetas (ingredientes) de los productos que la pizzería ofrece actualmente. | L43: Otro | M43: List<DetalleReceta> | N43: No existen recetas de productos activos.
A44: public | B44: consultarRecetasDeProductosInactivos | C44: static | D44: final | E44: Permite consultar las recetas de los productos que la pizzería ya no ofrece, para conservar su historial. | L44: Otro | M44: List<DetalleReceta> | N44: No existen recetas de productos inactivos.
A46: Builder (clase interna public static)
A47: Modificador de acceso | B47: Nombre | C47: Tipo acceso método | D47: Tipo modificación método | E47: Descripción | F47: Parámetros | L47: Tipo dato de retorno | N47: Excepciones
F48: Nombre | G48: Tipo de dato | H48: ¿Cuál? | I48: Tipo parámetro | J48: Tipo modificación atributo | K48: Descripción | L48: Tipo de dato | M48: ¿Cuál?
A49: public | B49: Builder | C49: no static | D49: no final | E49: Constructor del Builder: asigna a cada atributo su valor por defecto.
A50: public | B50: id | C50: no static | D50: no final | E50: Asigna el identificador recibido; si es nulo, asigna el identificador por defecto (00000000-0000-0000-0000-000000000000). | F50: id | G50: Otro | H50: UUID | I50: Por valor | J50: no final | K50: Valor que se desea asignar al atributo id. | L50: Otro | M50: Builder
A51: public | B51: productoInterno | C51: no static | D51: no final | E51: Asigna el valor recibido; si es nulo, asigna la instancia por defecto de ProductoInterno. | F51: productoInterno | G51: Otro | H51: ProductoInterno | I51: Por valor | J51: no final | K51: Valor que se desea asignar al atributo productoInterno. | L51: Otro | M51: Builder
A52: public | B52: cantidad | C52: no static | D52: no final | E52: Asigna el valor recibido; si es nulo o negativo, asigna 0. | F52: cantidad | G52: Otro | H52: BigDecimal | I52: Por valor | J52: no final | K52: Valor que se desea asignar al atributo cantidad. | L52: Otro | M52: Builder
A53: public | B53: unidadMedida | C53: no static | D53: no final | E53: Asigna el valor recibido; si es nulo, asigna la instancia por defecto de UnidadMedida. | F53: unidadMedida | G53: Otro | H53: UnidadMedida | I53: Por valor | J53: no final | K53: Valor que se desea asignar al atributo unidadMedida. | L53: Otro | M53: Builder
A54: public | B54: producto | C54: no static | D54: no final | E54: Asigna el valor recibido; si es nulo, asigna la instancia por defecto de Producto. | F54: producto | G54: Otro | H54: Producto | I54: Por valor | J54: no final | K54: Valor que se desea asignar al atributo producto. | L54: Otro | M54: Builder
A55: public | B55: build | C55: no static | D55: no final | E55: Crea la instancia de DetalleReceta con los valores reunidos en el Builder, usando su constructor privado. | L55: Otro | M55: DetalleReceta

Sheet Inventario
A1: <-Volver al inicio
A2: =Clases!$A$1 -> Clase | B2: =Clases!A12 -> Inventario
A3: =Clases!$B$1 -> Estereotipo | B3: =Clases!B12 -> class
A4: =Clases!$C$1 -> Descripción | B4: =Clases!C12 -> Representa las existencias disponibles de los insumos y productos que la pizzería necesita para operar y atender sus ventas.
A5: Modificador acceso: | B5: public
A6: Tipo clase: | B6: no final
A7: Relaciones
A8: Relación | B8: Tipo relación | E8: Estructura
A9: Necesita de | B9: Asociación | E9: ProductoInterno
A10: Necesita de | B10: Asociación | E10: UnidadMedida
A12: Atributos
A13: Modificador de acceso | B13: Nombre | C13: Tipo de dato | E13: Tipo modificación atributo | F13: Tipo acceso atributo | G13: Valor por defecto | J13: Descripción atributo
C14: Tipo de dato | D14: ¿Cuál?
A15: private | B15: id | C15: Otro | D15: UUID | E15: no final | F15: no static | G15: 00000000-0000-0000-0000-000000000000 | J15: Identificador único del registro de inventario.
A16: private | B16: cantidadTotal | C16: Otro | D16: BigDecimal | E16: no final | F16: no static | G16: 0 | J16: Cantidad total disponible del producto interno, expresada en su unidad de medida de inventario.
A17: private | B17: productoInterno | C17: Otro | D17: ProductoInterno | E17: no final | F17: no static | G17: Instancia por defecto de ProductoInterno | J17: Producto interno (ingrediente o bebida) al que corresponde este registro de inventario; cada producto interno tiene un único registro.
A18: private | B18: unidadMedidaInventario | C18: Otro | D18: UnidadMedida | E18: no final | F18: no static | G18: Instancia por defecto de UnidadMedida | J18: Unidad de medida en la que se maneja el inventario (kg, l o und), determinada por el tipo de medida del producto interno.
A19: private | B19: stockMinimo | C19: Otro | D19: BigDecimal | E19: no final | F19: no static | G19: 1 | J19: Cantidad mínima que debe mantenerse disponible antes de requerir reposición.
A21: Constructores
A22: Modificador de acceso | B22: Nombre | C22: Tipo constructor | D22: Descripción | E22: Parámetros | M22: Excepciones
E23: Nombre | F23: Tipo de dato | G23: ¿Cuál? | H23: Tipo parámetro | I23: Tipo modificación atributo | J23: Descripción
A24: private | B24: =B2 -> Inventario | C24: Parametrizado | D24: Constructor privado: crea la instancia de Inventario copiando los valores ya saneados que reunió el Builder. Solo se invoca desde Builder.build(). | E24: builder | F24: Otro | G24: Builder | H24: Por valor | I24: no final | J24: Builder con los valores de los atributos de la clase.
A26: Métodos accesores
A27: Modificador de acceso | B27: Nombre | C27: Tipo método accesor | D27: Tipo modificación método | E27: Descripción | F27: Parámetros | L27: Tipo dato de retorno | N27: Excepciones
F28: Nombre | G28: Tipo de dato | H28: ¿Cuál? | I28: Tipo parámetro | J28: Tipo modificación atributo | K28: Descripción | L28: Tipo de dato | M28: ¿Cuál?
A29: public | B29: getId | C29: getter | D29: no final | E29: Método encargado de obtener el valor del atributo id. | L29: Otro | M29: UUID
A30: public | B30: getCantidadTotal | C30: getter | D30: no final | E30: Método encargado de obtener el valor del atributo cantidadTotal. | L30: Otro | M30: BigDecimal
A31: public | B31: getProductoInterno | C31: getter | D31: no final | E31: Método encargado de obtener el valor del atributo productoInterno. | L31: Otro | M31: ProductoInterno
A32: public | B32: getUnidadMedidaInventario | C32: getter | D32: no final | E32: Método encargado de obtener el valor del atributo unidadMedidaInventario. | L32: Otro | M32: UnidadMedida
A33: public | B33: getStockMinimo | C33: getter | D33: no final | E33: Método encargado de obtener el valor del atributo stockMinimo. | L33: Otro | M33: BigDecimal
A35: Métodos
A36: Modificador de acceso | B36: Nombre | C36: Tipo acceso método | D36: Tipo modificación método | E36: Descripción | F36: Parámetros | L36: Tipo dato de retorno | N36: Excepciones
F37: Nombre | G37: Tipo de dato | H37: ¿Cuál? | I37: Tipo parámetro | J37: Tipo modificación atributo | K37: Descripción | L37: Tipo de dato | M37: ¿Cuál?
A38: public | B38: actualizarInventario | C38: no static | D38: no final | E38: Actualizar la existencia representada en el inventario como consecuencia de un movimiento de entrada, salida o ajuste previamente registrado. | F38: movimientoInventario | G38: Otro | H38: MovimientoInventario | I38: Por valor | J38: no final | K38: Información del movimiento que permite determinar la variación que debe reflejarse en la existencia del inventario. | L38: Otro | M38: Inventario | N38: El lote asociado a la actualización del inventario no es válido o no está registrado. La cantidad resultante sería inferior a cero o superior a 100.000. Ya existe otro registro de inventario para el mismo producto interno. La cantidad calculada no corresponde a la suma de las cantidades disponibles de los lotes asociados al producto.
A39: public | B39: consultarInventario | C39: static | D39: final | E39: Permite visualizar el estado actual y las existencias de ingredientes y bebidas. | F39: inventario | G39: Otro | H39: Inventario | I39: Por valor | J39: no final | K39: Información necesaria para poder consultar el inventario. | L39: Otro | M39: Inventario | N39: No se encuentra una existencia que corresponda a los criterios de consulta.
A40: public | B40: consultarExistenciasPorLote | C40: static | D40: final | E40: Consultar las cantidades disponibles asociadas a los lotes existentes para conocer la trazabilidad de las existencias. | F40: inventario | G40: Otro | H40: Inventario | I40: Por valor | J40: no final | K40: Información necesaria para identificar el producto y lote cuya existencia se desea consultar. | L40: Otro | M40: Inventario | N40: El lote indicado no corresponde a una existencia disponible para consulta, o el lote no se encuentra registrado en el sistema.
A41: public | B41: establecerStockMinimo | C41: no static | D41: no final | E41: Permite definir la cantidad mínima de existencias que debe mantenerse para controlar la necesidad de reposición. | F41: inventario | G41: Otro | H41: Inventario | I41: Por valor | J41: no final | K41: Cantidad de stock mínimo que se desea establecer para el producto. | L41: Otro | M41: Inventario | N41: El stock mínimo no es mayor que cero o supera 100.000.
A42: public | B42: emitirAlertaDeStockBajo | C42: no static | D42: no final | E42: Cuando la cantidad total disponible de un producto cae por debajo del stock mínimo establecido, el sistema emite una alerta para que el administrador gestione la compra de reposición. | F42: inventario | G42: Otro | H42: Inventario | I42: Por valor | J42: no final | K42: Cantidad total disponible y stock mínimo establecido para el producto. | L42: Otro | M42: Inventario | N42: El stock mínimo no está definido para el producto, o no se puede determinar la cantidad total disponible.
A44: Builder (clase interna public static)
A45: Modificador de acceso | B45: Nombre | C45: Tipo acceso método | D45: Tipo modificación método | E45: Descripción | F45: Parámetros | L45: Tipo dato de retorno | N45: Excepciones
F46: Nombre | G46: Tipo de dato | H46: ¿Cuál? | I46: Tipo parámetro | J46: Tipo modificación atributo | K46: Descripción | L46: Tipo de dato | M46: ¿Cuál?
A47: public | B47: Builder | C47: no static | D47: no final | E47: Constructor del Builder: asigna a cada atributo su valor por defecto.
A48: public | B48: id | C48: no static | D48: no final | E48: Asigna el identificador recibido; si es nulo, asigna el identificador por defecto (00000000-0000-0000-0000-000000000000). | F48: id | G48: Otro | H48: UUID | I48: Por valor | J48: no final | K48: Valor que se desea asignar al atributo id. | L48: Otro | M48: Builder
A49: public | B49: cantidadTotal | C49: no static | D49: no final | E49: Asigna el valor recibido; si es nulo o negativo, asigna 0. | F49: cantidadTotal | G49: Otro | H49: BigDecimal | I49: Por valor | J49: no final | K49: Valor que se desea asignar al atributo cantidadTotal. | L49: Otro | M49: Builder
A50: public | B50: productoInterno | C50: no static | D50: no final | E50: Asigna el valor recibido; si es nulo, asigna la instancia por defecto de ProductoInterno. | F50: productoInterno | G50: Otro | H50: ProductoInterno | I50: Por valor | J50: no final | K50: Valor que se desea asignar al atributo productoInterno. | L50: Otro | M50: Builder
A51: public | B51: unidadMedidaInventario | C51: no static | D51: no final | E51: Asigna el valor recibido; si es nulo, asigna la instancia por defecto de UnidadMedida. | F51: unidadMedidaInventario | G51: Otro | H51: UnidadMedida | I51: Por valor | J51: no final | K51: Valor que se desea asignar al atributo unidadMedidaInventario. | L51: Otro | M51: Builder
A52: public | B52: stockMinimo | C52: no static | D52: no final | E52: Asigna el valor recibido; si es nulo o negativo, asigna 1. | F52: stockMinimo | G52: Otro | H52: BigDecimal | I52: Por valor | J52: no final | K52: Valor que se desea asignar al atributo stockMinimo. | L52: Otro | M52: Builder
A53: public | B53: build | C53: no static | D53: no final | E53: Crea la instancia de Inventario con los valores reunidos en el Builder, usando su constructor privado. | L53: Otro | M53: Inventario

Sheet Lote
A1: <-Volver al inicio
A2: =Clases!$A$1 -> Clase | B2: =Clases!A13 -> Lote
A3: =Clases!$B$1 -> Estereotipo | B3: =Clases!B13 -> class
A4: =Clases!$C$1 -> Descripción | B4: =Clases!C13 -> Representa un conjunto de unidades de un mismo insumo recibido en una compra o como reemplazo en un cambio, identificado para controlar su cantidad, saldo, fecha de vencimiento y trazabilidad dentro del inventario.
A5: Modificador acceso: | B5: public
A6: Tipo clase: | B6: no final
A7: Relaciones
A8: Relación | B8: Tipo relación | E8: Estructura
A9: Necesita de | B9: Asociación | E9: ProductoInterno
A10: Necesita de | B10: Asociación | E10: UnidadMedida
A11: Es usada por | B11: Asociación | E11: SalidaLote
A12: Es usada por | B12: Asociación | E12: MovimientoInventario
A14: Atributos
A15: Modificador de acceso | B15: Nombre | C15: Tipo de dato | E15: Tipo modificación atributo | F15: Tipo acceso atributo | G15: Valor por defecto | J15: Descripción atributo
C16: Tipo de dato | D16: ¿Cuál?
A17: private | B17: id | C17: Otro | D17: UUID | E17: no final | F17: no static | G17: 00000000-0000-0000-0000-000000000000 | J17: Identificador único del lote.
A18: private | B18: fechaVencimiento | C18: Otro | D18: LocalDate | E18: no final | F18: no static | G18: 1000-01-01 | J18: Fecha de vencimiento del producto contenido en el lote.
A19: private | B19: disponible | C19: boolean/Boolean | E19: no final | F19: no static | G19: false | J19: Indica si el lote todavía tiene existencias disponibles para consumo.
A20: private | B20: productoInterno | C20: Otro | D20: ProductoInterno | E20: no final | F20: no static | G20: Instancia por defecto de ProductoInterno | J20: Producto interno al que pertenece el lote.
A21: private | B21: cantidad | C21: Otro | D21: BigDecimal | E21: no final | F21: no static | G21: 0 | J21: Cantidad con la que ingresó el lote, ya convertida a la unidad de medida de inventario.
A22: private | B22: saldo | C22: Otro | D22: BigDecimal | E22: no final | F22: no static | G22: 0 | J22: Cantidad que aún queda disponible del lote, descontando las salidas registradas y el retiro por vencimiento (SalidaLote).
A23: private | B23: unidadMedidaInventario | C23: Otro | D23: UnidadMedida | E23: no final | F23: no static | G23: Instancia por defecto de UnidadMedida | J23: Unidad de medida estándar del lote: kg para peso, l para volumen y und para unidades.
A24: private | B24: numeroLote | C24: int/Integer | E24: no final | F24: no static | G24: 0 | J24: Número diferenciador del lote dentro de su respectivo producto interno.
A26: Constructores
A27: Modificador de acceso | B27: Nombre | C27: Tipo constructor | D27: Descripción | E27: Parámetros | M27: Excepciones
E28: Nombre | F28: Tipo de dato | G28: ¿Cuál? | H28: Tipo parámetro | I28: Tipo modificación atributo | J28: Descripción
A29: private | B29: =B2 -> Lote | C29: Parametrizado | D29: Constructor privado: crea la instancia de Lote copiando los valores ya saneados que reunió el Builder. Solo se invoca desde Builder.build(). | E29: builder | F29: Otro | G29: Builder | H29: Por valor | I29: no final | J29: Builder con los valores de los atributos de la clase.
A31: Métodos accesores
A32: Modificador de acceso | B32: Nombre | C32: Tipo método accesor | D32: Tipo modificación método | E32: Descripción | F32: Parámetros | L32: Tipo dato de retorno | N32: Excepciones
F33: Nombre | G33: Tipo de dato | H33: ¿Cuál? | I33: Tipo parámetro | J33: Tipo modificación atributo | K33: Descripción | L33: Tipo de dato | M33: ¿Cuál?
A34: public | B34: getId | C34: getter | D34: no final | E34: Método encargado de obtener el valor del atributo id. | L34: Otro | M34: UUID
A35: public | B35: getFechaVencimiento | C35: getter | D35: no final | E35: Método encargado de obtener el valor del atributo fechaVencimiento. | L35: Otro | M35: LocalDate
A36: public | B36: isDisponible | C36: getter | D36: no final | E36: Método encargado de obtener el valor del atributo disponible. | L36: boolean/Boolean
A37: public | B37: getProductoInterno | C37: getter | D37: no final | E37: Método encargado de obtener el valor del atributo productoInterno. | L37: Otro | M37: ProductoInterno
A38: public | B38: getCantidad | C38: getter | D38: no final | E38: Método encargado de obtener el valor del atributo cantidad. | L38: Otro | M38: BigDecimal
A39: public | B39: getSaldo | C39: getter | D39: no final | E39: Método encargado de obtener el valor del atributo saldo. | L39: Otro | M39: BigDecimal
A40: public | B40: getUnidadMedidaInventario | C40: getter | D40: no final | E40: Método encargado de obtener el valor del atributo unidadMedidaInventario. | L40: Otro | M40: UnidadMedida
A41: public | B41: getNumeroLote | C41: getter | D41: no final | E41: Método encargado de obtener el valor del atributo numeroLote. | L41: int/Integer
A43: Métodos
A44: Modificador de acceso | B44: Nombre | C44: Tipo acceso método | D44: Tipo modificación método | E44: Descripción | F44: Parámetros | L44: Tipo dato de retorno | N44: Excepciones
F45: Nombre | G45: Tipo de dato | H45: ¿Cuál? | I45: Tipo parámetro | J45: Tipo modificación atributo | K45: Descripción | L45: Tipo de dato | M45: ¿Cuál?
A46: public | B46: registrarLote | C46: no static | D46: no final | E46: Cuando se registra un detalle de compra o el reemplazo de un cambio, el sistema crea automáticamente el lote del producto interno con su cantidad, saldo, fecha de vencimiento y número de lote consecutivo. | F46: movimientoInventario | G46: Otro | H46: MovimientoInventario | I46: Por valor | J46: no final | K46: Movimiento de entrada que origina el lote: producto interno, cantidad, unidad de medida y fecha del movimiento. | L46: Otro | M46: Lote | N46: Los datos ingresados para registrar el lote no son válidos. El identificador generado ya está siendo utilizado por otro lote. El producto interno asociado al lote no existe o no es válido. La cantidad inicial no es mayor que cero o supera 10.000. La unidad de medida asociada a la cantidad del lote no es válida. El movimiento de inventario que origina el lote no existe o no es válido. Ya existe otro lote con el mismo NumeroLote para el mismo ProductoInterno. El número de lote no es el siguiente consecutivo del producto interno. Se intentó modificar manualmente un atributo que solo se calcula a partir de los movimientos de inventario.
A47: public | B47: recalcularSaldoDeLote | C47: no static | D47: no final | E47: Cada vez que se registra una salida por venta o por cambio, o un retiro (SalidaLote), el saldo del lote se recalcula automáticamente. | F47: movimientoInventario | G47: Otro | H47: MovimientoInventario | I47: Por valor | J47: no final | K47: Movimiento de Salida que afecta el lote y cantidad consumida. | L47: Otro | M47: Lote | N47: El recálculo dejaría el saldo por debajo de cero o por encima de la cantidad. El saldo del lote llegó a cero.
A48: public | B48: emitirAlertaDeVencimientoProximo | C48: no static | D48: no final | E48: Cuando la fecha de vencimiento de un lote está próxima a cumplirse, el sistema emite una alerta para que el administrador registre el Cambio (si el producto no es perecedero) o el retiro del lote con una SalidaLote (si es perecedero). | F48: lote | G48: Otro | H48: Lote | I48: Por valor | J48: no final | K48: Lote cuya fecha de vencimiento está próxima; por su producto interno se sabe si es perecedero. | L48: Otro | M48: Lote | N48: El producto interno asociado al lote no es válido, o no se puede determinar si es perecedero.
A49: public | B49: consultarLote | C49: static | D49: final | E49: Permite consultar la información de un lote específico, incluyendo su cantidad, saldo, fecha de vencimiento y disponibilidad. | F49: id | G49: Otro | H49: UUID | I49: Por valor | J49: no final | K49: Identificador único del lote que se desea consultar. | L49: Otro | M49: Lote | N49: No existe un lote con el identificador indicado.
A51: Builder (clase interna public static)
A52: Modificador de acceso | B52: Nombre | C52: Tipo acceso método | D52: Tipo modificación método | E52: Descripción | F52: Parámetros | L52: Tipo dato de retorno | N52: Excepciones
F53: Nombre | G53: Tipo de dato | H53: ¿Cuál? | I53: Tipo parámetro | J53: Tipo modificación atributo | K53: Descripción | L53: Tipo de dato | M53: ¿Cuál?
A54: public | B54: Builder | C54: no static | D54: no final | E54: Constructor del Builder: asigna a cada atributo su valor por defecto.
A55: public | B55: id | C55: no static | D55: no final | E55: Asigna el identificador recibido; si es nulo, asigna el identificador por defecto (00000000-0000-0000-0000-000000000000). | F55: id | G55: Otro | H55: UUID | I55: Por valor | J55: no final | K55: Valor que se desea asignar al atributo id. | L55: Otro | M55: Builder
A56: public | B56: fechaVencimiento | C56: no static | D56: no final | E56: Asigna la fecha recibida; si es nula, asigna la fecha por defecto 1000-01-01. | F56: fechaVencimiento | G56: Otro | H56: LocalDate | I56: Por valor | J56: no final | K56: Valor que se desea asignar al atributo fechaVencimiento. | L56: Otro | M56: Builder
A57: public | B57: disponible | C57: no static | D57: no final | E57: Asigna el valor recibido. | F57: disponible | G57: boolean/Boolean | I57: Por valor | J57: no final | K57: Valor que se desea asignar al atributo disponible. | L57: Otro | M57: Builder
A58: public | B58: productoInterno | C58: no static | D58: no final | E58: Asigna el valor recibido; si es nulo, asigna la instancia por defecto de ProductoInterno. | F58: productoInterno | G58: Otro | H58: ProductoInterno | I58: Por valor | J58: no final | K58: Valor que se desea asignar al atributo productoInterno. | L58: Otro | M58: Builder
A59: public | B59: cantidad | C59: no static | D59: no final | E59: Asigna el valor recibido; si es nulo o negativo, asigna 0. | F59: cantidad | G59: Otro | H59: BigDecimal | I59: Por valor | J59: no final | K59: Valor que se desea asignar al atributo cantidad. | L59: Otro | M59: Builder
A60: public | B60: saldo | C60: no static | D60: no final | E60: Asigna el valor recibido; si es nulo o negativo, asigna 0. | F60: saldo | G60: Otro | H60: BigDecimal | I60: Por valor | J60: no final | K60: Valor que se desea asignar al atributo saldo. | L60: Otro | M60: Builder
A61: public | B61: unidadMedidaInventario | C61: no static | D61: no final | E61: Asigna el valor recibido; si es nulo, asigna la instancia por defecto de UnidadMedida. | F61: unidadMedidaInventario | G61: Otro | H61: UnidadMedida | I61: Por valor | J61: no final | K61: Valor que se desea asignar al atributo unidadMedidaInventario. | L61: Otro | M61: Builder
A62: public | B62: numeroLote | C62: no static | D62: no final | E62: Asigna el valor recibido; si es nulo o negativo, asigna 0. | F62: numeroLote | G62: int/Integer | I62: Por valor | J62: no final | K62: Valor que se desea asignar al atributo numeroLote. | L62: Otro | M62: Builder
A63: public | B63: build | C63: no static | D63: no final | E63: Crea la instancia de Lote con los valores reunidos en el Builder, usando su constructor privado. | L63: Otro | M63: Lote

Sheet SalidaLote
A1: <-Volver al inicio
A2: =Clases!$A$1 -> Clase | B2: =Clases!A14 -> SalidaLote
A3: =Clases!$B$1 -> Estereotipo | B3: =Clases!B14 -> class
A4: =Clases!$C$1 -> Descripción | B4: =Clases!C14 -> Representa el retiro de una cantidad de producto de un lote próximo a vencer; un lote puede tener como máximo un retiro y este no genera movimiento de inventario.
A5: Modificador acceso: | B5: public
A6: Tipo clase: | B6: no final
A7: Relaciones
A8: Relación | B8: Tipo relación | E8: Estructura
A9: Necesita de | B9: Asociación | E9: Lote
A11: Atributos
A12: Modificador de acceso | B12: Nombre | C12: Tipo de dato | E12: Tipo modificación atributo | F12: Tipo acceso atributo | G12: Valor por defecto | J12: Descripción atributo
C13: Tipo de dato | D13: ¿Cuál?
A14: private | B14: id | C14: Otro | D14: UUID | E14: no final | F14: no static | G14: 00000000-0000-0000-0000-000000000000 | J14: Identificador único de cada retiro realizado sobre un lote.
A15: private | B15: lote | C15: Otro | D15: Lote | E15: no final | F15: no static | G15: Instancia por defecto de Lote | J15: Lote del cual se retira el producto; un lote solo puede tener un retiro.
A16: private | B16: cantidad | C16: Otro | D16: BigDecimal | E16: no final | F16: no static | G16: 0 | J16: Cantidad de producto que se retira efectivamente del lote; no puede superar su saldo.
A17: private | B17: fechaMovimiento | C17: Otro | D17: LocalDate | E17: no final | F17: no static | G17: 1000-01-01 | J17: Fecha en la que se realiza el retiro del producto del lote.
A19: Constructores
A20: Modificador de acceso | B20: Nombre | C20: Tipo constructor | D20: Descripción | E20: Parámetros | M20: Excepciones
E21: Nombre | F21: Tipo de dato | G21: ¿Cuál? | H21: Tipo parámetro | I21: Tipo modificación atributo | J21: Descripción
A22: private | B22: =B2 -> SalidaLote | C22: Parametrizado | D22: Constructor privado: crea la instancia de SalidaLote copiando los valores ya saneados que reunió el Builder. Solo se invoca desde Builder.build(). | E22: builder | F22: Otro | G22: Builder | H22: Por valor | I22: no final | J22: Builder con los valores de los atributos de la clase.
A24: Métodos accesores
A25: Modificador de acceso | B25: Nombre | C25: Tipo método accesor | D25: Tipo modificación método | E25: Descripción | F25: Parámetros | L25: Tipo dato de retorno | N25: Excepciones
F26: Nombre | G26: Tipo de dato | H26: ¿Cuál? | I26: Tipo parámetro | J26: Tipo modificación atributo | K26: Descripción | L26: Tipo de dato | M26: ¿Cuál?
A27: public | B27: getId | C27: getter | D27: no final | E27: Método encargado de obtener el valor del atributo id. | L27: Otro | M27: UUID
A28: public | B28: getLote | C28: getter | D28: no final | E28: Método encargado de obtener el valor del atributo lote. | L28: Otro | M28: Lote
A29: public | B29: getCantidad | C29: getter | D29: no final | E29: Método encargado de obtener el valor del atributo cantidad. | L29: Otro | M29: BigDecimal
A30: public | B30: getFechaMovimiento | C30: getter | D30: no final | E30: Método encargado de obtener el valor del atributo fechaMovimiento. | L30: Otro | M30: LocalDate
A32: Métodos
A33: Modificador de acceso | B33: Nombre | C33: Tipo acceso método | D33: Tipo modificación método | E33: Descripción | F33: Parámetros | L33: Tipo dato de retorno | N33: Excepciones
F34: Nombre | G34: Tipo de dato | H34: ¿Cuál? | I34: Tipo parámetro | J34: Tipo modificación atributo | K34: Descripción | L34: Tipo de dato | M34: ¿Cuál?
A35: public | B35: registrarSalidaDeLote | C35: no static | D35: no final | E35: Registra el retiro de una cantidad de un lote próximo a vencer, después de atender la alerta de vencimiento. | F35: salidaLote | G35: Otro | H35: SalidaLote | I35: Por valor | J35: no final | K35: Lote, cantidad y fecha del retiro. | L35: Otro | M35: SalidaLote | N35: Los datos de la salida no son válidos. El lote no existe o no tiene saldo disponible. La cantidad a retirar supera el saldo del lote. El lote ya tiene una salida registrada. No fue posible actualizar el saldo del lote o el inventario.
A36: public | B36: consultarSalidaDeLote | C36: static | D36: final | E36: Permite consultar un retiro registrado sobre un lote. | F36: id | G36: Otro | H36: UUID | I36: Por valor | J36: no final | K36: Identificador de la salida de lote. | L36: Otro | M36: SalidaLote | N36: No existe una salida de lote con el identificador indicado.
A38: Builder (clase interna public static)
A39: Modificador de acceso | B39: Nombre | C39: Tipo acceso método | D39: Tipo modificación método | E39: Descripción | F39: Parámetros | L39: Tipo dato de retorno | N39: Excepciones
F40: Nombre | G40: Tipo de dato | H40: ¿Cuál? | I40: Tipo parámetro | J40: Tipo modificación atributo | K40: Descripción | L40: Tipo de dato | M40: ¿Cuál?
A41: public | B41: Builder | C41: no static | D41: no final | E41: Constructor del Builder: asigna a cada atributo su valor por defecto.
A42: public | B42: id | C42: no static | D42: no final | E42: Asigna el identificador recibido; si es nulo, asigna el identificador por defecto (00000000-0000-0000-0000-000000000000). | F42: id | G42: Otro | H42: UUID | I42: Por valor | J42: no final | K42: Valor que se desea asignar al atributo id. | L42: Otro | M42: Builder
A43: public | B43: lote | C43: no static | D43: no final | E43: Asigna el valor recibido; si es nulo, asigna la instancia por defecto de Lote. | F43: lote | G43: Otro | H43: Lote | I43: Por valor | J43: no final | K43: Valor que se desea asignar al atributo lote. | L43: Otro | M43: Builder
A44: public | B44: cantidad | C44: no static | D44: no final | E44: Asigna el valor recibido; si es nulo o negativo, asigna 0. | F44: cantidad | G44: Otro | H44: BigDecimal | I44: Por valor | J44: no final | K44: Valor que se desea asignar al atributo cantidad. | L44: Otro | M44: Builder
A45: public | B45: fechaMovimiento | C45: no static | D45: no final | E45: Asigna la fecha recibida; si es nula, asigna la fecha por defecto 1000-01-01. | F45: fechaMovimiento | G45: Otro | H45: LocalDate | I45: Por valor | J45: no final | K45: Valor que se desea asignar al atributo fechaMovimiento. | L45: Otro | M45: Builder
A46: public | B46: build | C46: no static | D46: no final | E46: Crea la instancia de SalidaLote con los valores reunidos en el Builder, usando su constructor privado. | L46: Otro | M46: SalidaLote

Sheet Compra
A1: <-Volver al inicio
A2: =Clases!$A$1 -> Clase | B2: =Clases!A15 -> Compra
A3: =Clases!$B$1 -> Estereotipo | B3: =Clases!B15 -> class
A4: =Clases!$C$1 -> Descripción | B4: =Clases!C15 -> Representa la adquisición de insumos o productos que realiza la pizzería a un proveedor para abastecer las necesidades de su operación.
A5: Modificador acceso: | B5: public
A6: Tipo clase: | B6: no final
A7: Relaciones
A8: Relación | B8: Tipo relación | E8: Estructura
A9: Necesita de | B9: Asociación | E9: Proveedor
A10: Es usada por | B10: Composición | E10: DetalleCompra
A12: Atributos
A13: Modificador de acceso | B13: Nombre | C13: Tipo de dato | E13: Tipo modificación atributo | F13: Tipo acceso atributo | G13: Valor por defecto | J13: Descripción atributo
C14: Tipo de dato | D14: ¿Cuál?
A15: private | B15: id | C15: Otro | D15: UUID | E15: no final | F15: no static | G15: 00000000-0000-0000-0000-000000000000 | J15: Identificador único de la compra.
A16: private | B16: proveedor | C16: Otro | D16: Proveedor | E16: no final | F16: no static | G16: Instancia por defecto de Proveedor | J16: Proveedor al que se le realizó la compra.
A17: private | B17: fechaCompra | C17: Otro | D17: LocalDate | E17: no final | F17: no static | G17: 1000-01-01 | J17: Fecha en la que se efectuó la compra.
A18: private | B18: numeroFactura | C18: String | E18: no final | F18: no static | G18: "" (cadena vacía) | J18: Número de factura entregado por el proveedor al momento de la compra.
A19: private | B19: total | C19: Otro | D19: BigDecimal | E19: no final | F19: no static | G19: 0 | J19: Valor monetario total de la compra, calculado como la suma de los precios de compra de sus detalles; no puede superar 5.000.000.
A21: Constructores
A22: Modificador de acceso | B22: Nombre | C22: Tipo constructor | D22: Descripción | E22: Parámetros | M22: Excepciones
E23: Nombre | F23: Tipo de dato | G23: ¿Cuál? | H23: Tipo parámetro | I23: Tipo modificación atributo | J23: Descripción
A24: private | B24: =B2 -> Compra | C24: Parametrizado | D24: Constructor privado: crea la instancia de Compra copiando los valores ya saneados que reunió el Builder. Solo se invoca desde Builder.build(). | E24: builder | F24: Otro | G24: Builder | H24: Por valor | I24: no final | J24: Builder con los valores de los atributos de la clase.
A26: Métodos accesores
A27: Modificador de acceso | B27: Nombre | C27: Tipo método accesor | D27: Tipo modificación método | E27: Descripción | F27: Parámetros | L27: Tipo dato de retorno | N27: Excepciones
F28: Nombre | G28: Tipo de dato | H28: ¿Cuál? | I28: Tipo parámetro | J28: Tipo modificación atributo | K28: Descripción | L28: Tipo de dato | M28: ¿Cuál?
A29: public | B29: getId | C29: getter | D29: no final | E29: Método encargado de obtener el valor del atributo id. | L29: Otro | M29: UUID
A30: public | B30: getProveedor | C30: getter | D30: no final | E30: Método encargado de obtener el valor del atributo proveedor. | L30: Otro | M30: Proveedor
A31: public | B31: getFechaCompra | C31: getter | D31: no final | E31: Método encargado de obtener el valor del atributo fechaCompra. | L31: Otro | M31: LocalDate
A32: public | B32: getNumeroFactura | C32: getter | D32: no final | E32: Método encargado de obtener el valor del atributo numeroFactura. | L32: String
A33: public | B33: getTotal | C33: getter | D33: no final | E33: Método encargado de obtener el valor del atributo total. | L33: Otro | M33: BigDecimal
A35: Métodos
A36: Modificador de acceso | B36: Nombre | C36: Tipo acceso método | D36: Tipo modificación método | E36: Descripción | F36: Parámetros | L36: Tipo dato de retorno | N36: Excepciones
F37: Nombre | G37: Tipo de dato | H37: ¿Cuál? | I37: Tipo parámetro | J37: Tipo modificación atributo | K37: Descripción | L37: Tipo de dato | M37: ¿Cuál?
A38: public | B38: registrarCompra | C38: no static | D38: no final | E38: Registrar una nueva compra asociada a un proveedor y a la pizzería correspondiente, dejando constancia de la operación de adquisición. | F38: compra | G38: Otro | H38: Compra | I38: Por valor | J38: no final | K38: Información necesaria para registrar la compra. | L38: Otro | M38: Compra | N38: Los datos ingresados para registrar la compra no son válidos. El proveedor asociado a la compra no existe en el sistema. Ya existe otra compra registrada con el mismo Proveedor y el mismo NumeroFactura. El proveedor asociado a la compra se encuentra retirado o inactivo. El total calculado no corresponde a la suma de los detalles o supera 5.000.000.
A39: public | B39: modificarCompra | C39: no static | D39: no final | E39: Permite corregir la información de una compra existente antes de que tenga movimientos de inventario asociados. | F39: compra | G39: Otro | H39: Compra | I39: Por valor | J39: no final | K39: Identificador de la compra y datos que se desean modificar. | L39: Otro | M39: Compra | N39: La compra no existe con el identificador indicado. Los nuevos datos de la compra no son válidos. La modificación deja dos compras con el mismo Proveedor y el mismo NumeroFactura. El proveedor indicado se encuentra retirado o inactivo.
A40: public | B40: eliminarCompra | C40: no static | D40: no final | E40: Permite eliminar una compra que no tenga detalles de compra asociados que deban conservarse para mantener la trazabilidad. | F40: id | G40: Otro | H40: UUID | I40: Por valor | J40: no final | K40: Identificador de la compra que se desea eliminar. | L40: void | N40: La compra que se desea eliminar no existe. La compra tiene detalles de compra asociados que deben conservarse.
A41: public | B41: consultarCompra | C41: static | D41: final | E41: Consultar la información registrada de una compra para conocer su proveedor, fecha, pizzería y los detalles asociados. | F41: id | G41: Otro | H41: UUID | I41: Por valor | J41: no final | K41: Identificador que permite localizar la compra que se desea consultar. | L41: Otro | M41: Compra | N41: No existe una compra asociada al identificador indicado.
A43: Builder (clase interna public static)
A44: Modificador de acceso | B44: Nombre | C44: Tipo acceso método | D44: Tipo modificación método | E44: Descripción | F44: Parámetros | L44: Tipo dato de retorno | N44: Excepciones
F45: Nombre | G45: Tipo de dato | H45: ¿Cuál? | I45: Tipo parámetro | J45: Tipo modificación atributo | K45: Descripción | L45: Tipo de dato | M45: ¿Cuál?
A46: public | B46: Builder | C46: no static | D46: no final | E46: Constructor del Builder: asigna a cada atributo su valor por defecto.
A47: public | B47: id | C47: no static | D47: no final | E47: Asigna el identificador recibido; si es nulo, asigna el identificador por defecto (00000000-0000-0000-0000-000000000000). | F47: id | G47: Otro | H47: UUID | I47: Por valor | J47: no final | K47: Valor que se desea asignar al atributo id. | L47: Otro | M47: Builder
A48: public | B48: proveedor | C48: no static | D48: no final | E48: Asigna el valor recibido; si es nulo, asigna la instancia por defecto de Proveedor. | F48: proveedor | G48: Otro | H48: Proveedor | I48: Por valor | J48: no final | K48: Valor que se desea asignar al atributo proveedor. | L48: Otro | M48: Builder
A49: public | B49: fechaCompra | C49: no static | D49: no final | E49: Asigna la fecha recibida; si es nula, asigna la fecha por defecto 1000-01-01. | F49: fechaCompra | G49: Otro | H49: LocalDate | I49: Por valor | J49: no final | K49: Valor que se desea asignar al atributo fechaCompra. | L49: Otro | M49: Builder
A50: public | B50: numeroFactura | C50: no static | D50: no final | E50: Asigna el texto recibido sin espacios en blanco al inicio y al final; si es nulo, asigna una cadena vacía. | F50: numeroFactura | G50: String | I50: Por valor | J50: no final | K50: Valor que se desea asignar al atributo numeroFactura. | L50: Otro | M50: Builder
A51: public | B51: total | C51: no static | D51: no final | E51: Asigna el valor recibido; si es nulo o negativo, asigna 0. | F51: total | G51: Otro | H51: BigDecimal | I51: Por valor | J51: no final | K51: Valor que se desea asignar al atributo total. | L51: Otro | M51: Builder
A52: public | B52: build | C52: no static | D52: no final | E52: Crea la instancia de Compra con los valores reunidos en el Builder, usando su constructor privado. | L52: Otro | M52: Compra

Sheet DetalleCompra
A1: <-Volver al inicio
A2: =Clases!$A$1 -> Clase | B2: =Clases!A16 -> DetalleCompra
A3: =Clases!$B$1 -> Estereotipo | B3: =Clases!B16 -> class
A4: =Clases!$C$1 -> Descripción | B4: =Clases!C16 -> Representa cada uno de los insumos o productos adquiridos dentro de una compra, especificando qué se compró y en qué cantidad.
A5: Modificador acceso: | B5: public
A6: Tipo clase: | B6: no final
A7: Relaciones
A8: Relación | B8: Tipo relación | E8: Estructura
A9: Necesita de | B9: Asociación | E9: ProductoInterno
A10: Necesita de | B10: Asociación | E10: UnidadMedida
A11: Necesita de | B11: Composición | E11: Compra
A12: Necesita de | B12: Asociación | E12: TipoMovimiento
A14: Atributos
A15: Modificador de acceso | B15: Nombre | C15: Tipo de dato | E15: Tipo modificación atributo | F15: Tipo acceso atributo | G15: Valor por defecto | J15: Descripción atributo
C16: Tipo de dato | D16: ¿Cuál?
A17: private | B17: id | C17: Otro | D17: UUID | E17: no final | F17: no static | G17: 00000000-0000-0000-0000-000000000000 | J17: Identificador único del detalle de compra.
A18: private | B18: productoInterno | C18: Otro | D18: ProductoInterno | E18: no final | F18: no static | G18: Instancia por defecto de ProductoInterno | J18: Producto interno adquirido en este detalle de compra.
A19: private | B19: cantidad | C19: Otro | D19: BigDecimal | E19: no final | F19: no static | G19: 0 | J19: Cantidad adquirida del producto interno.
A20: private | B20: unidadMedida | C20: Otro | D20: UnidadMedida | E20: no final | F20: no static | G20: Instancia por defecto de UnidadMedida | J20: Unidad de medida en la que se realizó la compra del producto interno.
A21: private | B21: precioCompra | C21: Otro | D21: BigDecimal | E21: no final | F21: no static | G21: 0 | J21: Valor monetario pagado por el producto interno adquirido.
A22: private | B22: fechaVencimiento | C22: Otro | D22: LocalDate | E22: no final | F22: no static | G22: 1000-01-01 | J22: Fecha de vencimiento del producto, cuando aplica (solo productos no perecederos).
A23: private | B23: compra | C23: Otro | D23: Compra | E23: no final | F23: no static | G23: Instancia por defecto de Compra | J23: Compra a la que pertenece este detalle.
A24: private | B24: tipoMovimiento | C24: Otro | D24: TipoMovimiento | E24: no final | F24: no static | G24: Instancia por defecto de TipoMovimiento | J24: Código de la operación (TipoMovimiento) propio de este detalle de compra; es el mismo que lleva su movimiento de entrada.
A26: Constructores
A27: Modificador de acceso | B27: Nombre | C27: Tipo constructor | D27: Descripción | E27: Parámetros | M27: Excepciones
E28: Nombre | F28: Tipo de dato | G28: ¿Cuál? | H28: Tipo parámetro | I28: Tipo modificación atributo | J28: Descripción
A29: private | B29: =B2 -> DetalleCompra | C29: Parametrizado | D29: Constructor privado: crea la instancia de DetalleCompra copiando los valores ya saneados que reunió el Builder. Solo se invoca desde Builder.build(). | E29: builder | F29: Otro | G29: Builder | H29: Por valor | I29: no final | J29: Builder con los valores de los atributos de la clase.
A31: Métodos accesores
A32: Modificador de acceso | B32: Nombre | C32: Tipo método accesor | D32: Tipo modificación método | E32: Descripción | F32: Parámetros | L32: Tipo dato de retorno | N32: Excepciones
F33: Nombre | G33: Tipo de dato | H33: ¿Cuál? | I33: Tipo parámetro | J33: Tipo modificación atributo | K33: Descripción | L33: Tipo de dato | M33: ¿Cuál?
A34: public | B34: getId | C34: getter | D34: no final | E34: Método encargado de obtener el valor del atributo id. | L34: Otro | M34: UUID
A35: public | B35: getProductoInterno | C35: getter | D35: no final | E35: Método encargado de obtener el valor del atributo productoInterno. | L35: Otro | M35: ProductoInterno
A36: public | B36: getCantidad | C36: getter | D36: no final | E36: Método encargado de obtener el valor del atributo cantidad. | L36: Otro | M36: BigDecimal
A37: public | B37: getUnidadMedida | C37: getter | D37: no final | E37: Método encargado de obtener el valor del atributo unidadMedida. | L37: Otro | M37: UnidadMedida
A38: public | B38: getPrecioCompra | C38: getter | D38: no final | E38: Método encargado de obtener el valor del atributo precioCompra. | L38: Otro | M38: BigDecimal
A39: public | B39: getFechaVencimiento | C39: getter | D39: no final | E39: Método encargado de obtener el valor del atributo fechaVencimiento. | L39: Otro | M39: LocalDate
A40: public | B40: getCompra | C40: getter | D40: no final | E40: Método encargado de obtener el valor del atributo compra. | L40: Otro | M40: Compra
A41: public | B41: getTipoMovimiento | C41: getter | D41: no final | E41: Método encargado de obtener el valor del atributo tipoMovimiento. | L41: Otro | M41: TipoMovimiento
A43: Métodos
A44: Modificador de acceso | B44: Nombre | C44: Tipo acceso método | D44: Tipo modificación método | E44: Descripción | F44: Parámetros | L44: Tipo dato de retorno | N44: Excepciones
F45: Nombre | G45: Tipo de dato | H45: ¿Cuál? | I45: Tipo parámetro | J45: Tipo modificación atributo | K45: Descripción | L45: Tipo de dato | M45: ¿Cuál?
A46: public | B46: registrarDetalleDeCompra | C46: no static | D46: no final | E46: Registrar un producto adquirido dentro de una compra, indicando la cantidad, unidad de medida, precio de compra y, cuando corresponda, su fecha de vencimiento. | F46: detalleCompra | G46: Otro | H46: DetalleCompra | I46: Por valor | J46: no final | K46: Información necesaria para registrar el detalle de la compra. | L46: Otro | M46: DetalleCompra | N46: Los datos ingresados para registrar el detalle de compra no son válidos. La compra a la que pertenece el detalle de compra no existe en el sistema. El producto interno asociado al detalle de compra no existe en el sistema. El producto interno se encuentra inactivo. Se registró una fecha de vencimiento real para un producto interno perecedero, o no se registró para uno no perecedero cuando sí debía. La cantidad no es mayor que cero o supera 100.000. El precio de compra es negativo o supera 5.000.000. La unidad de medida utilizada para el detalle de compra no es válida. El mismo producto interno ya está registrado dentro de la misma compra con la misma fecha de vencimiento. No fue posible generar el TipoMovimiento del detalle. No fue posible crear el lote del producto interno. No fue posible registrar la entrada de inventario. El total recalculado de la compra supera 5.000.000.
A47: public | B47: modificarDetalleDeCompra | C47: no static | D47: no final | E47: Actualizar la información de un detalle de compra existente sin comprometer la trazabilidad de los movimientos de inventario ya generados. | F47: detalleCompra | G47: Otro | H47: DetalleCompra | I47: Por valor | J47: no final | K47: Identificador del detalle y datos que se desean modificar. | L47: Otro | M47: DetalleCompra | N47: El detalle de compra que se desea modificar no existe. Los nuevos datos del detalle de compra no son válidos. La nueva cantidad no es mayor que cero o supera 100.000. El nuevo precio de compra es negativo o supera 5.000.000. El total recalculado de la compra supera 5.000.000.
A48: public | B48: eliminarDetalleDeCompra | C48: no static | D48: no final | E48: Permite eliminar un detalle de compra que no haya generado un lote asociado que deba conservarse para mantener la trazabilidad. | F48: id | G48: Otro | H48: UUID | I48: Por valor | J48: no final | K48: Identificador del detalle de compra que se desea eliminar. | L48: void | N48: El detalle de compra que se desea eliminar no existe. El detalle de compra ya generó un lote asociado que debe conservarse. No fue posible recalcular el total de la compra.
A50: Builder (clase interna public static)
A51: Modificador de acceso | B51: Nombre | C51: Tipo acceso método | D51: Tipo modificación método | E51: Descripción | F51: Parámetros | L51: Tipo dato de retorno | N51: Excepciones
F52: Nombre | G52: Tipo de dato | H52: ¿Cuál? | I52: Tipo parámetro | J52: Tipo modificación atributo | K52: Descripción | L52: Tipo de dato | M52: ¿Cuál?
A53: public | B53: Builder | C53: no static | D53: no final | E53: Constructor del Builder: asigna a cada atributo su valor por defecto.
A54: public | B54: id | C54: no static | D54: no final | E54: Asigna el identificador recibido; si es nulo, asigna el identificador por defecto (00000000-0000-0000-0000-000000000000). | F54: id | G54: Otro | H54: UUID | I54: Por valor | J54: no final | K54: Valor que se desea asignar al atributo id. | L54: Otro | M54: Builder
A55: public | B55: productoInterno | C55: no static | D55: no final | E55: Asigna el valor recibido; si es nulo, asigna la instancia por defecto de ProductoInterno. | F55: productoInterno | G55: Otro | H55: ProductoInterno | I55: Por valor | J55: no final | K55: Valor que se desea asignar al atributo productoInterno. | L55: Otro | M55: Builder
A56: public | B56: cantidad | C56: no static | D56: no final | E56: Asigna el valor recibido; si es nulo o negativo, asigna 0. | F56: cantidad | G56: Otro | H56: BigDecimal | I56: Por valor | J56: no final | K56: Valor que se desea asignar al atributo cantidad. | L56: Otro | M56: Builder
A57: public | B57: unidadMedida | C57: no static | D57: no final | E57: Asigna el valor recibido; si es nulo, asigna la instancia por defecto de UnidadMedida. | F57: unidadMedida | G57: Otro | H57: UnidadMedida | I57: Por valor | J57: no final | K57: Valor que se desea asignar al atributo unidadMedida. | L57: Otro | M57: Builder
A58: public | B58: precioCompra | C58: no static | D58: no final | E58: Asigna el valor recibido; si es nulo o negativo, asigna 0. | F58: precioCompra | G58: Otro | H58: BigDecimal | I58: Por valor | J58: no final | K58: Valor que se desea asignar al atributo precioCompra. | L58: Otro | M58: Builder
A59: public | B59: fechaVencimiento | C59: no static | D59: no final | E59: Asigna la fecha recibida; si es nula, asigna la fecha por defecto 1000-01-01. | F59: fechaVencimiento | G59: Otro | H59: LocalDate | I59: Por valor | J59: no final | K59: Valor que se desea asignar al atributo fechaVencimiento. | L59: Otro | M59: Builder
A60: public | B60: compra | C60: no static | D60: no final | E60: Asigna el valor recibido; si es nulo, asigna la instancia por defecto de Compra. | F60: compra | G60: Otro | H60: Compra | I60: Por valor | J60: no final | K60: Valor que se desea asignar al atributo compra. | L60: Otro | M60: Builder
A61: public | B61: tipoMovimiento | C61: no static | D61: no final | E61: Asigna el valor recibido; si es nulo, asigna la instancia por defecto de TipoMovimiento. | F61: tipoMovimiento | G61: Otro | H61: TipoMovimiento | I61: Por valor | J61: no final | K61: Valor que se desea asignar al atributo tipoMovimiento. | L61: Otro | M61: Builder
A62: public | B62: build | C62: no static | D62: no final | E62: Crea la instancia de DetalleCompra con los valores reunidos en el Builder, usando su constructor privado. | L62: Otro | M62: DetalleCompra

Sheet DetalleVenta
A1: <-Volver al inicio
A2: =Clases!$A$1 -> Clase | B2: =Clases!A17 -> DetalleVenta
A3: =Clases!$B$1 -> Estereotipo | B3: =Clases!B17 -> class
A4: =Clases!$C$1 -> Descripción | B4: =Clases!C17 -> Representa cada uno de los productos incluidos en una venta, registrando la cantidad adquirida y el valor correspondiente a cada producto.
A5: Modificador acceso: | B5: public
A6: Tipo clase: | B6: no final
A7: Relaciones
A8: Relación | B8: Tipo relación | E8: Estructura
A9: Necesita de | B9: Composición | E9: Venta
A10: Necesita de | B10: Asociación | E10: Producto
A11: Es usada por | B11: Composición | E11: ConsumoVenta
A13: Atributos
A14: Modificador de acceso | B14: Nombre | C14: Tipo de dato | E14: Tipo modificación atributo | F14: Tipo acceso atributo | G14: Valor por defecto | J14: Descripción atributo
C15: Tipo de dato | D15: ¿Cuál?
A16: private | B16: id | C16: Otro | D16: UUID | E16: no final | F16: no static | G16: 00000000-0000-0000-0000-000000000000 | J16: Identificador único del detalle de venta.
A17: private | B17: venta | C17: Otro | D17: Venta | E17: no final | F17: no static | G17: Instancia por defecto de Venta | J17: Venta a la que pertenece este detalle.
A18: private | B18: cantidad | C18: int/Integer | E18: no final | F18: no static | G18: 0 | J18: Cantidad solicitada del producto por el cliente.
A19: private | B19: producto | C19: Otro | D19: Producto | E19: no final | F19: no static | G19: Instancia por defecto de Producto | J19: Producto solicitado por el cliente.
A20: private | B20: precioProducto | C20: Otro | D20: BigDecimal | E20: no final | F20: no static | G20: 0 | J20: Precio del producto vigente en el momento de la venta.
A21: private | B21: subtotal | C21: Otro | D21: BigDecimal | E21: no final | F21: no static | G21: 0 | J21: Valor calculado a partir de la cantidad solicitada y el precio del producto.
A23: Constructores
A24: Modificador de acceso | B24: Nombre | C24: Tipo constructor | D24: Descripción | E24: Parámetros | M24: Excepciones
E25: Nombre | F25: Tipo de dato | G25: ¿Cuál? | H25: Tipo parámetro | I25: Tipo modificación atributo | J25: Descripción
A26: private | B26: =B2 -> DetalleVenta | C26: Parametrizado | D26: Constructor privado: crea la instancia de DetalleVenta copiando los valores ya saneados que reunió el Builder. Solo se invoca desde Builder.build(). | E26: builder | F26: Otro | G26: Builder | H26: Por valor | I26: no final | J26: Builder con los valores de los atributos de la clase.
A28: Métodos accesores
A29: Modificador de acceso | B29: Nombre | C29: Tipo método accesor | D29: Tipo modificación método | E29: Descripción | F29: Parámetros | L29: Tipo dato de retorno | N29: Excepciones
F30: Nombre | G30: Tipo de dato | H30: ¿Cuál? | I30: Tipo parámetro | J30: Tipo modificación atributo | K30: Descripción | L30: Tipo de dato | M30: ¿Cuál?
A31: public | B31: getId | C31: getter | D31: no final | E31: Método encargado de obtener el valor del atributo id. | L31: Otro | M31: UUID
A32: public | B32: getVenta | C32: getter | D32: no final | E32: Método encargado de obtener el valor del atributo venta. | L32: Otro | M32: Venta
A33: public | B33: getCantidad | C33: getter | D33: no final | E33: Método encargado de obtener el valor del atributo cantidad. | L33: int/Integer
A34: public | B34: getProducto | C34: getter | D34: no final | E34: Método encargado de obtener el valor del atributo producto. | L34: Otro | M34: Producto
A35: public | B35: getPrecioProducto | C35: getter | D35: no final | E35: Método encargado de obtener el valor del atributo precioProducto. | L35: Otro | M35: BigDecimal
A36: public | B36: getSubtotal | C36: getter | D36: no final | E36: Método encargado de obtener el valor del atributo subtotal. | L36: Otro | M36: BigDecimal
A38: Métodos
A39: Modificador de acceso | B39: Nombre | C39: Tipo acceso método | D39: Tipo modificación método | E39: Descripción | F39: Parámetros | L39: Tipo dato de retorno | N39: Excepciones
F40: Nombre | G40: Tipo de dato | H40: ¿Cuál? | I40: Tipo parámetro | J40: Tipo modificación atributo | K40: Descripción | L40: Tipo de dato | M40: ¿Cuál?
A41: public | B41: agregarProductoAVenta | C41: no static | D41: no final | E41: Permite incorporar a la venta un producto solicitado. | F41: detalleVenta | G41: Otro | H41: DetalleVenta | I41: Por valor | J41: no final | K41: Información necesaria para incorporar el producto a la venta. | L41: Otro | M41: DetalleVenta | N41: La venta a la que se agrega el producto no existe. La venta ya fue confirmada. La información del detalle de venta no es válida o está incompleta. El producto no existe o se encuentra inactivo. La cantidad no es un número entero entre 1 y 1000. El precio registrado no corresponde al precio vigente del producto en el momento de la venta. El producto ya está en la venta. El subtotal no corresponde a la cantidad por el precio.
A42: public | B42: modificarCantidadDeProducto | C42: no static | D42: no final | E42: Permite ajustar la cantidad de un producto incluido en la venta. | F42: detalleVenta | G42: Otro | H42: DetalleVenta | I42: Por valor | J42: no final | K42: Identificador del detalle y nueva información necesaria para modificar la cantidad. | L42: Otro | M42: DetalleVenta | N42: El detalle de venta que se pretende modificar no existe. La venta ya fue confirmada. La nueva cantidad no es un número entero entre 1 y 1000. El subtotal no corresponde a la cantidad por el precio.
A43: public | B43: retirarProductoDeLaVenta | C43: no static | D43: no final | E43: Permite quitar un producto de una venta que todavía no ha sido confirmada. | F43: id | G43: Otro | H43: UUID | I43: Por valor | J43: no final | K43: Identificador del detalle de venta. | L43: void | N43: El detalle de venta que se desea retirar no existe. La venta ya fue confirmada.
A45: Builder (clase interna public static)
A46: Modificador de acceso | B46: Nombre | C46: Tipo acceso método | D46: Tipo modificación método | E46: Descripción | F46: Parámetros | L46: Tipo dato de retorno | N46: Excepciones
F47: Nombre | G47: Tipo de dato | H47: ¿Cuál? | I47: Tipo parámetro | J47: Tipo modificación atributo | K47: Descripción | L47: Tipo de dato | M47: ¿Cuál?
A48: public | B48: Builder | C48: no static | D48: no final | E48: Constructor del Builder: asigna a cada atributo su valor por defecto.
A49: public | B49: id | C49: no static | D49: no final | E49: Asigna el identificador recibido; si es nulo, asigna el identificador por defecto (00000000-0000-0000-0000-000000000000). | F49: id | G49: Otro | H49: UUID | I49: Por valor | J49: no final | K49: Valor que se desea asignar al atributo id. | L49: Otro | M49: Builder
A50: public | B50: venta | C50: no static | D50: no final | E50: Asigna el valor recibido; si es nulo, asigna la instancia por defecto de Venta. | F50: venta | G50: Otro | H50: Venta | I50: Por valor | J50: no final | K50: Valor que se desea asignar al atributo venta. | L50: Otro | M50: Builder
A51: public | B51: cantidad | C51: no static | D51: no final | E51: Asigna el valor recibido; si es nulo o negativo, asigna 0. | F51: cantidad | G51: int/Integer | I51: Por valor | J51: no final | K51: Valor que se desea asignar al atributo cantidad. | L51: Otro | M51: Builder
A52: public | B52: producto | C52: no static | D52: no final | E52: Asigna el valor recibido; si es nulo, asigna la instancia por defecto de Producto. | F52: producto | G52: Otro | H52: Producto | I52: Por valor | J52: no final | K52: Valor que se desea asignar al atributo producto. | L52: Otro | M52: Builder
A53: public | B53: precioProducto | C53: no static | D53: no final | E53: Asigna el valor recibido; si es nulo o negativo, asigna 0. | F53: precioProducto | G53: Otro | H53: BigDecimal | I53: Por valor | J53: no final | K53: Valor que se desea asignar al atributo precioProducto. | L53: Otro | M53: Builder
A54: public | B54: subtotal | C54: no static | D54: no final | E54: Asigna el valor recibido; si es nulo o negativo, asigna 0. | F54: subtotal | G54: Otro | H54: BigDecimal | I54: Por valor | J54: no final | K54: Valor que se desea asignar al atributo subtotal. | L54: Otro | M54: Builder
A55: public | B55: build | C55: no static | D55: no final | E55: Crea la instancia de DetalleVenta con los valores reunidos en el Builder, usando su constructor privado. | L55: Otro | M55: DetalleVenta

Sheet ConsumoVenta
A1: <-Volver al inicio
A2: =Clases!$A$1 -> Clase | B2: =Clases!A18 -> ConsumoVenta
A3: =Clases!$B$1 -> Estereotipo | B3: =Clases!B18 -> class
A4: =Clases!$C$1 -> Descripción | B4: =Clases!C18 -> Representa los productos internos que se consumen por cada detalle de venta, según la receta del producto vendido o su producto interno asociado.
A5: Modificador acceso: | B5: public
A6: Tipo clase: | B6: no final
A7: Relaciones
A8: Relación | B8: Tipo relación | E8: Estructura
A9: Necesita de | B9: Composición | E9: DetalleVenta
A10: Necesita de | B10: Asociación | E10: ProductoInterno
A11: Necesita de | B11: Asociación | E11: UnidadMedida
A12: Necesita de | B12: Asociación | E12: TipoMovimiento
A14: Atributos
A15: Modificador de acceso | B15: Nombre | C15: Tipo de dato | E15: Tipo modificación atributo | F15: Tipo acceso atributo | G15: Valor por defecto | J15: Descripción atributo
C16: Tipo de dato | D16: ¿Cuál?
A17: private | B17: id | C17: Otro | D17: UUID | E17: no final | F17: no static | G17: 00000000-0000-0000-0000-000000000000 | J17: Identificador único de cada consumo de venta.
A18: private | B18: detalleVenta | C18: Otro | D18: DetalleVenta | E18: no final | F18: no static | G18: Instancia por defecto de DetalleVenta | J18: Detalle de venta que origina el consumo.
A19: private | B19: productoInterno | C19: Otro | D19: ProductoInterno | E19: no final | F19: no static | G19: Instancia por defecto de ProductoInterno | J19: Producto interno que se consume según la receta del producto vendido (o el propio producto interno si se vende directamente).
A20: private | B20: cantidad | C20: Otro | D20: BigDecimal | E20: no final | F20: no static | G20: 0 | J20: Cantidad del producto interno que se consume: la cantidad de la receta multiplicada por la cantidad vendida.
A21: private | B21: unidadMedida | C21: Otro | D21: UnidadMedida | E21: no final | F21: no static | G21: Instancia por defecto de UnidadMedida | J21: Unidad de medida de la cantidad consumida; es la misma de la receta (g, ml o und).
A22: private | B22: tipoMovimiento | C22: Otro | D22: TipoMovimiento | E22: no final | F22: no static | G22: Instancia por defecto de TipoMovimiento | J22: Código de la operación (TipoMovimiento) propio de este consumo; es el mismo que lleva su movimiento de salida.
A24: Constructores
A25: Modificador de acceso | B25: Nombre | C25: Tipo constructor | D25: Descripción | E25: Parámetros | M25: Excepciones
E26: Nombre | F26: Tipo de dato | G26: ¿Cuál? | H26: Tipo parámetro | I26: Tipo modificación atributo | J26: Descripción
A27: private | B27: =B2 -> ConsumoVenta | C27: Parametrizado | D27: Constructor privado: crea la instancia de ConsumoVenta copiando los valores ya saneados que reunió el Builder. Solo se invoca desde Builder.build(). | E27: builder | F27: Otro | G27: Builder | H27: Por valor | I27: no final | J27: Builder con los valores de los atributos de la clase.
A29: Métodos accesores
A30: Modificador de acceso | B30: Nombre | C30: Tipo método accesor | D30: Tipo modificación método | E30: Descripción | F30: Parámetros | L30: Tipo dato de retorno | N30: Excepciones
F31: Nombre | G31: Tipo de dato | H31: ¿Cuál? | I31: Tipo parámetro | J31: Tipo modificación atributo | K31: Descripción | L31: Tipo de dato | M31: ¿Cuál?
A32: public | B32: getId | C32: getter | D32: no final | E32: Método encargado de obtener el valor del atributo id. | L32: Otro | M32: UUID
A33: public | B33: getDetalleVenta | C33: getter | D33: no final | E33: Método encargado de obtener el valor del atributo detalleVenta. | L33: Otro | M33: DetalleVenta
A34: public | B34: getProductoInterno | C34: getter | D34: no final | E34: Método encargado de obtener el valor del atributo productoInterno. | L34: Otro | M34: ProductoInterno
A35: public | B35: getCantidad | C35: getter | D35: no final | E35: Método encargado de obtener el valor del atributo cantidad. | L35: Otro | M35: BigDecimal
A36: public | B36: getUnidadMedida | C36: getter | D36: no final | E36: Método encargado de obtener el valor del atributo unidadMedida. | L36: Otro | M36: UnidadMedida
A37: public | B37: getTipoMovimiento | C37: getter | D37: no final | E37: Método encargado de obtener el valor del atributo tipoMovimiento. | L37: Otro | M37: TipoMovimiento
A39: Métodos
A40: Modificador de acceso | B40: Nombre | C40: Tipo acceso método | D40: Tipo modificación método | E40: Descripción | F40: Parámetros | L40: Tipo dato de retorno | N40: Excepciones
F41: Nombre | G41: Tipo de dato | H41: ¿Cuál? | I41: Tipo parámetro | J41: Tipo modificación atributo | K41: Descripción | L41: Tipo de dato | M41: ¿Cuál?
A42: public | B42: registrarConsumoDeVenta | C42: no static | D42: no final | E42: Al confirmar una venta, registra por cada detalle de venta los productos internos que se consumen según la receta del producto vendido. | F42: detalleVenta | G42: Otro | H42: DetalleVenta | I42: Por valor | J42: no final | K42: Detalle de venta confirmado que origina el consumo. | L42: Otro | M42: List<ConsumoVenta> | N42: El detalle de venta no existe. El producto vendido no tiene receta ni producto interno asociado. El producto interno ya fue consumido para ese detalle de venta. No hay saldo suficiente en inventario. No fue posible registrar las salidas de inventario del consumo.
A43: public | B43: consultarConsumosDeUnDetalleDeVenta | C43: static | D43: final | E43: Permite consultar los productos internos consumidos por un detalle de venta. | F43: id | G43: Otro | H43: UUID | I43: Por valor | J43: no final | K43: Identificador del detalle de venta. | L43: Otro | M43: List<ConsumoVenta> | N43: El detalle de venta no existe.
A45: Builder (clase interna public static)
A46: Modificador de acceso | B46: Nombre | C46: Tipo acceso método | D46: Tipo modificación método | E46: Descripción | F46: Parámetros | L46: Tipo dato de retorno | N46: Excepciones
F47: Nombre | G47: Tipo de dato | H47: ¿Cuál? | I47: Tipo parámetro | J47: Tipo modificación atributo | K47: Descripción | L47: Tipo de dato | M47: ¿Cuál?
A48: public | B48: Builder | C48: no static | D48: no final | E48: Constructor del Builder: asigna a cada atributo su valor por defecto.
A49: public | B49: id | C49: no static | D49: no final | E49: Asigna el identificador recibido; si es nulo, asigna el identificador por defecto (00000000-0000-0000-0000-000000000000). | F49: id | G49: Otro | H49: UUID | I49: Por valor | J49: no final | K49: Valor que se desea asignar al atributo id. | L49: Otro | M49: Builder
A50: public | B50: detalleVenta | C50: no static | D50: no final | E50: Asigna el valor recibido; si es nulo, asigna la instancia por defecto de DetalleVenta. | F50: detalleVenta | G50: Otro | H50: DetalleVenta | I50: Por valor | J50: no final | K50: Valor que se desea asignar al atributo detalleVenta. | L50: Otro | M50: Builder
A51: public | B51: productoInterno | C51: no static | D51: no final | E51: Asigna el valor recibido; si es nulo, asigna la instancia por defecto de ProductoInterno. | F51: productoInterno | G51: Otro | H51: ProductoInterno | I51: Por valor | J51: no final | K51: Valor que se desea asignar al atributo productoInterno. | L51: Otro | M51: Builder
A52: public | B52: cantidad | C52: no static | D52: no final | E52: Asigna el valor recibido; si es nulo o negativo, asigna 0. | F52: cantidad | G52: Otro | H52: BigDecimal | I52: Por valor | J52: no final | K52: Valor que se desea asignar al atributo cantidad. | L52: Otro | M52: Builder
A53: public | B53: unidadMedida | C53: no static | D53: no final | E53: Asigna el valor recibido; si es nulo, asigna la instancia por defecto de UnidadMedida. | F53: unidadMedida | G53: Otro | H53: UnidadMedida | I53: Por valor | J53: no final | K53: Valor que se desea asignar al atributo unidadMedida. | L53: Otro | M53: Builder
A54: public | B54: tipoMovimiento | C54: no static | D54: no final | E54: Asigna el valor recibido; si es nulo, asigna la instancia por defecto de TipoMovimiento. | F54: tipoMovimiento | G54: Otro | H54: TipoMovimiento | I54: Por valor | J54: no final | K54: Valor que se desea asignar al atributo tipoMovimiento. | L54: Otro | M54: Builder
A55: public | B55: build | C55: no static | D55: no final | E55: Crea la instancia de ConsumoVenta con los valores reunidos en el Builder, usando su constructor privado. | L55: Otro | M55: ConsumoVenta

Sheet Venta
A1: <-Volver al inicio
A2: =Clases!$A$1 -> Clase | B2: =Clases!A19 -> Venta
A3: =Clases!$B$1 -> Estereotipo | B3: =Clases!B19 -> class
A4: =Clases!$C$1 -> Descripción | B4: =Clases!C19 -> Representa la operación comercial mediante la cual la pizzería registra los productos adquiridos por un cliente.
A5: Modificador acceso: | B5: public
A6: Tipo clase: | B6: no final
A7: Relaciones
A8: Relación | B8: Tipo relación | E8: Estructura
A9: Es usada por | B9: Composición | E9: DetalleVenta
A11: Atributos
A12: Modificador de acceso | B12: Nombre | C12: Tipo de dato | E12: Tipo modificación atributo | F12: Tipo acceso atributo | G12: Valor por defecto | J12: Descripción atributo
C13: Tipo de dato | D13: ¿Cuál?
A14: private | B14: id | C14: Otro | D14: UUID | E14: no final | F14: no static | G14: 00000000-0000-0000-0000-000000000000 | J14: Identificador único de la venta.
A15: private | B15: fecha | C15: Otro | D15: LocalDate | E15: no final | F15: no static | G15: 1000-01-01 | J15: Fecha en la que se realizó la venta.
A16: private | B16: hora | C16: Otro | D16: LocalTime | E16: no final | F16: no static | G16: 00:00 | J16: Hora en la que se realizó la venta.
A17: private | B17: factura | C17: String | E17: no final | F17: no static | G17: "" (cadena vacía) | J17: Número de la factura de venta (FV- seguido de 6 dígitos); el sistema lo asigna al confirmar la venta.
A18: private | B18: cliente | C18: String | E18: no final | F18: no static | G18: 2222222222 | J18: Documento del cliente; si no se indica, se registra 2222222222 (consumidor final).
A19: private | B19: total | C19: Otro | D19: BigDecimal | E19: no final | F19: no static | G19: 0 | J19: Valor total de la venta, calculado a partir de la suma de sus detalles de venta.
A21: Constructores
A22: Modificador de acceso | B22: Nombre | C22: Tipo constructor | D22: Descripción | E22: Parámetros | M22: Excepciones
E23: Nombre | F23: Tipo de dato | G23: ¿Cuál? | H23: Tipo parámetro | I23: Tipo modificación atributo | J23: Descripción
A24: private | B24: =B2 -> Venta | C24: Parametrizado | D24: Constructor privado: crea la instancia de Venta copiando los valores ya saneados que reunió el Builder. Solo se invoca desde Builder.build(). | E24: builder | F24: Otro | G24: Builder | H24: Por valor | I24: no final | J24: Builder con los valores de los atributos de la clase.
A26: Métodos accesores
A27: Modificador de acceso | B27: Nombre | C27: Tipo método accesor | D27: Tipo modificación método | E27: Descripción | F27: Parámetros | L27: Tipo dato de retorno | N27: Excepciones
F28: Nombre | G28: Tipo de dato | H28: ¿Cuál? | I28: Tipo parámetro | J28: Tipo modificación atributo | K28: Descripción | L28: Tipo de dato | M28: ¿Cuál?
A29: public | B29: getId | C29: getter | D29: no final | E29: Método encargado de obtener el valor del atributo id. | L29: Otro | M29: UUID
A30: public | B30: getFecha | C30: getter | D30: no final | E30: Método encargado de obtener el valor del atributo fecha. | L30: Otro | M30: LocalDate
A31: public | B31: getHora | C31: getter | D31: no final | E31: Método encargado de obtener el valor del atributo hora. | L31: Otro | M31: LocalTime
A32: public | B32: getFactura | C32: getter | D32: no final | E32: Método encargado de obtener el valor del atributo factura. | L32: String
A33: public | B33: getCliente | C33: getter | D33: no final | E33: Método encargado de obtener el valor del atributo cliente. | L33: String
A34: public | B34: getTotal | C34: getter | D34: no final | E34: Método encargado de obtener el valor del atributo total. | L34: Otro | M34: BigDecimal
A36: Métodos
A37: Modificador de acceso | B37: Nombre | C37: Tipo acceso método | D37: Tipo modificación método | E37: Descripción | F37: Parámetros | L37: Tipo dato de retorno | N37: Excepciones
F38: Nombre | G38: Tipo de dato | H38: ¿Cuál? | I38: Tipo parámetro | J38: Tipo modificación atributo | K38: Descripción | L38: Tipo de dato | M38: ¿Cuál?
A39: public | B39: registrarVenta | C39: no static | D39: no final | E39: Permite registrar una venta realizada en el establecimiento, asociando los productos solicitados y la información correspondiente. | F39: venta | G39: Otro | H39: Venta | I39: Por valor | J39: no final | K39: Información necesaria para registrar la venta. | L39: Otro | M39: Venta | N39: Los datos ingresados para registrar la venta no son válidos. Ya existe otra venta registrada con la misma Fecha y la misma Hora. No se indicó el cliente de la venta.
A40: public | B40: confirmarVenta | C40: no static | D40: no final | E40: Permite confirmar una venta: se calcula el total, se asigna el número de factura, se registran los consumos y se descuenta el inventario por FIFO. Una venta confirmada ya no se puede modificar. | F40: id | G40: Otro | H40: UUID | I40: Por valor | J40: no final | K40: Identificador de la venta que se desea confirmar. | L40: Otro | M40: Venta | N40: La venta que se desea confirmar no existe. La venta ya se encuentra confirmada. La venta no contiene ningún detalle de venta. Alguno de los detalles asociados a la venta no es válido. No existe disponibilidad suficiente de inventario para atender los productos que requieren consumo. El total no corresponde a la suma de los subtotales o supera 1.000.000. El número de factura que le corresponde a la venta ya está asignado a otra venta. No fue posible registrar los consumos de la venta. No hay saldo suficiente en los lotes para descontar los productos internos.
A41: public | B41: eliminarVenta | C41: no static | D41: no final | E41: Permite eliminar una venta que no haya sido confirmada y que no tenga detalles de venta asociados que deban conservarse para mantener la trazabilidad. | F41: id | G41: Otro | H41: UUID | I41: Por valor | J41: no final | K41: Identificador de la venta que se desea eliminar. | L41: void | N41: La venta que se desea eliminar no existe. La venta ya se encuentra confirmada. La venta tiene detalles de venta asociados que deben conservarse.
A42: public | B42: consultarVenta | C42: static | D42: final | E42: Permite consultar una venta con sus detalles, su total y su número de factura. | F42: id | G42: Otro | H42: UUID | I42: Por valor | J42: no final | K42: Identificador de la venta. | L42: Otro | M42: Venta | N42: No existe una venta con el identificador indicado.
A44: Builder (clase interna public static)
A45: Modificador de acceso | B45: Nombre | C45: Tipo acceso método | D45: Tipo modificación método | E45: Descripción | F45: Parámetros | L45: Tipo dato de retorno | N45: Excepciones
F46: Nombre | G46: Tipo de dato | H46: ¿Cuál? | I46: Tipo parámetro | J46: Tipo modificación atributo | K46: Descripción | L46: Tipo de dato | M46: ¿Cuál?
A47: public | B47: Builder | C47: no static | D47: no final | E47: Constructor del Builder: asigna a cada atributo su valor por defecto.
A48: public | B48: id | C48: no static | D48: no final | E48: Asigna el identificador recibido; si es nulo, asigna el identificador por defecto (00000000-0000-0000-0000-000000000000). | F48: id | G48: Otro | H48: UUID | I48: Por valor | J48: no final | K48: Valor que se desea asignar al atributo id. | L48: Otro | M48: Builder
A49: public | B49: fecha | C49: no static | D49: no final | E49: Asigna la fecha recibida; si es nula, asigna la fecha por defecto 1000-01-01. | F49: fecha | G49: Otro | H49: LocalDate | I49: Por valor | J49: no final | K49: Valor que se desea asignar al atributo fecha. | L49: Otro | M49: Builder
A50: public | B50: hora | C50: no static | D50: no final | E50: Asigna la hora recibida; si es nula, asigna 00:00. | F50: hora | G50: Otro | H50: LocalTime | I50: Por valor | J50: no final | K50: Valor que se desea asignar al atributo hora. | L50: Otro | M50: Builder
A51: public | B51: factura | C51: no static | D51: no final | E51: Asigna el texto recibido sin espacios en blanco al inicio y al final; si es nulo, asigna una cadena vacía. | F51: factura | G51: String | I51: Por valor | J51: no final | K51: Valor que se desea asignar al atributo factura. | L51: Otro | M51: Builder
A52: public | B52: cliente | C52: no static | D52: no final | E52: Asigna el documento recibido sin espacios en blanco al inicio y al final; si es nulo o vacío, asigna 2222222222 (consumidor final). | F52: cliente | G52: String | I52: Por valor | J52: no final | K52: Valor que se desea asignar al atributo cliente. | L52: Otro | M52: Builder
A53: public | B53: total | C53: no static | D53: no final | E53: Asigna el valor recibido; si es nulo o negativo, asigna 0. | F53: total | G53: Otro | H53: BigDecimal | I53: Por valor | J53: no final | K53: Valor que se desea asignar al atributo total. | L53: Otro | M53: Builder
A54: public | B54: build | C54: no static | D54: no final | E54: Crea la instancia de Venta con los valores reunidos en el Builder, usando su constructor privado. | L54: Otro | M54: Venta

Sheet HistoricoPrecio
A1: <-Volver al inicio
A2: =Clases!$A$1 -> Clase | B2: =Clases!A20 -> HistoricoPrecio
A3: =Clases!$B$1 -> Estereotipo | B3: =Clases!B20 -> class
A4: =Clases!$C$1 -> Descripción | B4: =Clases!C20 -> Representa el registro de los precios que han tenido los productos de la pizzería a lo largo del tiempo, permitiendo consultar su evolución histórica.
A5: Modificador acceso: | B5: public
A6: Tipo clase: | B6: no final
A7: Relaciones
A8: Relación | B8: Tipo relación | E8: Estructura
A9: Necesita de | B9: Asociación | E9: Producto
A11: Atributos
A12: Modificador de acceso | B12: Nombre | C12: Tipo de dato | E12: Tipo modificación atributo | F12: Tipo acceso atributo | G12: Valor por defecto | J12: Descripción atributo
C13: Tipo de dato | D13: ¿Cuál?
A14: private | B14: id | C14: Otro | D14: UUID | E14: no final | F14: no static | G14: 00000000-0000-0000-0000-000000000000 | J14: Identificador único del registro histórico de precio.
A15: private | B15: producto | C15: Otro | D15: Producto | E15: no final | F15: no static | G15: Instancia por defecto de Producto | J15: Producto al que corresponde este registro de precio.
A16: private | B16: precio | C16: Otro | D16: BigDecimal | E16: no final | F16: no static | G16: 0 | J16: Precio asignado al producto durante este período de vigencia.
A17: private | B17: fechaInicio | C17: Otro | D17: LocalDate | E17: no final | F17: no static | G17: 1000-01-01 | J17: Fecha de inicio de vigencia de este precio.
A18: private | B18: fechaFin | C18: Otro | D18: LocalDate | E18: no final | F18: no static | G18: 1000-01-01 | J18: Fecha de finalización de vigencia de este precio; mientras el precio está vigente vale 1000-01-01.
A20: Constructores
A21: Modificador de acceso | B21: Nombre | C21: Tipo constructor | D21: Descripción | E21: Parámetros | M21: Excepciones
E22: Nombre | F22: Tipo de dato | G22: ¿Cuál? | H22: Tipo parámetro | I22: Tipo modificación atributo | J22: Descripción
A23: private | B23: =B2 -> HistoricoPrecio | C23: Parametrizado | D23: Constructor privado: crea la instancia de HistoricoPrecio copiando los valores ya saneados que reunió el Builder. Solo se invoca desde Builder.build(). | E23: builder | F23: Otro | G23: Builder | H23: Por valor | I23: no final | J23: Builder con los valores de los atributos de la clase.
A25: Métodos accesores
A26: Modificador de acceso | B26: Nombre | C26: Tipo método accesor | D26: Tipo modificación método | E26: Descripción | F26: Parámetros | L26: Tipo dato de retorno | N26: Excepciones
F27: Nombre | G27: Tipo de dato | H27: ¿Cuál? | I27: Tipo parámetro | J27: Tipo modificación atributo | K27: Descripción | L27: Tipo de dato | M27: ¿Cuál?
A28: public | B28: getId | C28: getter | D28: no final | E28: Método encargado de obtener el valor del atributo id. | L28: Otro | M28: UUID
A29: public | B29: getProducto | C29: getter | D29: no final | E29: Método encargado de obtener el valor del atributo producto. | L29: Otro | M29: Producto
A30: public | B30: getPrecio | C30: getter | D30: no final | E30: Método encargado de obtener el valor del atributo precio. | L30: Otro | M30: BigDecimal
A31: public | B31: getFechaInicio | C31: getter | D31: no final | E31: Método encargado de obtener el valor del atributo fechaInicio. | L31: Otro | M31: LocalDate
A32: public | B32: getFechaFin | C32: getter | D32: no final | E32: Método encargado de obtener el valor del atributo fechaFin. | L32: Otro | M32: LocalDate
A34: Métodos
A35: Modificador de acceso | B35: Nombre | C35: Tipo acceso método | D35: Tipo modificación método | E35: Descripción | F35: Parámetros | L35: Tipo dato de retorno | N35: Excepciones
F36: Nombre | G36: Tipo de dato | H36: ¿Cuál? | I36: Tipo parámetro | J36: Tipo modificación atributo | K36: Descripción | L36: Tipo de dato | M36: ¿Cuál?
A37: public | B37: registrarPrecio | C37: no static | D37: no final | E37: Permite establecer un nuevo precio para un producto, iniciando su nuevo período de vigencia y conservando el precio anterior para mantener la trazabilidad. | F37: historicoPrecio | G37: Otro | H37: HistoricoPrecio | I37: Por valor | J37: no final | K37: Información necesaria para registrar el nuevo precio y su período de vigencia, conservando el precio anterior como parte del historial. | L37: Otro | M37: HistoricoPrecio | N37: Los datos ingresados para registrar el nuevo precio no son válidos. El producto al que se asocia el nuevo precio no existe. El precio no es mayor que cero o supera 1.000.000. La fecha de inicio de vigencia del precio no es válida. La fecha de finalización es anterior a la fecha de inicio. El nuevo período de vigencia se superpone con otro período vigente del mismo producto. Ya existe un precio vigente para el producto en este momento. No fue posible cerrar el precio vigente anterior.
A38: public | B38: consultarHistoricoDePreciosDeUnProducto | C38: static | D38: final | E38: Permite consultar todos los precios que ha tenido un producto, con su período de vigencia. | F38: id | G38: Otro | H38: UUID | I38: Por valor | J38: no final | K38: Identificador del producto. | L38: Otro | M38: List<HistoricoPrecio> | N38: El producto no existe.
A40: Builder (clase interna public static)
A41: Modificador de acceso | B41: Nombre | C41: Tipo acceso método | D41: Tipo modificación método | E41: Descripción | F41: Parámetros | L41: Tipo dato de retorno | N41: Excepciones
F42: Nombre | G42: Tipo de dato | H42: ¿Cuál? | I42: Tipo parámetro | J42: Tipo modificación atributo | K42: Descripción | L42: Tipo de dato | M42: ¿Cuál?
A43: public | B43: Builder | C43: no static | D43: no final | E43: Constructor del Builder: asigna a cada atributo su valor por defecto.
A44: public | B44: id | C44: no static | D44: no final | E44: Asigna el identificador recibido; si es nulo, asigna el identificador por defecto (00000000-0000-0000-0000-000000000000). | F44: id | G44: Otro | H44: UUID | I44: Por valor | J44: no final | K44: Valor que se desea asignar al atributo id. | L44: Otro | M44: Builder
A45: public | B45: producto | C45: no static | D45: no final | E45: Asigna el valor recibido; si es nulo, asigna la instancia por defecto de Producto. | F45: producto | G45: Otro | H45: Producto | I45: Por valor | J45: no final | K45: Valor que se desea asignar al atributo producto. | L45: Otro | M45: Builder
A46: public | B46: precio | C46: no static | D46: no final | E46: Asigna el valor recibido; si es nulo o negativo, asigna 0. | F46: precio | G46: Otro | H46: BigDecimal | I46: Por valor | J46: no final | K46: Valor que se desea asignar al atributo precio. | L46: Otro | M46: Builder
A47: public | B47: fechaInicio | C47: no static | D47: no final | E47: Asigna la fecha recibida; si es nula, asigna la fecha por defecto 1000-01-01. | F47: fechaInicio | G47: Otro | H47: LocalDate | I47: Por valor | J47: no final | K47: Valor que se desea asignar al atributo fechaInicio. | L47: Otro | M47: Builder
A48: public | B48: fechaFin | C48: no static | D48: no final | E48: Asigna la fecha recibida; si es nula, asigna la fecha por defecto 1000-01-01. | F48: fechaFin | G48: Otro | H48: LocalDate | I48: Por valor | J48: no final | K48: Valor que se desea asignar al atributo fechaFin. | L48: Otro | M48: Builder
A49: public | B49: build | C49: no static | D49: no final | E49: Crea la instancia de HistoricoPrecio con los valores reunidos en el Builder, usando su constructor privado. | L49: Otro | M49: HistoricoPrecio

Sheet Cambio
A1: <-Volver al inicio
A2: =Clases!$A$1 -> Clase | B2: =Clases!A21 -> Cambio
A3: =Clases!$B$1 -> Estereotipo | B3: =Clases!B21 -> class
A4: =Clases!$C$1 -> Descripción | B4: =Clases!C21 -> Representa la operación mediante la cual un insumo no perecedero próximo a vencer se devuelve al proveedor y se reemplaza por uno nuevo, manteniendo la disponibilidad y las condiciones adecuadas de los insumos de la pizzería.
A5: Modificador acceso: | B5: public
A6: Tipo clase: | B6: no final
A7: Relaciones
A8: Relación | B8: Tipo relación | E8: Estructura
A9: Necesita de | B9: Asociación | E9: ProductoInterno
A10: Necesita de | B10: Asociación | E10: UnidadMedida
A11: Necesita de | B11: Asociación | E11: TipoMovimiento
A13: Atributos
A14: Modificador de acceso | B14: Nombre | C14: Tipo de dato | E14: Tipo modificación atributo | F14: Tipo acceso atributo | G14: Valor por defecto | J14: Descripción atributo
C15: Tipo de dato | D15: ¿Cuál?
A16: private | B16: id | C16: Otro | D16: UUID | E16: no final | F16: no static | G16: 00000000-0000-0000-0000-000000000000 | J16: Identificador único del cambio.
A17: private | B17: productoCambio | C17: Otro | D17: ProductoInterno | E17: no final | F17: no static | G17: Instancia por defecto de ProductoInterno | J17: Producto interno que se cambia (siempre un producto no perecedero).
A18: private | B18: cantidad | C18: Otro | D18: BigDecimal | E18: no final | F18: no static | G18: 0 | J18: Cantidad del producto que sale y entra por efecto del cambio.
A19: private | B19: unidadMedida | C19: Otro | D19: UnidadMedida | E19: no final | F19: no static | G19: Instancia por defecto de UnidadMedida | J19: Unidad de medida en la que se expresa la cantidad del cambio.
A20: private | B20: fechaVencimiento | C20: Otro | D20: LocalDate | E20: no final | F20: no static | G20: 1000-01-01 | J20: Fecha de vencimiento del producto que ingresa como reemplazo.
A21: private | B21: fechaCambio | C21: Otro | D21: LocalDate | E21: no final | F21: no static | G21: 1000-01-01 | J21: Fecha en la que se realiza el cambio.
A22: private | B22: tipoMovimiento | C22: Otro | D22: TipoMovimiento | E22: no final | F22: no static | G22: Instancia por defecto de TipoMovimiento | J22: Código de la operación (TipoMovimiento) del cambio; con él se rastrean los movimientos que generó.
A24: Constructores
A25: Modificador de acceso | B25: Nombre | C25: Tipo constructor | D25: Descripción | E25: Parámetros | M25: Excepciones
E26: Nombre | F26: Tipo de dato | G26: ¿Cuál? | H26: Tipo parámetro | I26: Tipo modificación atributo | J26: Descripción
A27: private | B27: =B2 -> Cambio | C27: Parametrizado | D27: Constructor privado: crea la instancia de Cambio copiando los valores ya saneados que reunió el Builder. Solo se invoca desde Builder.build(). | E27: builder | F27: Otro | G27: Builder | H27: Por valor | I27: no final | J27: Builder con los valores de los atributos de la clase.
A29: Métodos accesores
A30: Modificador de acceso | B30: Nombre | C30: Tipo método accesor | D30: Tipo modificación método | E30: Descripción | F30: Parámetros | L30: Tipo dato de retorno | N30: Excepciones
F31: Nombre | G31: Tipo de dato | H31: ¿Cuál? | I31: Tipo parámetro | J31: Tipo modificación atributo | K31: Descripción | L31: Tipo de dato | M31: ¿Cuál?
A32: public | B32: getId | C32: getter | D32: no final | E32: Método encargado de obtener el valor del atributo id. | L32: Otro | M32: UUID
A33: public | B33: getProductoCambio | C33: getter | D33: no final | E33: Método encargado de obtener el valor del atributo productoCambio. | L33: Otro | M33: ProductoInterno
A34: public | B34: getCantidad | C34: getter | D34: no final | E34: Método encargado de obtener el valor del atributo cantidad. | L34: Otro | M34: BigDecimal
A35: public | B35: getUnidadMedida | C35: getter | D35: no final | E35: Método encargado de obtener el valor del atributo unidadMedida. | L35: Otro | M35: UnidadMedida
A36: public | B36: getFechaVencimiento | C36: getter | D36: no final | E36: Método encargado de obtener el valor del atributo fechaVencimiento. | L36: Otro | M36: LocalDate
A37: public | B37: getFechaCambio | C37: getter | D37: no final | E37: Método encargado de obtener el valor del atributo fechaCambio. | L37: Otro | M37: LocalDate
A38: public | B38: getTipoMovimiento | C38: getter | D38: no final | E38: Método encargado de obtener el valor del atributo tipoMovimiento. | L38: Otro | M38: TipoMovimiento
A40: Métodos
A41: Modificador de acceso | B41: Nombre | C41: Tipo acceso método | D41: Tipo modificación método | E41: Descripción | F41: Parámetros | L41: Tipo dato de retorno | N41: Excepciones
F42: Nombre | G42: Tipo de dato | H42: ¿Cuál? | I42: Tipo parámetro | J42: Tipo modificación atributo | K42: Descripción | L42: Tipo de dato | M42: ¿Cuál?
A43: public | B43: registrarCambioDeProducto | C43: no static | D43: no final | E43: Registrar el reemplazo de un producto próximo a vencer por uno nuevo, en respuesta a la alerta de vencimiento emitida por Lote, generando la salida del lote saliente y la entrada del nuevo lote en el inventario. | F43: cambio | G43: Otro | H43: Cambio | I43: Por valor | J43: no final | K43: Información necesaria para registrar el cambio (producto, cantidad, unidad de medida, fecha de vencimiento del producto nuevo y fecha del cambio). | L43: Otro | M43: Cambio | N43: Los datos ingresados para registrar el cambio no son válidos. El producto interno asociado al cambio no existe en el sistema. El producto interno asociado al cambio es perecedero. La cantidad no es mayor que cero o supera 10.000. La unidad de medida utilizada para el cambio no es válida. La fecha de vencimiento del producto de reemplazo no es posterior a la fecha del cambio. Ya existe otro cambio registrado con el mismo producto y la misma fecha de cambio. El cambio se está registrando sin que exista una alerta de vencimiento próximo emitida por Lote para el producto interno indicado. No fue posible generar el TipoMovimiento del cambio. No fue posible registrar la salida del lote o la entrada del reemplazo.
A44: public | B44: consultarCambio | C44: static | D44: final | E44: Permite consultar un cambio de producto registrado, con su producto, cantidad y fechas. | F44: id | G44: Otro | H44: UUID | I44: Por valor | J44: no final | K44: Identificador del cambio. | L44: Otro | M44: Cambio | N44: No existe un cambio con el identificador indicado.
A46: Builder (clase interna public static)
A47: Modificador de acceso | B47: Nombre | C47: Tipo acceso método | D47: Tipo modificación método | E47: Descripción | F47: Parámetros | L47: Tipo dato de retorno | N47: Excepciones
F48: Nombre | G48: Tipo de dato | H48: ¿Cuál? | I48: Tipo parámetro | J48: Tipo modificación atributo | K48: Descripción | L48: Tipo de dato | M48: ¿Cuál?
A49: public | B49: Builder | C49: no static | D49: no final | E49: Constructor del Builder: asigna a cada atributo su valor por defecto.
A50: public | B50: id | C50: no static | D50: no final | E50: Asigna el identificador recibido; si es nulo, asigna el identificador por defecto (00000000-0000-0000-0000-000000000000). | F50: id | G50: Otro | H50: UUID | I50: Por valor | J50: no final | K50: Valor que se desea asignar al atributo id. | L50: Otro | M50: Builder
A51: public | B51: productoCambio | C51: no static | D51: no final | E51: Asigna el valor recibido; si es nulo, asigna la instancia por defecto de ProductoInterno. | F51: productoCambio | G51: Otro | H51: ProductoInterno | I51: Por valor | J51: no final | K51: Valor que se desea asignar al atributo productoCambio. | L51: Otro | M51: Builder
A52: public | B52: cantidad | C52: no static | D52: no final | E52: Asigna el valor recibido; si es nulo o negativo, asigna 0. | F52: cantidad | G52: Otro | H52: BigDecimal | I52: Por valor | J52: no final | K52: Valor que se desea asignar al atributo cantidad. | L52: Otro | M52: Builder
A53: public | B53: unidadMedida | C53: no static | D53: no final | E53: Asigna el valor recibido; si es nulo, asigna la instancia por defecto de UnidadMedida. | F53: unidadMedida | G53: Otro | H53: UnidadMedida | I53: Por valor | J53: no final | K53: Valor que se desea asignar al atributo unidadMedida. | L53: Otro | M53: Builder
A54: public | B54: fechaVencimiento | C54: no static | D54: no final | E54: Asigna la fecha recibida; si es nula, asigna la fecha por defecto 1000-01-01. | F54: fechaVencimiento | G54: Otro | H54: LocalDate | I54: Por valor | J54: no final | K54: Valor que se desea asignar al atributo fechaVencimiento. | L54: Otro | M54: Builder
A55: public | B55: fechaCambio | C55: no static | D55: no final | E55: Asigna la fecha recibida; si es nula, asigna la fecha por defecto 1000-01-01. | F55: fechaCambio | G55: Otro | H55: LocalDate | I55: Por valor | J55: no final | K55: Valor que se desea asignar al atributo fechaCambio. | L55: Otro | M55: Builder
A56: public | B56: tipoMovimiento | C56: no static | D56: no final | E56: Asigna el valor recibido; si es nulo, asigna la instancia por defecto de TipoMovimiento. | F56: tipoMovimiento | G56: Otro | H56: TipoMovimiento | I56: Por valor | J56: no final | K56: Valor que se desea asignar al atributo tipoMovimiento. | L56: Otro | M56: Builder
A57: public | B57: build | C57: no static | D57: no final | E57: Crea la instancia de Cambio con los valores reunidos en el Builder, usando su constructor privado. | L57: Otro | M57: Cambio

Sheet MovimientoInventario
A1: <-Volver al inicio
A2: =Clases!$A$1 -> Clase | B2: =Clases!A22 -> MovimientoInventario
A3: =Clases!$B$1 -> Estereotipo | B3: =Clases!B22 -> class
A4: =Clases!$C$1 -> Descripción | B4: =Clases!C22 -> Representa cada entrada o salida de existencias sobre un lote, generada por una compra, una venta o un cambio, permitiendo mantener el control y la trazabilidad del inventario.
A5: Modificador acceso: | B5: public
A6: Tipo clase: | B6: no final
A7: Relaciones
A8: Relación | B8: Tipo relación | E8: Estructura
A9: Necesita de | B9: Asociación | E9: ClaseMovimiento
A10: Necesita de | B10: Asociación | E10: TipoMovimiento
A11: Necesita de | B11: Asociación | E11: Lote
A13: Atributos
A14: Modificador de acceso | B14: Nombre | C14: Tipo de dato | E14: Tipo modificación atributo | F14: Tipo acceso atributo | G14: Valor por defecto | J14: Descripción atributo
C15: Tipo de dato | D15: ¿Cuál?
A16: private | B16: id | C16: Otro | D16: UUID | E16: no final | F16: no static | G16: 00000000-0000-0000-0000-000000000000 | J16: Identificador único del movimiento de inventario.
A17: private | B17: claseMovimiento | C17: Otro | D17: ClaseMovimiento | E17: no final | F17: no static | G17: Instancia por defecto de ClaseMovimiento | J17: Clase de movimiento: Entrada (suma al inventario) o Salida (resta del inventario).
A18: private | B18: tipoMovimiento | C18: Otro | D18: TipoMovimiento | E18: no final | F18: no static | G18: Instancia por defecto de TipoMovimiento | J18: Código de la operación (TipoMovimiento) que generó el movimiento; a través de él se conoce la categoría de origen.
A19: private | B19: cantidad | C19: Otro | D19: BigDecimal | E19: no final | F19: no static | G19: 0 | J19: Cantidad que entra o sale del lote en este movimiento, expresada en la unidad de medida del lote.
A20: private | B20: fechaMovimiento | C20: Otro | D20: LocalDate | E20: no final | F20: no static | G20: 1000-01-01 | J20: Fecha en la que ocurrió el movimiento.
A21: private | B21: lote | C21: Otro | D21: Lote | E21: no final | F21: no static | G21: Instancia por defecto de Lote | J21: Lote sobre el que se realiza la entrada o salida; por el lote se conoce el producto interno.
A23: Constructores
A24: Modificador de acceso | B24: Nombre | C24: Tipo constructor | D24: Descripción | E24: Parámetros | M24: Excepciones
E25: Nombre | F25: Tipo de dato | G25: ¿Cuál? | H25: Tipo parámetro | I25: Tipo modificación atributo | J25: Descripción
A26: private | B26: =B2 -> MovimientoInventario | C26: Parametrizado | D26: Constructor privado: crea la instancia de MovimientoInventario copiando los valores ya saneados que reunió el Builder. Solo se invoca desde Builder.build(). | E26: builder | F26: Otro | G26: Builder | H26: Por valor | I26: no final | J26: Builder con los valores de los atributos de la clase.
A28: Métodos accesores
A29: Modificador de acceso | B29: Nombre | C29: Tipo método accesor | D29: Tipo modificación método | E29: Descripción | F29: Parámetros | L29: Tipo dato de retorno | N29: Excepciones
F30: Nombre | G30: Tipo de dato | H30: ¿Cuál? | I30: Tipo parámetro | J30: Tipo modificación atributo | K30: Descripción | L30: Tipo de dato | M30: ¿Cuál?
A31: public | B31: getId | C31: getter | D31: no final | E31: Método encargado de obtener el valor del atributo id. | L31: Otro | M31: UUID
A32: public | B32: getClaseMovimiento | C32: getter | D32: no final | E32: Método encargado de obtener el valor del atributo claseMovimiento. | L32: Otro | M32: ClaseMovimiento
A33: public | B33: getTipoMovimiento | C33: getter | D33: no final | E33: Método encargado de obtener el valor del atributo tipoMovimiento. | L33: Otro | M33: TipoMovimiento
A34: public | B34: getCantidad | C34: getter | D34: no final | E34: Método encargado de obtener el valor del atributo cantidad. | L34: Otro | M34: BigDecimal
A35: public | B35: getFechaMovimiento | C35: getter | D35: no final | E35: Método encargado de obtener el valor del atributo fechaMovimiento. | L35: Otro | M35: LocalDate
A36: public | B36: getLote | C36: getter | D36: no final | E36: Método encargado de obtener el valor del atributo lote. | L36: Otro | M36: Lote
A38: Métodos
A39: Modificador de acceso | B39: Nombre | C39: Tipo acceso método | D39: Tipo modificación método | E39: Descripción | F39: Parámetros | L39: Tipo dato de retorno | N39: Excepciones
F40: Nombre | G40: Tipo de dato | H40: ¿Cuál? | I40: Tipo parámetro | J40: Tipo modificación atributo | K40: Descripción | L40: Tipo de dato | M40: ¿Cuál?
A41: public | B41: registrarEntradaDeInventarioPorCompra | C41: no static | D41: no final | E41: Registrar el ingreso de las existencias recibidas como consecuencia de una compra válida, asociando la entrada con el lote correspondiente. | F41: detalleCompra | G41: Otro | H41: DetalleCompra | I41: Por valor | J41: no final | K41: Producto adquirido, cantidad recibida, unidad de medida, compra, detalle de compra y lote sobre el cual se registra la entrada. | L41: Otro | M41: MovimientoInventario | N41: Los datos requeridos para registrar el movimiento no son válidos. La clase de movimiento no corresponde a la operación. El TipoMovimiento no existe o su categoría de origen no es válida. El detalle de compra asociado no es válido. El lote sobre el cual se registra el movimiento no existe. La cantidad no es mayor que cero o supera 10.000. Ya existe un movimiento con el mismo TipoMovimiento sobre el mismo lote. La cantidad no corresponde a la de la operación que genera el movimiento. No fue posible actualizar el saldo del lote o el inventario.
A42: public | B42: registrarSalidaDeInventarioPorVenta | C42: no static | D42: no final | E42: Registra la salida de los productos internos consumidos en una venta confirmada, descontándolos de los lotes por FIFO. | F42: consumoVenta | G42: Otro | H42: ConsumoVenta | I42: Por valor | J42: no final | K42: Consumo de venta que origina la salida. | L42: Otro | M42: List<MovimientoInventario> | N42: Los datos requeridos para registrar el movimiento no son válidos. La clase de movimiento no corresponde a la operación. El TipoMovimiento no existe o su categoría de origen no es válida. El consumo de venta asociado no es válido. No hay lotes con saldo suficiente para cubrir la salida. El lote sobre el cual se registra el movimiento no existe. La cantidad no es mayor que cero o supera 10.000. Ya existe un movimiento con el mismo TipoMovimiento sobre el mismo lote. La cantidad no corresponde a la de la operación que genera el movimiento. No fue posible actualizar el saldo del lote o el inventario.
A43: public | B43: registrarMovimientosPorCambioDeProducto | C43: no static | D43: no final | E43: Cuando se registra el cambio de un producto no perecedero, registra la Salida del lote que se devuelve al proveedor y la Entrada del lote de reemplazo, con el TipoMovimiento del cambio. | F43: cambio | G43: Otro | H43: Cambio | I43: Por valor | J43: no final | K43: Cambio registrado que origina la salida del lote próximo a vencer y la entrada del lote de reemplazo. | L43: Otro | M43: List<MovimientoInventario> | N43: Los datos requeridos para registrar el movimiento no son válidos. La clase de movimiento no corresponde a la operación. El TipoMovimiento no existe o su categoría de origen no es válida. El cambio asociado no existe o no es válido. El producto interno del cambio es perecedero. El lote sobre el cual se registra el movimiento no existe. La cantidad no es mayor que cero o supera 10.000. Ya existe un movimiento con el mismo TipoMovimiento sobre el mismo lote. La cantidad no corresponde a la de la operación que genera el movimiento. No fue posible actualizar el saldo del lote o el inventario.
A44: public | B44: consultarMovimientosDeUnLote | C44: static | D44: final | E44: Permite consultar las entradas y salidas registradas sobre un lote, para conocer la trazabilidad de sus existencias. | F44: id | G44: Otro | H44: UUID | I44: Por valor | J44: no final | K44: Identificador del lote. | L44: Otro | M44: List<MovimientoInventario> | N44: El lote no existe. Se buscan retiros por vencimiento entre los movimientos de inventario.
A46: Builder (clase interna public static)
A47: Modificador de acceso | B47: Nombre | C47: Tipo acceso método | D47: Tipo modificación método | E47: Descripción | F47: Parámetros | L47: Tipo dato de retorno | N47: Excepciones
F48: Nombre | G48: Tipo de dato | H48: ¿Cuál? | I48: Tipo parámetro | J48: Tipo modificación atributo | K48: Descripción | L48: Tipo de dato | M48: ¿Cuál?
A49: public | B49: Builder | C49: no static | D49: no final | E49: Constructor del Builder: asigna a cada atributo su valor por defecto.
A50: public | B50: id | C50: no static | D50: no final | E50: Asigna el identificador recibido; si es nulo, asigna el identificador por defecto (00000000-0000-0000-0000-000000000000). | F50: id | G50: Otro | H50: UUID | I50: Por valor | J50: no final | K50: Valor que se desea asignar al atributo id. | L50: Otro | M50: Builder
A51: public | B51: claseMovimiento | C51: no static | D51: no final | E51: Asigna el valor recibido; si es nulo, asigna la instancia por defecto de ClaseMovimiento. | F51: claseMovimiento | G51: Otro | H51: ClaseMovimiento | I51: Por valor | J51: no final | K51: Valor que se desea asignar al atributo claseMovimiento. | L51: Otro | M51: Builder
A52: public | B52: tipoMovimiento | C52: no static | D52: no final | E52: Asigna el valor recibido; si es nulo, asigna la instancia por defecto de TipoMovimiento. | F52: tipoMovimiento | G52: Otro | H52: TipoMovimiento | I52: Por valor | J52: no final | K52: Valor que se desea asignar al atributo tipoMovimiento. | L52: Otro | M52: Builder
A53: public | B53: cantidad | C53: no static | D53: no final | E53: Asigna el valor recibido; si es nulo o negativo, asigna 0. | F53: cantidad | G53: Otro | H53: BigDecimal | I53: Por valor | J53: no final | K53: Valor que se desea asignar al atributo cantidad. | L53: Otro | M53: Builder
A54: public | B54: fechaMovimiento | C54: no static | D54: no final | E54: Asigna la fecha recibida; si es nula, asigna la fecha por defecto 1000-01-01. | F54: fechaMovimiento | G54: Otro | H54: LocalDate | I54: Por valor | J54: no final | K54: Valor que se desea asignar al atributo fechaMovimiento. | L54: Otro | M54: Builder
A55: public | B55: lote | C55: no static | D55: no final | E55: Asigna el valor recibido; si es nulo, asigna la instancia por defecto de Lote. | F55: lote | G55: Otro | H55: Lote | I55: Por valor | J55: no final | K55: Valor que se desea asignar al atributo lote. | L55: Otro | M55: Builder
A56: public | B56: build | C56: no static | D56: no final | E56: Crea la instancia de MovimientoInventario con los valores reunidos en el Builder, usando su constructor privado. | L56: Otro | M56: MovimientoInventario

Sheet Usuario
A1: <-Volver al inicio
A2: =Clases!$A$1 -> Clase | B2: =Clases!A23 -> Usuario
A3: =Clases!$B$1 -> Estereotipo | B3: =Clases!B23 -> class
A4: =Clases!$C$1 -> Descripción | B4: =Clases!C23 -> Representa a la persona que puede ingresar a la aplicación; solo los usuarios activos con rol Administrador pueden iniciar sesión.
A5: Modificador acceso: | B5: public
A6: Tipo clase: | B6: no final
A7: Relaciones
A8: Relación | B8: Tipo relación | E8: Estructura
A11: Atributos
A12: Modificador de acceso | B12: Nombre | C12: Tipo de dato | E12: Tipo modificación atributo | F12: Tipo acceso atributo | G12: Valor por defecto | J12: Descripción atributo
C13: Tipo de dato | D13: ¿Cuál?
A14: private | B14: id | C14: Otro | D14: UUID | E14: no final | F14: no static | G14: 00000000-0000-0000-0000-000000000000 | J14: Identificador único de cada usuario de la aplicación.
A15: private | B15: usuario | C15: String | E15: no final | F15: no static | G15: "" (cadena vacía) | J15: Nombre de usuario con el que se inicia sesión; no se puede repetir.
A16: private | B16: clave | C16: String | E16: no final | F16: no static | G16: "" (cadena vacía) | J16: Contraseña del usuario; se guarda cifrada con BCrypt y nunca se devuelve al consultar el usuario.
A17: private | B17: rol | C17: String | E17: no final | F17: no static | G17: "" (cadena vacía) | J17: Rol del usuario dentro de la aplicación; solo existe el rol Administrador.
A18: private | B18: activo | C18: boolean/Boolean | E18: no final | F18: no static | G18: true | J18: Indica si el usuario está activo; un usuario inactivo no puede iniciar sesión.
A20: Constructores
A21: Modificador de acceso | B21: Nombre | C21: Tipo constructor | D21: Descripción | E21: Parámetros | M21: Excepciones
E22: Nombre | F22: Tipo de dato | G22: ¿Cuál? | H22: Tipo parámetro | I22: Tipo modificación atributo | J22: Descripción
A23: private | B23: =B2 -> Usuario | C23: Parametrizado | D23: Constructor privado: crea la instancia de Usuario copiando los valores ya saneados que reunió el Builder. Solo se invoca desde Builder.build(). | E23: builder | F23: Otro | G23: Builder | H23: Por valor | I23: no final | J23: Builder con los valores de los atributos de la clase.
A25: Métodos accesores
A26: Modificador de acceso | B26: Nombre | C26: Tipo método accesor | D26: Tipo modificación método | E26: Descripción | F26: Parámetros | L26: Tipo dato de retorno | N26: Excepciones
F27: Nombre | G27: Tipo de dato | H27: ¿Cuál? | I27: Tipo parámetro | J27: Tipo modificación atributo | K27: Descripción | L27: Tipo de dato | M27: ¿Cuál?
A28: public | B28: getId | C28: getter | D28: no final | E28: Método encargado de obtener el valor del atributo id. | L28: Otro | M28: UUID
A29: public | B29: getUsuario | C29: getter | D29: no final | E29: Método encargado de obtener el valor del atributo usuario. | L29: String
A30: public | B30: getClave | C30: getter | D30: no final | E30: Método encargado de obtener el valor del atributo clave. | L30: String
A31: public | B31: getRol | C31: getter | D31: no final | E31: Método encargado de obtener el valor del atributo rol. | L31: String
A32: public | B32: isActivo | C32: getter | D32: no final | E32: Método encargado de obtener el valor del atributo activo. | L32: boolean/Boolean
A34: Métodos
A35: Modificador de acceso | B35: Nombre | C35: Tipo acceso método | D35: Tipo modificación método | E35: Descripción | F35: Parámetros | L35: Tipo dato de retorno | N35: Excepciones
F36: Nombre | G36: Tipo de dato | H36: ¿Cuál? | I36: Tipo parámetro | J36: Tipo modificación atributo | K36: Descripción | L36: Tipo de dato | M36: ¿Cuál?
A37: public | B37: iniciarSesion | C37: no static | D37: no final | E37: Permite que el administrador ingrese a la aplicación con su usuario y contraseña. | F37: credenciales | G37: Otro | H37: Usuario | I37: Por valor | J37: no final | K37: Usuario y contraseña con los que se desea ingresar. | L37: Otro | M37: Usuario | N37: No se recibieron el usuario o la contraseña, o no cumplen la longitud permitida. El usuario no existe, está inactivo o la contraseña no coincide. El usuario no tiene el rol Administrador.
A39: Builder (clase interna public static)
A40: Modificador de acceso | B40: Nombre | C40: Tipo acceso método | D40: Tipo modificación método | E40: Descripción | F40: Parámetros | L40: Tipo dato de retorno | N40: Excepciones
F41: Nombre | G41: Tipo de dato | H41: ¿Cuál? | I41: Tipo parámetro | J41: Tipo modificación atributo | K41: Descripción | L41: Tipo de dato | M41: ¿Cuál?
A42: public | B42: Builder | C42: no static | D42: no final | E42: Constructor del Builder: asigna a cada atributo su valor por defecto.
A43: public | B43: id | C43: no static | D43: no final | E43: Asigna el identificador recibido; si es nulo, asigna el identificador por defecto (00000000-0000-0000-0000-000000000000). | F43: id | G43: Otro | H43: UUID | I43: Por valor | J43: no final | K43: Valor que se desea asignar al atributo id. | L43: Otro | M43: Builder
A44: public | B44: usuario | C44: no static | D44: no final | E44: Asigna el texto recibido sin espacios en blanco al inicio y al final; si es nulo, asigna una cadena vacía. | F44: usuario | G44: String | I44: Por valor | J44: no final | K44: Valor que se desea asignar al atributo usuario. | L44: Otro | M44: Builder
A45: public | B45: clave | C45: no static | D45: no final | E45: Asigna el texto recibido tal como llega, sin quitar espacios (hacen parte de la clave); si es nulo, asigna una cadena vacía. | F45: clave | G45: String | I45: Por valor | J45: no final | K45: Valor que se desea asignar al atributo clave. | L45: Otro | M45: Builder
A46: public | B46: rol | C46: no static | D46: no final | E46: Asigna el texto recibido sin espacios en blanco al inicio y al final, con la primera letra en mayúscula y el resto en minúscula; si es nulo o vacío, asigna una cadena vacía. | F46: rol | G46: String | I46: Por valor | J46: no final | K46: Valor que se desea asignar al atributo rol. | L46: Otro | M46: Builder
A47: public | B47: activo | C47: no static | D47: no final | E47: Asigna el valor recibido. | F47: activo | G47: boolean/Boolean | I47: Por valor | J47: no final | K47: Valor que se desea asignar al atributo activo. | L47: Otro | M47: Builder
A48: public | B48: build | C48: no static | D48: no final | E48: Crea la instancia de Usuario con los valores reunidos en el Builder, usando su constructor privado. | L48: Otro | M48: Usuario
