Workbook

Sheet MER
N20: #VALUE!

Sheet Entidades
A1: Entidad | B1: Descripción
A2: Producto | B2: Representa los artículos que la pizzería comercializa y que pueden ser vendidos al cliente, sirviendo como referencia para identificar y gestionar su oferta comercial.
A3: Proveedor | B3: Representa a las personas o empresas que suministran a la pizzería los insumos y productos necesarios para su operación.
A4: UnidadMedida | B4: Representa las unidades utilizadas por la pizzería para cuantificar los ingredientes, productos y demás elementos que requieren control de cantidades.
A5: Compra | B5: Representa la adquisición de insumos o productos que realiza la pizzería a un proveedor para abastecer las necesidades de su operación.
A6: HistoricoPrecio | B6: Representa el registro de los precios que han tenido los productos de la pizzería a lo largo del tiempo, permitiendo consultar su evolución histórica.
A7: Venta | B7: Representa la operación comercial mediante la cual la pizzería registra los productos adquiridos por un cliente.
A8: DetalleCompra | B8: Representa cada uno de los insumos o productos adquiridos dentro de una compra, especificando qué se compró y en qué cantidad.
A9: DetalleVenta | B9: Representa cada uno de los productos incluidos en una venta, registrando la cantidad adquirida y el valor correspondiente a cada producto.
A10: DetalleReceta | B10: Representa cada uno de los ingredientes necesarios para elaborar una receta, indicando la cantidad requerida y la unidad de medida utilizada.
A11: MovimientoInventario | B11: Representa cada entrada o salida de existencias sobre un lote, generada por una compra, una venta o un cambio, permitiendo mantener el control y la trazabilidad del inventario.
A12: Inventario | B12: Representa las existencias disponibles de los insumos y productos que la pizzería necesita para operar y atender sus ventas.
... A23: Usuario | B23: Representa a la persona que puede ingresar a la aplicación; solo los usuarios activos con rol Administrador pueden iniciar sesión.

Sheet Producto
A1: <-Volver al inicio
A2: =Entidades!$A$1 -> Entidad | B2: =Entidades!A2 -> Producto
A3: =Entidades!$B$1 -> Descripción | B3: =Entidades!B2 -> Representa los artículos que la pizzería comercializa y que pueden ser vendidos al cliente, sirviendo como referencia para identificar y gestionar su oferta comercial.
A4: Atributos
A5: Nombre | B5: Tipo de dato | C5: Longitud | D5: Cantidad dígitos parte entera | E5: Cantidad dígitos parte decimal (Precisión) | F5: ¿Es autoincremento? | G5: ¿Es obligatorio? | H5: ¿Es llave primeria o es parte de ella? | I5: Llave Foránea | L5: Restricciones de unicidad | N5: Restricciones de chequeo | P5: Restricciones de índice | S5: Alias | T5: Descripción del campo
I6: ¿Es llave foránea? | J6: Entidad | K6: Columna(s) | L6: ¿Posee restricción de unicidad o es parte de ella? | M6: Nombre restricción unicidad a la que pertenece | N6: ¿Posee restricción de chequeo o es parte de ella? | O6: Nombre restricción chequeo a la que pertenece | P6: ¿Posee restricción de índice o es parte de ella? | Q6: Tipo | R6: Nombre restricción índice a la que pertenece
A7: id_producto | B7: uniqueidentifier | F7: No | G7: SI | H7: SI | I7: NO | L7: NO | N7: NO | P7: NO | R7: NO | T7: Identificador unico de cada producto que vende la pizzeria (Valor por defecto: newid())
A8: nombre | B8: varchar | C8: 40 | F8: No | G8: SI | H8: NO | I8: NO | L8: SI | M8: uk_producto_nombre_tamano | N8: NO | P8: NO | R8: NO | T8: Nombre del producto; si es un producto interno, el nombre debe coincidir con uno ya existente en ProductoInterno
A9: id_tipo_producto | B9: uniqueidentifier | F9: No | G9: SI | H9: NO | I9: SI | J9: TipoProducto | K9: id_tipo_producto | L9: NO | N9: NO | P9: NO | R9: NO | T9: Tipo de producto al que pertenece (Pizza, Bebida o Adicion)
A10: id_tamano | B10: uniqueidentifier | F10: No | G10: SI | H10: NO | I10: SI | J10: Tamaño | K10: id_tamano | L10: SI | M10: uk_producto_nombre_tamano | N10: NO | P10: NO | R10: NO | T10: Tamaño del producto (Grande, Mediana o Pequeña) para productos que no son pizza el valor es No aplica
A11: id_producto_interno | B11: uniqueidentifier | F11: No | G11: SI | H11: NO | I11: SI | J11: ProductoInterno | K11: id_producto_interno | L11: NO | N11: NO | P11: NO | R11: NO | T11: Producto interno asociado al producto. Si ProductoInterno es Si, es el producto interno con el mismo nombre; si no, es el registro "Sin insumo"
A12: producto_interno | B12: int | F12: No | G12: SI | H12: NO | I12: NO | L12: NO | N12: NO | P12: NO | R12: NO | T12: Dato calculado: indica si el producto se vende directamente desde el inventario (por ejemplo una bebida). Es Si cuando tiene un ProductoInternoAsociado y No cuando el asociado es "Sin insumo" (Columna calculada: case when id_producto_interno = '00000000-0000-0000-0000-000000000000' then 0 else 1 end)
A13: precio | B13: decimal | D13: 18 | E13: 2 | F13: No | G13: SI | H13: NO | I13: NO | L13: NO | N13: SI | O13: ck_producto_precio | P13: NO | R13: NO | T13: Contiene el precio de venta publico del producto
A14: activo | B14: bit | F14: No | G14: SI | H14: NO | I14: NO | L14: NO | N14: NO | P14: NO | R14: NO | T14: Indica si el producto esta activo y disponible para la venta (Valor por defecto: 1)

Sheet Proveedor
A1: <-Volver al inicio
A2: =Entidades!$A$1 -> Entidad | B2: =Entidades!A3 -> Proveedor
A3: =Entidades!$B$1 -> Descripción | B3: =Entidades!B3 -> Representa a las personas o empresas que suministran a la pizzería los insumos y productos necesarios para su operación.
A4: Atributos
A5: Nombre | B5: Tipo de dato | C5: Longitud | D5: Cantidad dígitos parte entera | E5: Cantidad dígitos parte decimal (Precisión) | F5: ¿Es autoincremento? | G5: ¿Es obligatorio? | H5: ¿Es llave primeria o es parte de ella? | I5: Llave Foránea | L5: Restricciones de unicidad | N5: Restricciones de chequeo | P5: Restricciones de índice | S5: Alias | T5: Descripción del campo
I6: ¿Es llave foránea? | J6: Entidad | K6: Columna(s) | L6: ¿Posee restricción de unicidad o es parte de ella? | M6: Nombre restricción unicidad a la que pertenece | N6: ¿Posee restricción de chequeo o es parte de ella? | O6: Nombre restricción chequeo a la que pertenece | P6: ¿Posee restricción de índice o es parte de ella? | Q6: Tipo | R6: Nombre restricción índice a la que pertenece
A7: id_proveedor | B7: uniqueidentifier | F7: No | G7: SI | H7: SI | I7: NO | L7: NO | N7: NO | P7: NO | R7: NO | T7: Identificador unico del proveedor dentro de la pizzeria (Valor por defecto: newid())
A8: nombre_empresa | B8: varchar | C8: 60 | F8: No | G8: SI | H8: NO | I8: NO | L8: SI | M8: Unique de columna (sin nombre en el script) | N8: NO | P8: NO | R8: NO | T8: Nombre de la empresa a la que pertenece el proveedor
A9: nit | B9: varchar | C9: 15 | F9: No | G9: SI | H9: NO | I9: NO | L9: SI | M9: Unique de columna (sin nombre en el script) | N9: NO | P9: NO | R9: NO | T9: Numero de identificacion tributaria (NIT) del proveedor; no se puede repetir entre proveedores
A10: contacto | B10: varchar | C10: 10 | F10: No | G10: SI | H10: NO | I10: NO | L10: NO | N10: NO | P10: NO | R10: NO | T10: Forma de comunicacion directa con el proveedor
A11: activo | B11: bit | F11: No | G11: SI | H11: NO | I11: NO | L11: NO | N11: NO | P11: NO | R11: NO | T11: Indica si el proveedor esta activo y disponible para nuevas compras (Valor por defecto: 1)

Sheet UnidadMedida
A1: <-Volver al inicio
A2: =Entidades!$A$1 -> Entidad | B2: =Entidades!A4 -> UnidadMedida
A3: =Entidades!$B$1 -> Descripción | B3: =Entidades!B4 -> Representa las unidades utilizadas por la pizzería para cuantificar los ingredientes, productos y demás elementos que requieren control de cantidades.
A4: Atributos
A5: Nombre | B5: Tipo de dato | C5: Longitud | D5: Cantidad dígitos parte entera | E5: Cantidad dígitos parte decimal (Precisión) | F5: ¿Es autoincremento? | G5: ¿Es obligatorio? | H5: ¿Es llave primeria o es parte de ella? | I5: Llave Foránea | L5: Restricciones de unicidad | N5: Restricciones de chequeo | P5: Restricciones de índice | S5: Alias | T5: Descripción del campo
I6: ¿Es llave foránea? | J6: Entidad | K6: Columna(s) | L6: ¿Posee restricción de unicidad o es parte de ella? | M6: Nombre restricción unicidad a la que pertenece | N6: ¿Posee restricción de chequeo o es parte de ella? | O6: Nombre restricción chequeo a la que pertenece | P6: ¿Posee restricción de índice o es parte de ella? | Q6: Tipo | R6: Nombre restricción índice a la que pertenece
A7: id_unidad_medida | B7: uniqueidentifier | F7: No | G7: SI | H7: SI | I7: NO | L7: NO | N7: NO | P7: NO | R7: NO | T7: Identificador unico de unidad de medida dentro del sistema (Valor por defecto: newid())
A8: unidad_medida | B8: varchar | C8: 4 | F8: No | G8: SI | H8: NO | I8: NO | L8: SI | M8: Unique de columna (sin nombre en el script) | N8: NO | P8: NO | R8: NO | T8: Abreviatura de la unidad de medida (g, kg, ml, l o und)
A9: tipo_medida | B9: varchar | C9: 10 | F9: No | G9: SI | H9: NO | I9: NO | L9: NO | N9: SI | O9: ck_unidad_medida_tipo_medida | P9: NO | R9: NO | T9: Tipo de medida a la que corresponde cada unidad de medida

Sheet Compra
A1: <-Volver al inicio
A2: =Entidades!$A$1 -> Entidad | B2: =Entidades!A5 -> Compra
A3: =Entidades!$B$1 -> Descripción | B3: =Entidades!B5 -> Representa la adquisición de insumos o productos que realiza la pizzería a un proveedor para abastecer las necesidades de su operación.
A4: Atributos
A5: Nombre | B5: Tipo de dato | C5: Longitud | D5: Cantidad dígitos parte entera | E5: Cantidad dígitos parte decimal (Precisión) | F5: ¿Es autoincremento? | G5: ¿Es obligatorio? | H5: ¿Es llave primeria o es parte de ella? | I5: Llave Foránea | L5: Restricciones de unicidad | N5: Restricciones de chequeo | P5: Restricciones de índice | S5: Alias | T5: Descripción del campo
I6: ¿Es llave foránea? | J6: Entidad | K6: Columna(s) | L6: ¿Posee restricción de unicidad o es parte de ella? | M6: Nombre restricción unicidad a la que pertenece | N6: ¿Posee restricción de chequeo o es parte de ella? | O6: Nombre restricción chequeo a la que pertenece | P6: ¿Posee restricción de índice o es parte de ella? | Q6: Tipo | R6: Nombre restricción índice a la que pertenece
A7: id_compra | B7: uniqueidentifier | F7: No | G7: SI | H7: SI | I7: NO | L7: NO | N7: NO | P7: NO | R7: NO | T7: Identificador unico de cada compra de la pizzeria (Valor por defecto: newid())
A8: id_proveedor | B8: uniqueidentifier | F8: No | G8: SI | H8: NO | I8: SI | J8: Proveedor | K8: id_proveedor | L8: SI | M8: uk_compra_proveedor_numero_factura | N8: NO | P8: NO | R8: NO | T8: Proveedor al que se le hizo la compra
A9: fecha_compra | B9: date | F9: No | G9: SI | H9: NO | I9: NO | L9: NO | N9: NO | P9: NO | R9: NO | T9: Representa la fecha en la que se efectuó la compra
A10: numero_factura | B10: varchar | C10: 40 | F10: No | G10: SI | H10: NO | I10: NO | L10: SI | M10: uk_compra_proveedor_numero_factura | N10: NO | P10: NO | R10: NO | T10: Número de factura que el proveedor entrega al momento de la compra.
A11: total | B11: decimal | D11: 18 | E11: 2 | F11: No | G11: SI | H11: NO | I11: NO | L11: NO | N11: SI | O11: ck_compra_total | P11: NO | R11: NO | T11: Representa el valor monetario total de los productos comprados al proveedor.

Sheet HistoricoPrecio
A1: <-Volver al inicio
A2: =Entidades!$A$1 -> Entidad | B2: =Entidades!A6 -> HistoricoPrecio
A3: =Entidades!$B$1 -> Descripción | B3: =Entidades!B6 -> Representa el registro de los precios que han tenido los productos de la pizzería a lo largo del tiempo, permitiendo consultar su evolución histórica.
A4: Atributos
A5: Nombre | B5: Tipo de dato | C5: Longitud | D5: Cantidad dígitos parte entera | E5: Cantidad dígitos parte decimal (Precisión) | F5: ¿Es autoincremento? | G5: ¿Es obligatorio? | H5: ¿Es llave primeria o es parte de ella? | I5: Llave Foránea | L5: Restricciones de unicidad | N5: Restricciones de chequeo | P5: Restricciones de índice | S5: Alias | T5: Descripción del campo
I6: ¿Es llave foránea? | J6: Entidad | K6: Columna(s) | L6: ¿Posee restricción de unicidad o es parte de ella? | M6: Nombre restricción unicidad a la que pertenece | N6: ¿Posee restricción de chequeo o es parte de ella? | O6: Nombre restricción chequeo a la que pertenece | P6: ¿Posee restricción de índice o es parte de ella? | Q6: Tipo | R6: Nombre restricción índice a la que pertenece
A7: id_historico_precio | B7: uniqueidentifier | F7: No | G7: SI | H7: SI | I7: NO | L7: NO | N7: NO | P7: NO | R7: NO | T7: Representa el identificador único de cada historico de precio (Valor por defecto: newid())
A8: id_producto | B8: uniqueidentifier | F8: No | G8: SI | H8: NO | I8: SI | J8: Producto | K8: id_producto | L8: SI | M8: uk_historico_precio_producto_fecha_inicio, uk_historico_precio_producto_fecha_fin | N8: NO | P8: NO | R8: NO | T8: Producto al cual se le realizo un cambio de precio
A9: precio | B9: decimal | D9: 18 | E9: 2 | F9: No | G9: SI | H9: NO | I9: NO | L9: NO | N9: SI | O9: ck_historico_precio_precio | P9: NO | R9: NO | T9: Precio correspondiente al producto en ese periodo
A10: fecha_inicio | B10: date | F10: No | G10: SI | H10: NO | I10: NO | L10: SI | M10: uk_historico_precio_producto_fecha_inicio | N10: SI | O10: ck_historico_precio_fechas | P10: NO | R10: NO | T10: Fecha en la que se dio inicio al precio de un producto, ya sea que en esta fecha se ingreso por primera vez el producto o en esta fecha se inicio el nuevo precio de un producto
A11: fecha_fin | B11: date | F11: No | G11: SI | H11: NO | I11: NO | L11: SI | M11: uk_historico_precio_producto_fecha_fin | N11: SI | O11: ck_historico_precio_fechas | P11: NO | R11: NO | T11: Fecha en la que finaliza ese precio en especifico (Valor por defecto: 1000-01-01)

Sheet Venta
A1: <-Volver al inicio
A2: =Entidades!$A$1 -> Entidad | B2: =Entidades!A7 -> Venta
A3: =Entidades!$B$1 -> Descripción | B3: =Entidades!B7 -> Representa la operación comercial mediante la cual la pizzería registra los productos adquiridos por un cliente.
A4: Atributos
A5: Nombre | B5: Tipo de dato | C5: Longitud | D5: Cantidad dígitos parte entera | E5: Cantidad dígitos parte decimal (Precisión) | F5: ¿Es autoincremento? | G5: ¿Es obligatorio? | H5: ¿Es llave primeria o es parte de ella? | I5: Llave Foránea | L5: Restricciones de unicidad | N5: Restricciones de chequeo | P5: Restricciones de índice | S5: Alias | T5: Descripción del campo
I6: ¿Es llave foránea? | J6: Entidad | K6: Columna(s) | L6: ¿Posee restricción de unicidad o es parte de ella? | M6: Nombre restricción unicidad a la que pertenece | N6: ¿Posee restricción de chequeo o es parte de ella? | O6: Nombre restricción chequeo a la que pertenece | P6: ¿Posee restricción de índice o es parte de ella? | Q6: Tipo | R6: Nombre restricción índice a la que pertenece
A7: id_venta | B7: uniqueidentifier | F7: No | G7: SI | H7: SI | I7: NO | L7: NO | N7: NO | P7: NO | R7: NO | T7: Identificador de cada venta dentro del sistema (Valor por defecto: newid())
A8: fecha | B8: date | F8: No | G8: SI | H8: NO | I8: NO | L8: NO | N8: NO | P8: NO | R8: NO | T8: Fecha en la que se realizo la venta
A9: hora | B9: time | E9: 0 | F9: No | G9: SI | H9: NO | I9: NO | L9: NO | N9: NO | P9: NO | R9: NO | T9: Hora en la que se realizo la venta
A10: factura | B10: varchar | C10: 9 | F10: No | G10: SI | H10: NO | I10: NO | L10: SI | M10: Unique de columna (sin nombre en el script) | N10: SI | O10: ck_venta_factura | P10: NO | R10: NO | T10: Número de la factura de venta. El sistema lo asigna solo en el momento en que la venta se hace
A11: cliente | B11: varchar | C11: 10 | F11: No | G11: SI | H11: NO | I11: NO | L11: NO | N11: NO | P11: NO | R11: NO | T11: Indicativo de a que cliente le pertenece la venta (Valor por defecto: 2222222222)
A12: total | B12: decimal | D12: 18 | E12: 2 | F12: No | G12: SI | H12: NO | I12: NO | L12: NO | N12: SI | O12: ck_venta_total | P12: NO | R12: NO | T12: Total de la venta

Sheet DetalleCompra
A1: <-Volver al inicio
A2: =Entidades!$A$1 -> Entidad | B2: =Entidades!A8 -> DetalleCompra
A3: =Entidades!$B$1 -> Descripción | B3: =Entidades!B8 -> Representa cada uno de los insumos o productos adquiridos dentro de una compra, especificando qué se compró y en qué cantidad.
A4: Atributos
A5: Nombre | B5: Tipo de dato | C5: Longitud | D5: Cantidad dígitos parte entera | E5: Cantidad dígitos parte decimal (Precisión) | F5: ¿Es autoincremento? | G5: ¿Es obligatorio? | H5: ¿Es llave primeria o es parte de ella? | I5: Llave Foránea | L5: Restricciones de unicidad | N5: Restricciones de chequeo | P5: Restricciones de índice | S5: Alias | T5: Descripción del campo
I6: ¿Es llave foránea? | J6: Entidad | K6: Columna(s) | L6: ¿Posee restricción de unicidad o es parte de ella? | M6: Nombre restricción unicidad a la que pertenece | N6: ¿Posee restricción de chequeo o es parte de ella? | O6: Nombre restricción chequeo a la que pertenece | P6: ¿Posee restricción de índice o es parte de ella? | Q6: Tipo | R6: Nombre restricción índice a la que pertenece
A7: id_detalle_compra | B7: uniqueidentifier | F7: No | G7: SI | H7: SI | I7: NO | L7: NO | N7: NO | P7: NO | R7: NO | T7: Identificador unico de cada detalle de compra (Valor por defecto: newid())
A8: id_compra | B8: uniqueidentifier | F8: No | G8: SI | H8: NO | I8: SI | J8: Compra | K8: id_compra | L8: SI | M8: uk_detalle_compra_compra_producto_fecha | N8: NO | P8: NO | R8: NO | T8: Compra a la que pertenece este detalle
A9: id_producto_interno | B9: uniqueidentifier | F9: No | G9: SI | H9: NO | I9: SI | J9: ProductoInterno | K9: id_producto_interno | L9: SI | M9: uk_detalle_compra_compra_producto_fecha | N9: NO | P9: NO | R9: NO | T9: Producto interno que se compra en este detalle
A10: cantidad | B10: decimal | D10: 18 | E10: 4 | F10: No | G10: SI | H10: NO | I10: NO | L10: NO | N10: SI | O10: ck_detalle_compra_cantidad | P10: NO | R10: NO | T10: Cantidad que se compro de un producto determinado
A11: id_unidad_medida | B11: uniqueidentifier | F11: No | G11: SI | H11: NO | I11: SI | J11: UnidadMedida | K11: id_unidad_medida | L11: NO | N11: NO | P11: NO | R11: NO | T11: Se ingresa la unidad de medida en la que se hizo la compra, esta unidad de medida debe ser valida para el tipo de dato, por ejemplo si el producto es aceite de oliva, el va a ser de tipo volumen entonces puede estar en ml o l
A12: precio_compra | B12: decimal | D12: 18 | E12: 2 | F12: No | G12: SI | H12: NO | I12: NO | L12: NO | N12: SI | O12: ck_detalle_compra_precio_compra | P12: NO | R12: NO | T12: Valor monetario de cada producto
A13: fecha_vencimiento | B13: date | F13: No | G13: SI | H13: NO | I13: NO | L13: SI | M13: uk_detalle_compra_compra_producto_fecha | N13: NO | P13: NO | R13: NO | T13: Se ingresa la fecha de vencimiento del producto, en caso de que la traiga de lo contrario hay que calcular una vida util (Valor por defecto: 1000-01-01)
A14: id_tipo_movimiento | B14: uniqueidentifier | F14: No | G14: SI | H14: NO | I14: SI | J14: TipoMovimiento | K14: id_tipo_movimiento | L14: SI | M14: Unique de columna (sin nombre en el script) | N14: NO | P14: NO | R14: NO | T14: Codigo de la operacion (TipoMovimiento) propio de este detalle de compra; es el mismo que lleva su movimiento de entrada

Sheet DetalleVenta
A1: <-Volver al inicio
A2: =Entidades!$A$1 -> Entidad | B2: =Entidades!A9 -> DetalleVenta
A3: =Entidades!$B$1 -> Descripción | B3: =Entidades!B9 -> Representa cada uno de los productos incluidos en una venta, registrando la cantidad adquirida y el valor correspondiente a cada producto.
A4: Atributos
A5: Nombre | B5: Tipo de dato | C5: Longitud | D5: Cantidad dígitos parte entera | E5: Cantidad dígitos parte decimal (Precisión) | F5: ¿Es autoincremento? | G5: ¿Es obligatorio? | H5: ¿Es llave primeria o es parte de ella? | I5: Llave Foránea | L5: Restricciones de unicidad | N5: Restricciones de chequeo | P5: Restricciones de índice | S5: Alias | T5: Descripción del campo
I6: ¿Es llave foránea? | J6: Entidad | K6: Columna(s) | L6: ¿Posee restricción de unicidad o es parte de ella? | M6: Nombre restricción unicidad a la que pertenece | N6: ¿Posee restricción de chequeo o es parte de ella? | O6: Nombre restricción chequeo a la que pertenece | P6: ¿Posee restricción de índice o es parte de ella? | Q6: Tipo | R6: Nombre restricción índice a la que pertenece
A7: id_detalle_venta | B7: uniqueidentifier | F7: No | G7: SI | H7: SI | I7: NO | L7: NO | N7: NO | P7: NO | R7: NO | T7: Identificador unico del detalle venta dentro de la pizzeria (Valor por defecto: newid())
A8: id_venta | B8: uniqueidentifier | F8: No | G8: SI | H8: NO | I8: SI | J8: Venta | K8: id_venta | L8: SI | M8: uk_detalle_venta_venta_producto | N8: NO | P8: NO | R8: NO | T8: Venta a la que pertenece; se identifica con su numero de factura
A9: id_producto | B9: uniqueidentifier | F9: No | G9: SI | H9: NO | I9: SI | J9: Producto | K9: id_producto | L9: SI | M9: uk_detalle_venta_venta_producto | N9: NO | P9: NO | R9: NO | T9: Producto que ofrece la pizzeria
A10: cantidad | B10: int | F10: No | G10: SI | H10: NO | I10: NO | L10: NO | N10: SI | O10: ck_detalle_venta_cantidad | P10: NO | R10: NO | T10: Cantidad del producto que pide el cliente
A11: precio_producto | B11: decimal | D11: 18 | E11: 2 | F11: No | G11: SI | H11: NO | I11: NO | L11: NO | N11: SI | O11: ck_detalle_venta_precio_producto | P11: NO | R11: NO | T11: Precio de cada producto
A12: subtotal | B12: decimal | D12: 18 | E12: 2 | F12: No | G12: SI | H12: NO | I12: NO | L12: NO | N12: NO | P12: NO | R12: NO | T12: Por cada cantidad que pide el cliente de un producto se calcula un total (Columna calculada: cantidad * precio_producto)

Sheet ConsumoVenta
A1: <-Volver al inicio
A2: =Entidades!$A$1 -> Entidad | B2: =Entidades!A21 -> ConsumoVenta
A3: =Entidades!$B$1 -> Descripción | B3: =Entidades!B21 -> Representa los productos internos que se consumen por cada detalle de venta, según la receta del producto vendido o su producto interno asociado.
A4: Atributos
A5: Nombre | B5: Tipo de dato | C5: Longitud | D5: Cantidad dígitos parte entera | E5: Cantidad dígitos parte decimal (Precisión) | F5: ¿Es autoincremento? | G5: ¿Es obligatorio? | H5: ¿Es llave primeria o es parte de ella? | I5: Llave Foránea | L5: Restricciones de unicidad | N5: Restricciones de chequeo | P5: Restricciones de índice | S5: Alias | T5: Descripción del campo
I6: ¿Es llave foránea? | J6: Entidad | K6: Columna(s) | L6: ¿Posee restricción de unicidad o es parte de ella? | M6: Nombre restricción unicidad a la que pertenece | N6: ¿Posee restricción de chequeo o es parte de ella? | O6: Nombre restricción chequeo a la que pertenece | P6: ¿Posee restricción de índice o es parte de ella? | Q6: Tipo | R6: Nombre restricción índice a la que pertenece
A7: id_consumo_venta | B7: uniqueidentifier | F7: No | G7: SI | H7: SI | I7: NO | L7: NO | N7: NO | P7: NO | R7: NO | T7: Identificador unico de cada consumo de venta (Valor por defecto: newid())
A8: id_detalle_venta | B8: uniqueidentifier | F8: No | G8: SI | H8: NO | I8: SI | J8: DetalleVenta | K8: id_detalle_venta | L8: SI | M8: uk_consumo_venta_detalle_venta_producto_interno | N8: NO | P8: NO | R8: NO | T8: Detalle de venta (renglon de la venta) que origina el consumo
A9: id_producto_interno | B9: uniqueidentifier | F9: No | G9: SI | H9: NO | I9: SI | J9: ProductoInterno | K9: id_producto_interno | L9: SI | M9: uk_consumo_venta_detalle_venta_producto_interno | N9: NO | P9: NO | R9: NO | T9: Producto interno que se debe consumir segun la receta del producto vendido
A10: cantidad | B10: decimal | D10: 18 | E10: 4 | F10: No | G10: SI | H10: NO | I10: NO | L10: NO | N10: SI | O10: ck_consumo_venta_cantidad | P10: NO | R10: NO | T10: Cantidad del producto interno que se consume: cantidad vendida por la cantidad de la receta, en la unidad de la receta
A11: id_unidad_medida | B11: uniqueidentifier | F11: No | G11: SI | H11: NO | I11: SI | J11: UnidadMedida | K11: id_unidad_medida | L11: NO | N11: NO | P11: NO | R11: NO | T11: Unidad de medida de la cantidad; es la misma de la receta y queda guardada aunque la receta cambie despues
A12: id_tipo_movimiento | B12: uniqueidentifier | F12: No | G12: SI | H12: NO | I12: SI | J12: TipoMovimiento | K12: id_tipo_movimiento | L12: SI | M12: Unique de columna (sin nombre en el script) | N12: NO | P12: NO | R12: NO | T12: Codigo de la operacion (TipoMovimiento) propio de este consumo; es el mismo que lleva su movimiento de salida

Sheet DetalleReceta
A1: <-Volver al inicio
A2: =Entidades!$A$1 -> Entidad | B2: =Entidades!A10 -> DetalleReceta
A3: =Entidades!$B$1 -> Descripción | B3: =Entidades!B10 -> Representa cada uno de los ingredientes necesarios para elaborar una receta, indicando la cantidad requerida y la unidad de medida utilizada.
A4: Atributos
A5: Nombre | B5: Tipo de dato | C5: Longitud | D5: Cantidad dígitos parte entera | E5: Cantidad dígitos parte decimal (Precisión) | F5: ¿Es autoincremento? | G5: ¿Es obligatorio? | H5: ¿Es llave primeria o es parte de ella? | I5: Llave Foránea | L5: Restricciones de unicidad | N5: Restricciones de chequeo | P5: Restricciones de índice | S5: Alias | T5: Descripción del campo
I6: ¿Es llave foránea? | J6: Entidad | K6: Columna(s) | L6: ¿Posee restricción de unicidad o es parte de ella? | M6: Nombre restricción unicidad a la que pertenece | N6: ¿Posee restricción de chequeo o es parte de ella? | O6: Nombre restricción chequeo a la que pertenece | P6: ¿Posee restricción de índice o es parte de ella? | Q6: Tipo | R6: Nombre restricción índice a la que pertenece
A7: id_detalle_receta | B7: uniqueidentifier | F7: No | G7: SI | H7: SI | I7: NO | L7: NO | N7: NO | P7: NO | R7: NO | T7: Identificador unico de cada ingrediente (linea) de una receta (Valor por defecto: newid())
A8: id_producto | B8: uniqueidentifier | F8: No | G8: SI | H8: NO | I8: SI | J8: Producto | K8: id_producto | L8: SI | M8: uk_detalle_receta_producto_producto_interno | N8: NO | P8: NO | R8: NO | T8: Producto (Pizza o Adicion) al que pertenece esta linea de receta (Al eliminar el producto se eliminan sus detalles de receta: on delete cascade)
A9: id_producto_interno | B9: uniqueidentifier | F9: No | G9: SI | H9: NO | I9: SI | J9: ProductoInterno | K9: id_producto_interno | L9: SI | M9: uk_detalle_receta_producto_producto_interno | N9: NO | P9: NO | R9: NO | T9: Producto interno que se utiliza en la receta
A10: cantidad | B10: decimal | D10: 18 | E10: 4 | F10: No | G10: SI | H10: NO | I10: NO | L10: NO | N10: SI | O10: ck_detalle_receta_cantidad | P10: NO | R10: NO | T10: Cantidad del producto interno
A11: id_unidad_medida | B11: uniqueidentifier | F11: No | G11: SI | H11: NO | I11: SI | J11: UnidadMedida | K11: id_unidad_medida | L11: NO | N11: NO | P11: NO | R11: NO | T11: Unidad de medida del ingrediente; se asigna automaticamente segun el tipo de medida del producto interno (Peso: g, Volumen: ml, Unidad: und)

Sheet MovimientoInventario
A1: <-Volver al inicio
A2: =Entidades!$A$1 -> Entidad | B2: =Entidades!A11 -> MovimientoInventario
A3: =Entidades!$B$1 -> Descripción | B3: =Entidades!B11 -> Representa cada entrada o salida de existencias sobre un lote, generada por una compra, una venta o un cambio, permitiendo mantener el control y la trazabilidad del inventario.
A4: Atributos
A5: Nombre | B5: Tipo de dato | C5: Longitud | D5: Cantidad dígitos parte entera | E5: Cantidad dígitos parte decimal (Precisión) | F5: ¿Es autoincremento? | G5: ¿Es obligatorio? | H5: ¿Es llave primeria o es parte de ella? | I5: Llave Foránea | L5: Restricciones de unicidad | N5: Restricciones de chequeo | P5: Restricciones de índice | S5: Alias | T5: Descripción del campo
I6: ¿Es llave foránea? | J6: Entidad | K6: Columna(s) | L6: ¿Posee restricción de unicidad o es parte de ella? | M6: Nombre restricción unicidad a la que pertenece | N6: ¿Posee restricción de chequeo o es parte de ella? | O6: Nombre restricción chequeo a la que pertenece | P6: ¿Posee restricción de índice o es parte de ella? | Q6: Tipo | R6: Nombre restricción índice a la que pertenece
A7: id_movimiento_inventario | B7: uniqueidentifier | F7: No | G7: SI | H7: SI | I7: NO | L7: NO | N7: NO | P7: NO | R7: NO | T7: Identificador unico de cada movimiento: una entrada o salida concreta de un lote (Valor por defecto: newid())
A8: id_clase_movimiento | B8: uniqueidentifier | F8: No | G8: SI | H8: NO | I8: SI | J8: ClaseMovimiento | K8: id_clase_movimiento | L8: NO | N8: NO | P8: NO | R8: NO | T8: Clase de movimiento: Entrada (suma al inventario) o Salida (resta del inventario)
A9: id_tipo_movimiento | B9: uniqueidentifier | F9: No | G9: SI | H9: NO | I9: SI | J9: TipoMovimiento | K9: id_tipo_movimiento | L9: NO | N9: NO | P9: NO | R9: NO | T9: Codigo de la operacion (TipoMovimiento) que genero el movimiento; a traves de el se conoce la CategoriaOrigen y el documento de origen
A10: cantidad | B10: decimal | D10: 18 | E10: 4 | F10: No | G10: SI | H10: NO | I10: NO | L10: NO | N10: SI | O10: ck_movimiento_inventario_cantidad | P10: NO | R10: NO | T10: Cantidad que entro o salio del lote, expresada en la unidad de medida del lote (kg, l o und)
A11: fecha_movimiento | B11: date | F11: No | G11: SI | H11: NO | I11: NO | L11: NO | N11: NO | P11: NO | R11: NO | T11: Fecha en la que se registra el movimiento de inventario, correspondiente al momento en que se realiza la entrada o salida sobre el lote.
A12: id_lote | B12: uniqueidentifier | F12: No | G12: SI | H12: NO | I12: SI | J12: Lote | K12: id_lote | L12: NO | N12: NO | P12: NO | R12: NO | T12: Lote sobre el que se realizo la entrada o salida. Por el lote se conoce el producto interno y la unidad de medida

Sheet Inventario
A1: <-Volver al inicio
A2: =Entidades!$A$1 -> Entidad | B2: =Entidades!A12 -> Inventario
A3: =Entidades!$B$1 -> Descripción | B3: =Entidades!B12 -> Representa las existencias disponibles de los insumos y productos que la pizzería necesita para operar y atender sus ventas.
A4: Atributos
A5: Nombre | B5: Tipo de dato | C5: Longitud | D5: Cantidad dígitos parte entera | E5: Cantidad dígitos parte decimal (Precisión) | F5: ¿Es autoincremento? | G5: ¿Es obligatorio? | H5: ¿Es llave primeria o es parte de ella? | I5: Llave Foránea | L5: Restricciones de unicidad | N5: Restricciones de chequeo | P5: Restricciones de índice | S5: Alias | T5: Descripción del campo
I6: ¿Es llave foránea? | J6: Entidad | K6: Columna(s) | L6: ¿Posee restricción de unicidad o es parte de ella? | M6: Nombre restricción unicidad a la que pertenece | N6: ¿Posee restricción de chequeo o es parte de ella? | O6: Nombre restricción chequeo a la que pertenece | P6: ¿Posee restricción de índice o es parte de ella? | Q6: Tipo | R6: Nombre restricción índice a la que pertenece
A7: id_inventario | B7: uniqueidentifier | F7: No | G7: SI | H7: SI | I7: NO | L7: NO | N7: NO | P7: NO | R7: NO | T7: Identificador unico de cada registro de inventario (Valor por defecto: newid())
A8: id_producto_interno | B8: uniqueidentifier | F8: No | G8: SI | H8: NO | I8: SI | J8: ProductoInterno | K8: id_producto_interno | L8: SI | M8: Unique de columna (sin nombre en el script) | N8: NO | P8: NO | R8: NO | T8: Producto interno (ingrediente o bebida) al que corresponde este registro de inventario
A9: cantidad_total | B9: decimal | D9: 18 | E9: 4 | F9: No | G9: SI | H9: NO | I9: NO | L9: NO | N9: SI | O9: ck_inventario_cantidad_total | P9: NO | R9: NO | T9: Cantidad Total del producto
A10: id_unidad_medida | B10: uniqueidentifier | F10: No | G10: SI | H10: NO | I10: SI | J10: UnidadMedida | K10: id_unidad_medida | L10: NO | N10: NO | P10: NO | R10: NO | T10: Unidad de medida que se maneja en el inventario
A11: stock_minimo | B11: decimal | D11: 18 | E11: 4 | F11: No | G11: SI | H11: NO | I11: NO | L11: NO | N11: SI | O11: ck_inventario_stock_minimo | P11: NO | R11: NO | T11: Cantidad minima de cada producto interno que debe haber en el inventario, expresada en la misma unidad de medida de inventario (Valor por defecto: 1)

Sheet Lote
A1: <-Volver al inicio
A2: =Entidades!$A$1 -> Entidad | B2: =Entidades!A13 -> Lote
A3: =Entidades!$B$1 -> Descripción | B3: =Entidades!B13 -> Representa un conjunto de unidades de un mismo insumo recibido en una compra o como reemplazo en un cambio, identificado para controlar su cantidad, saldo, fecha de vencimiento y trazabilidad dentro del inventario.
A4: Atributos
A5: Nombre | B5: Tipo de dato | C5: Longitud | D5: Cantidad dígitos parte entera | E5: Cantidad dígitos parte decimal (Precisión) | F5: ¿Es autoincremento? | G5: ¿Es obligatorio? | H5: ¿Es llave primeria o es parte de ella? | I5: Llave Foránea | L5: Restricciones de unicidad | N5: Restricciones de chequeo | P5: Restricciones de índice | S5: Alias | T5: Descripción del campo
I6: ¿Es llave foránea? | J6: Entidad | K6: Columna(s) | L6: ¿Posee restricción de unicidad o es parte de ella? | M6: Nombre restricción unicidad a la que pertenece | N6: ¿Posee restricción de chequeo o es parte de ella? | O6: Nombre restricción chequeo a la que pertenece | P6: ¿Posee restricción de índice o es parte de ella? | Q6: Tipo | R6: Nombre restricción índice a la que pertenece
A7: id_lote | B7: uniqueidentifier | F7: No | G7: SI | H7: SI | I7: NO | L7: NO | N7: NO | P7: NO | R7: NO | T7: Identificador unico de cada lote dentro de la pizzeria (Valor por defecto: newid())
A8: numero_lote | B8: int | F8: No | G8: SI | H8: NO | I8: NO | L8: SI | M8: uk_lote_producto_numero_lote | N8: SI | O8: ck_lote_numero_lote | P8: NO | R8: NO | T8: Diferenciador numerico de cada lote dependiendo de su respectivo producto
A9: id_producto_interno | B9: uniqueidentifier | F9: No | G9: SI | H9: NO | I9: SI | J9: ProductoInterno | K9: id_producto_interno | L9: SI | M9: uk_lote_producto_numero_lote | N9: NO | P9: NO | R9: NO | T9: Producto interno al que pertenece el lote
A10: cantidad | B10: decimal | D10: 18 | E10: 4 | F10: No | G10: SI | H10: NO | I10: NO | L10: NO | N10: SI | O10: ck_lote_cantidad, ck_lote_saldo | P10: NO | R10: NO | T10: Cantidad con la que entro el lote
A11: saldo | B11: decimal | D11: 18 | E11: 4 | F11: No | G11: SI | H11: NO | I11: NO | L11: NO | N11: SI | O11: ck_lote_saldo | P11: NO | R11: NO | T11: Cantidad que aun queda disponible de este lote, descontando las salidas registradas en Movimiento y los retiros registrados en SalidaLote
A12: id_unidad_medida | B12: uniqueidentifier | F12: No | G12: SI | H12: NO | I12: SI | J12: UnidadMedida | K12: id_unidad_medida | L12: NO | N12: NO | P12: NO | R12: NO | T12: Unidad de medida estandar en lote y posteriormente inventario
A13: fecha_vencimiento | B13: date | F13: No | G13: SI | H13: NO | I13: NO | L13: NO | N13: NO | P13: NO | R13: NO | T13: Fecha de vencimiento del producto
A14: disponible | B14: int | F14: No | G14: SI | H14: NO | I14: NO | L14: NO | N14: NO | P14: NO | R14: NO | T14: Indicativo de disponibilidad de un lote (Columna calculada: case when saldo > 0 then 1 else 0 end)

Sheet SalidaLote
A1: <-Volver al inicio
A2: =Entidades!$A$1 -> Entidad | B2: =Entidades!A22 -> SalidaLote
A3: =Entidades!$B$1 -> Descripción | B3: =Entidades!B22 -> Representa el retiro de una cantidad de producto de un lote próximo a vencer; un lote puede tener como máximo un retiro y este no genera movimiento de inventario.
A4: Atributos
A5: Nombre | B5: Tipo de dato | C5: Longitud | D5: Cantidad dígitos parte entera | E5: Cantidad dígitos parte decimal (Precisión) | F5: ¿Es autoincremento? | G5: ¿Es obligatorio? | H5: ¿Es llave primeria o es parte de ella? | I5: Llave Foránea | L5: Restricciones de unicidad | N5: Restricciones de chequeo | P5: Restricciones de índice | S5: Alias | T5: Descripción del campo
I6: ¿Es llave foránea? | J6: Entidad | K6: Columna(s) | L6: ¿Posee restricción de unicidad o es parte de ella? | M6: Nombre restricción unicidad a la que pertenece | N6: ¿Posee restricción de chequeo o es parte de ella? | O6: Nombre restricción chequeo a la que pertenece | P6: ¿Posee restricción de índice o es parte de ella? | Q6: Tipo | R6: Nombre restricción índice a la que pertenece
A7: id_salida_lote | B7: uniqueidentifier | F7: No | G7: SI | H7: SI | I7: NO | L7: NO | N7: NO | P7: NO | R7: NO | T7: Identificador único de cada retiro realizado sobre un lote. (Valor por defecto: newid())
A8: id_lote | B8: uniqueidentifier | F8: No | G8: SI | H8: NO | I8: SI | J8: Lote | K8: id_lote | L8: SI | M8: Unique de columna (sin nombre en el script) | N8: NO | P8: NO | R8: NO | T8: Lote específico del cual se retira el producto.
A9: cantidad | B9: decimal | D9: 18 | E9: 4 | F9: No | G9: SI | H9: NO | I9: NO | L9: NO | N9: SI | O9: ck_salida_lote_cantidad | P9: NO | R9: NO | T9: Cantidad de producto que se retira efectivamente del lote.
A10: fecha_movimiento | B10: date | F10: No | G10: SI | H10: NO | I10: NO | L10: NO | N10: NO | P10: NO | R10: NO | T10: Fecha en la que se realiza efectivamente el retiro del producto del lote por decisión del usuario.

Sheet ProductoInterno
A1: <-Volver al inicio
A2: =Entidades!$A$1 -> Entidad | B2: =Entidades!A14 -> ProductoInterno
A3: =Entidades!$B$1 -> Descripción | B3: =Entidades!B14 -> Representa cada insumo o producto que la pizzeria compra y almacena en su inventario, ya sea que se consuma dentro de una receta o se venda directamente al cliente.
A4: Atributos
A5: Nombre | B5: Tipo de dato | C5: Longitud | D5: Cantidad dígitos parte entera | E5: Cantidad dígitos parte decimal (Precisión) | F5: ¿Es autoincremento? | G5: ¿Es obligatorio? | H5: ¿Es llave primeria o es parte de ella? | I5: Llave Foránea | L5: Restricciones de unicidad | N5: Restricciones de chequeo | P5: Restricciones de índice | S5: Alias | T5: Descripción del campo
I6: ¿Es llave foránea? | J6: Entidad | K6: Columna(s) | L6: ¿Posee restricción de unicidad o es parte de ella? | M6: Nombre restricción unicidad a la que pertenece | N6: ¿Posee restricción de chequeo o es parte de ella? | O6: Nombre restricción chequeo a la que pertenece | P6: ¿Posee restricción de índice o es parte de ella? | Q6: Tipo | R6: Nombre restricción índice a la que pertenece
A7: id_producto_interno | B7: uniqueidentifier | F7: No | G7: SI | H7: SI | I7: NO | L7: NO | N7: NO | P7: NO | R7: NO | T7: Identificador unico de cada producto interno dentro de la pizzeria (Valor por defecto: newid())
A8: nombre | B8: varchar | C8: 40 | F8: No | G8: SI | H8: NO | I8: NO | L8: SI | M8: Unique de columna (sin nombre en el script) | N8: NO | P8: NO | R8: NO | T8: Nombre de cada producto interno (ingrediente o bebida almacenada)
A9: perecedero | B9: bit | F9: No | G9: SI | H9: NO | I9: NO | L9: NO | N9: SI | O9: ck_producto_interno_vida_util | P9: NO | R9: NO | T9: Cuando se crea el ingrediente se debe decir si es un producto perecedero o no
A10: vida_util | B10: int | F10: No | G10: SI | H10: NO | I10: NO | L10: NO | N10: SI | O10: ck_producto_interno_vida_util | P10: NO | R10: NO | T10: Vida util en dias: de 1 a 400 si el producto es perecedero y 0 si no lo es (Valor por defecto: 0)
A11: id_unidad_medida | B11: uniqueidentifier | F11: No | G11: SI | H11: NO | I11: SI | J11: UnidadMedida | K11: id_unidad_medida | L11: NO | N11: NO | P11: NO | R11: NO | T11: Unidad de medida (UnidadMedida) en la que se maneja el producto interno; su tipo (Peso, Volumen o Unidad) define la unidad de las recetas
A12: activo | B12: bit | F12: No | G12: SI | H12: NO | I12: NO | L12: NO | N12: NO | P12: NO | R12: NO | T12: Indica si el producto interno esta activo y disponible para usarse (Valor por defecto: 1)

Sheet TipoProducto
A1: <-Volver al inicio
A2: =Entidades!$A$1 -> Entidad | B2: =Entidades!A15 -> TipoProducto
A3: =Entidades!$B$1 -> Descripción | B3: =Entidades!B15 -> Representa la clasificacion de cada producto que ofrece la pizzeria, indicando si corresponde a una pizza, una bebida o una adicion.
A4: Atributos
A5: Nombre | B5: Tipo de dato | C5: Longitud | D5: Cantidad dígitos parte entera | E5: Cantidad dígitos parte decimal (Precisión) | F5: ¿Es autoincremento? | G5: ¿Es obligatorio? | H5: ¿Es llave primeria o es parte de ella? | I5: Llave Foránea | L5: Restricciones de unicidad | N5: Restricciones de chequeo | P5: Restricciones de índice | S5: Alias | T5: Descripción del campo
I6: ¿Es llave foránea? | J6: Entidad | K6: Columna(s) | L6: ¿Posee restricción de unicidad o es parte de ella? | M6: Nombre restricción unicidad a la que pertenece | N6: ¿Posee restricción de chequeo o es parte de ella? | O6: Nombre restricción chequeo a la que pertenece | P6: ¿Posee restricción de índice o es parte de ella? | Q6: Tipo | R6: Nombre restricción índice a la que pertenece
A7: id_tipo_producto | B7: uniqueidentifier | F7: No | G7: SI | H7: SI | I7: NO | L7: NO | N7: NO | P7: NO | R7: NO | T7: Identificador unico de cada tipo de producto (Valor por defecto: newid())
A8: nombre | B8: varchar | C8: 20 | F8: No | G8: SI | H8: NO | I8: NO | L8: SI | M8: Unique de columna (sin nombre en el script) | N8: NO | P8: NO | R8: NO | T8: Nombre del tipo de producto (Pizza, Bebida o Adicion)

Sheet ClaseMovimiento
A1: <-Volver al inicio
A2: =Entidades!$A$1 -> Entidad | B2: =Entidades!A16 -> ClaseMovimiento
A3: =Entidades!$B$1 -> Descripción | B3: =Entidades!B16 -> Representa la clase de cada movimiento de inventario, indicando si corresponde a una entrada o a una salida de existencias.
A4: Atributos
A5: Nombre | B5: Tipo de dato | C5: Longitud | D5: Cantidad dígitos parte entera | E5: Cantidad dígitos parte decimal (Precisión) | F5: ¿Es autoincremento? | G5: ¿Es obligatorio? | H5: ¿Es llave primeria o es parte de ella? | I5: Llave Foránea | L5: Restricciones de unicidad | N5: Restricciones de chequeo | P5: Restricciones de índice | S5: Alias | T5: Descripción del campo
I6: ¿Es llave foránea? | J6: Entidad | K6: Columna(s) | L6: ¿Posee restricción de unicidad o es parte de ella? | M6: Nombre restricción unicidad a la que pertenece | N6: ¿Posee restricción de chequeo o es parte de ella? | O6: Nombre restricción chequeo a la que pertenece | P6: ¿Posee restricción de índice o es parte de ella? | Q6: Tipo | R6: Nombre restricción índice a la que pertenece
A7: id_clase_movimiento | B7: uniqueidentifier | F7: No | G7: SI | H7: SI | I7: NO | L7: NO | N7: NO | P7: NO | R7: NO | T7: Representa el identificador unico de cada clase de movimiento (Valor por defecto: newid())
A8: nombre | B8: varchar | C8: 10 | F8: No | G8: SI | H8: NO | I8: NO | L8: SI | M8: Unique de columna (sin nombre en el script) | N8: SI | O8: ck_clase_movimiento_nombre | P8: NO | R8: NO | T8: Nombre de la clase de movimiento (Entrada o Salida): indica si el movimiento suma (Entrada) o resta (Salida) inventario

Sheet Tamaño
A1: <-Volver al inicio
A2: =Entidades!$A$1 -> Entidad | B2: =Entidades!A17 -> Tamaño
A3: =Entidades!$B$1 -> Descripción | B3: =Entidades!B17 -> Representa las distintas presentaciones de tamaño en las que la pizzería puede ofrecer un producto; los productos que no son pizza usan "No aplica".
A4: Atributos
A5: Nombre | B5: Tipo de dato | C5: Longitud | D5: Cantidad dígitos parte entera | E5: Cantidad dígitos parte decimal (Precisión) | F5: ¿Es autoincremento? | G5: ¿Es obligatorio? | H5: ¿Es llave primeria o es parte de ella? | I5: Llave Foránea | L5: Restricciones de unicidad | N5: Restricciones de chequeo | P5: Restricciones de índice | S5: Alias | T5: Descripción del campo
I6: ¿Es llave foránea? | J6: Entidad | K6: Columna(s) | L6: ¿Posee restricción de unicidad o es parte de ella? | M6: Nombre restricción unicidad a la que pertenece | N6: ¿Posee restricción de chequeo o es parte de ella? | O6: Nombre restricción chequeo a la que pertenece | P6: ¿Posee restricción de índice o es parte de ella? | Q6: Tipo | R6: Nombre restricción índice a la que pertenece
A7: id_tamano | B7: uniqueidentifier | F7: No | G7: SI | H7: SI | I7: NO | L7: NO | N7: NO | P7: NO | R7: NO | T7: Representa el identificador unico de cada tamaño (Valor por defecto: newid())
A8: tamano | B8: varchar | C8: 20 | F8: No | G8: SI | H8: NO | I8: NO | L8: SI | M8: Unique de columna (sin nombre en el script) | N8: NO | P8: NO | R8: NO | T8: Nombre del tamaño (Grande, Mediana, Pequeña o No aplica)

Sheet Cambio
A1: <-Volver al inicio
A2: =Entidades!$A$1 -> Entidad | B2: =Entidades!A18 -> Cambio
A3: =Entidades!$B$1 -> Descripción | B3: =Entidades!B18 -> Representa la operación mediante la cual un insumo no perecedero próximo a vencer se devuelve al proveedor y se reemplaza por uno nuevo, manteniendo la disponibilidad y las condiciones adecuadas de los insumos de la pizzería.
A4: Atributos
A5: Nombre | B5: Tipo de dato | C5: Longitud | D5: Cantidad dígitos parte entera | E5: Cantidad dígitos parte decimal (Precisión) | F5: ¿Es autoincremento? | G5: ¿Es obligatorio? | H5: ¿Es llave primeria o es parte de ella? | I5: Llave Foránea | L5: Restricciones de unicidad | N5: Restricciones de chequeo | P5: Restricciones de índice | S5: Alias | T5: Descripción del campo
I6: ¿Es llave foránea? | J6: Entidad | K6: Columna(s) | L6: ¿Posee restricción de unicidad o es parte de ella? | M6: Nombre restricción unicidad a la que pertenece | N6: ¿Posee restricción de chequeo o es parte de ella? | O6: Nombre restricción chequeo a la que pertenece | P6: ¿Posee restricción de índice o es parte de ella? | Q6: Tipo | R6: Nombre restricción índice a la que pertenece
A7: id_cambio | B7: uniqueidentifier | F7: No | G7: SI | H7: SI | I7: NO | L7: NO | N7: NO | P7: NO | R7: NO | T7: Identificador unico de cada cambio registrado (Valor por defecto: newid())
A8: id_producto_interno | B8: uniqueidentifier | F8: No | G8: SI | H8: NO | I8: SI | J8: ProductoInterno | K8: id_producto_interno | L8: SI | M8: uk_cambio_producto_fecha_cambio | N8: NO | P8: NO | R8: NO | T8: Producto interno que se cambia (siempre un producto no perecedero)
A9: cantidad | B9: decimal | D9: 18 | E9: 4 | F9: No | G9: SI | H9: NO | I9: NO | L9: NO | N9: SI | O9: ck_cambio_cantidad | P9: NO | R9: NO | T9: Cantidad del producto que entra o sale por el cambio
A10: id_unidad_medida | B10: uniqueidentifier | F10: No | G10: SI | H10: NO | I10: SI | J10: UnidadMedida | K10: id_unidad_medida | L10: NO | N10: NO | P10: NO | R10: NO | T10: Unidad de medida en la que se registra la cantidad del cambio, debe ser valida para el tipo de producto
A11: fecha_vencimiento | B11: date | F11: No | G11: SI | H11: NO | I11: NO | L11: NO | N11: SI | O11: ck_cambio_fechas | P11: NO | R11: NO | T11: Fecha de vencimiento del producto que entra por el cambio
A12: fecha_cambio | B12: date | F12: No | G12: SI | H12: NO | I12: NO | L12: SI | M12: uk_cambio_producto_fecha_cambio | N12: SI | O12: ck_cambio_fechas | P12: NO | R12: NO | T12: Fecha en la que se realiza el cambio
A13: id_tipo_movimiento | B13: uniqueidentifier | F13: No | G13: SI | H13: NO | I13: SI | J13: TipoMovimiento | K13: id_tipo_movimiento | L13: SI | M13: Unique de columna (sin nombre en el script) | N13: NO | P13: NO | R13: NO | T13: Codigo de la operacion (TipoMovimiento) del cambio; con el se rastrean los movimientos que genero el cambio

Sheet CategoriaOrigen
A1: <-Volver al inicio
A2: =Entidades!$A$1 -> Entidad | B2: =Entidades!A19 -> CategoriaOrigen
A3: =Entidades!$B$1 -> Descripción | B3: =Entidades!B19 -> Representa la categoría de origen de la operación que genera un movimiento de inventario: una compra, una venta o un cambio de producto.
A4: Atributos
A5: Nombre | B5: Tipo de dato | C5: Longitud | D5: Cantidad dígitos parte entera | E5: Cantidad dígitos parte decimal (Precisión) | F5: ¿Es autoincremento? | G5: ¿Es obligatorio? | H5: ¿Es llave primeria o es parte de ella? | I5: Llave Foránea | L5: Restricciones de unicidad | N5: Restricciones de chequeo | P5: Restricciones de índice | S5: Alias | T5: Descripción del campo
I6: ¿Es llave foránea? | J6: Entidad | K6: Columna(s) | L6: ¿Posee restricción de unicidad o es parte de ella? | M6: Nombre restricción unicidad a la que pertenece | N6: ¿Posee restricción de chequeo o es parte de ella? | O6: Nombre restricción chequeo a la que pertenece | P6: ¿Posee restricción de índice o es parte de ella? | Q6: Tipo | R6: Nombre restricción índice a la que pertenece
A7: id_categoria_origen | B7: uniqueidentifier | F7: No | G7: SI | H7: SI | I7: NO | L7: NO | N7: NO | P7: NO | R7: NO | T7: Representa el identificador unico de cada categoria de origen (Valor por defecto: newid())
A8: nombre | B8: varchar | C8: 10 | F8: No | G8: SI | H8: NO | I8: NO | L8: SI | M8: Unique de columna (sin nombre en el script) | N8: SI | O8: ck_categoria_origen_nombre | P8: NO | R8: NO | T8: Nombre de la categoria de origen: indica de donde proviene la operacion (Compra, Venta o Cambio)

Sheet TipoMovimiento
A1: <-Volver al inicio
A2: =Entidades!$A$1 -> Entidad | B2: =Entidades!A20 -> TipoMovimiento
A3: =Entidades!$B$1 -> Descripción | B3: =Entidades!B20 -> Representa el código de una operación concreta que mueve el inventario (cada detalle de compra, consumo de venta o cambio tiene el suyo); pertenece a una categoría de origen y lo comparten la operación y los movimientos que genera.
A4: Atributos
A5: Nombre | B5: Tipo de dato | C5: Longitud | D5: Cantidad dígitos parte entera | E5: Cantidad dígitos parte decimal (Precisión) | F5: ¿Es autoincremento? | G5: ¿Es obligatorio? | H5: ¿Es llave primeria o es parte de ella? | I5: Llave Foránea | L5: Restricciones de unicidad | N5: Restricciones de chequeo | P5: Restricciones de índice | S5: Alias | T5: Descripción del campo
I6: ¿Es llave foránea? | J6: Entidad | K6: Columna(s) | L6: ¿Posee restricción de unicidad o es parte de ella? | M6: Nombre restricción unicidad a la que pertenece | N6: ¿Posee restricción de chequeo o es parte de ella? | O6: Nombre restricción chequeo a la que pertenece | P6: ¿Posee restricción de índice o es parte de ella? | Q6: Tipo | R6: Nombre restricción índice a la que pertenece
A7: id_tipo_movimiento | B7: uniqueidentifier | F7: No | G7: SI | H7: SI | I7: NO | L7: NO | N7: NO | P7: NO | R7: NO | T7: Codigo unico de una operacion concreta que genera movimientos de inventario (cada detalle de compra, consumo de venta o cambio tiene el suyo) (Valor por defecto: newid())
A8: id_categoria_origen | B8: uniqueidentifier | F8: No | G8: SI | H8: NO | I8: SI | J8: CategoriaOrigen | K8: id_categoria_origen | L8: NO | N8: NO | P8: NO | R8: NO | T8: Categoria de origen a la que pertenece la operacion. Cada TipoMovimiento pertenece a una sola CategoriaOrigen

Sheet Usuario
A1: <-Volver al inicio
A2: =Entidades!$A$1 -> Entidad | B2: =Entidades!A23 -> Usuario
A3: =Entidades!$B$1 -> Descripción | B3: =Entidades!B23 -> Representa a la persona que puede ingresar a la aplicación; solo los usuarios activos con rol Administrador pueden iniciar sesión.
A4: Atributos
A5: Nombre | B5: Tipo de dato | C5: Longitud | D5: Cantidad dígitos parte entera | E5: Cantidad dígitos parte decimal (Precisión) | F5: ¿Es autoincremento? | G5: ¿Es obligatorio? | H5: ¿Es llave primeria o es parte de ella? | I5: Llave Foránea | L5: Restricciones de unicidad | N5: Restricciones de chequeo | P5: Restricciones de índice | S5: Alias | T5: Descripción del campo
I6: ¿Es llave foránea? | J6: Entidad | K6: Columna(s) | L6: ¿Posee restricción de unicidad o es parte de ella? | M6: Nombre restricción unicidad a la que pertenece | N6: ¿Posee restricción de chequeo o es parte de ella? | O6: Nombre restricción chequeo a la que pertenece | P6: ¿Posee restricción de índice o es parte de ella? | Q6: Tipo | R6: Nombre restricción índice a la que pertenece
A7: id_usuario | B7: uniqueidentifier | F7: No | G7: SI | H7: SI | I7: NO | L7: NO | N7: NO | P7: NO | R7: NO | T7: Identificador unico de cada usuario de la aplicacion (Valor por defecto: newid())
A8: usuario | B8: varchar | C8: 30 | F8: No | G8: SI | H8: NO | I8: NO | L8: SI | M8: Unique de columna (sin nombre en el script) | N8: NO | P8: NO | R8: NO | T8: Nombre de usuario con el que se inicia sesion; no se puede repetir
A9: clave | B9: varchar | C9: 100 | F9: No | G9: SI | H9: NO | I9: NO | L9: NO | N9: NO | P9: NO | R9: NO | T9: Contrasena del usuario; se guarda cifrada con BCrypt, nunca en texto plano
A10: rol | B10: varchar | C10: 20 | F10: No | G10: SI | H10: NO | I10: NO | L10: NO | N10: SI | O10: ck_usuario_rol | P10: NO | R10: NO | T10: Rol del usuario dentro de la aplicacion; solo existe el rol Administrador
A11: activo | B11: bit | F11: No | G11: SI | H11: NO | I11: NO | L11: NO | N11: NO | P11: NO | R11: NO | T11: Indica si el usuario esta activo; un usuario inactivo no puede iniciar sesion

Sheet Valores
A1: Relación | B1: Tipo relación | C1: Estado | D1: TipoIndice
A2: Necesita de | B2: Asociación | C2: SI | D2: ASC
A3: Es usada por | C3: NO | D3: DESC
