Workbook

Sheet Modelo de dominio
A1: Ir a Objetos de Dominio >>>

Sheet Objetos de dominio
A1: <<<Modelo de Dominio
A2: Nombre | B2: Descripcion | C2: Linea de vida | D2: Muestreo | E2: Caracterizacion | F2: Eventos | G2: Politicas
A3: Proveedor | B3: Son las personas o empresas que le venden a la pizzería los insumos que necesita para funcionar. | C3: 1 | D3: Ir | E3: Ir | F3: Ir | G3: Ir
A4: UnidadMedida | B4: Es la unidad con la que se mide cada ingrediente o producto, por ejemplo kilos, litros o unidades. | C4: 1 | D4: Ir | E4: Ir | F4: Ir | G4: Ir
A5: TipoProducto | B5: Indica en qué categoría entra cada producto que vende la pizzería, por ejemplo si es una pizza, una bebida o una adición. | C5: 1 | D5: Ir | E5: Ir | F5: Ir | G5: Ir
A6: ClaseMovimiento | B6: Indica si un movimiento de inventario fue una entrada o una salida de insumos o productos. | C6: 1 | D6: Ir | E6: Ir | F6: Ir | G6: Ir
A7: Tamaño | B7: Son los distintos tamaños en los que la pizzería puede ofrecer una pizza. | C7: 1 | D7: Ir | E7: Ir | F7: Ir | G7: Ir
A8: CategoriaOrigen | B8: Indica qué operación fue la que generó un movimiento de inventario: una compra, una venta, un cambio de un producto que no es perecedero, o el retiro de un lote (porque se cambió o porque se venció). | C8: 1 | D8: Ir | E8: Ir | F8: Ir | G8: Ir
A9: Usuario | B9: Es la persona que puede ingresar a la aplicacion; solo el administrador de la pizzeria puede iniciar sesion. | C9: 1 | D9: Ir | E9: Ir | F9: Ir | G9: Ir
A10: Compra | B10: Es cuando la pizzería le compra insumos o productos a un proveedor. | C10: 2 | D10: Ir | E10: Ir | F10: Ir | G10: Ir
A11: ProductoInterno | B11: Es cada insumo o producto que la pizzería compra y guarda en su inventario, sin importar si se usa para preparar algo o si se vende directamente al cliente. | C11: 2 | D11: Ir | E11: Ir | F11: Ir | G11: Ir
A12: TipoMovimiento | B12: Es el código de una operación concreta que mueve el inventario (cada detalle de compra, consumo de una venta o cambio tiene el suyo). Pertenece a una CategoriaOrigen y lo comparten la operación y los movimientos que genera. | C12: 2 | D12: Ir | E12: Ir | F12: Ir | G12: Ir
A13: DetalleCompra | B13: Es cada uno de los productos o insumos que se compraron en una compra, con la cantidad de cada uno. | C13: 3 | D13: Ir | E13: Ir | F13: Ir | G13: Ir
A14: Producto | B14: Son los productos que la pizzería vende, como las pizzas, las bebidas y las adiciones. | C14: 4 | D14: Ir | E14: Ir | F14: Ir | G14: Ir
... A24: SalidaLote | B24: SalidaLote representa el retiro efectivo de una cantidad de producto perteneciente a un lote, realizado por el usuario después de atender una alerta de proximidad al vencimiento. Atributos: Id, Lote, Cantidad y FechaMovimiento. Relación: Lote 1 — 0..1 SalidaLote (un lote puede tener como máximo un retiro; cada retiro pertenece a un único lote). La alerta no se almacena aquí: se calcula a partir de Lote.FechaVencimiento. | C24: 7 | D24: Ir | E24: Ir | F24: Ir | G24: Ir
A27: Categorias de colores
A28: Descripciones
A29: Id's
A30: combinacion unica
A31: objeto
A32: Tipo de dato
A33: Si es obligatorio o no el atributo
A34: Calculado

Sheet Reglas de negocio
A1: Cada pizzería administra un inventario independiente.
A2: Todo cambio en las existencias de los productos internos debe quedar registrado: las entradas y salidas por compra, venta y cambio mediante un MovimientoInventario, y los retiros por vencimiento mediante una SalidaLote.
A3: El inventario debe reflejar automáticamente los movimientos y retiros registrados (actualizaciones).
A4: Cada pizza y cada adición posee una única receta. Las bebidas no tienen receta, porque se venden directamente del inventario.
A5: Una venta puede tener muchos productos, cada uno registrado en un DetalleVenta. El total de la venta se calcula como la suma de los subtotales de sus detalles y, con base en él, se emite la factura y se realiza el pago.
A7: Todo se paga de contado, para no manejar sistemas de crédito con los proveedores.
A8: No se maneja nómina: el sistema no registra empleados ni sueldos. Solo existe el usuario Administrador, que es quien ingresa a la aplicación.
A9: El precio de un producto puede cambiarse cuando sea necesario; cada cambio queda registrado en HistoricoPrecio.
A10: Cada instancia del sistema corresponde a una sola pizzería, y la información operativa pertenece exclusivamente a la pizzería que utiliza dicha instancia.
A11: El valor total de una compra corresponde a la suma de los precios de compra de todos sus detalles de compra, y no puede superar 5.000.000.
A12: Solo los usuarios activos con rol Administrador pueden ingresar a la aplicación.
A13: La unidad de medida de cada ingrediente de una receta se asigna automáticamente según el tipo de medida del producto interno: Peso = g, Volumen = ml, Unidad = und.
... A23: Cuando un lote está próximo a vencer: si el producto es no perecedero se cambia con el proveedor (Cambio); si es perecedero no se cambia, se retira del lote con una SalidaLote.

Sheet M-Proveedor
A1: <<<Modelo de Dominio | B1: <<<Objetos de Dominio
A2: Identificador unico del proveedor dentro de la pizzeria | B2: Nombre de la empresa a la que pertenece el proveedor | C2: Numero de identificacion tributaria (NIT) del proveedor; no se puede repetir entre proveedores | D2: Forma de comunicacion directa con el proveedor | E2: Indica si el proveedor esta activo y disponible para nuevas compras
A3: Tipo de dato | B3: Alfanumerico(max 60 caracteres) | C3: Alfanumerico(max 15 caracteres) | D3: Alfanumerico(max 10 caracteres) | E3: Tipo Logico
A4: Obligatorio | B4: Si | C4: Si | D4: Si | E4: Si
A5: Id | B5: Nombre Empresa | C5: NIT | D5: Contacto | E5: Activo | F5: Combinacion unica 1 | G5: Combinacion unica 2
A6: 1 | B6: Colanta | C6: 900100001-1 | D6: 3053086510 | E6: Si | F6: =B6 -> Colanta | G6: =C6 -> 900100001-1
A7: 2 | B7: Harinera del valle | C7: 900100002-2 | D7: 3139562216 | E7: Si | F7: =B7 -> Harinera del valle | G7: =C7 -> 900100002-2
A8: 3 | B8: Postobon | C8: 900100003-3 | D8: 3108582230 | E8: Si | F8: =B8 -> Postobon | G8: =C8 -> 900100003-3
A9: 4 | B9: Central de Abastos | C9: 900100004-4 | D9: 3201234567 | E9: Si | F9: =B9 -> Central de Abastos | G9: =C9 -> 900100004-4

Sheet C-Proveedor
A1: <<<Modelo de Dominio | B1: <<<Objetos de Dominio
A2: Nombre | B2: Proveedor
A3: Descripción | B3: =HYPERLINK("#'Objetos de dominio'!B3", 'Objetos de dominio'!B3) -> Son las personas o empresas que le venden a la pizzería los insumos que necesita para funcionar.
A4: Nombre atributo | B4: Descripción atributo | C4: Identificador del objeto de dominio | D4: Tipo de dato | E4: Obligatorio | F4: Longitud mínima (si aplica) | G4: Longitud máxima (si aplica) | H4: Precisión (si aplica) | I4: Rendondeo (si aplica) | J4: Rango inicial (si aplica) | K4: Rango final (si aplica) | L4: Formato (si aplica) | M4: Reglas especiales (si aplica) | N4: Dato calculado | O4: Aplica ajuste del dato (si aplica) | P4: Carácter de ajuste (si aplica) | Q4: Quitar espacios en blanco al inicio (si aplica) | R4: Quitar espacios en blanco al fin (si aplica) | S4: Dato sensible (si aplica) | T4: Valor por defecto (si aplica) | U4: Auto generado | V4: =HYPERLINK("#'C-Proveedor'!A18", 'C-Proveedor'!A18) -> Registrar proveedor | W4: =HYPERLINK("#'C-Proveedor'!A22", 'C-Proveedor'!A22) -> Modificar proveedor | Y4: =HYPERLINK("#'C-Proveedor'!A25", 'C-Proveedor'!A25) -> Retirar proveedor | Z4: =HYPERLINK("#'C-Proveedor'!A28", 'C-Proveedor'!A28) -> Consultar proveedores activos
A5: =HYPERLINK("#'M-Proveedor'!A5", 'M-Proveedor'!A5) -> Id | B5: =HYPERLINK("#'M-Proveedor'!A2", 'M-Proveedor'!A2) -> Identificador unico del proveedor dentro de la pizzeria | C5: Si | D5: Identificador universal | E5: Si | N5: No | O5: No | Q5: No | R5: No | S5: No | U5: Si | V5: Requerido | W5: Requerido | X5: No Modificable | Y5: Requerido | Z5: No Mostrar
A6: =HYPERLINK("#'M-Proveedor'!B5", 'M-Proveedor'!B5) -> Nombre Empresa | B6: =HYPERLINK("#'M-Proveedor'!B2", 'M-Proveedor'!B2) -> Nombre de la empresa a la que pertenece el proveedor | C6: No | D6: Alfanumerico | E6: Si | F6: 1 | G6: 60 | M6: Se debe asegurar una sanitización del dato | N6: No | O6: No | Q6: Si | R6: Si | S6: No | U6: No | V6: Requerido | W6: No Requerido | X6: Modificable | Y6: No Requerido | Z6: Mostrar
A7: =HYPERLINK("#'M-Proveedor'!C5", 'M-Proveedor'!C5) -> NIT | B7: =HYPERLINK("#'M-Proveedor'!C2", 'M-Proveedor'!C2) -> Numero de identificacion tributaria (NIT) del proveedor; no se puede repetir entre proveedores | C7: No | D7: Alfanumerico | E7: Si | F7: 1 | G7: 15 | M7: No puede existir otro proveedor con el mismo NIT. Se debe asegurar una sanitizacion del dato. | N7: No | O7: No | Q7: Si | R7: Si | S7: No | U7: No | V7: Requerido | W7: No Requerido | X7: Modificable | Y7: No Requerido | Z7: Mostrar
A8: =HYPERLINK("#'M-Proveedor'!D5", 'M-Proveedor'!D5) -> Contacto | B8: =HYPERLINK("#'M-Proveedor'!D2", 'M-Proveedor'!D2) -> Forma de comunicacion directa con el proveedor | C8: No | D8: Alfanumerico | E8: Si | F8: 1 | G8: 10 | M8: Se debe asegurar una sanitizacion del dato | N8: No | O8: No | Q8: Si | R8: Si | S8: No | U8: No | V8: Requerido | W8: No Requerido | X8: Modificable | Y8: No Requerido | Z8: Mostrar
A9: =HYPERLINK("#'M-Proveedor'!E5", 'M-Proveedor'!E5) -> Activo | B9: =HYPERLINK("#'M-Proveedor'!E2", 'M-Proveedor'!E2) -> Indica si el proveedor esta activo y disponible para nuevas compras | C9: No | D9: Tipo Logico | E9: Si | M9: Se registra como activo (Si). Al retirar el proveedor pasa a No y ya no puede usarse en nuevas compras. | N9: No | O9: No | Q9: No | R9: No | S9: No | T9: Si | U9: No | V9: No Requerido | W9: No Requerido | X9: No Modificable | Y9: No Requerido | Z9: No Mostrar
A12: Nombre combinación única | B12: Descripción | C12: Atributos involucrados
A13: Combinación única 1 | B13: No puede existir otro proveedor con el mismo nombre de empresa | C13: =HYPERLINK("#'C-Proveedor'!A6", 'C-Proveedor'!A6) -> Nombre Empresa
A14: Combinación única 2 | B14: No pueden existir dos proveedores con el mismo NIT. | C14: =HYPERLINK("#'C-Proveedor'!A7", 'C-Proveedor'!A7) -> NIT
A16: Responsabilidad | C16: Descripción | G16: Entradas | J16: Salida | O16: Políticas (Reglas de Negocio) | Q16: Excepción
G17: Parámetro | H17: Tipo de dato | I17: Descripción | J17: Tipo de Dato | K17: Descripción | O17: Política | P17: Descripción | Q17: Detalle | R17: ¿Qué hago?
A18: =HYPERLINK("#'C-Proveedor'!V4", 'E-Proveedor'!B7) -> Registrar proveedor | C18: ='E-Proveedor'!C7 -> Permite imcorporar un crear un proveedor | G18: Datos | H18: Proveedor | I18: Información necesaria para registrar e identificar al proveedor. | J18: Proveedor | K18: Proveedor registrado con la información proporcionada. | O18: =HYPERLINK("#'P-Proveedor'!A5", 'P-Proveedor'!A5) -> P-PROV-001 | P18: ='P-Proveedor'!B5 -> Asegurar que los datos requeridos para registrar un proveedor sean válidos de acuerdo con el tipo de dato, obligatoriedad, formato, longitud y rango correspondiente. | Q18: Los datos ingresados para registrar el proveedor no son validos. | R18: Rechazar el registro e informar cual dato no es valido.
O19: =HYPERLINK("#'P-Proveedor'!A6", 'P-Proveedor'!A6) -> P-PROV-002 | P19: ='P-Proveedor'!B6 -> Asegurar que el identificador generado para el proveedor no esté siendo utilizado por otro proveedor. | Q19: El identificador generado ya esta siendo utilizado por otro proveedor. | R19: Generar un nuevo identificador hasta garantizar que no exista.
O20: =HYPERLINK("#'P-Proveedor'!A7", 'P-Proveedor'!A7) -> P-PROV-003 | P20: ='P-Proveedor'!B7 -> Asegurar que no exista otro proveedor registrado con el mismo NIT. | Q20: Ya existe otro proveedor registrado con el mismo NIT. | R20: Rechazar el registro e informar que ya existe un proveedor con ese NIT.
O21: =HYPERLINK("#'P-Proveedor'!A14", 'P-Proveedor'!A14) -> P-PROV-010 | P21: ='P-Proveedor'!B14 -> Asegurar que no exista otro proveedor registrado con el mismo nombre de empresa. | Q21: Ya existe otro proveedor registrado con el mismo nombre de empresa. | R21: Rechazar el registro e informar que ya existe un proveedor con ese nombre.
A22: =HYPERLINK("#'C-Proveedor'!W4", 'E-Proveedor'!B11) -> Modificar proveedor | C22: ='E-Proveedor'!C11 -> Actualizar la información de un proveedor existente sin afectar la trazabilidad de las compras históricas asociadas a este. | G22: Datos | H22: Proveedor | I22: Identificador del proveedor y datos que se desean modificar. | J22: Proveedor | K22: Proveedor actualizado con la información proporcionada. | O22: =HYPERLINK("#'P-Proveedor'!A8", 'P-Proveedor'!A8) -> P-PROV-004 | P22: ='P-Proveedor'!B8 -> Asegurar que el proveedor que se desea actualizar se encuentre registrado en el sistema. | Q22: El proveedor que se desea actualizar no existe. | R22: Rechazar la actualizacion e informar que el proveedor no existe.
O23: =HYPERLINK("#'P-Proveedor'!A5", 'P-Proveedor'!A5) -> P-PROV-001 | P23: ='P-Proveedor'!B5 -> Asegurar que los datos requeridos para registrar un proveedor sean válidos de acuerdo con el tipo de dato, obligatoriedad, formato, longitud y rango correspondiente. | Q23: Los nuevos datos del proveedor no son validos. | R23: Rechazar la modificacion e informar cual dato no es valido.
O24: =HYPERLINK("#'P-Proveedor'!A9", 'P-Proveedor'!A9) -> P-PROV-005 | P24: ='P-Proveedor'!B9 -> Asegurar que la información modificada del proveedor no genere duplicidad con otro proveedor registrado. | Q24: La informacion modificada genera duplicidad con otro proveedor registrado. | R24: Rechazar la actualizacion e informar la duplicidad encontrada.
A25: =HYPERLINK("#'C-Proveedor'!Y4", 'E-Proveedor'!B14) -> Retirar proveedor | C25: ='E-Proveedor'!C14 -> Permite retirar un proveedor con el que la pizzeria ya no trabaja: queda inactivo y no se puede usar en nuevas compras, pero se conservan sus compras. | G25: Id | H25: UUID | I25: Identificador del proveedor que se desea retirar. | J25: Proveedor | K25: Proveedor retirado de acuerdo con las reglas establecidas. | O25: =HYPERLINK("#'P-Proveedor'!A10", 'P-Proveedor'!A10) -> P-PROV-006 | P25: ='P-Proveedor'!B10 -> Asegurar que el proveedor que se desea retirar se encuentre registrado en el sistema. | Q25: El proveedor que se desea retirar no existe. | R25: Rechazar el retiro e informar que el proveedor no existe.
O26: =HYPERLINK("#'P-Proveedor'!A15", 'P-Proveedor'!A15) -> P-PROV-011 | P26: ='P-Proveedor'!B15 -> Asegurar que el proveedor que se desea retirar no se encuentre ya retirado. | Q26: El proveedor ya se encuentra retirado. | R26: Informar que el proveedor ya esta retirado.
O27: =HYPERLINK("#'P-Proveedor'!A11", 'P-Proveedor'!A11) -> P-PROV-007 | P27: ='P-Proveedor'!B11 -> Asegurar que al retirar un proveedor se conserven sus compras registradas: el retiro solo cambia su estado a inactivo y no borra informacion. | Q27: El proveedor tiene compras registradas. | R27: Retirar el proveedor sin borrar sus compras; siguen disponibles para consulta.
A28: =HYPERLINK("#'C-Proveedor'!Z4", 'E-Proveedor'!B17) -> Consultar proveedores activos | C28: ='E-Proveedor'!C17 -> Permite consultar los proveedores activos, ordenados por nombre de empresa, para seleccionarlos al registrar una compra. | G28: Ninguno | I28: No requiere datos de entrada. | J28: Lista de Proveedor | K28: Proveedores activos ordenados por nombre de empresa. | O28: =HYPERLINK("#'P-Proveedor'!A16", 'P-Proveedor'!A16) -> P-PROV-012 | P28: ='P-Proveedor'!B16 -> Asegurar que solo se consulten los proveedores activos, que son los disponibles para registrar nuevas compras. | Q28: No existen proveedores activos. | R28: Informar que no hay proveedores activos disponibles.

Sheet E-Proveedor
A1: <<<Modelo de Dominio | B1: <<<Objetos de Dominio
A2: Objeto de Dominio: | B2: Proveedor
A3: Descripción: | B3: ='C-Proveedor'!B3 -> Son las personas o empresas que le venden a la pizzería los insumos que necesita para funcionar.
A4: Actor | B4: Action/Command | D4: Entity/Aggregate/Object domain | E4: Read Model | G4: Business Rule/Policy | H4: External System | I4: Domain Event | J4: Hotspot/questions/Risk
A5: Actor | B5: Acción | C5: Descripción | D5: Objeto de dominio | E5: Información externa | G5: Políticas | H5: Sistema Externo | I5: Evento | J5: Aspectos por solucionar
E6: Información | F6: Descripción | G6: Número
A7: Administrador | B7: Registrar proveedor | C7: Permite imcorporar un crear un proveedor | D7: Proveedor | E7: Información del proveedor | F7: Datos necesarios para identificar y contactar al proveedor, como nombre de empresa y medio de contacto. | G7: =HYPERLINK("#'P-Proveedor'!A5", "P-PROV-001") -> P-PROV-001 | I7: Proveedor registrado
G8: =HYPERLINK("#'P-Proveedor'!A6", "P-PROV-002") -> P-PROV-002
G9: =HYPERLINK("#'P-Proveedor'!A7", "P-PROV-003") -> P-PROV-003
G10: =HYPERLINK("#'P-Proveedor'!A14", "P-PROV-010") -> P-PROV-010
A11: Administrador | B11: Modificar proveedor | C11: Actualizar la información de un proveedor existente sin afectar la trazabilidad de las compras históricas asociadas a este. | D11: Proveedor | E11: Información del proveedor | F11: Datos actuales y nuevos del proveedor necesarios para identificarlo y realizar la actualización. | G11: =HYPERLINK("#'P-Proveedor'!A8", "P-PROV-004") -> P-PROV-004 | I11: Proveedor modificado
G12: =HYPERLINK("#'P-Proveedor'!A5", "P-PROV-001") -> P-PROV-001
G13: =HYPERLINK("#'P-Proveedor'!A9", "P-PROV-005") -> P-PROV-005
A14: Administrador | B14: Retirar proveedor | C14: Permite retirar un proveedor con el que la pizzeria ya no trabaja: queda inactivo y no se puede usar en nuevas compras, pero se conservan sus compras. | D14: Proveedor | E14: Compras hechas al proveedor | F14: Permite verificar las compras asociadas al proveedor antes de retirarlo y conservar su información histórica. | G14: =HYPERLINK("#'P-Proveedor'!A10", "P-PROV-006") -> P-PROV-006 | I14: Proveedor retirado
G15: =HYPERLINK("#'P-Proveedor'!A15", "P-PROV-011") -> P-PROV-011
G16: =HYPERLINK("#'P-Proveedor'!A11", "P-PROV-007") -> P-PROV-007
A17: Administrador | B17: Consultar proveedores activos | C17: Permite consultar los proveedores activos, ordenados por nombre de empresa, para seleccionarlos al registrar una compra. | E17: Proveedores registrados | F17: Proveedores con estado activo. | G17: =HYPERLINK("#'P-Proveedor'!A16", "P-PROV-012") -> P-PROV-012 | I17: Proveedores activos consultados

Sheet P-Proveedor
A1: <<<Modelo de Dominio | B1: <<<Objetos de Dominio
A2: Objeto de Dominio | B2: Proveedor
A3: Descripcion | B3: ='C-Proveedor'!B3 -> Son las personas o empresas que le venden a la pizzería los insumos que necesita para funcionar.
A4: Numero politica | B4: Descripcion Politica | C4: Objeto Responsable | D4: Regla Referenciada
A5: P-PROV-001 | B5: Asegurar que los datos requeridos para registrar un proveedor sean válidos de acuerdo con el tipo de dato, obligatoriedad, formato, longitud y rango correspondiente. | C5: Proveedor
A6: P-PROV-002 | B6: Asegurar que el identificador generado para el proveedor no esté siendo utilizado por otro proveedor. | C6: Proveedor
A7: P-PROV-003 | B7: Asegurar que no exista otro proveedor registrado con el mismo NIT. | C7: Proveedor
A8: P-PROV-004 | B8: Asegurar que el proveedor que se desea actualizar se encuentre registrado en el sistema. | C8: Proveedor
A9: P-PROV-005 | B9: Asegurar que la información modificada del proveedor no genere duplicidad con otro proveedor registrado. | C9: Proveedor
A10: P-PROV-006 | B10: Asegurar que el proveedor que se desea retirar se encuentre registrado en el sistema. | C10: Proveedor
A11: P-PROV-007 | B11: Asegurar que al retirar un proveedor se conserven sus compras registradas: el retiro solo cambia su estado a inactivo y no borra informacion. | C11: Proveedor
A12: P-PROV-008 | B12: Asegurar que un proveedor retirado o inactivo no pueda ser utilizado para registrar nuevas compras, conservando la información histórica de las compras realizadas. | C12: Proveedor
A13: P-PROV-009 | B13: Asegurar que el proveedor exista con el identificador indicado | C13: Proveedor
A14: P-PROV-010 | B14: Asegurar que no exista otro proveedor registrado con el mismo nombre de empresa. | C14: Proveedor
A15: P-PROV-011 | B15: Asegurar que el proveedor que se desea retirar no se encuentre ya retirado. | C15: Proveedor
A16: P-PROV-012 | B16: Asegurar que solo se consulten los proveedores activos, que son los disponibles para registrar nuevas compras. | C16: Proveedor

Sheet M-UnidadMedida
A1: <<<Modelo de Dominio | B1: <<<Objetos de Dominio
A2: Identificador unico de unidad de medida dentro del sistema | B2: Unidad de medida | C2: Tipo de medida a la que corresponde cada unidad de medida
A3: Tipo de dato | B3: Alfanumerico(max 4 caracteres) | C3: Alfanumerico(max 10 caracteres)
A4: Obligatorio | B4: Si | C4: Si
A5: Id | B5: UnidadMedida | C5: TipoMedida | D5: Combinación única 1
A6: 1 | B6: g | C6: Peso | D6: =B6 -> g
A7: 2 | B7: kg | C7: Peso | D7: =B7 -> kg
A8: 3 | B8: ml | C8: Volumen | D8: =B8 -> ml
A9: 4 | B9: l | C9: Volumen | D9: =B9 -> l
A10: 5 | B10: und | C10: Unidad | D10: =B10 -> und

Sheet C-UnidadMedida
A1: <<<Modelo de Dominio | B1: <<<Objetos de Dominio
A2: Nombre | B2: UnidadMedida
A3: Descripción | B3: =HYPERLINK("#'Objetos de dominio'!B4", 'Objetos de dominio'!B4) -> Es la unidad con la que se mide cada ingrediente o producto, por ejemplo kilos, litros o unidades.
A4: Nombre atributo | B4: Descripción atributo | C4: Identificador del objeto de dominio | D4: Tipo de dato | E4: Obligatorio | F4: Longitud mínima (si aplica) | G4: Longitud máxima (si aplica) | H4: Precisión (si aplica) | I4: Rendondeo (si aplica) | J4: Rango inicial (si aplica) | K4: Rango final (si aplica) | L4: Formato (si aplica) | M4: Reglas especiales (si aplica) | N4: Dato calculado | O4: Aplica ajuste del dato (si aplica) | P4: Carácter de ajuste (si aplica) | Q4: Quitar espacios en blanco al inicio (si aplica) | R4: Quitar espacios en blanco al fin (si aplica) | S4: Dato sensible (si aplica) | T4: Valor por defecto (si aplica) | U4: Auto generado | V4: =HYPERLINK("#'C-UnidadMedida'!A17", 'C-UnidadMedida'!A17) -> Consultar unidades de medida disponibles | W4: =HYPERLINK("#'C-UnidadMedida'!A19", 'C-UnidadMedida'!A19) -> Eliminar unidad de medida
A5: =HYPERLINK("#'M-UnidadMedida'!A5", 'M-UnidadMedida'!A5) -> Id | B5: =HYPERLINK("#'M-UnidadMedida'!A2", 'M-UnidadMedida'!A2) -> Identificador unico de unidad de medida dentro del sistema | C5: Si | D5: Identificador universal | E5: Si | N5: No | O5: No | S5: No | U5: Si | V5: No Mostrar | W5: Requerido
A6: =HYPERLINK("#'M-UnidadMedida'!B5", 'M-UnidadMedida'!B5) -> UnidadMedida | B6: =HYPERLINK("#'M-UnidadMedida'!B2", 'M-UnidadMedida'!B2) -> Unidad de medida | C6: No | D6: Alfanumerico | E6: Si | F6: 1 | G6: 4 | M6: Se debe asegurar una sanitizacion del dato. | N6: No | O6: No | Q6: Si | R6: Si | S6: No | U6: No | V6: Mostrar | W6: No Requerido
A7: =HYPERLINK("#'M-UnidadMedida'!C5", 'M-UnidadMedida'!C5) -> TipoMedida | B7: =HYPERLINK("#'M-UnidadMedida'!C2", 'M-UnidadMedida'!C2) -> Tipo de medida a la que corresponde cada unidad de medida | C7: No | D7: Alfanumerico | E7: Si | F7: 1 | G7: 10 | M7: Solo se permiten los tipos Peso (g, kg), Volumen (ml, l) y Unidad (und). Asi el producto interno queda asociado a una unidad valida para su tipo de medida. | N7: No | O7: No | Q7: Si | R7: Si | S7: No | U7: No | V7: No Mostrar | W7: No Requerido
A10: Nombre combinación única | B10: Descripción | C10: Atributos involucrados
A11: Combinación única 1 | B11: No pueden existir dos unidades de medida con el mismo nombre. | C11: =HYPERLINK("#'C-UnidadMedida'!A6", 'C-UnidadMedida'!A6) -> UnidadMedida
A15: Responsabilidad | C15: Descripción | G15: Entradas | J15: Salida | O15: Políticas (Reglas de Negocio) | Q15: Excepción
G16: Parámetro | H16: Tipo de dato | I16: Descripción | J16: Tipo de Dato | K16: Descripción | O16: Política | P16: Descripción | Q16: Detalle | R16: ¿Qué hago?
A17: =HYPERLINK("#'C-UnidadMedida'!V4", 'E-UnidadMedida'!B7) -> Consultar unidades de medida disponibles | C17: ='E-UnidadMedida'!C7 -> Permite consultar las unidades de medida precargadas en el sistema para seleccionar la unidad adecuada al registrar cantidades de productos, ingredientes, compras, recetas o movimientos de inventario. | G17: Datos | H17: UnidadMedida | I17: Criterios necesarios para realizar la consulta de las unidades de medida disponibles. | J17: Lista de UnidadesMedida | K17: Conjunto de unidades de medida disponibles para selección. | O17: =HYPERLINK("#'P-UnidadMedida'!A5", 'P-UnidadMedida'!A5) -> P-UM-001 | P17: ='P-UnidadMedida'!B5 -> Asegurar que solo se consulten las unidades de medida del catalogo definido por la pizzeria (g, kg, ml, l y und), cada una con su tipo de medida (Peso, Volumen o Unidad). | Q17: No existen unidades de medida registradas en el catalogo. | R17: Informar al administrador que no hay unidades de medida disponibles.
O18: =HYPERLINK("#'P-UnidadMedida'!A6", 'P-UnidadMedida'!A6) -> P-UM-002 | P18: ='P-UnidadMedida'!B6 -> Asegurar que la unidad de medida exista con el identificador indicado | Q18: No existe una unidad de medida asociada al identificador indicado. | R18: Informar que la unidad de medida no existe.
A19: =HYPERLINK("#'C-UnidadMedida'!W4", 'E-UnidadMedida'!B9) -> Eliminar unidad de medida | C19: ='E-UnidadMedida'!C9 -> Permite eliminar una unidad de medida que no este siendo utilizada por ningun otro registro de la pizzeria. | G19: Id | H19: UUID | I19: Identificador de la unidad de medida que se desea eliminar. | J19: UnidadMedida | K19: Unidad de medida eliminada correctamente. | O19: =HYPERLINK("#'P-UnidadMedida'!A7", 'P-UnidadMedida'!A7) -> P-UM-003 | P19: ='P-UnidadMedida'!B7 -> Asegurar que la unidad de medida que se desea eliminar se encuentre registrada en el sistema. | Q19: La unidad de medida que se desea eliminar no existe. | R19: Rechazar la eliminacion e informar que la unidad de medida no existe.
O20: =HYPERLINK("#'P-UnidadMedida'!A8", 'P-UnidadMedida'!A8) -> P-UM-004 | P20: ='P-UnidadMedida'!B8 -> Asegurar que la unidad de medida que se desea eliminar no este siendo utilizada por productos internos, lotes o registros de inventario que requieran conservarla. | Q20: La unidad de medida esta siendo utilizada por un producto interno, un lote o un registro de inventario. | R20: Rechazar la eliminacion e informar en que registros esta en uso la unidad de medida.
O21: =HYPERLINK("#'P-UnidadMedida'!A9", 'P-UnidadMedida'!A9) -> P-UM-005 | P21: ='P-UnidadMedida'!B9 -> Asegurar que la unidad de medida que se desea eliminar no este siendo utilizada por detalles de receta, detalles de compra, cambios o consumos de venta que requieran conservarla. | Q21: La unidad de medida esta siendo utilizada por un detalle de receta, un detalle de compra, un cambio o un consumo de venta. | R21: Rechazar la eliminacion e informar en que registros esta en uso la unidad de medida.

Sheet E-UnidadMedida
A1: <<<Modelo de Dominio | B1: <<<Objetos de Dominio
A2: Objeto de Dominio: | B2: UnidadMedida
A3: Descripción: | B3: ='C-UnidadMedida'!B3 -> Es la unidad con la que se mide cada ingrediente o producto, por ejemplo kilos, litros o unidades.
A4: Actor | B4: Action/Command | D4: Entity/Aggregate/Object domain | E4: Read Model | G4: Business Rule/Policy | H4: Domain Event | I4: Hotspot/questions/Risk
A5: Actor | B5: Acción | C5: Descripción | D5: Objeto de dominio | E5: Información externa | G5: Políticas | H5: Evento | I5: Aspectos por solucionar
E6: Información | F6: Descripción | G6: Número
A7: Administrador | B7: Consultar unidades de medida disponibles | C7: Permite consultar las unidades de medida precargadas en el sistema para seleccionar la unidad adecuada al registrar cantidades de productos, ingredientes, compras, recetas o movimientos de inventario. | D7: UnidadMedida | G7: =HYPERLINK("#'P-UnidadMedida'!A5", "P-UM-001") -> P-UM-001 | H7: Unidades de medida consultadas
G8: =HYPERLINK("#'P-UnidadMedida'!A6", "P-UM-002") -> P-UM-002
A9: Administrador | B9: Eliminar unidad de medida | C9: Permite eliminar una unidad de medida que no este siendo utilizada por ningun otro registro de la pizzeria. | D9: UnidadMedida | G9: =HYPERLINK("#'P-UnidadMedida'!A7", "P-UM-003") -> P-UM-003 | H9: Unidad de medida eliminada
G10: =HYPERLINK("#'P-UnidadMedida'!A8", "P-UM-004") -> P-UM-004
G11: =HYPERLINK("#'P-UnidadMedida'!A9", "P-UM-005") -> P-UM-005

Sheet P-UnidadMedida
A1: <<<Modelo de Dominio | B1: <<<Objetos de Dominio
A2: Objeto de Dominio | B2: UnidadMedida
A3: Descripcion | B3: ='C-UnidadMedida'!B3 -> Es la unidad con la que se mide cada ingrediente o producto, por ejemplo kilos, litros o unidades.
A4: Numero politica | B4: Descripcion Politica | C4: Objeto Responsable | D4: Regla Referenciada
A5: P-UM-001 | B5: Asegurar que solo se consulten las unidades de medida del catalogo definido por la pizzeria (g, kg, ml, l y und), cada una con su tipo de medida (Peso, Volumen o Unidad). | C5: UnidadMedida
A6: P-UM-002 | B6: Asegurar que la unidad de medida exista con el identificador indicado | C6: UnidadMedida
A7: P-UM-003 | B7: Asegurar que la unidad de medida que se desea eliminar se encuentre registrada en el sistema. | C7: UnidadMedida
A8: P-UM-004 | B8: Asegurar que la unidad de medida que se desea eliminar no este siendo utilizada por productos internos, lotes o registros de inventario que requieran conservarla. | C8: UnidadMedida
A9: P-UM-005 | B9: Asegurar que la unidad de medida que se desea eliminar no este siendo utilizada por detalles de receta, detalles de compra, cambios o consumos de venta que requieran conservarla. | C9: UnidadMedida

Sheet M-TipoProducto
A1: <<<Modelo de Dominio | B1: <<<Objetos de Dominio
A2: Representa el identificador unico de cada producto | B2: Nombre del tipo de producto (Pizza, Bebida o Adicion)
A3: Tipo de dato | B3: Alfanumerico(max 20 caracteres)
A6: Obligatorio | B6: Si
A7: Id | B7: Nombre
A8: 1 | B8: Pizza
A9: 2 | B9: Bebida
A10: 3 | B10: Adicion

Sheet C-TipoProducto
A1: <<<Modelo de Dominio | B1: <<<Objetos de Dominio
A2: Nombre | B2: TipoProducto
A3: Descripción | B3: =HYPERLINK("#'Objetos de dominio'!B5", 'Objetos de dominio'!B5) -> Indica en qué categoría entra cada producto que vende la pizzería, por ejemplo si es una pizza, una bebida o una adición.
A4: Nombre atributo | B4: Descripción atributo | C4: Identificador del objeto de dominio | D4: Tipo de dato | E4: Obligatorio | F4: Longitud mínima (si aplica) | G4: Longitud máxima (si aplica) | H4: Precisión (si aplica) | I4: Rendondeo (si aplica) | J4: Rango inicial (si aplica) | K4: Rango final (si aplica) | L4: Formato (si aplica) | M4: Reglas especiales (si aplica) | N4: Dato calculado | O4: Aplica ajuste del dato (si aplica) | P4: Carácter de ajuste (si aplica) | Q4: Quitar espacios en blanco al inicio (si aplica) | R4: Quitar espacios en blanco al fin (si aplica) | S4: Dato sensible (si aplica) | T4: Valor por defecto (si aplica) | U4: Auto generado | V4: =HYPERLINK("#'C-TipoProducto'!A18", 'C-TipoProducto'!A18) -> Consultar tipos de producto disponibles | W4: =HYPERLINK("#'C-TipoProducto'!A19", 'C-TipoProducto'!A19) -> Registrar tipo de producto | X4: =HYPERLINK("#'C-TipoProducto'!A21", 'C-TipoProducto'!A21) -> Actualizar tipo de producto | Z4: =HYPERLINK("#'C-TipoProducto'!A23", 'C-TipoProducto'!A23) -> Eliminar tipo de producto
A5: =HYPERLINK("#'M-TipoProducto'!A7", 'M-TipoProducto'!A7) -> Id | B5: =HYPERLINK("#'M-TipoProducto'!A2", 'M-TipoProducto'!A2) -> Representa el identificador unico de cada producto | C5: Si | D5: Identificador unico universal | E5: Si | N5: No | O5: No | Q5: No | R5: No | S5: No | U5: Si | V5: No Mostrar | W5: No Requerido | X5: Requerido | Y5: No Modificable | Z5: Requerido
A6: =HYPERLINK("#'M-TipoProducto'!B7", 'M-TipoProducto'!B7) -> Nombre | B6: =HYPERLINK("#'M-TipoProducto'!B2", 'M-TipoProducto'!B2) -> Nombre del tipo de producto (Pizza, Bebida o Adicion) | C6: No | D6: Alfanumerico | E6: Si | F6: 1 | G6: 20 | M6: Estos son los tipos de producto con los que arranca el catalogo (Pizza, Bebida, Adicion), pero se pueden agregar nuevos si la pizzeria llega a manejar una categoria de producto distinta. | N6: No | O6: No | Q6: Si | R6: Si | S6: No | U6: No | V6: Mostrar | W6: Requerido | X6: Requerido | Y6: Modificable | Z6: No Requerido
A11: Nombre combinación única | B11: Descripción | C11: Atributos involucrados
A12: Combinación única 1 | B12: No pueden existir dos tipos de producto con el mismo Nombre. | C12: =HYPERLINK("#'C-TipoProducto'!A6", 'C-TipoProducto'!A6) -> Nombre
A16: Responsabilidad | C16: Descripción | G16: Entradas | J16: Salida | O16: Políticas (Reglas de Negocio) | Q16: Excepción
G17: Parámetro | H17: Tipo de dato | I17: Descripción | J17: Tipo de Dato | K17: Descripción | O17: Política | P17: Descripción | Q17: Detalle | R17: ¿Qué hago?
A18: =HYPERLINK("#'C-TipoProducto'!V4", 'E-TipoProducto'!B7) -> Consultar tipos de producto disponibles | C18: ='E-TipoProducto'!C7 -> Permite consultar los tipos de producto disponibles en el sistema para clasificar un producto. | G18: id | H18: UUID | I18: Id necesario para realizar la consulta de los tipos de producto disponibles. | J18: Lista de Tipos de Producto | K18: Conjunto de tipos de producto registrados y disponibles para selección. | O18: =HYPERLINK("#'P-TipoProducto'!A5", 'P-TipoProducto'!A5) -> P-TP-001 | P18: ='P-TipoProducto'!B5 -> Asegurar que el tipo de producto exista con el identificador indicado. | Q18: No existen tipos de producto disponibles. | R18: Informar que el tipo de producto que está buscando no existe.
A19: =HYPERLINK("#'E-TipoProducto'!B8", 'E-TipoProducto'!B8) -> Registrar tipo de producto | C19: ='E-TipoProducto'!C8 -> Permite agregar un nuevo tipo de producto al catalogo, para cuando la pizzeria empiece a manejar una categoria de producto que no exista todavia. | G19: Nombre | H19: Alfanumerico | I19: Nombre del nuevo tipo de producto que se desea registrar. | J19: TipoProducto | K19: Tipo de producto registrado. | O19: =HYPERLINK("#'P-TipoProducto'!A6", 'P-TipoProducto'!A6) -> P-TP-002 | P19: ='P-TipoProducto'!B6 -> Asegurar que los datos ingresados sean validos segun el tipo de dato, la obligatoriedad y el formato correspondiente. | Q19: El dato ingresado no es valido segun el tipo de dato, la obligatoriedad o el formato esperado. | R19: Rechazar el registro e informar cual dato no es valido y por que.
O20: =HYPERLINK("#'P-TipoProducto'!A7", 'P-TipoProducto'!A7) -> P-TP-003 | P20: ='P-TipoProducto'!B7 -> Asegurar que no exista otro tipo de producto con el mismo Nombre al registrarlo. | Q20: Ya existe otro tipo de producto registrado con el mismo Nombre. | R20: Rechazar el registro e informar que ya existe un tipo de producto con ese Nombre.
A21: =HYPERLINK("#'E-TipoProducto'!B10", 'E-TipoProducto'!B10) -> Actualizar tipo de producto | C21: ='E-TipoProducto'!C10 -> Permite modificar el nombre de un tipo de producto que ya existe. | G21: Id | H21: UUID | I21: Identificador del tipo de producto que se desea modificar, junto con el nuevo Nombre. | J21: TipoProducto | K21: Tipo de producto actualizado. | O21: =HYPERLINK("#'P-TipoProducto'!A8", 'P-TipoProducto'!A8) -> P-TP-004 | P21: ='P-TipoProducto'!B8 -> Asegurar que el tipo de producto que se desea modificar se encuentre registrado en el sistema. | Q21: El tipo de producto no existe en el sistema. | R21: Rechazar la actualizacion e informar que el tipo de producto no existe.
O22: =HYPERLINK("#'P-TipoProducto'!A6", 'P-TipoProducto'!A6) -> P-TP-002 | P22: ='P-TipoProducto'!B6 -> Asegurar que los datos ingresados sean validos segun el tipo de dato, la obligatoriedad y el formato correspondiente. | Q22: El nuevo dato ingresado no es valido segun el tipo de dato, la obligatoriedad o el formato esperado. | R22: Rechazar la actualizacion e informar cual dato no es valido y por que.
A23: =HYPERLINK("#'E-TipoProducto'!B12", 'E-TipoProducto'!B12) -> Eliminar tipo de producto | C23: ='E-TipoProducto'!C12 -> Permite eliminar un tipo de producto que no tenga productos asociados que deban conservarse. | G23: Id | H23: UUID | I23: Identificador del tipo de producto que se desea eliminar. | J23: TipoProducto | K23: Tipo de producto eliminado correctamente. | O23: =HYPERLINK("#'P-TipoProducto'!A9", 'P-TipoProducto'!A9) -> P-TP-005 | P23: ='P-TipoProducto'!B9 -> Asegurar que un tipo de producto no pueda eliminarse cuando tenga productos asociados que deban conservarse para mantener la trazabilidad. | Q23: El tipo de producto tiene productos asociados que deben conservarse. | R23: Rechazar la eliminacion e informar que el tipo de producto tiene productos asociados.
O24: =HYPERLINK("#'P-TipoProducto'!A10", 'P-TipoProducto'!A10) -> P-TP-006 | P24: ='P-TipoProducto'!B10 -> Asegurar que el tipo de producto que se desea eliminar exista con el identificador indicado. | Q24: El tipo de producto no existe en el sistema. | R24: Rechazar la eliminacion e informar que el tipo de producto no existe.

Sheet E-TipoProducto
A1: <<<Modelo de Dominio | B1: <<<Objetos de Dominio
A2: Objeto de Dominio: | B2: TipoProducto
A3: Descripción: | B3: ='C-TipoProducto'!B3 -> Indica en qué categoría entra cada producto que vende la pizzería, por ejemplo si es una pizza, una bebida o una adición.
A4: Actor | B4: Action/Command | D4: Entity/Aggregate/Object domain | E4: Read Model | G4: Business Rule/Policy | H4: External System | I4: Domain Event | J4: Hotspot/questions/Risk
A5: Actor | B5: Acción | C5: Descripción | D5: Objeto de dominio | E5: Información externa | G5: Políticas | H5: Sistema Externo | I5: Evento | J5: Aspectos por solucionar
E6: Información | F6: Descripción | G6: Número
A7: Administrador | B7: Consultar tipos de producto disponibles | C7: Permite consultar los tipos de producto disponibles en el sistema para clasificar un producto. | D7: TipoProducto | G7: =HYPERLINK("#'P-TipoProducto'!A5", "P-TP-001") -> P-TP-001 | I7: Tipos de producto consultados
A8: Administrador | B8: Registrar tipo de producto | C8: Permite agregar un nuevo tipo de producto al catalogo, para cuando la pizzeria empiece a manejar una categoria de producto que no exista todavia. | D8: TipoProducto | G8: =HYPERLINK("#'P-TipoProducto'!A6", "P-TP-002") -> P-TP-002 | I8: Tipo de producto registrado
G9: =HYPERLINK("#'P-TipoProducto'!A7", "P-TP-003") -> P-TP-003
A10: Administrador | B10: Actualizar tipo de producto | C10: Permite modificar el nombre de un tipo de producto que ya existe. | D10: TipoProducto | G10: =HYPERLINK("#'P-TipoProducto'!A8", "P-TP-004") -> P-TP-004 | I10: Tipo de producto actualizado
G11: =HYPERLINK("#'P-TipoProducto'!A6", "P-TP-002") -> P-TP-002
A12: Administrador | B12: Eliminar tipo de producto | C12: Permite eliminar un tipo de producto que no tenga productos asociados que deban conservarse. | D12: TipoProducto | G12: =HYPERLINK("#'P-TipoProducto'!A9", "P-TP-005") -> P-TP-005 | I12: Tipo de producto eliminado
G13: =HYPERLINK("#'P-TipoProducto'!A10", "P-TP-006") -> P-TP-006

Sheet P-TipoProducto
A1: <<<Modelo de Dominio | B1: <<<Objetos de Dominio
A2: Objeto de Dominio | B2: TipoProducto
A3: Descripcion | B3: ='C-TipoProducto'!B3 -> Indica en qué categoría entra cada producto que vende la pizzería, por ejemplo si es una pizza, una bebida o una adición.
A4: Numero politica | B4: Descripcion Politica | C4: Objeto Responsable | D4: Regla Referenciada
A5: P-TP-001 | B5: Asegurar que el tipo de producto exista con el identificador indicado. | C5: TipoProducto
A6: P-TP-002 | B6: Asegurar que los datos ingresados sean validos segun el tipo de dato, la obligatoriedad y el formato correspondiente. | C6: TipoProducto
A7: P-TP-003 | B7: Asegurar que no exista otro tipo de producto con el mismo Nombre al registrarlo. | C7: TipoProducto
A8: P-TP-004 | B8: Asegurar que el tipo de producto que se desea modificar se encuentre registrado en el sistema. | C8: TipoProducto
A9: P-TP-005 | B9: Asegurar que un tipo de producto no pueda eliminarse cuando tenga productos asociados que deban conservarse para mantener la trazabilidad. | C9: TipoProducto
A10: P-TP-006 | B10: Asegurar que el tipo de producto que se desea eliminar exista con el identificador indicado. | C10: TipoProducto

Sheet M-ClaseMovimiento
A1: <<<Modelo de Dominio | B1: <<<Objetos de Dominio
A2: Representa el identificador unico de cada clase de movimiento | B2: Nombre de la clase de movimiento (Entrada o Salida): indica si el movimiento suma (Entrada) o resta (Salida) inventario
A3: Tipo de dato | B3: Alfanumerico(max 10 caracteres)
A6: Obligatorio | B6: Si
A7: Id | B7: Nombre
A8: 1 | B8: Entrada
A9: 2 | B9: Salida

Sheet C-ClaseMovimiento
A1: <<<Modelo de Dominio | B1: <<<Objetos de Dominio
A2: Nombre | B2: ClaseMovimiento
A3: Descripción | B3: =HYPERLINK("#'Objetos de dominio'!B6", 'Objetos de dominio'!B6) -> Indica si un movimiento de inventario fue una entrada o una salida de insumos o productos.
A4: Nombre atributo | B4: Descripción atributo | C4: Identificador del objeto de dominio | D4: Tipo de dato | E4: Obligatorio | F4: Longitud mínima (si aplica) | G4: Longitud máxima (si aplica) | H4: Precisión (si aplica) | I4: Rendondeo (si aplica) | J4: Rango inicial (si aplica) | K4: Rango final (si aplica) | L4: Formato (si aplica) | M4: Reglas especiales (si aplica) | N4: Dato calculado | O4: Aplica ajuste del dato (si aplica) | P4: Carácter de ajuste (si aplica) | Q4: Quitar espacios en blanco al inicio (si aplica) | R4: Quitar espacios en blanco al fin (si aplica) | S4: Dato sensible (si aplica) | T4: Valor por defecto (si aplica) | U4: Auto generado | V4: =HYPERLINK("#'C-ClaseMovimiento'!A19", 'C-ClaseMovimiento'!A19) -> Consultar clases de movimiento disponibles
A5: =HYPERLINK("#'M-ClaseMovimiento'!A7", 'M-ClaseMovimiento'!A7) -> Id | B5: =HYPERLINK("#'M-ClaseMovimiento'!A2", 'M-ClaseMovimiento'!A2) -> Representa el identificador unico de cada clase de movimiento | C5: Si | D5: Identificador unico universal | E5: Si | N5: No | O5: No | Q5: No | R5: No | S5: No | U5: Si | V5: No Mostrar
A6: =HYPERLINK("#'M-ClaseMovimiento'!B7", 'M-ClaseMovimiento'!B7) -> Nombre | B6: =HYPERLINK("#'M-ClaseMovimiento'!B2", 'M-ClaseMovimiento'!B2) -> Nombre de la clase de movimiento (Entrada o Salida): indica si el movimiento suma (Entrada) o resta (Salida) inventario | C6: No | D6: Alfanumerico | E6: Si | F6: 1 | G6: 10 | M6: Catalogo fijo de solo 2 valores (Entrada, Salida) | N6: No | O6: No | Q6: Si | R6: Si | S6: No | U6: No | V6: Mostrar
A12: Nombre combinación única | B12: Descripción | C12: Atributos involucrados
A13: Combinación única 1 | B13: No pueden existir dos clases de movimiento con el mismo Nombre. | C13: =HYPERLINK("#'C-ClaseMovimiento'!A6", 'C-ClaseMovimiento'!A6) -> Nombre
A17: Responsabilidad | C17: Descripción | G17: Entradas | J17: Salida | O17: Políticas (Reglas de Negocio) | Q17: Excepción
G18: Parámetro | H18: Tipo de dato | I18: Descripción | J18: Tipo de Dato | K18: Descripción | O18: Política | P18: Descripción | Q18: Detalle | R18: ¿Qué hago?
A19: =HYPERLINK("#'C-ClaseMovimiento'!V4", 'E-ClaseMovimiento'!B7) -> Consultar clases de movimiento disponibles | C19: ='E-ClaseMovimiento'!C7 -> Permite consultar las clases de movimiento (Entrada o Salida) disponibles para clasificar un movimiento de inventario. | G19: id | H19: UUID | I19: Id necesario para realizar la consulta de las clases de movimiento disponibles. | J19: Lista de ClasesMovimiento | K19: Conjunto de clases de movimiento (Entrada y Salida) disponibles para seleccion. | O19: =HYPERLINK("#'P-ClaseMovimiento'!A5", 'P-ClaseMovimiento'!A5) -> P-CM-001 | P19: ='P-ClaseMovimiento'!B5 -> Asegurar que la clase de movimiento exista con el identificador indicado. | Q19: No existen clases de movimiento disponibles. | R19: Informar que la clase de movimiento que esta buscando no existe.

Sheet E-ClaseMovimiento
A1: <<<Modelo de Dominio | B1: <<<Objetos de Dominio
A2: Objeto de Dominio: | B2: ClaseMovimiento
A3: Descripción: | B3: ='C-ClaseMovimiento'!B3 -> Indica si un movimiento de inventario fue una entrada o una salida de insumos o productos.
A4: Actor | B4: Action/Command | D4: Entity/Aggregate/Object domain | E4: Read Model | G4: Business Rule/Policy | H4: External System | I4: Domain Event | J4: Hotspot/questions/Risk
A5: Actor | B5: Acción | C5: Descripción | D5: Objeto de dominio | E5: Información externa | G5: Políticas | H5: Sistema Externo | I5: Evento | J5: Aspectos por solucionar
E6: Información | F6: Descripción | G6: Número
A7: Administrador | B7: Consultar clases de movimiento disponibles | C7: Permite consultar las clases de movimiento (Entrada o Salida) disponibles para clasificar un movimiento de inventario. | D7: ClaseMovimiento | G7: =HYPERLINK("#'P-ClaseMovimiento'!A5", "P-CM-001") -> P-CM-001 | I7: Clases de movimiento consultadas

Sheet P-ClaseMovimiento
A1: <<<Modelo de Dominio | B1: <<<Objetos de Dominio
A2: Objeto de Dominio | B2: ClaseMovimiento
A3: Descripcion | B3: ='C-ClaseMovimiento'!B3 -> Indica si un movimiento de inventario fue una entrada o una salida de insumos o productos.
A4: Numero politica | B4: Descripcion Politica | C4: Objeto Responsable | D4: Regla Referenciada
A5: P-CM-001 | B5: Asegurar que la clase de movimiento exista con el identificador indicado. | C5: ClaseMovimiento

Sheet M-Tamaño
A1: <<<Modelo de Dominio | B1: <<<Objetos de Dominio
A2: Representa el identificador unico de cada tamaño | B2: Nombre del tamaño (Grande, Mediana, Pequeña o No aplica)
A3: Tipo de dato | B3: Alfanumerico(max 20 caracteres)
A6: Obligatorio | B6: Si
A7: Id | B7: Tamaño
A8: 1 | B8: Grande
A9: 2 | B9: Mediana
A10: 3 | B10: Pequeña
A11: 4 | B11: No aplica

Sheet C-Tamaño
A1: <<<Modelo de Dominio | B1: <<<Objetos de Dominio
A2: Nombre | B2: Tamaño
A3: Descripción | B3: =HYPERLINK("#'Objetos de dominio'!B7", 'Objetos de dominio'!B7) -> Son los distintos tamaños en los que la pizzería puede ofrecer una pizza.
A4: Nombre atributo | B4: Descripción atributo | C4: Identificador del objeto de dominio | D4: Tipo de dato | E4: Obligatorio | F4: Longitud mínima (si aplica) | G4: Longitud máxima (si aplica) | H4: Precisión (si aplica) | I4: Rendondeo (si aplica) | J4: Rango inicial (si aplica) | K4: Rango final (si aplica) | L4: Formato (si aplica) | M4: Reglas especiales (si aplica) | N4: Dato calculado | O4: Aplica ajuste del dato (si aplica) | P4: Carácter de ajuste (si aplica) | Q4: Quitar espacios en blanco al inicio (si aplica) | R4: Quitar espacios en blanco al fin (si aplica) | S4: Dato sensible (si aplica) | T4: Valor por defecto (si aplica) | U4: Auto generado | V4: =HYPERLINK("#'C-Tamaño'!A18", 'C-Tamaño'!A18) -> Consultar tamaños disponibles | W4: =HYPERLINK("#'C-Tamaño'!A19", 'C-Tamaño'!A19) -> Registrar tamaño | X4: =HYPERLINK("#'C-Tamaño'!A21", 'C-Tamaño'!A21) -> Actualizar tamaño | Z4: =HYPERLINK("#'C-Tamaño'!A23", 'C-Tamaño'!A23) -> Eliminar tamaño
A5: =HYPERLINK("#'M-Tamaño'!A7", 'M-Tamaño'!A7) -> Id | B5: =HYPERLINK("#'M-Tamaño'!A2", 'M-Tamaño'!A2) -> Representa el identificador unico de cada tamaño | C5: Si | D5: Identificador unico universal | E5: Si | N5: No | O5: No | Q5: No | R5: No | S5: No | U5: Si | V5: No Mostrar | W5: No Requerido | X5: Requerido | Y5: No Modificable | Z5: Requerido
A6: =HYPERLINK("#'M-Tamaño'!B7", 'M-Tamaño'!B7) -> Tamaño | B6: =HYPERLINK("#'M-Tamaño'!B2", 'M-Tamaño'!B2) -> Nombre del tamaño (Grande, Mediana, Pequeña o No aplica) | C6: No | D6: Alfanumerico | E6: Si | F6: 1 | G6: 20 | M6: Estos son los tamaños con los que arranca el catalogo (Grande, Mediana, Pequeña, No aplica), pero se pueden agregar nuevos si la pizzeria llega a manejar una presentacion de tamaño distinta. | N6: No | O6: No | Q6: Si | R6: Si | S6: No | U6: No | V6: Mostrar | W6: Requerido | X6: Requerido | Y6: Modificable | Z6: No Requerido
A11: Nombre combinación única | B11: Descripción | C11: Atributos involucrados
A12: Combinación única 1 | B12: No pueden existir dos tamaños con el mismo Nombre. | C12: =HYPERLINK("#'C-Tamaño'!A6", 'C-Tamaño'!A6) -> Tamaño
A16: Responsabilidad | C16: Descripción | G16: Entradas | J16: Salida | O16: Políticas (Reglas de Negocio) | Q16: Excepción
G17: Parámetro | H17: Tipo de dato | I17: Descripción | J17: Tipo de Dato | K17: Descripción | O17: Política | P17: Descripción | Q17: Detalle | R17: ¿Qué hago?
A18: =HYPERLINK("#'C-Tamaño'!V4", 'E-Tamaño'!B7) -> Consultar tamaños disponibles | C18: ='E-Tamaño'!C7 -> Permite consultar los tamaños disponibles en el sistema para definir el tamaño de un producto. | G18: id | H18: UUID | I18: Id necesario para realizar la consulta de los tamaños disponibles. | J18: Lista de Tamaños | K18: Conjunto de tamaños registrados y disponibles para selección. | O18: =HYPERLINK("#'P-Tamaño'!A5", 'P-Tamaño'!A5) -> P-TAM-001 | P18: ='P-Tamaño'!B5 -> Asegurar que el tamaño exista con el identificador indicado. | Q18: No existen tamaños disponibles. | R18: Informar que el tamaño que está buscando no existe.
A19: =HYPERLINK("#'E-Tamaño'!B8", 'E-Tamaño'!B8) -> Registrar tamaño | C19: ='E-Tamaño'!C8 -> Permite agregar un nuevo tamaño al catalogo, para cuando la pizzeria empiece a ofrecer una presentacion que no exista todavia. | G19: Nombre | H19: Alfanumerico | I19: Nombre del nuevo tamaño que se desea registrar. | J19: Tamaño | K19: Tamaño registrado. | O19: =HYPERLINK("#'P-Tamaño'!A6", 'P-Tamaño'!A6) -> P-TAM-002 | P19: ='P-Tamaño'!B6 -> Asegurar que los datos ingresados sean validos segun el tipo de dato, la obligatoriedad y el formato correspondiente. | Q19: El dato ingresado no es valido segun el tipo de dato, la obligatoriedad o el formato esperado. | R19: Rechazar el registro e informar cual dato no es valido y por que.
O20: =HYPERLINK("#'P-Tamaño'!A7", 'P-Tamaño'!A7) -> P-TAM-003 | P20: ='P-Tamaño'!B7 -> Asegurar que no exista otro tamaño con el mismo Nombre al registrarlo. | Q20: Ya existe otro tamaño registrado con el mismo Nombre. | R20: Rechazar el registro e informar que ya existe un tamaño con ese Nombre.
A21: =HYPERLINK("#'E-Tamaño'!B10", 'E-Tamaño'!B10) -> Actualizar tamaño | C21: ='E-Tamaño'!C10 -> Permite modificar el nombre de un tamaño que ya existe. | G21: Id | H21: UUID | I21: Identificador del tamaño que se desea modificar, junto con el nuevo Nombre. | J21: Tamaño | K21: Tamaño actualizado. | O21: =HYPERLINK("#'P-Tamaño'!A8", 'P-Tamaño'!A8) -> P-TAM-004 | P21: ='P-Tamaño'!B8 -> Asegurar que el tamaño que se desea modificar se encuentre registrado en el sistema. | Q21: El tamaño no existe en el sistema. | R21: Rechazar la actualizacion e informar que el tamaño no existe.
O22: =HYPERLINK("#'P-Tamaño'!A6", 'P-Tamaño'!A6) -> P-TAM-002 | P22: ='P-Tamaño'!B6 -> Asegurar que los datos ingresados sean validos segun el tipo de dato, la obligatoriedad y el formato correspondiente. | Q22: El nuevo dato ingresado no es valido segun el tipo de dato, la obligatoriedad o el formato esperado. | R22: Rechazar la actualizacion e informar cual dato no es valido y por que.
A23: =HYPERLINK("#'E-Tamaño'!B12", 'E-Tamaño'!B12) -> Eliminar tamaño | C23: ='E-Tamaño'!C12 -> Permite eliminar un tamaño que no tenga productos asociados que deban conservarse. | G23: Id | H23: UUID | I23: Identificador del tamaño que se desea eliminar. | J23: Tamaño | K23: Tamaño eliminado correctamente. | O23: =HYPERLINK("#'P-Tamaño'!A9", 'P-Tamaño'!A9) -> P-TAM-005 | P23: ='P-Tamaño'!B9 -> Asegurar que un tamaño no pueda eliminarse cuando tenga productos asociados que deban conservarse para mantener la trazabilidad. | Q23: El tamaño tiene productos asociados que deben conservarse. | R23: Rechazar la eliminacion e informar que el tamaño tiene productos asociados.
O24: =HYPERLINK("#'P-Tamaño'!A10", 'P-Tamaño'!A10) -> P-TAM-006 | P24: ='P-Tamaño'!B10 -> Asegurar que el tamaño que se desea eliminar exista con el identificador indicado. | Q24: El tamaño no existe en el sistema. | R24: Rechazar la eliminacion e informar que el tamaño no existe.

Sheet E-Tamaño
A1: <<<Modelo de Dominio | B1: <<<Objetos de Dominio
A2: Objeto de Dominio: | B2: Tamaño
A3: Descripción: | B3: ='C-Tamaño'!B3 -> Son los distintos tamaños en los que la pizzería puede ofrecer una pizza.
A4: Actor | B4: Action/Command | D4: Entity/Aggregate/Object domain | E4: Read Model | G4: Business Rule/Policy | H4: External System | I4: Domain Event | J4: Hotspot/questions/Risk
A5: Actor | B5: Acción | C5: Descripción | D5: Objeto de dominio | E5: Información externa | G5: Políticas | H5: Sistema Externo | I5: Evento | J5: Aspectos por solucionar
E6: Información | F6: Descripción | G6: Número
A7: Administrador | B7: Consultar tamaños disponibles | C7: Permite consultar los tamaños disponibles en el sistema para definir el tamaño de un producto. | D7: Tamaño | G7: =HYPERLINK("#'P-Tamaño'!A5", "P-TAM-001") -> P-TAM-001 | I7: Tamaños consultados
A8: Administrador | B8: Registrar tamaño | C8: Permite agregar un nuevo tamaño al catalogo, para cuando la pizzeria empiece a ofrecer una presentacion que no exista todavia. | D8: Tamaño | G8: =HYPERLINK("#'P-Tamaño'!A6", "P-TAM-002") -> P-TAM-002 | I8: Tamaño registrado
G9: =HYPERLINK("#'P-Tamaño'!A7", "P-TAM-003") -> P-TAM-003
A10: Administrador | B10: Actualizar tamaño | C10: Permite modificar el nombre de un tamaño que ya existe. | D10: Tamaño | G10: =HYPERLINK("#'P-Tamaño'!A8", "P-TAM-004") -> P-TAM-004 | I10: Tamaño actualizado
G11: =HYPERLINK("#'P-Tamaño'!A6", "P-TAM-002") -> P-TAM-002
A12: Administrador | B12: Eliminar tamaño | C12: Permite eliminar un tamaño que no tenga productos asociados que deban conservarse. | D12: Tamaño | G12: =HYPERLINK("#'P-Tamaño'!A9", "P-TAM-005") -> P-TAM-005 | I12: Tamaño eliminado
G13: =HYPERLINK("#'P-Tamaño'!A10", "P-TAM-006") -> P-TAM-006

Sheet P-Tamaño
A1: <<<Modelo de Dominio | B1: <<<Objetos de Dominio
A2: Objeto de Dominio | B2: Tamaño
A3: Descripcion | B3: ='C-Tamaño'!B3 -> Son los distintos tamaños en los que la pizzería puede ofrecer una pizza.
A4: Numero politica | B4: Descripcion Politica | C4: Objeto Responsable | D4: Regla Referenciada
A5: P-TAM-001 | B5: Asegurar que el tamaño exista con el identificador indicado. | C5: Tamaño
A6: P-TAM-002 | B6: Asegurar que los datos ingresados sean validos segun el tipo de dato, la obligatoriedad y el formato correspondiente. | C6: Tamaño
A7: P-TAM-003 | B7: Asegurar que no exista otro tamaño con el mismo Nombre al registrarlo. | C7: Tamaño
A8: P-TAM-004 | B8: Asegurar que el tamaño que se desea modificar se encuentre registrado en el sistema. | C8: Tamaño
A9: P-TAM-005 | B9: Asegurar que un tamaño no pueda eliminarse cuando tenga productos asociados que deban conservarse para mantener la trazabilidad. | C9: Tamaño
A10: P-TAM-006 | B10: Asegurar que el tamaño que se desea eliminar exista con el identificador indicado. | C10: Tamaño

Sheet M-CategoriaOrigen
A1: <<<Modelo de Dominio | B1: <<<Objetos de Dominio
A2: Representa el identificador unico de cada categoria de origen | B2: Nombre de la categoria de origen: indica de donde proviene la operacion (Compra, Venta o Cambio)
A3: Tipo de dato | B3: Alfanumerico(max 10 caracteres)
A6: Obligatorio | B6: Si
A7: Id | B7: Nombre
A8: 1 | B8: Compra
A9: 2 | B9: Venta
A10: 3 | B10: Cambio

Sheet C-CategoriaOrigen
A1: <<<Modelo de Dominio | B1: <<<Objetos de Dominio
A2: Nombre | B2: CategoriaOrigen
A3: Descripción | B3: =HYPERLINK("#'Objetos de dominio'!B8", 'Objetos de dominio'!B8) -> Indica qué operación fue la que generó un movimiento de inventario: una compra, una venta, un cambio de un producto que no es perecedero, o el retiro de un lote (porque se cambió o porque se venció).
A4: Nombre atributo | B4: Descripción atributo | C4: Identificador del objeto de dominio | D4: Tipo de dato | E4: Obligatorio | F4: Longitud mínima (si aplica) | G4: Longitud máxima (si aplica) | H4: Precisión (si aplica) | I4: Rendondeo (si aplica) | J4: Rango inicial (si aplica) | K4: Rango final (si aplica) | L4: Formato (si aplica) | M4: Reglas especiales (si aplica) | N4: Dato calculado | O4: Aplica ajuste del dato (si aplica) | P4: Carácter de ajuste (si aplica) | Q4: Quitar espacios en blanco al inicio (si aplica) | R4: Quitar espacios en blanco al fin (si aplica) | S4: Dato sensible (si aplica) | T4: Valor por defecto (si aplica) | U4: Auto generado | V4: =HYPERLINK("#'C-CategoriaOrigen'!A18", 'C-CategoriaOrigen'!A18) -> Consultar categorias de origen disponibles
A5: =HYPERLINK("#'M-CategoriaOrigen'!A7", 'M-CategoriaOrigen'!A7) -> Id | B5: =HYPERLINK("#'M-CategoriaOrigen'!A2", 'M-CategoriaOrigen'!A2) -> Representa el identificador unico de cada categoria de origen | C5: Si | D5: Identificador unico universal | E5: Si | N5: No | O5: No | Q5: No | R5: No | S5: No | U5: Si | V5: No Mostrar
A6: =HYPERLINK("#'M-CategoriaOrigen'!B7", 'M-CategoriaOrigen'!B7) -> Nombre | B6: =HYPERLINK("#'M-CategoriaOrigen'!B2", 'M-CategoriaOrigen'!B2) -> Nombre de la categoria de origen: indica de donde proviene la operacion (Compra, Venta o Cambio) | C6: No | D6: Alfanumerico | E6: Si | F6: 1 | G6: 10 | M6: Catalogo fijo de 3 valores (Compra, Venta, Cambio) | N6: No | O6: No | Q6: Si | R6: Si | S6: No | U6: No | V6: Mostrar
A11: Nombre combinación única | B11: Descripción | C11: Atributos involucrados
A12: Combinación única 1 | B12: No pueden existir dos categorias de origen con el mismo Nombre. | C12: =HYPERLINK("#'C-CategoriaOrigen'!A6", 'C-CategoriaOrigen'!A6) -> Nombre
A16: Responsabilidad | C16: Descripción | G16: Entradas | J16: Salida | O16: Políticas (Reglas de Negocio) | Q16: Excepción
G17: Parámetro | H17: Tipo de dato | I17: Descripción | J17: Tipo de Dato | K17: Descripción | O17: Política | P17: Descripción | Q17: Detalle | R17: ¿Qué hago?
A18: =HYPERLINK("#'C-CategoriaOrigen'!V4", 'E-CategoriaOrigen'!B7) -> Consultar categorias de origen disponibles | C18: ='E-CategoriaOrigen'!C7 -> Permite consultar las categorias de origen (Compra, Venta o Cambio) que indican que operacion genero un movimiento de inventario. | G18: id | H18: UUID | I18: Id necesario para realizar la consulta de las categorias de origen disponibles. | J18: Lista de CategoriasOrigen | K18: Conjunto de categorias de origen (Compra, Venta y Cambio) disponibles para seleccion. | O18: =HYPERLINK("#'P-CategoriaOrigen'!A5", 'P-CategoriaOrigen'!A5) -> P-ORI-001 | P18: ='P-CategoriaOrigen'!B5 -> Asegurar que la categoria de origen exista con el identificador indicado. | Q18: No existen categorias de origen disponibles. | R18: Informar que la categoria de origen que esta buscando no existe.

Sheet E-CategoriaOrigen
A1: <<<Modelo de Dominio | B1: <<<Objetos de Dominio
A2: Objeto de Dominio: | B2: CategoriaOrigen
A3: Descripción: | B3: ='C-CategoriaOrigen'!B3 -> Indica qué operación fue la que generó un movimiento de inventario: una compra, una venta, un cambio de un producto que no es perecedero, o el retiro de un lote (porque se cambió o porque se venció).
A4: Actor | B4: Action/Command | D4: Entity/Aggregate/Object domain | E4: Read Model | G4: Business Rule/Policy | H4: External System | I4: Domain Event | J4: Hotspot/questions/Risk
A5: Actor | B5: Acción | C5: Descripción | D5: Objeto de dominio | E5: Información externa | G5: Políticas | H5: Sistema Externo | I5: Evento | J5: Aspectos por solucionar
E6: Información | F6: Descripción | G6: Número
A7: Administrador | B7: Consultar categorias de origen disponibles | C7: Permite consultar las categorias de origen (Compra, Venta o Cambio) que indican que operacion genero un movimiento de inventario. | D7: CategoriaOrigen | G7: =HYPERLINK("#'P-CategoriaOrigen'!A5", "P-ORI-001") -> P-ORI-001 | I7: Categorias de origen consultadas

Sheet P-CategoriaOrigen
A1: <<<Modelo de Dominio | B1: <<<Objetos de Dominio
A2: Objeto de Dominio | B2: CategoriaOrigen
A3: Descripcion | B3: ='C-CategoriaOrigen'!B3 -> Indica qué operación fue la que generó un movimiento de inventario: una compra, una venta, un cambio de un producto que no es perecedero, o el retiro de un lote (porque se cambió o porque se venció).
A4: Numero politica | B4: Descripcion Politica | C4: Objeto Responsable | D4: Regla Referenciada
A5: P-ORI-001 | B5: Asegurar que la categoria de origen exista con el identificador indicado. | C5: CategoriaOrigen

Sheet M-Compra
A1: ent | B1: <<< Objetos de dominio
A2: Identificador unico de cada compra de la pizzeria | B2: Nombre del proveedor al que se le hizo la compra | C2: Representa la fecha en la que se efectuó la compra | D2: Número de factura que el proveedor entrega al momento de la compra. | E2: Representa el valor monetario total de los productos comprados al proveedor.
A3: Tipo de dato | B3: Proveedor | C3: Fecha | D3: Alfanumerico(max 40 caracteres) | E3: Decimal Europeo (2)
A4: Obligatorio | B4: Si | C4: Si | D4: Si | E4: Si
A5: Id | B5: Proveedor | C5: FechaCompra | D5: NumeroFactura | E5: Total | F5: CombinacionUnica
A6: 1 | B6: =HYPERLINK("#'M-Proveedor'!B6", 'M-Proveedor'!B6) -> Colanta | C6: 46266 | D6: FE-1023 | E6: =SUMIF('M-DetalleCompra'!$G:$G,F6,'M-DetalleCompra'!$E:$E) -> 692500 | F6: =CONCATENATE(B6," ",D6) -> Colanta FE-1023
A7: 2 | B7: =HYPERLINK("#'M-Proveedor'!B7", 'M-Proveedor'!B7) -> Harinera del valle | C7: 46144 | D7: FV-4587 | E7: =SUMIF('M-DetalleCompra'!$G:$G,F7,'M-DetalleCompra'!$E:$E) -> 551000 | F7: =CONCATENATE(B7," ",D7) -> Harinera del valle FV-4587
A8: 3 | B8: =HYPERLINK("#'M-Proveedor'!B8", 'M-Proveedor'!B8) -> Postobon | C8: 46213 | D8: PO-9012 | E8: =SUMIF('M-DetalleCompra'!$G:$G,F8,'M-DetalleCompra'!$E:$E) -> 3600 | F8: =CONCATENATE(B8," ",D8) -> Postobon PO-9012
A9: 4 | B9: =HYPERLINK("#'M-Proveedor'!B7", 'M-Proveedor'!B7) -> Harinera del valle | C9: 46249 | D9: FV-5102 | E9: =SUMIF('M-DetalleCompra'!$G:$G,F9,'M-DetalleCompra'!$E:$E) -> 126000 | F9: =CONCATENATE(B9," ",D9) -> Harinera del valle FV-5102
A10: 5 | B10: =HYPERLINK("#'M-Proveedor'!B6", 'M-Proveedor'!B6) -> Colanta | C10: 46204 | D10: FE-1102 | E10: =SUMIF('M-DetalleCompra'!$G:$G,F10,'M-DetalleCompra'!$E:$E) -> 3750 | F10: =CONCATENATE(B10," ",D10) -> Colanta FE-1102
A11: 6 | B11: =HYPERLINK("#'M-Proveedor'!B9", 'M-Proveedor'!B9) -> Central de Abastos | C11: 46188 | D11: CA-2201 | E11: =SUMIF('M-DetalleCompra'!$G:$G,F11,'M-DetalleCompra'!$E:$E) -> 105000 | F11: =CONCATENATE(B11," ",D11) -> Central de Abastos CA-2201
A12: 7 | B12: =HYPERLINK("#'M-Proveedor'!B6", 'M-Proveedor'!B6) -> Colanta | C12: 46291 | D12: FE-1250 | E12: =SUMIF('M-DetalleCompra'!$G:$G,F12,'M-DetalleCompra'!$E:$E) -> 7500 | F12: =CONCATENATE(B12," ",D12) -> Colanta FE-1250
A13: 8 | B13: =HYPERLINK("#'M-Proveedor'!B9", 'M-Proveedor'!B9) -> Central de Abastos | C13: 46293 | D13: CA-2310 | E13: =SUMIF('M-DetalleCompra'!$G:$G,F13,'M-DetalleCompra'!$E:$E) -> 36000 | F13: =CONCATENATE(B13," ",D13) -> Central de Abastos CA-2310
A14: 9 | B14: =HYPERLINK("#'M-Proveedor'!B6", 'M-Proveedor'!B6) -> Colanta | C14: 46295 | D14: FE-1263 | E14: =SUMIF('M-DetalleCompra'!$G:$G,F14,'M-DetalleCompra'!$E:$E) -> 12500 | F14: =CONCATENATE(B14," ",D14) -> Colanta FE-1263

Sheet C-Compra
A1: <<<Modelo de Dominio | B1: <<<Objetos de Dominio
A2: Nombre | B2: Compra
A3: Descripción | B3: =HYPERLINK("#'Objetos de dominio'!B9", 'Objetos de dominio'!B10) -> Es cuando la pizzería le compra insumos o productos a un proveedor.
A4: Nombre atributo | B4: Descripción atributo | C4: Identificador del objeto de dominio | D4: Tipo de dato | E4: Obligatorio | F4: Longitud mínima (si aplica) | G4: Longitud máxima (si aplica) | H4: Precisión (si aplica) | I4: Rendondeo (si aplica) | J4: Rango inicial (si aplica) | K4: Rango final (si aplica) | L4: Formato (si aplica) | M4: Reglas especiales (si aplica) | N4: Dato calculado | O4: Aplica ajuste del dato (si aplica) | P4: Carácter de ajuste (si aplica) | Q4: Quitar espacios en blanco al inicio (si aplica) | R4: Quitar espacios en blanco al fin (si aplica) | S4: Dato sensible (si aplica) | T4: Valor por defecto (si aplica) | U4: Auto generado | V4: =HYPERLINK("#'C-Compra'!A20", 'C-Compra'!A20) -> Registrar compra | W4: =HYPERLINK("#'C-Compra'!A25", 'C-Compra'!A25) -> Modificar compra | Y4: =HYPERLINK("#'C-Compra'!A29", 'C-Compra'!A29) -> Eliminar compra | Z4: =HYPERLINK("#'C-Compra'!A31", 'C-Compra'!A31) -> Consultar compra
A5: =HYPERLINK("#'M-Compra'!A5", 'M-Compra'!A5) -> Id | B5: =HYPERLINK("#'M-Compra'!A2", 'M-Compra'!A2) -> Identificador unico de cada compra de la pizzeria | C5: Si | D5: Identificador único universal | E5: Si | N5: No | O5: No | Q5: No | R5: No | S5: No | T5: No | U5: Si | V5: Requerido | W5: Requerido | X5: No Modificable | Y5: Requerido | Z5: No Mostrar
A6: =HYPERLINK("#'M-Compra'!B5", 'M-Compra'!B5) -> Proveedor | B6: =HYPERLINK("#'M-Compra'!B2", 'M-Compra'!B2) -> Nombre del proveedor al que se le hizo la compra | C6: No | D6: Proveedor | E6: Si | M6: Debe corresponder a un Proveedor existente en el sistema | N6: No | O6: No | Q6: No | R6: No | S6: No | T6: No | U6: No | V6: Requerido | W6: No Requerido | X6: Modificable | Y6: No Requerido | Z6: Mostrar
A7: =HYPERLINK("#'M-Compra'!C5", 'M-Compra'!C5) -> FechaCompra | B7: =HYPERLINK("#'M-Compra'!C2", 'M-Compra'!C2) -> Representa la fecha en la que se efectuó la compra | C7: No | D7: Fecha | E7: Si | L7: dd/mm/yyyy | M7: La fecha no puede ser futura. | N7: No | O7: No | Q7: No | R7: No | S7: No | T7: No | U7: No | V7: Requerido | W7: No Requerido | X7: Modificable | Y7: No Requerido | Z7: Mostrar
A8: =HYPERLINK("#'M-Compra'!D5", 'M-Compra'!D5) -> NumeroFactura | B8: =HYPERLINK("#'M-Compra'!D2", 'M-Compra'!D2) -> Número de factura que el proveedor entrega al momento de la compra. | C8: No | D8: Alfanumerico | E8: Si | F8: 4 | G8: 40 | M8: Dato real tomado de la factura fisica que entrega el proveedor, no es un codigo generado por el sistema. | N8: No | O8: No | Q8: Si | R8: Si | S8: No | T8: No | U8: No | V8: Requerido | W8: No Requerido | X8: Modificable | Y8: No Requerido | Z8: Mostrar
A9: =HYPERLINK("#'M-Compra'!E5", 'M-Compra'!E5) -> Total | B9: =HYPERLINK("#'M-Compra'!E2", 'M-Compra'!E2) -> Representa el valor monetario total de los productos comprados al proveedor. | C9: No | D9: Decimal Europeo | E9: Si | H9: 2 | I9: A la unidad(0) | J9: >0 | K9: 5000000 | M9: El valor total de una compra corresponde a la suma de los valores registrados en el atributo PrecioCompra de todos los DetalleCompra asociados a dicha compra. | N9: Si | O9: No | Q9: No | R9: No | S9: No | T9: No | U9: No | V9: Requerido | W9: No Requerido | X9: No Modificable | Y9: No Requerido | Z9: Mostrar
A11: Nombre combinación única | B11: Descripción | C11: Atributos involucrados
A12: Combinación única 1 | B12: No pueden existir dos compras con el mismo Proveedor y el mismo numero de factura | C12: =HYPERLINK("#'C-Compra'!A6", 'C-Compra'!A6) -> Proveedor
C13: =HYPERLINK("#'C-Compra'!A8", 'C-Compra'!A8) -> NumeroFactura
A18: Responsabilidad | C18: Descripción | G18: Entradas | J18: Salida | O18: Políticas (Reglas de Negocio) | Q18: Excepción
G19: Parámetro | H19: Tipo de dato | I19: Descripción | J19: Tipo de Dato | K19: Descripción | O19: Política | P19: Descripción | Q19: Detalle | R19: ¿Qué hago?
A20: =HYPERLINK("#'C-Compra'!V4", 'E-Compra'!B7) -> Registrar compra | C20: ='E-Compra'!C7 -> Registrar una nueva compra asociada a un proveedor y a la pizzería correspondiente, dejando constancia de la operación de adquisición. | G20: Datos | H20: Compra | I20: Información necesaria para registrar la compra. | J20: Compra | K20: Compra registrada con la información proporcionada. | O20: =HYPERLINK("#'P-Compra'!A5", 'P-Compra'!A5) -> P-COM-001 | P20: ='P-Compra'!B5 -> Asegurar que los datos requeridos para registrar una compra sean válidos de acuerdo con el tipo de dato, obligatoriedad, formato y rango correspondiente. | Q20: Los datos ingresados para registrar la compra no son validos. | R20: Rechazar el registro e informar cual dato no es valido.
O21: =HYPERLINK("#'P-Compra'!A6", 'P-Compra'!A6) -> P-COM-002 | P21: ='P-Compra'!B6 -> Asegurar que el proveedor asociado a la compra exista y se encuentre registrado en el sistema. | Q21: El proveedor asociado a la compra no existe en el sistema. | R21: Rechazar el registro e informar que el proveedor no existe.
O22: =HYPERLINK("#'P-Compra'!A11", 'P-Compra'!A11) -> P-COM-007 | P22: ='P-Compra'!B11 -> Asegurar que no exista otra compra con el mismo Proveedor y el mismo NumeroFactura. | Q22: Ya existe otra compra registrada con el mismo Proveedor y el mismo NumeroFactura. | R22: Rechazar el registro e informar que ya existe una compra igual registrada.
O23: =HYPERLINK("#'P-Compra'!A12", 'P-Compra'!A12) -> P-COM-008 | P23: ='P-Compra'!B12 -> Asegurar que el proveedor asociado a la compra no se encuentre retirado o inactivo al momento de registrar la compra. | Q23: El proveedor asociado a la compra se encuentra retirado o inactivo. | R23: Rechazar el registro e informar que el proveedor no esta disponible para nuevas compras.
O24: =HYPERLINK("#'P-Compra'!A13", 'P-Compra'!A13) -> P-COM-009 | P24: ='P-Compra'!B13 -> Asegurar que el total de la compra corresponda a la suma de los precios de compra de sus detalles y no supere 5.000.000; el total no lo digita el usuario, se calcula. | Q24: El total calculado no corresponde a la suma de los detalles o supera 5.000.000. | R24: Rechazar el registro e informar que el total de la compra no es valido.
A25: =HYPERLINK("#'C-Compra'!W4", 'E-Compra'!B12) -> Modificar compra | C25: ='E-Compra'!C12 -> Permite corregir la información de una compra existente antes de que tenga movimientos de inventario asociados. | G25: Datos | H25: Compra | I25: Identificador de la compra y datos que se desean modificar. | J25: Compra | K25: Compra modificada correctamente. | O25: =HYPERLINK("#'P-Compra'!A7", 'P-Compra'!A7) -> P-COM-003 | P25: ='P-Compra'!B7 -> Asegurar que la compra que se desea modificar se encuentre registrada en el sistema. | Q25: La compra no existe con el identificador indicado. | R25: Rechazar la modificación e informar que la compra no existe.
O26: =HYPERLINK("#'P-Compra'!A5", 'P-Compra'!A5) -> P-COM-001 | P26: ='P-Compra'!B5 -> Asegurar que los datos requeridos para registrar una compra sean válidos de acuerdo con el tipo de dato, obligatoriedad, formato y rango correspondiente. | Q26: Los nuevos datos de la compra no son validos. | R26: Rechazar la modificacion e informar cual dato no es valido.
O27: =HYPERLINK("#'P-Compra'!A11", 'P-Compra'!A11) -> P-COM-007 | P27: ='P-Compra'!B11 -> Asegurar que no exista otra compra con el mismo Proveedor y el mismo NumeroFactura. | Q27: La modificacion deja dos compras con el mismo Proveedor y el mismo NumeroFactura. | R27: Rechazar la modificacion e informar la duplicidad.
O28: =HYPERLINK("#'P-Compra'!A12", 'P-Compra'!A12) -> P-COM-008 | P28: ='P-Compra'!B12 -> Asegurar que el proveedor asociado a la compra no se encuentre retirado o inactivo al momento de registrar la compra. | Q28: El proveedor indicado se encuentra retirado o inactivo. | R28: Rechazar la modificacion e informar que el proveedor no esta disponible.
A29: =HYPERLINK("#'C-Compra'!Y4", 'E-Compra'!B16) -> Eliminar compra | C29: ='E-Compra'!C16 -> Permite eliminar una compra que no tenga detalles de compra asociados que deban conservarse para mantener la trazabilidad. | G29: Id | H29: UUID | I29: Identificador de la compra que se desea eliminar. | J29: Compra | K29: Compra eliminada correctamente. | O29: =HYPERLINK("#'P-Compra'!A8", 'P-Compra'!A8) -> P-COM-004 | P29: ='P-Compra'!B8 -> Asegurar que la compra que se desea eliminar se encuentre registrada en el sistema. | Q29: La compra que se desea eliminar no existe. | R29: Rechazar la eliminacion e informar que la compra no existe.
O30: =HYPERLINK("#'P-Compra'!A9", 'P-Compra'!A9) -> P-COM-005 | P30: ='P-Compra'!B9 -> Asegurar que una compra no pueda eliminarse cuando tenga detalles de compra asociados que deban conservarse para mantener la trazabilidad de la adquisición. | Q30: La compra tiene detalles de compra asociados que deben conservarse. | R30: Rechazar la eliminacion e informar que la compra tiene detalles asociados.
A31: =HYPERLINK("#'C-Compra'!Z4", 'E-Compra'!B18) -> Consultar compra | C31: ='E-Compra'!C18 -> Consultar la información registrada de una compra para conocer su proveedor, fecha, pizzería y los detalles asociados. | G31: Id | H31: UUID | I31: Identificador que permite localizar la compra que se desea consultar. | J31: Compra | K31: Información de la compra consultada. | O31: =HYPERLINK("#'P-Compra'!A10", 'P-Compra'!A10) -> P-COM-006 | P31: ='P-Compra'!B10 -> Asegurar que la compra exista con el identificador indicado | Q31: No existe una compra asociada al identificador indicado. | R31: Informar que la compra no existe y no retornar informacion.

Sheet E-Compra
A1: <<<Modelo de Dominio | B1: <<<Objetos de Dominio
A2: Objeto de Dominio: | B2: Compra
A3: Descripción: | B3: ='C-Compra'!B3 -> Es cuando la pizzería le compra insumos o productos a un proveedor.
A4: Actor | B4: Action/Command | D4: Entity/Aggregate/Object domain | E4: Read Model | G4: Business Rule/Policy | H4: External System | I4: Domain Event | J4: Hotspot/questions/Risk
A5: Actor | B5: Acción | C5: Descripción | D5: Objeto de dominio | E5: Información externa | G5: Políticas | H5: Sistema Externo | I5: Evento | J5: Aspectos por solucionar
E6: Información | F6: Descripción | G6: Número
A7: Administrador | B7: Registrar compra | C7: Registrar una nueva compra asociada a un proveedor y a la pizzería correspondiente, dejando constancia de la operación de adquisición. | D7: Compra | E7: Información de la compra | F7: Datos necesarios para registrar la compra, como proveedor, pizzería, fecha y demás información requerida por la operación. | G7: =HYPERLINK("#'P-Compra'!A5", "P-COM-001") -> P-COM-001 | I7: Compra registrada
G8: =HYPERLINK("#'P-Compra'!A6", "P-COM-002") -> P-COM-002
G9: =HYPERLINK("#'P-Compra'!A11", "P-COM-007") -> P-COM-007
G10: =HYPERLINK("#'P-Compra'!A12", "P-COM-008") -> P-COM-008
G11: =HYPERLINK("#'P-Compra'!A13", "P-COM-009") -> P-COM-009
A12: Administrador | B12: Modificar compra | C12: Permite corregir la información de una compra existente antes de que tenga movimientos de inventario asociados. | D12: Compra | E12: Compras registradas | F12: Permite identificar la compra existente y consultar su información actual antes de realizar la modificación. | G12: =HYPERLINK("#'P-Compra'!A7", "P-COM-003") -> P-COM-003 | I12: Compra modificada
G13: =HYPERLINK("#'P-Compra'!A5", "P-COM-001") -> P-COM-001
G14: =HYPERLINK("#'P-Compra'!A11", "P-COM-007") -> P-COM-007
G15: =HYPERLINK("#'P-Compra'!A12", "P-COM-008") -> P-COM-008
A16: Administrador | B16: Eliminar compra | C16: Permite eliminar una compra que no tenga detalles de compra asociados que deban conservarse para mantener la trazabilidad. | D16: Compra | E16: Compras registradas | F16: Permite identificar la compra existente antes de eliminarla. | G16: =HYPERLINK("#'P-Compra'!A8", "P-COM-004") -> P-COM-004 | I16: Compra eliminada
G17: =HYPERLINK("#'P-Compra'!A9", "P-COM-005") -> P-COM-005
A18: Administrador | B18: Consultar compra | C18: Consultar la información registrada de una compra para conocer su proveedor, fecha, pizzería y los detalles asociados. | D18: Compra | E18: Información de la compra | F18: Identificador o criterios necesarios para localizar la compra y consultar su información. | G18: =HYPERLINK("#'P-Compra'!A10", "P-COM-006") -> P-COM-006 | I18: Compra consultada

Sheet P-Compra
A1: <<<Modelo de Dominio | B1: <<<Objetos de Dominio
A2: Objeto de Dominio | B2: Compra
A3: Descripcion | B3: ='C-Compra'!B3 -> Es cuando la pizzería le compra insumos o productos a un proveedor.
A4: Numero politica | B4: Descripcion Politica | C4: Objeto Responsable | D4: Regla Referenciada
A5: P-COM-001 | B5: Asegurar que los datos requeridos para registrar una compra sean válidos de acuerdo con el tipo de dato, obligatoriedad, formato y rango correspondiente. | C5: Compra
A6: P-COM-002 | B6: Asegurar que el proveedor asociado a la compra exista y se encuentre registrado en el sistema. | C6: Proveedor | D6: =HYPERLINK("#'P-Proveedor'!A13", 'P-Proveedor'!A13) -> P-PROV-009
A7: P-COM-003 | B7: Asegurar que la compra que se desea modificar se encuentre registrada en el sistema. | C7: Compra
A8: P-COM-004 | B8: Asegurar que la compra que se desea eliminar se encuentre registrada en el sistema. | C8: Compra
A9: P-COM-005 | B9: Asegurar que una compra no pueda eliminarse cuando tenga detalles de compra asociados que deban conservarse para mantener la trazabilidad de la adquisición. | C9: DetalleCompra | D9: =HYPERLINK("#'P-DetalleCompra'!A14", 'P-DetalleCompra'!A14) -> P-DC-010
A10: P-COM-006 | B10: Asegurar que la compra exista con el identificador indicado | C10: Compra
A11: P-COM-007 | B11: Asegurar que no exista otra compra con el mismo Proveedor y el mismo NumeroFactura. | C11: Compra
A12: P-COM-008 | B12: Asegurar que el proveedor asociado a la compra no se encuentre retirado o inactivo al momento de registrar la compra. | C12: Proveedor | D12: =HYPERLINK("#'P-Proveedor'!A12", 'P-Proveedor'!A12) -> P-PROV-008
A13: P-COM-009 | B13: Asegurar que el total de la compra corresponda a la suma de los precios de compra de sus detalles y no supere 5.000.000; el total no lo digita el usuario, se calcula. | C13: Compra

Sheet M-ProductoInterno
A1: <<<Modelo de Dominio | B1: <<<Objetos de Dominio
A2: Identificador unico de cada producto interno dentro de la pizzeria | B2: Nombre de cada producto interno (ingrediente o bebida almacenada) | C2: Cuando se crea el ingrediente se debe decir si es un producto perecedero o no | D2: Vida util en dias: de 1 a 400 si el producto es perecedero y 0 si no lo es | E2: Unidad de medida (UnidadMedida) en la que se maneja el producto interno; su tipo (Peso, Volumen o Unidad) define la unidad de las recetas | F2: Indica si el producto interno esta activo y disponible para usarse | G2: Combinacion unica: como cada producto interno se identifica solo por su nombre, la combinacion es el mismo Nombre
A3: Tipo de dato | B3: Alfanumerico(max 40 caracteres) | C3: Tipo Logico | D3: Entero | E3: UnidadMedida | F3: Tipo Logico | G3: Texto
A4: Obligatorio | B4: Si | C4: Si | D4: Si | E4: Si | F4: Si | G4: Si
A5: Id | B5: Nombre | C5: Perecedero | D5: VidaUtil | E5: TipoMedida | F5: Activo | G5: Combinacion Unica
A6: 1 | B6: Masa de Pizza | C6: No | D6: 0 | E6: =HYPERLINK("#'M-UnidadMedida'!B6", 'M-UnidadMedida'!B6) -> g | F6: Si | G6: =B6 -> Masa de Pizza
A7: 2 | B7: Salsa de Tomate | C7: No | D7: 0 | E7: =HYPERLINK("#'M-UnidadMedida'!B6", 'M-UnidadMedida'!B6) -> g | F7: Si | G7: =B7 -> Salsa de Tomate
A8: 3 | B8: Aceite de oliva | C8: No | D8: 0 | E8: =HYPERLINK("#'M-UnidadMedida'!B8", 'M-UnidadMedida'!B8) -> ml | F8: Si | G8: =B8 -> Aceite de oliva
A9: 4 | B9: Queso | C9: Si | D9: 7 | E9: =HYPERLINK("#'M-UnidadMedida'!B6", 'M-UnidadMedida'!B6) -> g | F9: Si | G9: =B9 -> Queso
A10: 5 | B10: Albahaca | C10: Si | D10: 8 | E10: =HYPERLINK("#'M-UnidadMedida'!B6", 'M-UnidadMedida'!B6) -> g | F10: Si | G10: =B10 -> Albahaca
A11: 6 | B11: Azucar | C11: No | D11: 0 | E11: =HYPERLINK("#'M-UnidadMedida'!B6", 'M-UnidadMedida'!B6) -> g | F11: Si | G11: =B11 -> Azucar
A12: 7 | B12: Peperoni | C12: Si | D12: 9 | E12: =HYPERLINK("#'M-UnidadMedida'!B6", 'M-UnidadMedida'!B6) -> g | F12: Si | G12: =B12 -> Peperoni
A13: 8 | B13: Piña | C13: Si | D13: 6 | E13: =HYPERLINK("#'M-UnidadMedida'!B6", 'M-UnidadMedida'!B6) -> g | F13: Si | G13: =B13 -> Piña
A14: 9 | B14: Sal | C14: No | D14: 0 | E14: =HYPERLINK("#'M-UnidadMedida'!B6", 'M-UnidadMedida'!B6) -> g | F14: Si | G14: =B14 -> Sal
A15: 10 | B15: Leche | C15: No | D15: 0 | E15: =HYPERLINK("#'M-UnidadMedida'!B8", 'M-UnidadMedida'!B8) -> ml | F15: Si | G15: =B15 -> Leche
A16: 11 | B16: Jugo Hit Mora 200 ml | C16: No | D16: 0 | E16: =HYPERLINK("#'M-UnidadMedida'!B10", 'M-UnidadMedida'!B10) -> und | F16: Si | G16: =B16 -> Jugo Hit Mora 200 ml
A17: 12 | B17: Pepsi 400 ml | C17: No | D17: 0 | E17: =HYPERLINK("#'M-UnidadMedida'!B10", 'M-UnidadMedida'!B10) -> und | F17: Si | G17: =B17 -> Pepsi 400 ml
A18: 13 | B18: Monster 473 ml | C18: No | D18: 0 | E18: =HYPERLINK("#'M-UnidadMedida'!B10", 'M-UnidadMedida'!B10) -> und | F18: Si | G18: =B18 -> Monster 473 ml
A19: 14 | B19: Colombiana 400 ml | C19: No | D19: 0 | E19: =HYPERLINK("#'M-UnidadMedida'!B10", 'M-UnidadMedida'!B10) -> und | F19: Si | G19: =B19 -> Colombiana 400 ml
A20: 15 | B20: Mr tea 300 ml | C20: No | D20: 0 | E20: =HYPERLINK("#'M-UnidadMedida'!B10", 'M-UnidadMedida'!B10) -> und | F20: Si | G20: =B20 -> Mr tea 300 ml
A21: 16 | B21: Jamón | C21: Si | D21: 10 | E21: =HYPERLINK("#'M-UnidadMedida'!B6", 'M-UnidadMedida'!B6) -> g | F21: Si | G21: =B21 -> Jamón
A22: 0 | B22: Sin insumo | C22: No | D22: 0 | E22: =HYPERLINK("#'M-UnidadMedida'!B10", 'M-UnidadMedida'!B10) -> und | F22: No | G22: =B22 -> Sin insumo

Sheet C-ProductoInterno
A1: <<<Modelo de Dominio | B1: <<<Objetos de Dominio
A2: Nombre | B2: ProductoInterno
A3: Descripción | B3: =HYPERLINK("#'Objetos de dominio'!B10", 'Objetos de dominio'!B11) -> Es cada insumo o producto que la pizzería compra y guarda en su inventario, sin importar si se usa para preparar algo o si se vende directamente al cliente.
A4: Nombre atributo | B4: Descripción atributo | C4: Identificador del objeto de dominio | D4: Tipo de dato | E4: Obligatorio | F4: Longitud mínima (si aplica) | G4: Longitud máxima (si aplica) | H4: Precisión (si aplica) | I4: Rendondeo (si aplica) | J4: Rango inicial (si aplica) | K4: Rango final (si aplica) | L4: Formato (si aplica) | M4: Reglas especiales (si aplica) | N4: Dato calculado | O4: Aplica ajuste del dato (si aplica) | P4: Carácter de ajuste (si aplica) | Q4: Quitar espacios en blanco al inicio (si aplica) | R4: Quitar espacios en blanco al fin (si aplica) | S4: Dato sensible (si aplica) | T4: Valor por defecto (si aplica) | U4: Auto generado | V4: =HYPERLINK("#'C-ProductoInterno'!A22", 'C-ProductoInterno'!A22) -> Registrar producto interno | W4: =HYPERLINK("#'C-ProductoInterno'!A27", 'C-ProductoInterno'!A27) -> Actualizar producto interno | Y4: =HYPERLINK("#'C-ProductoInterno'!A32", 'C-ProductoInterno'!A32) -> Inactivar producto interno | Z4: =HYPERLINK("#'C-ProductoInterno'!A36", 'C-ProductoInterno'!A36) -> Consultar productos internos activos
A5: =HYPERLINK("#'M-ProductoInterno'!A5", 'M-ProductoInterno'!A5) -> Id | B5: =HYPERLINK("#'M-ProductoInterno'!A2", 'M-ProductoInterno'!A2) -> Identificador unico de cada producto interno dentro de la pizzeria | C5: Si | D5: Identificador unico universal | E5: Si | M5: Existe un registro especial "Sin insumo" con el identificador por defecto (00000000-0000-0000-0000-000000000000) e inactivo; lo usan los productos que no corresponden a un producto interno. | N5: No | O5: No | P5: No | Q5: No | R5: No | S5: No | U5: Si | V5: Requerido | W5: Requerido | X5: No Modificable | Y5: Requerido | Z5: No Mostrar
A6: =HYPERLINK("#'M-ProductoInterno'!B5", 'M-ProductoInterno'!B5) -> Nombre | B6: =HYPERLINK("#'M-ProductoInterno'!B2", 'M-ProductoInterno'!B2) -> Nombre de cada producto interno (ingrediente o bebida almacenada) | C6: No | D6: Alfanumerico | E6: Si | F6: 1 | G6: 40 | N6: No | O6: No | P6: No | Q6: Si | R6: Si | S6: No | U6: No | V6: Requerido | W6: No Requerido | X6: Modificable | Y6: No Requerido | Z6: Mostrar
A7: =HYPERLINK("#'M-ProductoInterno'!C5", 'M-ProductoInterno'!C5) -> Perecedero | B7: =HYPERLINK("#'M-ProductoInterno'!C2", 'M-ProductoInterno'!C2) -> Cuando se crea el ingrediente se debe decir si es un producto perecedero o no | C7: No | D7: Tipo Logico | E7: Si | M7: Indica si el producto se descompone con el tiempo. De ahi depende como se saca la fecha de vencimiento en Lote. | N7: No | O7: No | P7: No | Q7: No | R7: No | S7: No | U7: No | V7: Requerido | W7: No Requerido | X7: Modificable | Y7: No Requerido | Z7: Mostrar
A8: =HYPERLINK("#'M-ProductoInterno'!D5", 'M-ProductoInterno'!D5) -> VidaUtil | B8: =HYPERLINK("#'M-ProductoInterno'!D2", 'M-ProductoInterno'!D2) -> Vida util en dias: de 1 a 400 si el producto es perecedero y 0 si no lo es | C8: No | D8: Entero | E8: Si | J8: 0 | K8: 400 | M8: Si el producto es perecedero la vida util va de 1 a 400 dias; si no es perecedero debe ser 0. | N8: No | O8: No | P8: No | Q8: No | R8: No | S8: No | T8: 0 | U8: No | V8: Requerido | W8: No Requerido | X8: Modificable | Y8: No Requerido | Z8: Mostrar
A9: =HYPERLINK("#'M-ProductoInterno'!E5", 'M-ProductoInterno'!E5) -> TipoMedida | B9: =HYPERLINK("#'M-ProductoInterno'!E2", 'M-ProductoInterno'!E2) -> Unidad de medida (UnidadMedida) en la que se maneja el producto interno; su tipo (Peso, Volumen o Unidad) define la unidad de las recetas | C9: No | D9: UnidadMedida | E9: Si | M9: Debe corresponder a una UnidadMedida existente. Su tipo de medida (Peso, Volumen o Unidad) define la unidad en que se registran las recetas (g, ml o und). | N9: No | O9: No | P9: No | Q9: No | R9: No | S9: No | U9: No | V9: Requerido | W9: No Requerido | X9: Modificable | Y9: No Requerido | Z9: Mostrar
A10: =HYPERLINK("#'M-ProductoInterno'!F5", 'M-ProductoInterno'!F5) -> Activo | B10: =HYPERLINK("#'M-ProductoInterno'!F2", 'M-ProductoInterno'!F2) -> Indica si el producto interno esta activo y disponible para usarse | C10: No | D10: Tipo Logico | E10: Si | M10: Se registra como activo (Si). Solo los productos internos activos se pueden usar en recetas y compras. | N10: No | O10: No | P10: No | Q10: No | R10: No | S10: No | T10: Si | U10: No | V10: No Requerido | W10: No Requerido | X10: No Modificable | Y10: No Requerido | Z10: No Mostrar
A15: Nombre combinación única | B15: Descripción | C15: Atributos involucrados
A16: Combinación única 1 | B16: No pueden existir dos productos internos con el mismo Nombre. | C16: =HYPERLINK("#'C-ProductoInterno'!A6", 'C-ProductoInterno'!A6) -> Nombre
A20: Responsabilidad | C20: Descripción | G20: Entradas | J20: Salida | O20: Políticas (Reglas de Negocio) | Q20: Excepción
G21: Parámetro | H21: Tipo de dato | I21: Descripción | J21: Tipo de Dato | K21: Descripción | O21: Política | P21: Descripción | Q21: Detalle | R21: ¿Qué hago?
A22: =HYPERLINK("#'C-ProductoInterno'!V4", 'E-ProductoInterno'!B7) -> Registrar producto interno | C22: ='E-ProductoInterno'!C7 -> Permite incorporar un nuevo producto interno (ingrediente o bebida almacenada) al inventario de la pizzeria. | G22: Datos | H22: ProductoInterno | I22: Información propia necesaria para registrar el producto interno. | J22: ProductoInterno | K22: Producto interno registrado con la información proporcionada. | O22: =HYPERLINK("#'P-ProductoInterno'!A5", 'P-ProductoInterno'!A5) -> P-PI-001 | P22: ='P-ProductoInterno'!B5 -> Asegurar que los datos requeridos para registrar un producto interno sean validos de acuerdo con el tipo de dato, obligatoriedad, formato y rango correspondiente. | Q22: Los datos ingresados para registrar el producto interno no son validos. | R22: Rechazar el registro e informar cual dato no es valido.
O23: =HYPERLINK("#'P-ProductoInterno'!A6", 'P-ProductoInterno'!A6) -> P-PI-002 | P23: ='P-ProductoInterno'!B6 -> Asegurar que no exista otro producto interno con el mismo Nombre al registrarlo. | Q23: Ya existe otro producto interno registrado con el mismo Nombre. | R23: Rechazar el registro e informar que ya existe un producto interno con ese Nombre.
O24: =HYPERLINK("#'P-ProductoInterno'!A7", 'P-ProductoInterno'!A7) -> P-PI-003 | P24: ='P-ProductoInterno'!B7 -> Asegurar que la VidaUtil este entre 1 y 400 dias cuando el producto interno sea perecedero, y que sea 0 cuando no lo sea. | Q24: La vida util no esta entre 1 y 400 dias para un producto perecedero, o no es 0 para uno no perecedero. | R24: Rechazar el registro e informar el valor permitido.
O25: =HYPERLINK("#'P-ProductoInterno'!A8", 'P-ProductoInterno'!A8) -> P-PI-004 | P25: ='P-ProductoInterno'!B8 -> Asegurar que la TipoMedida corresponda a una unidad de medida existente del catalogo. | Q25: La TipoMedida indicada no corresponde a una unidad de medida existente. | R25: Rechazar el registro e informar que la unidad de medida no es valida.
O26: =HYPERLINK("#'P-ProductoInterno'!A14", 'P-ProductoInterno'!A14) -> P-PI-010 | P26: ='P-ProductoInterno'!B14 -> Al registrar un producto interno se crea su registro de inventario con cantidad total 0 y stock minimo 1. | Q26: No fue posible crear el registro de inventario del producto interno. | R26: Rechazar el registro completo para que el producto interno no quede sin inventario.
A27: =HYPERLINK("#'C-ProductoInterno'!W4", 'E-ProductoInterno'!B12) -> Actualizar producto interno | C27: ='E-ProductoInterno'!C12 -> Permite modificar la informacion de un producto interno existente. | G27: Datos | H27: ProductoInterno | I27: Identificador del producto interno y datos que se desean actualizar. | J27: ProductoInterno | K27: Producto interno actualizado. | O27: =HYPERLINK("#'P-ProductoInterno'!A9", 'P-ProductoInterno'!A9) -> P-PI-005 | P27: ='P-ProductoInterno'!B9 -> Asegurar que el producto interno que se desea modificar se encuentre registrado en el sistema. | Q27: El producto interno no existe en el sistema. | R27: Rechazar la actualización e informar que el producto interno no existe.
O28: =HYPERLINK("#'P-ProductoInterno'!A13", 'P-ProductoInterno'!A13) -> P-PI-009 | P28: ='P-ProductoInterno'!B13 -> Asegurar que el registro especial "Sin insumo" no pueda modificarse, inactivarse ni usarse en recetas o compras. | Q28: Se intento modificar el registro "Sin insumo". | R28: Rechazar la modificacion e informar que ese registro no se puede modificar.
O29: =HYPERLINK("#'P-ProductoInterno'!A5", 'P-ProductoInterno'!A5) -> P-PI-001 | P29: ='P-ProductoInterno'!B5 -> Asegurar que los datos requeridos para registrar un producto interno sean validos de acuerdo con el tipo de dato, obligatoriedad, formato y rango correspondiente. | Q29: Los nuevos datos del producto interno no son validos. | R29: Rechazar la modificacion e informar cual dato no es valido.
O30: =HYPERLINK("#'P-ProductoInterno'!A6", 'P-ProductoInterno'!A6) -> P-PI-002 | P30: ='P-ProductoInterno'!B6 -> Asegurar que no exista otro producto interno con el mismo Nombre al registrarlo. | Q30: El nuevo Nombre ya lo tiene otro producto interno. | R30: Rechazar la modificacion e informar la duplicidad.
O31: =HYPERLINK("#'P-ProductoInterno'!A7", 'P-ProductoInterno'!A7) -> P-PI-003 | P31: ='P-ProductoInterno'!B7 -> Asegurar que la VidaUtil este entre 1 y 400 dias cuando el producto interno sea perecedero, y que sea 0 cuando no lo sea. | Q31: La nueva vida util no corresponde a si el producto es perecedero o no. | R31: Rechazar la modificacion e informar el valor permitido.
A32: =HYPERLINK("#'C-ProductoInterno'!Y4", 'E-ProductoInterno'!B17) -> Inactivar producto interno | C32: ='E-ProductoInterno'!C17 -> Permite inactivar un producto interno que la pizzeria ya no usa: no se puede usar en nuevas recetas ni compras, pero se conserva su historial. | G32: Id | H32: UUID | I32: Identificador del producto interno que se desea eliminar. | J32: ProductoInterno | K32: Producto interno inactivado. | O32: =HYPERLINK("#'P-ProductoInterno'!A11", 'P-ProductoInterno'!A11) -> P-PI-007 | P32: ='P-ProductoInterno'!B11 -> Asegurar que el producto interno exista con el identificador indicado. | Q32: El producto interno que se desea inactivar no existe. | R32: Rechazar la inactivacion e informar que el producto interno no existe.
O33: =HYPERLINK("#'P-ProductoInterno'!A12", 'P-ProductoInterno'!A12) -> P-PI-008 | P33: ='P-ProductoInterno'!B12 -> Asegurar que el producto interno que se desea inactivar no se encuentre ya inactivo. | Q33: El producto interno ya se encuentra inactivo. | R33: Informar que el producto interno ya esta inactivo.
O34: =HYPERLINK("#'P-ProductoInterno'!A13", 'P-ProductoInterno'!A13) -> P-PI-009 | P34: ='P-ProductoInterno'!B13 -> Asegurar que el registro especial "Sin insumo" no pueda modificarse, inactivarse ni usarse en recetas o compras. | Q34: Se intento inactivar el registro "Sin insumo". | R34: Rechazar la inactivacion e informar que ese registro no se puede inactivar.
O35: =HYPERLINK("#'P-ProductoInterno'!A10", 'P-ProductoInterno'!A10) -> P-PI-006 | P35: ='P-ProductoInterno'!B10 -> Asegurar que un producto interno inactivo no pueda usarse en nuevas recetas ni en nuevas compras; al inactivarlo se conservan sus lotes, movimientos, compras y recetas registrados. | Q35: El producto interno tiene lotes, compras o recetas registradas. | R35: Inactivar el producto interno sin borrar su historial.
A36: =HYPERLINK("#'C-ProductoInterno'!Z4", 'E-ProductoInterno'!B21) -> Consultar productos internos activos | C36: ='E-ProductoInterno'!C21 -> Permite consultar los productos internos activos, por ejemplo para escoger los ingredientes de una receta. | G36: Ninguno | H36: - | I36: No requiere datos de entrada. | J36: Lista de ProductoInterno | K36: Productos internos activos. | O36: =HYPERLINK("#'P-ProductoInterno'!A15", 'P-ProductoInterno'!A15) -> P-PI-011 | P36: ='P-ProductoInterno'!B15 -> Asegurar que solo se consulten los productos internos activos. | Q36: No existen productos internos activos. | R36: Informar que no hay productos internos activos.

Sheet E-ProductoInterno
A1: <<<Modelo de Dominio | B1: <<<Objetos de Dominio
A2: Objeto de Dominio: | B2: ProductoInterno
A3: Descripción: | B3: ='C-ProductoInterno'!B3 -> Es cada insumo o producto que la pizzería compra y guarda en su inventario, sin importar si se usa para preparar algo o si se vende directamente al cliente.
A4: Actor | B4: Action/Command | D4: Entity/Aggregate/Object domain | E4: Read Model | G4: Business Rule/Policy | H4: External System | I4: Domain Event | J4: Hotspot/questions/Risk
A5: Actor | B5: Acción | C5: Descripción | D5: Objeto de dominio | E5: Información externa | G5: Políticas | H5: Sistema Externo | I5: Evento | J5: Aspectos por solucionar
E6: Información | F6: Descripción | G6: Número
A7: Administrador | B7: Registrar producto interno | C7: Permite incorporar un nuevo producto interno (ingrediente o bebida almacenada) al inventario de la pizzeria. | D7: ProductoInterno | E7: UnidadMedida | F7: Permite seleccionar una unidad de medida valida para el producto interno. | G7: =HYPERLINK("#'P-ProductoInterno'!A5", "P-PI-001") -> P-PI-001 | I7: Producto interno registrado
G8: =HYPERLINK("#'P-ProductoInterno'!A6", "P-PI-002") -> P-PI-002
G9: =HYPERLINK("#'P-ProductoInterno'!A7", "P-PI-003") -> P-PI-003
G10: =HYPERLINK("#'P-ProductoInterno'!A8", "P-PI-004") -> P-PI-004
G11: =HYPERLINK("#'P-ProductoInterno'!A14", "P-PI-010") -> P-PI-010
A12: Administrador | B12: Actualizar producto interno | C12: Permite modificar la informacion de un producto interno existente. | D12: ProductoInterno | E12: Productos internos registrados | F12: Permite identificar el producto interno existente antes de modificarlo. | G12: =HYPERLINK("#'P-ProductoInterno'!A9", "P-PI-005") -> P-PI-005 | I12: Producto interno actualizado
G13: =HYPERLINK("#'P-ProductoInterno'!A13", "P-PI-009") -> P-PI-009
G14: =HYPERLINK("#'P-ProductoInterno'!A5", "P-PI-001") -> P-PI-001
G15: =HYPERLINK("#'P-ProductoInterno'!A6", "P-PI-002") -> P-PI-002
G16: =HYPERLINK("#'P-ProductoInterno'!A7", "P-PI-003") -> P-PI-003
A17: Administrador | B17: Inactivar producto interno | C17: Permite inactivar un producto interno que la pizzeria ya no usa: no se puede usar en nuevas recetas ni compras, pero se conserva su historial. | D17: ProductoInterno | F17: Permite identificar el producto interno existente antes de eliminarlo. | G17: =HYPERLINK("#'P-ProductoInterno'!A11", "P-PI-007") -> P-PI-007 | I17: Producto interno inactivado
G18: =HYPERLINK("#'P-ProductoInterno'!A12", "P-PI-008") -> P-PI-008
G19: =HYPERLINK("#'P-ProductoInterno'!A13", "P-PI-009") -> P-PI-009
G20: =HYPERLINK("#'P-ProductoInterno'!A10", "P-PI-006") -> P-PI-006
A21: Administrador | B21: Consultar productos internos activos | C21: Permite consultar los productos internos activos, por ejemplo para escoger los ingredientes de una receta. | E21: Productos internos registrados | F21: Productos internos con estado activo. | G21: =HYPERLINK("#'P-ProductoInterno'!A15", "P-PI-011") -> P-PI-011 | I21: Productos internos activos consultados

Sheet P-ProductoInterno
A1: <<<Modelo de Dominio | B1: <<<Objetos de Dominio
A2: Objeto de Dominio | B2: ProductoInterno
A3: Descripcion | B3: ='C-ProductoInterno'!B3 -> Es cada insumo o producto que la pizzería compra y guarda en su inventario, sin importar si se usa para preparar algo o si se vende directamente al cliente.
A4: Numero politica | B4: Descripcion Politica | C4: Objeto Responsable | D4: Regla Referenciada
A5: P-PI-001 | B5: Asegurar que los datos requeridos para registrar un producto interno sean validos de acuerdo con el tipo de dato, obligatoriedad, formato y rango correspondiente. | C5: ProductoInterno
A6: P-PI-002 | B6: Asegurar que no exista otro producto interno con el mismo Nombre al registrarlo. | C6: ProductoInterno
A7: P-PI-003 | B7: Asegurar que la VidaUtil este entre 1 y 400 dias cuando el producto interno sea perecedero, y que sea 0 cuando no lo sea. | C7: ProductoInterno
A8: P-PI-004 | B8: Asegurar que la TipoMedida corresponda a una unidad de medida existente del catalogo. | C8: UnidadMedida | D8: =HYPERLINK("#'P-UnidadMedida'!A6", 'P-UnidadMedida'!A6) -> P-UM-002
A9: P-PI-005 | B9: Asegurar que el producto interno que se desea modificar se encuentre registrado en el sistema. | C9: ProductoInterno
A10: P-PI-006 | B10: Asegurar que un producto interno inactivo no pueda usarse en nuevas recetas ni en nuevas compras; al inactivarlo se conservan sus lotes, movimientos, compras y recetas registrados. | C10: ProductoInterno
A11: P-PI-007 | B11: Asegurar que el producto interno exista con el identificador indicado. | C11: ProductoInterno
A12: P-PI-008 | B12: Asegurar que el producto interno que se desea inactivar no se encuentre ya inactivo. | C12: ProductoInterno
A13: P-PI-009 | B13: Asegurar que el registro especial "Sin insumo" no pueda modificarse, inactivarse ni usarse en recetas o compras. | C13: ProductoInterno
A14: P-PI-010 | B14: Al registrar un producto interno se crea su registro de inventario con cantidad total 0 y stock minimo 1. | C14: Inventario | D14: =HYPERLINK("#'P-Inventario'!A9", 'P-Inventario'!A9) -> P-INV-005
A15: P-PI-011 | B15: Asegurar que solo se consulten los productos internos activos. | C15: ProductoInterno

Sheet M-DetalleCompra
A1: si y | B1: <<<Objetos de Dominio
A2: Identificador unico de cada detalle de compra | B2: Nombre del producto Interno | C2: Cantidad que se compro de un producto determinado | D2: Se ingresa la unidad de medida en la que se hizo la compra , esta unidad de medida debe ser valida para el tipo de dato , por ejemplo si el producto es aceite de oliva , el va a ser de tipo volumen entonces puede estar en ml o l | E2: Valor monetario de cada producto | F2: Se ingresa la fecha de vencimiento del producto , en caso de que la traiga de lo contrario hay que calcular una vida util | G2: Compra a la que pertenece este detalle | H2: Codigo de la operacion (TipoMovimiento) propio de este detalle de compra; es el mismo que lleva su movimiento de entrada
A3: Tipo de dato | B3: Producto interno | C3: Decimal Europeo (4) | D3: Unidad de medida | E3: Decimal Europeo(2) | F3: Fecha | G3: Compra | H3: TipoMovimiento
A5: Obligatorio | B5: Si | C5: Si | D5: Si | E5: Si | F5: No | G5: Si | H5: Si
A6: Id | B6: ProductoInterno | C6: Cantidad | D6: UnidadMedida | E6: PrecioCompra | F6: FechaVencimiento | G6: Compra | H6: TipoMovimiento | I6: Combinacion unica 1 | J6: Combinacion unica 2
A7: 1 | B7: =HYPERLINK("#'M-ProductoInterno'!B9", 'M-ProductoInterno'!B9) -> Queso | C7: 10200 | D7: =HYPERLINK("#'M-UnidadMedida'!B6", 'M-UnidadMedida'!B6) -> g | E7: 255000 | F7: 01/01/1000 | G7: =HYPERLINK("#'M-Compra'!F6", 'M-Compra'!F6) -> Colanta FE-1023 | H7: =HYPERLINK("#'M-TipoMovimiento'!A8", 'M-TipoMovimiento'!A8) -> 99 | I7: =CONCATENATE(G7," ",B7," ",TEXT(F7,"dd/mm/yyyy")) -> Colanta FE-1023 Queso 01/01/1000 | J7: =H7 -> 99
A8: 2 | B8: =HYPERLINK("#'M-ProductoInterno'!B10", 'M-ProductoInterno'!B10) -> Albahaca | C8: 10300 | D8: =HYPERLINK("#'M-UnidadMedida'!B6", 'M-UnidadMedida'!B6) -> g | E8: 300000 | F8: 46407 | G8: =HYPERLINK("#'M-Compra'!F6", 'M-Compra'!F6) -> Colanta FE-1023 | H8: =HYPERLINK("#'M-TipoMovimiento'!A9", 'M-TipoMovimiento'!A9) -> 100 | I8: =CONCATENATE(G8," ",B8," ",TEXT(F8,"dd/mm/yyyy")) -> Colanta FE-1023 Albahaca 20/01/2027 | J8: =H8 -> 100
A9: 3 | B9: =HYPERLINK("#'M-ProductoInterno'!B12", 'M-ProductoInterno'!B12) -> Peperoni | C9: 12.5 | D9: =HYPERLINK("#'M-UnidadMedida'!B7", 'M-UnidadMedida'!B7) -> kg | E9: 137500 | F9: 01/01/1000 | G9: =HYPERLINK("#'M-Compra'!F6", 'M-Compra'!F6) -> Colanta FE-1023 | H9: =HYPERLINK("#'M-TipoMovimiento'!A10", 'M-TipoMovimiento'!A10) -> 101 | I9: =CONCATENATE(G9," ",B9," ",TEXT(F9,"dd/mm/yyyy")) -> Colanta FE-1023 Peperoni 01/01/1000 | J9: =H9 -> 101
A10: 4 | B10: =HYPERLINK("#'M-ProductoInterno'!B8", 'M-ProductoInterno'!B8) -> Aceite de oliva | C10: 15200 | D10: =HYPERLINK("#'M-UnidadMedida'!B8", 'M-UnidadMedida'!B8) -> ml | E10: 456000 | F10: 46422 | G10: =HYPERLINK("#'M-Compra'!F7", 'M-Compra'!F7) -> Harinera del valle FV-4587 | H10: =HYPERLINK("#'M-TipoMovimiento'!A11", 'M-TipoMovimiento'!A11) -> 102 | I10: =CONCATENATE(G10," ",B10," ",TEXT(F10,"dd/mm/yyyy")) -> Harinera del valle FV-4587 Aceite de oliva 04/02/2027 | J10: =H10 -> 102
A11: 5 | B11: =HYPERLINK("#'M-ProductoInterno'!B8", 'M-ProductoInterno'!B8) -> Aceite de oliva | C11: 3000 | D11: =HYPERLINK("#'M-UnidadMedida'!B8", 'M-UnidadMedida'!B8) -> ml | E11: 93000 | F11: 46423 | G11: =HYPERLINK("#'M-Compra'!F7", 'M-Compra'!F7) -> Harinera del valle FV-4587 | H11: =HYPERLINK("#'M-TipoMovimiento'!A12", 'M-TipoMovimiento'!A12) -> 103 | I11: =CONCATENATE(G11," ",B11," ",TEXT(F11,"dd/mm/yyyy")) -> Harinera del valle FV-4587 Aceite de oliva 05/02/2027 | J11: =H11 -> 103
A12: 6 | B12: =HYPERLINK("#'M-ProductoInterno'!B6", 'M-ProductoInterno'!B6) -> Masa de Pizza | C12: 200 | D12: =HYPERLINK("#'M-UnidadMedida'!B6", 'M-UnidadMedida'!B6) -> g | E12: 2000 | F12: 46540 | G12: =HYPERLINK("#'M-Compra'!F7", 'M-Compra'!F7) -> Harinera del valle FV-4587 | H12: =HYPERLINK("#'M-TipoMovimiento'!A13", 'M-TipoMovimiento'!A13) -> 104 | I12: =CONCATENATE(G12," ",B12," ",TEXT(F12,"dd/mm/yyyy")) -> Harinera del valle FV-4587 Masa de Pizza 02/06/2027 | J12: =H12 -> 104
A13: 7 | B13: =HYPERLINK("#'M-ProductoInterno'!B17", 'M-ProductoInterno'!B17) -> Pepsi 400 ml | C13: 24 | D13: =HYPERLINK("#'M-UnidadMedida'!B10", 'M-UnidadMedida'!B10) -> und | E13: 3600 | F13: 46285 | G13: =HYPERLINK("#'M-Compra'!F8", 'M-Compra'!F8) -> Postobon PO-9012 | H13: =HYPERLINK("#'M-TipoMovimiento'!A14", 'M-TipoMovimiento'!A14) -> 105 | I13: =CONCATENATE(G13," ",B13," ",TEXT(F13,"dd/mm/yyyy")) -> Postobon PO-9012 Pepsi 400 ml 20/09/2026 | J13: =H13 -> 105
A14: 8 | B14: =HYPERLINK("#'M-ProductoInterno'!B6", 'M-ProductoInterno'!B6) -> Masa de Pizza | C14: 12000 | D14: =HYPERLINK("#'M-UnidadMedida'!B6", 'M-UnidadMedida'!B6) -> g | E14: 126000 | F14: 46645 | G14: =HYPERLINK("#'M-Compra'!F9", 'M-Compra'!F9) -> Harinera del valle FV-5102 | H14: =HYPERLINK("#'M-TipoMovimiento'!A15", 'M-TipoMovimiento'!A15) -> 106 | I14: =CONCATENATE(G14," ",B14," ",TEXT(F14,"dd/mm/yyyy")) -> Harinera del valle FV-5102 Masa de Pizza 15/09/2027 | J14: =H14 -> 106
A15: 9 | B15: =HYPERLINK("#'M-ProductoInterno'!B9", 'M-ProductoInterno'!B9) -> Queso | C15: 150 | D15: =HYPERLINK("#'M-UnidadMedida'!B6", 'M-UnidadMedida'!B6) -> g | E15: 3750 | F15: 01/01/1000 | G15: =HYPERLINK("#'M-Compra'!F10", 'M-Compra'!F10) -> Colanta FE-1102 | H15: =HYPERLINK("#'M-TipoMovimiento'!A16", 'M-TipoMovimiento'!A16) -> 107 | I15: =CONCATENATE(G15," ",B15," ",TEXT(F15,"dd/mm/yyyy")) -> Colanta FE-1102 Queso 01/01/1000 | J15: =H15 -> 107
A16: 10 | B16: =HYPERLINK("#'M-ProductoInterno'!B7", 'M-ProductoInterno'!B7) -> Salsa de Tomate | C16: 10500 | D16: =HYPERLINK("#'M-UnidadMedida'!B6", 'M-UnidadMedida'!B6) -> g | E16: 105000 | F16: 46553 | G16: =HYPERLINK("#'M-Compra'!F11", 'M-Compra'!F11) -> Central de Abastos CA-2201 | H16: =HYPERLINK("#'M-TipoMovimiento'!A17", 'M-TipoMovimiento'!A17) -> 108 | I16: =CONCATENATE(G16," ",B16," ",TEXT(F16,"dd/mm/yyyy")) -> Central de Abastos CA-2201 Salsa de Tomate 15/06/2027 | J16: =H16 -> 108
A17: 11 | B17: =HYPERLINK("#'M-ProductoInterno'!B9", 'M-ProductoInterno'!B9) -> Queso | C17: 300 | D17: =HYPERLINK("#'M-UnidadMedida'!B6", 'M-UnidadMedida'!B6) -> g | E17: 7500 | F17: 01/01/1000 | G17: =HYPERLINK("#'M-Compra'!F12", 'M-Compra'!F12) -> Colanta FE-1250 | H17: =HYPERLINK("#'M-TipoMovimiento'!A18", 'M-TipoMovimiento'!A18) -> 109 | I17: =CONCATENATE(G17," ",B17," ",TEXT(F17,"dd/mm/yyyy")) -> Colanta FE-1250 Queso 01/01/1000 | J17: =H17 -> 109
A18: 12 | B18: =HYPERLINK("#'M-ProductoInterno'!B21", 'M-ProductoInterno'!B21) -> Jamón | C18: 1000 | D18: =HYPERLINK("#'M-UnidadMedida'!B6", 'M-UnidadMedida'!B6) -> g | E18: 30000 | F18: 01/01/1000 | G18: =HYPERLINK("#'M-Compra'!F13", 'M-Compra'!F13) -> Central de Abastos CA-2310 | H18: =HYPERLINK("#'M-TipoMovimiento'!A19", 'M-TipoMovimiento'!A19) -> 110 | I18: =CONCATENATE(G18," ",B18," ",TEXT(F18,"dd/mm/yyyy")) -> Central de Abastos CA-2310 Jamón 01/01/1000 | J18: =H18 -> 110
A19: 13 | B19: =HYPERLINK("#'M-ProductoInterno'!B13", 'M-ProductoInterno'!B13) -> Piña | C19: 1000 | D19: =HYPERLINK("#'M-UnidadMedida'!B6", 'M-UnidadMedida'!B6) -> g | E19: 6000 | F19: 01/01/1000 | G19: =HYPERLINK("#'M-Compra'!F13", 'M-Compra'!F13) -> Central de Abastos CA-2310 | H19: =HYPERLINK("#'M-TipoMovimiento'!A20", 'M-TipoMovimiento'!A20) -> 111 | I19: =CONCATENATE(G19," ",B19," ",TEXT(F19,"dd/mm/yyyy")) -> Central de Abastos CA-2310 Piña 01/01/1000 | J19: =H19 -> 111
A20: 14 | B20: =HYPERLINK("#'M-ProductoInterno'!B9", 'M-ProductoInterno'!B9) -> Queso | C20: 500 | D20: =HYPERLINK("#'M-UnidadMedida'!B6", 'M-UnidadMedida'!B6) -> g | E20: 12500 | F20: 01/01/1000 | G20: =HYPERLINK("#'M-Compra'!F14", 'M-Compra'!F14) -> Colanta FE-1263 | H20: =HYPERLINK("#'M-TipoMovimiento'!A21", 'M-TipoMovimiento'!A21) -> 112 | I20: =CONCATENATE(G20," ",B20," ",TEXT(F20,"dd/mm/yyyy")) -> Colanta FE-1263 Queso 01/01/1000 | J20: =H20 -> 112

Sheet C-DetalleCompra
A1: <<<Modelo de Dominio | B1: <<<Objetos de Dominio
A2: Nombre | B2: DetalleCompra
A3: Descripción | B3: =HYPERLINK("#'Objetos de dominio'!B11", 'Objetos de dominio'!B13) -> Es cada uno de los productos o insumos que se compraron en una compra, con la cantidad de cada uno.
A4: Nombre atributo | B4: Descripción atributo | C4: Identificador del objeto de dominio | D4: Tipo de dato | E4: Obligatorio | F4: Longitud mínima (si aplica) | G4: Longitud máxima (si aplica) | H4: Precisión (si aplica) | I4: Rendondeo (si aplica) | J4: Rango inicial (si aplica) | K4: Rango final (si aplica) | L4: Formato (si aplica) | M4: Reglas especiales (si aplica) | N4: Dato calculado | O4: Aplica ajuste del dato (si aplica) | P4: Carácter de ajuste (si aplica) | Q4: Quitar espacios en blanco al inicio (si aplica) | R4: Quitar espacios en blanco al fin (si aplica) | S4: Dato sensible (si aplica) | T4: Valor por defecto (si aplica) | U4: Auto generado | V4: =HYPERLINK("#'C-DetalleCompra'!A24", 'C-DetalleCompra'!A24) -> Registrar detalle de compra | W4: =HYPERLINK("#'C-DetalleCompra'!A37", 'C-DetalleCompra'!A37) -> Modificar detalle de compra | Y4: =HYPERLINK("#'C-DetalleCompra'!A42", 'C-DetalleCompra'!A42) -> Eliminar detalle de compra
A5: =HYPERLINK("#'M-DetalleCompra'!A6", 'M-DetalleCompra'!A6) -> Id | B5: =HYPERLINK("#'M-DetalleCompra'!A2", 'M-DetalleCompra'!A2) -> Identificador unico de cada detalle de compra | C5: Si | D5: Identificador único universal | E5: Si | N5: No | O5: No | Q5: No | R5: No | S5: No | U5: Si | V5: Requerido | W5: Requerido | X5: No Modificable | Y5: Requerido
A6: =HYPERLINK("#'M-DetalleCompra'!B6", 'M-DetalleCompra'!B6) -> ProductoInterno | B6: =HYPERLINK("#'M-DetalleCompra'!B2", 'M-DetalleCompra'!B2) -> Nombre del producto Interno | C6: No | D6: ProductoInterno | E6: Si | M6: Debe corresponder a un ProductoInterno existente . | N6: No | O6: No | Q6: No | R6: No | S6: No | U6: No | V6: Requerido | W6: No Requerido | X6: Modificable | Y6: No Requerido
A7: =HYPERLINK("#'M-DetalleCompra'!C6", 'M-DetalleCompra'!C6) -> Cantidad | B7: =HYPERLINK("#'M-DetalleCompra'!C2", 'M-DetalleCompra'!C2) -> Cantidad que se compro de un producto determinado | C7: No | D7: Decimal Europeo | E7: Si | H7: 4 | I7: A la unidad (0) | J7: >0 | K7: 100000 | M7: La cantidad debe ser mayor a cero. | N7: No | O7: No | Q7: No | R7: No | S7: No | U7: No | V7: Requerido | W7: No Requerido | X7: Modificable | Y7: No Requerido
A8: =HYPERLINK("#'M-DetalleCompra'!D6", 'M-DetalleCompra'!D6) -> UnidadMedida | B8: =HYPERLINK("#'M-DetalleCompra'!D2", 'M-DetalleCompra'!D2) -> Se ingresa la unidad de medida en la que se hizo la compra , esta unidad de medida debe ser valida para el tipo de dato , por ejemplo si el producto es aceite de oliva , el va a ser de tipo volumen entonces puede estar en ml o l | C8: No | D8: UnidadMedida | E8: Si | M8: Debe corresponder a una UnidadMedida válida y compatible con el tipo de producto comprado. DetalleCompra permite registrar la cantidad en distintas unidades de medida compatibles; al momento de ingresar al inventario, la cantidad se convierte a una unidad estandar, y es esa cantidad estandar la que almacena y controla el Lote. | N8: No | O8: No | Q8: No | R8: No | S8: No | U8: No | V8: Requerido | W8: No Requerido | X8: Modificable | Y8: No Requerido
A9: =HYPERLINK("#'M-DetalleCompra'!E6", 'M-DetalleCompra'!E6) -> PrecioCompra | B9: =HYPERLINK("#'M-DetalleCompra'!E2", 'M-DetalleCompra'!E2) -> Valor monetario de cada producto | C9: No | D9: Decimal Europeo | E9: Si | H9: 2 | I9: A la unidad (0) | J9: >=0 | K9: 5000000 | N9: No | O9: No | Q9: No | R9: No | S9: No | U9: No | V9: Requerido | W9: No Requerido | X9: Modificable | Y9: No Requerido
A10: =HYPERLINK("#'M-DetalleCompra'!F6", 'M-DetalleCompra'!F6) -> FechaVencimiento | B10: =HYPERLINK("#'M-DetalleCompra'!F2", 'M-DetalleCompra'!F2) -> Se ingresa la fecha de vencimiento del producto , en caso de que la traiga de lo contrario hay que calcular una vida util | C10: No | D10: Fecha | E10: No | L10: dd/mm/yyyy | M10: Solo se ingresa un valor real cuando el producto interno es no perecedero ,si el producto interno es perecedero, no se ingresa ningun valor real y el sistema deja el valor por defecto, ya que su fecha de vencimiento se calcula despues en Lote | N10: No | O10: No | Q10: No | R10: No | S10: No | T10: 01/01/1000 | U10: No | V10: Requerido | W10: No Requerido | X10: Modificable | Y10: No Requerido
A11: =HYPERLINK("#'M-DetalleCompra'!G6", 'M-DetalleCompra'!G6) -> Compra | B11: =HYPERLINK("#'M-DetalleCompra'!G2", 'M-DetalleCompra'!G2) -> Compra a la que pertenece este detalle | C11: No | D11: Compra | E11: Si | M11: Indica a qué compra pertenece este detalle. | N11: No | O11: No | Q11: No | R11: No | S11: No | U11: No | V11: Requerido | W11: No Requerido | X11: No Modificable | Y11: No Requerido
A12: =HYPERLINK("#'M-DetalleCompra'!H6", 'M-DetalleCompra'!H6) -> TipoMovimiento | B12: =HYPERLINK("#'M-DetalleCompra'!H2", 'M-DetalleCompra'!H2) -> Codigo de la operacion (TipoMovimiento) propio de este detalle de compra; es el mismo que lleva su movimiento de entrada | C12: No | D12: TipoMovimiento | E12: Si | M12: Cada detalle de compra genera su propio TipoMovimiento (codigo de operacion), que no se puede repetir; con el se registra la entrada al inventario. | N12: No | O12: No | Q12: No | R12: No | S12: No | U12: Si | V12: No Requerido | W12: No Requerido | X12: No Modificable | Y12: No Requerido
A16: Nombre combinación única | B16: Descripción | C16: Atributos involucrados
A17: Combinación única 1 | B17: Combinacion unica de la linea de compra: la compra a la que pertenece, el producto interno y su fecha de vencimiento (si el producto es perecedero, esta ultima siempre sera la misma para todos, por lo que no puede repetirse el mismo producto sin una fecha real que lo distinga) | C17: =HYPERLINK("#'C-DetalleCompra'!A11", 'C-DetalleCompra'!A11) -> Compra
C18: =HYPERLINK("#'C-DetalleCompra'!A6", 'C-DetalleCompra'!A6) -> ProductoInterno
C19: =HYPERLINK("#'C-DetalleCompra'!A10", 'C-DetalleCompra'!A10) -> FechaVencimiento
A20: Combinación única 2 | B20: No pueden existir dos detalles de compra con el mismo TipoMovimiento; cada detalle tiene su propio codigo de operacion. | C20: =HYPERLINK("#'C-DetalleCompra'!A12", 'C-DetalleCompra'!A12) -> TipoMovimiento
A22: Responsabilidad | C22: Descripción | G22: Entradas | J22: Salida | O22: Políticas (Reglas de Negocio) | Q22: Excepción
G23: Parámetro | H23: Tipo de dato | I23: Descripción | J23: Tipo de Dato | K23: Descripción | O23: Política | P23: Descripción | Q23: Detalle | R23: ¿Qué hago?
A24: =HYPERLINK("#'C-DetalleCompra'!V4", 'E-DetalleCompra'!B7) -> Registrar detalle de compra | C24: ='E-DetalleCompra'!C7 -> Registrar un producto adquirido dentro de una compra, indicando la cantidad, unidad de medida, precio de compra y, cuando corresponda, su fecha de vencimiento. | G24: Datos | H24: DetalleCompra | I24: Información necesaria para registrar el detalle de la compra. | J24: DetalleCompra | K24: Detalle de compra registrado con la información proporcionada. | O24: =HYPERLINK("#'P-DetalleCompra'!A5", 'P-DetalleCompra'!A5) -> P-DC-001 | P24: ='P-DetalleCompra'!B5 -> Asegurar que los datos requeridos para registrar un detalle de compra sean válidos de acuerdo con el tipo de dato, obligatoriedad, formato y rango correspondiente. | Q24: Los datos ingresados para registrar el detalle de compra no son validos. | R24: Rechazar el registro e informar cual dato no es valido.
O25: =HYPERLINK("#'P-DetalleCompra'!A6", 'P-DetalleCompra'!A6) -> P-DC-002 | P25: ='P-DetalleCompra'!B6 -> Asegurar que la compra a la que pertenece el detalle de compra exista en el sistema. | Q25: La compra a la que pertenece el detalle de compra no existe en el sistema. | R25: Rechazar el registro e informar que la compra no existe.
O26: =HYPERLINK("#'P-DetalleCompra'!A7", 'P-DetalleCompra'!A7) -> P-DC-003 | P26: ='P-DetalleCompra'!B7 -> Asegurar que el producto interno asociado al detalle de compra exista en el sistema. | Q26: El producto interno asociado al detalle de compra no existe en el sistema. | R26: Rechazar el registro e informar que el producto interno no existe.
O27: =HYPERLINK("#'P-DetalleCompra'!A17", 'P-DetalleCompra'!A17) -> P-DC-013 | P27: ='P-DetalleCompra'!B17 -> Asegurar que el producto interno del detalle de compra se encuentre activo. | Q27: El producto interno se encuentra inactivo. | R27: Rechazar el registro e informar que el producto interno no esta disponible.
O28: =HYPERLINK("#'P-DetalleCompra'!A8", 'P-DetalleCompra'!A8) -> P-DC-004 | P28: ='P-DetalleCompra'!B8 -> Asegurar que la fecha de vencimiento del detalle de compra solo tenga un valor real cuando el producto interno sea no perecedero; si es perecedero, debe quedar en el valor por defecto (01/01/1000), ya que su vencimiento se calcula en Lote. | Q28: Se registro una fecha de vencimiento real para un producto interno perecedero, o no se registro para uno no perecedero cuando si debia. | R28: Rechazar el registro e informar la inconsistencia con la fecha de vencimiento.
O29: =HYPERLINK("#'P-DetalleCompra'!A9", 'P-DetalleCompra'!A9) -> P-DC-005 | P29: ='P-DetalleCompra'!B9 -> Asegurar que la cantidad registrada en un detalle de compra sea mayor que cero y como maximo 100.000. | Q29: La cantidad no es mayor que cero o supera 100.000. | R29: Rechazar el registro e informar el rango permitido.
O30: =HYPERLINK("#'P-DetalleCompra'!A16", 'P-DetalleCompra'!A16) -> P-DC-012 | P30: ='P-DetalleCompra'!B16 -> Asegurar que el precio de compra sea mayor o igual a cero y como maximo 5.000.000. | Q30: El precio de compra es negativo o supera 5.000.000. | R30: Rechazar el registro e informar el rango permitido.
O31: =HYPERLINK("#'P-DetalleCompra'!A10", 'P-DetalleCompra'!A10) -> P-DC-006 | P31: ='P-DetalleCompra'!B10 -> Asegurar que la unidad de medida utilizada para expresar la cantidad del detalle de compra sea válida. | Q31: La unidad de medida utilizada para el detalle de compra no es valida. | R31: Rechazar el registro e informar que la unidad de medida no es valida.
O32: =HYPERLINK("#'P-DetalleCompra'!A13", 'P-DetalleCompra'!A13) -> P-DC-009 | P32: ='P-DetalleCompra'!B13 -> Asegurar que un mismo producto interno no se repita dentro de una misma compra, salvo que tenga una fecha de vencimiento real distinta (aplicable unicamente a productos no perecederos, ya que un perecedero nunca trae fecha de vencimiento propia). | Q32: El mismo producto interno ya esta registrado dentro de la misma compra con la misma fecha de vencimiento. | R32: Rechazar el registro e informar que el producto interno ya esta registrado en esa compra.
O33: =HYPERLINK("#'P-DetalleCompra'!A18", 'P-DetalleCompra'!A18) -> P-DC-014 | P33: ='P-DetalleCompra'!B18 -> Al registrar un detalle de compra se genera su propio TipoMovimiento de categoria Compra, que no se repite. | Q33: No fue posible generar el TipoMovimiento del detalle. | R33: Rechazar el registro y no crear el lote ni el movimiento.
O34: =HYPERLINK("#'P-DetalleCompra'!A19", 'P-DetalleCompra'!A19) -> P-DC-015 | P34: ='P-DetalleCompra'!B19 -> Al registrar un detalle de compra se crea un nuevo Lote del producto interno con la cantidad comprada (en la unidad del inventario) y su numero de lote consecutivo. Su fecha de vencimiento es la del detalle si el producto no es perecedero, o la fecha de compra mas la vida util si es perecedero. | Q34: No fue posible crear el lote del producto interno. | R34: Rechazar el registro completo para no dejar el inventario inconsistente.
O35: =HYPERLINK("#'P-DetalleCompra'!A20", 'P-DetalleCompra'!A20) -> P-DC-016 | P35: ='P-DetalleCompra'!B20 -> Al registrar un detalle de compra se registra el movimiento de inventario de Entrada sobre el lote creado y se actualiza la cantidad total del inventario del producto interno. | Q35: No fue posible registrar la entrada de inventario. | R35: Rechazar el registro completo para no dejar el inventario inconsistente.
O36: =HYPERLINK("#'P-DetalleCompra'!A21", 'P-DetalleCompra'!A21) -> P-DC-017 | P36: ='P-DetalleCompra'!B21 -> Al registrar, modificar o eliminar un detalle de compra se recalcula el total de la compra. | Q36: El total recalculado de la compra supera 5.000.000. | R36: Rechazar el registro e informar que la compra supera el total permitido.
A37: =HYPERLINK("#'C-DetalleCompra'!W4", 'E-DetalleCompra'!B20) -> Modificar detalle de compra | C37: ='E-DetalleCompra'!C20 -> Actualizar la información de un detalle de compra existente sin comprometer la trazabilidad de los movimientos de inventario ya generados. | G37: Datos | H37: DetalleCompra | I37: Identificador del detalle y datos que se desean modificar. | J37: DetalleCompra | K37: Detalle de compra actualizado con la información proporcionada. | O37: =HYPERLINK("#'P-DetalleCompra'!A11", 'P-DetalleCompra'!A11) -> P-DC-007 | P37: ='P-DetalleCompra'!B11 -> Asegurar que el detalle de compra que se desea modificar se encuentre registrado en el sistema. | Q37: El detalle de compra que se desea modificar no existe. | R37: Rechazar la modificación e informar que el detalle de compra no existe.
O38: =HYPERLINK("#'P-DetalleCompra'!A5", 'P-DetalleCompra'!A5) -> P-DC-001 | P38: ='P-DetalleCompra'!B5 -> Asegurar que los datos requeridos para registrar un detalle de compra sean válidos de acuerdo con el tipo de dato, obligatoriedad, formato y rango correspondiente. | Q38: Los nuevos datos del detalle de compra no son validos. | R38: Rechazar la modificacion e informar cual dato no es valido.
O39: =HYPERLINK("#'P-DetalleCompra'!A9", 'P-DetalleCompra'!A9) -> P-DC-005 | P39: ='P-DetalleCompra'!B9 -> Asegurar que la cantidad registrada en un detalle de compra sea mayor que cero y como maximo 100.000. | Q39: La nueva cantidad no es mayor que cero o supera 100.000. | R39: Rechazar la modificacion e informar el rango permitido.
O40: =HYPERLINK("#'P-DetalleCompra'!A16", 'P-DetalleCompra'!A16) -> P-DC-012 | P40: ='P-DetalleCompra'!B16 -> Asegurar que el precio de compra sea mayor o igual a cero y como maximo 5.000.000. | Q40: El nuevo precio de compra es negativo o supera 5.000.000. | R40: Rechazar la modificacion e informar el rango permitido.
O41: =HYPERLINK("#'P-DetalleCompra'!A21", 'P-DetalleCompra'!A21) -> P-DC-017 | P41: ='P-DetalleCompra'!B21 -> Al registrar, modificar o eliminar un detalle de compra se recalcula el total de la compra. | Q41: El total recalculado de la compra supera 5.000.000. | R41: Rechazar la modificacion e informar que la compra supera el total permitido.
A42: =HYPERLINK("#'C-DetalleCompra'!Y4", 'E-DetalleCompra'!B25) -> Eliminar detalle de compra | C42: ='E-DetalleCompra'!C25 -> Permite eliminar un detalle de compra que no haya generado un lote asociado que deba conservarse para mantener la trazabilidad. | G42: Id | H42: UUID | I42: Identificador del detalle de compra que se desea eliminar. | J42: DetalleCompra | K42: Detalle de compra eliminado correctamente. | O42: =HYPERLINK("#'P-DetalleCompra'!A12", 'P-DetalleCompra'!A12) -> P-DC-008 | P42: ='P-DetalleCompra'!B12 -> Asegurar que el detalle de compra que se desea eliminar se encuentre registrado en el sistema. | Q42: El detalle de compra que se desea eliminar no existe. | R42: Rechazar la eliminacion e informar que el detalle de compra no existe.
O43: =HYPERLINK("#'P-DetalleCompra'!A15", 'P-DetalleCompra'!A15) -> P-DC-011 | P43: ='P-DetalleCompra'!B15 -> Asegurar que un detalle de compra no pueda eliminarse cuando ya haya generado un lote asociado que deba conservarse para mantener la trazabilidad. | Q43: El detalle de compra ya genero un lote asociado que debe conservarse. | R43: Rechazar la eliminacion e informar que el detalle de compra tiene un lote asociado.
O44: =HYPERLINK("#'P-DetalleCompra'!A21", 'P-DetalleCompra'!A21) -> P-DC-017 | P44: ='P-DetalleCompra'!B21 -> Al registrar, modificar o eliminar un detalle de compra se recalcula el total de la compra. | Q44: No fue posible recalcular el total de la compra. | R44: Rechazar la eliminacion para no dejar el total inconsistente.

Sheet E-DetalleCompra
A1: <<<Modelo de Dominio | B1: <<<Objetos de Dominio
A2: Objeto de Dominio: | B2: DetalleCompra
A3: Descripción: | B3: ='C-DetalleCompra'!B3 -> Es cada uno de los productos o insumos que se compraron en una compra, con la cantidad de cada uno.
A4: Actor | B4: Action/Command | D4: Entity/Aggregate/Object domain | E4: Read Model | G4: Business Rule/Policy | H4: External System | I4: Domain Event | J4: Hotspot/questions/Risk
A5: Actor | B5: Acción | C5: Descripción | D5: Objeto de dominio | E5: Información externa | G5: Políticas | H5: Sistema Externo | I5: Evento | J5: Aspectos por solucionar
E6: Información | F6: Descripción | G6: Número
A7: Administrador | B7: Registrar detalle de compra | C7: Registrar un producto adquirido dentro de una compra, indicando la cantidad, unidad de medida, precio de compra y, cuando corresponda, su fecha de vencimiento. | D7: DetalleCompra | E7: Información del detalle de compra | F7: Producto adquirido, cantidad, unidad de medida, precio de compra, fecha de vencimiento y compra a la que pertenece. | G7: =HYPERLINK("#'P-DetalleCompra'!A5", "P-DC-001") -> P-DC-001 | I7: Detalle de compra registrado
G8: =HYPERLINK("#'P-DetalleCompra'!A6", "P-DC-002") -> P-DC-002
G9: =HYPERLINK("#'P-DetalleCompra'!A7", "P-DC-003") -> P-DC-003
G10: =HYPERLINK("#'P-DetalleCompra'!A17", "P-DC-013") -> P-DC-013
G11: =HYPERLINK("#'P-DetalleCompra'!A8", "P-DC-004") -> P-DC-004
G12: =HYPERLINK("#'P-DetalleCompra'!A9", "P-DC-005") -> P-DC-005
G13: =HYPERLINK("#'P-DetalleCompra'!A16", "P-DC-012") -> P-DC-012
G14: =HYPERLINK("#'P-DetalleCompra'!A10", "P-DC-006") -> P-DC-006
G15: =HYPERLINK("#'P-DetalleCompra'!A13", "P-DC-009") -> P-DC-009
G16: =HYPERLINK("#'P-DetalleCompra'!A18", "P-DC-014") -> P-DC-014
G17: =HYPERLINK("#'P-DetalleCompra'!A19", "P-DC-015") -> P-DC-015
G18: =HYPERLINK("#'P-DetalleCompra'!A20", "P-DC-016") -> P-DC-016
G19: =HYPERLINK("#'P-DetalleCompra'!A21", "P-DC-017") -> P-DC-017
A20: Administrador | B20: Modificar detalle de compra | C20: Actualizar la información de un detalle de compra existente sin comprometer la trazabilidad de los movimientos de inventario ya generados. | D20: DetalleCompra | E20: Información del detalle de compra | F20: Identificador del detalle y nuevos datos necesarios para realizar la modificación. | G20: =HYPERLINK("#'P-DetalleCompra'!A11", "P-DC-007") -> P-DC-007 | I20: Detalle de compra modificado
G21: =HYPERLINK("#'P-DetalleCompra'!A5", "P-DC-001") -> P-DC-001
G22: =HYPERLINK("#'P-DetalleCompra'!A9", "P-DC-005") -> P-DC-005
G23: =HYPERLINK("#'P-DetalleCompra'!A16", "P-DC-012") -> P-DC-012
G24: =HYPERLINK("#'P-DetalleCompra'!A21", "P-DC-017") -> P-DC-017
A25: Administrador | B25: Eliminar detalle de compra | C25: Permite eliminar un detalle de compra que no haya generado un lote asociado que deba conservarse para mantener la trazabilidad. | D25: DetalleCompra | E25: Información del detalle de compra | F25: Permite identificar el detalle de compra existente antes de eliminarlo. | G25: =HYPERLINK("#'P-DetalleCompra'!A12", "P-DC-008") -> P-DC-008 | I25: Detalle de compra eliminado
G26: =HYPERLINK("#'P-DetalleCompra'!A15", "P-DC-011") -> P-DC-011
G27: =HYPERLINK("#'P-DetalleCompra'!A21", "P-DC-017") -> P-DC-017

Sheet P-DetalleCompra
A1: <<<Modelo de Dominio | B1: <<<Objetos de Dominio
A2: Objeto de Dominio | B2: DetalleCompra
A3: Descripcion | B3: ='C-DetalleCompra'!B3 -> Es cada uno de los productos o insumos que se compraron en una compra, con la cantidad de cada uno.
A4: Numero politica | B4: Descripcion Politica | C4: Objeto Responsable | D4: Regla Referenciada
A5: P-DC-001 | B5: Asegurar que los datos requeridos para registrar un detalle de compra sean válidos de acuerdo con el tipo de dato, obligatoriedad, formato y rango correspondiente. | C5: DetalleCompra
A6: P-DC-002 | B6: Asegurar que la compra a la que pertenece el detalle de compra exista en el sistema. | C6: Compra | D6: =HYPERLINK("#'P-Compra'!A10", 'P-Compra'!A10) -> P-COM-006
A7: P-DC-003 | B7: Asegurar que el producto interno asociado al detalle de compra exista en el sistema. | C7: ProductoInterno | D7: =HYPERLINK("#'P-ProductoInterno'!A11", 'P-ProductoInterno'!A11) -> P-PI-007
A8: P-DC-004 | B8: Asegurar que la fecha de vencimiento del detalle de compra solo tenga un valor real cuando el producto interno sea no perecedero; si es perecedero, debe quedar en el valor por defecto (01/01/1000), ya que su vencimiento se calcula en Lote. | C8: DetalleCompra
A9: P-DC-005 | B9: Asegurar que la cantidad registrada en un detalle de compra sea mayor que cero y como maximo 100.000. | C9: DetalleCompra
A10: P-DC-006 | B10: Asegurar que la unidad de medida utilizada para expresar la cantidad del detalle de compra sea válida. | C10: UnidadMedida | D10: =HYPERLINK("#'P-UnidadMedida'!A6", 'P-UnidadMedida'!A6) -> P-UM-002
A11: P-DC-007 | B11: Asegurar que el detalle de compra que se desea modificar se encuentre registrado en el sistema. | C11: DetalleCompra
A12: P-DC-008 | B12: Asegurar que el detalle de compra que se desea eliminar se encuentre registrado en el sistema. | C12: DetalleCompra
A13: P-DC-009 | B13: Asegurar que un mismo producto interno no se repita dentro de una misma compra, salvo que tenga una fecha de vencimiento real distinta (aplicable unicamente a productos no perecederos, ya que un perecedero nunca trae fecha de vencimiento propia). | C13: DetalleCompra
A14: P-DC-010 | B14: Asegurar que el detalle de compra exista con el identificador indicado | C14: DetalleCompra
A15: P-DC-011 | B15: Asegurar que un detalle de compra no pueda eliminarse cuando ya haya generado un lote asociado que deba conservarse para mantener la trazabilidad. | C15: Lote | D15: =HYPERLINK("#'P-Lote'!A12", 'P-Lote'!A12) -> P-LOT-008
A16: P-DC-012 | B16: Asegurar que el precio de compra sea mayor o igual a cero y como maximo 5.000.000. | C16: DetalleCompra
A17: P-DC-013 | B17: Asegurar que el producto interno del detalle de compra se encuentre activo. | C17: ProductoInterno
A18: P-DC-014 | B18: Al registrar un detalle de compra se genera su propio TipoMovimiento de categoria Compra, que no se repite. | C18: TipoMovimiento | D18: =HYPERLINK("#'P-TipoMovimiento'!A5", 'P-TipoMovimiento'!A5) -> P-TMV-001
A19: P-DC-015 | B19: Al registrar un detalle de compra se crea un nuevo Lote del producto interno con la cantidad comprada (en la unidad del inventario) y su numero de lote consecutivo. Su fecha de vencimiento es la del detalle si el producto no es perecedero, o la fecha de compra mas la vida util si es perecedero. | C19: Lote | D19: =HYPERLINK("#'P-Lote'!A5", 'P-Lote'!A5) -> P-LOT-001
A20: P-DC-016 | B20: Al registrar un detalle de compra se registra el movimiento de inventario de Entrada sobre el lote creado y se actualiza la cantidad total del inventario del producto interno. | C20: MovimientoInventario | D20: =HYPERLINK("#'P-MovimientoInventario'!A5", 'P-MovimientoInventario'!A5) -> P-MI-001
A21: P-DC-017 | B21: Al registrar, modificar o eliminar un detalle de compra se recalcula el total de la compra. | C21: Compra | D21: =HYPERLINK("#'P-Compra'!A13", 'P-Compra'!A13) -> P-COM-009

Sheet M-Producto
A1: <<<Modelo de Dominio | B1: <<<Objetos de Dominio | J1: Adiciones
A2: Identificador unico de cada producto que vende la pizzeria | B2: Nombre del prodcuto , si es un producto interno entonces el nombre debe coincidir con uno ya existente | C2: Tipo de producto al que pertenece (Pizza, Bebida o Adicion) | D2: Tamaño del producto (Grande, Mediana o Pequeña) para productos que no son pizza el valor es No aplica | E2: Dato calculado: indica si el producto se vende directamente desde el inventario (por ejemplo una bebida). Es Si cuando tiene un ProductoInternoAsociado y No cuando el asociado es "Sin insumo" | F2: Producto interno asociado al producto. Si ProductoInterno es Si, es el producto interno con el mismo nombre; si no, es el registro "Sin insumo" | G2: Contiene el precio de venta publico del producto | H2: Indica si el producto esta activo y disponible para la venta | I2: Combinacion de Nombre y Tamaño; si el Tamaño es No aplica, la combinacion es solo el Nombre
A3: Tipo de dato | B3: Alfanumerico(max 40 caracteres) | C3: TipoProducto | D3: Tamaño | E3: Tipo Logico | F3: ProductoInterno | G3: Decimal Europeo (2) | H3: Tipo Logico | I3: Texto
A6: Obligatorio | B6: Si | C6: Si | D6: Si | E6: Si | F6: Si | G6: Si | H6: Si | I6: Si
A7: Id | B7: Nombre | C7: TipoProducto | D7: Tamaño | E7: ProductoInterno | F7: ProductoInternoAsociado | G7: Precio | H7: Activo | I7: Combinacion unica 1
A8: 1 | B8: Margarita | C8: =HYPERLINK("#'M-TipoProducto'!B8", 'M-TipoProducto'!B8) -> Pizza | D8: =HYPERLINK("#'M-Tamaño'!B8", 'M-Tamaño'!B8) -> Grande | E8: =IF(F8="Sin insumo","No","Si") -> No | F8: =HYPERLINK("#'M-ProductoInterno'!B22", 'M-ProductoInterno'!B22) -> Sin insumo | G8: {=_xlfn.XLOOKUP(1,('M-HistoricoPrecio'!$B:$B=I8)*('M-HistoricoPrecio'!$E:$E="01/01/1000"),'M-HistoricoPrecio'!$C:$C,"")} -> 25000 | H8: Si | I8: =IF(TRIM(D8)="No aplica",B8,CONCATENATE(B8," ",D8)) -> Margarita Grande
A9: 2 | B9: Peperoni | C9: =HYPERLINK("#'M-TipoProducto'!B8", 'M-TipoProducto'!B8) -> Pizza | D9: =HYPERLINK("#'M-Tamaño'!B9", 'M-Tamaño'!B9) -> Mediana | E9: =IF(F9="Sin insumo","No","Si") -> No | F9: =HYPERLINK("#'M-ProductoInterno'!B22", 'M-ProductoInterno'!B22) -> Sin insumo | G9: {=_xlfn.XLOOKUP(1,('M-HistoricoPrecio'!$B:$B=I9)*('M-HistoricoPrecio'!$E:$E="01/01/1000"),'M-HistoricoPrecio'!$C:$C,"")} -> 23000 | H9: Si | I9: =IF(TRIM(D9)="No aplica",B9,CONCATENATE(B9," ",D9)) -> Peperoni Mediana
A10: 3 | B10: Margarita y Hawaiana | C10: =HYPERLINK("#'M-TipoProducto'!B8", 'M-TipoProducto'!B8) -> Pizza | D10: =HYPERLINK("#'M-Tamaño'!B10", 'M-Tamaño'!B10) -> Pequeña | E10: =IF(F10="Sin insumo","No","Si") -> No | F10: =HYPERLINK("#'M-ProductoInterno'!B22", 'M-ProductoInterno'!B22) -> Sin insumo | G10: {=_xlfn.XLOOKUP(1,('M-HistoricoPrecio'!$B:$B=I10)*('M-HistoricoPrecio'!$E:$E="01/01/1000"),'M-HistoricoPrecio'!$C:$C,"")} -> 30000 | H10: Si | I10: =IF(TRIM(D10)="No aplica",B10,CONCATENATE(B10," ",D10)) -> Margarita y Hawaiana Pequeña
A11: 4 | B11: Extra Queso | C11: =HYPERLINK("#'M-TipoProducto'!B10", 'M-TipoProducto'!B10) -> Adicion | D11: =HYPERLINK("#'M-Tamaño'!B11", 'M-Tamaño'!B11) -> No aplica | E11: =IF(F11="Sin insumo","No","Si") -> No | F11: =HYPERLINK("#'M-ProductoInterno'!B22", 'M-ProductoInterno'!B22) -> Sin insumo | G11: {=_xlfn.XLOOKUP(1,('M-HistoricoPrecio'!$B:$B=I11)*('M-HistoricoPrecio'!$E:$E="01/01/1000"),'M-HistoricoPrecio'!$C:$C,"")} -> 5000 | H11: Si | I11: =IF(TRIM(D11)="No aplica",B11,CONCATENATE(B11," ",D11)) -> Extra Queso
A12: 5 | B12: Extra Piña | C12: =HYPERLINK("#'M-TipoProducto'!B10", 'M-TipoProducto'!B10) -> Adicion | D12: =HYPERLINK("#'M-Tamaño'!B11", 'M-Tamaño'!B11) -> No aplica | E12: =IF(F12="Sin insumo","No","Si") -> No | F12: =HYPERLINK("#'M-ProductoInterno'!B22", 'M-ProductoInterno'!B22) -> Sin insumo | G12: {=_xlfn.XLOOKUP(1,('M-HistoricoPrecio'!$B:$B=I12)*('M-HistoricoPrecio'!$E:$E="01/01/1000"),'M-HistoricoPrecio'!$C:$C,"")} -> 6000 | H12: Si | I12: =IF(TRIM(D12)="No aplica",B12,CONCATENATE(B12," ",D12)) -> Extra Piña
A13: 6 | B13: Extra Peperoni | C13: =HYPERLINK("#'M-TipoProducto'!B10", 'M-TipoProducto'!B10) -> Adicion | D13: =HYPERLINK("#'M-Tamaño'!B11", 'M-Tamaño'!B11) -> No aplica | E13: =IF(F13="Sin insumo","No","Si") -> No | F13: =HYPERLINK("#'M-ProductoInterno'!B22", 'M-ProductoInterno'!B22) -> Sin insumo | G13: {=_xlfn.XLOOKUP(1,('M-HistoricoPrecio'!$B:$B=I13)*('M-HistoricoPrecio'!$E:$E="01/01/1000"),'M-HistoricoPrecio'!$C:$C,"")} -> 9000 | H13: Si | I13: =IF(TRIM(D13)="No aplica",B13,CONCATENATE(B13," ",D13)) -> Extra Peperoni
A14: 7 | B14: Jugo Hit Mora 200 ml | C14: =HYPERLINK("#'M-TipoProducto'!B9", 'M-TipoProducto'!B9) -> Bebida | D14: =HYPERLINK("#'M-Tamaño'!B11", 'M-Tamaño'!B11) -> No aplica | E14: =IF(F14="Sin insumo","No","Si") -> Si | F14: =HYPERLINK("#'M-ProductoInterno'!B16", 'M-ProductoInterno'!B16) -> Jugo Hit Mora 200 ml | G14: {=_xlfn.XLOOKUP(1,('M-HistoricoPrecio'!$B:$B=I14)*('M-HistoricoPrecio'!$E:$E="01/01/1000"),'M-HistoricoPrecio'!$C:$C,"")} -> 4000 | H14: Si | I14: =IF(TRIM(D14)="No aplica",B14,CONCATENATE(B14," ",D14)) -> Jugo Hit Mora 200 ml
A15: 8 | B15: Pepsi 400 ml | C15: =HYPERLINK("#'M-TipoProducto'!B9", 'M-TipoProducto'!B9) -> Bebida | D15: =HYPERLINK("#'M-Tamaño'!B11", 'M-Tamaño'!B11) -> No aplica | E15: =IF(F15="Sin insumo","No","Si") -> Si | F15: =HYPERLINK("#'M-ProductoInterno'!B17", 'M-ProductoInterno'!B17) -> Pepsi 400 ml | G15: {=_xlfn.XLOOKUP(1,('M-HistoricoPrecio'!$B:$B=I15)*('M-HistoricoPrecio'!$E:$E="01/01/1000"),'M-HistoricoPrecio'!$C:$C,"")} -> 6000 | H15: Si | I15: =IF(TRIM(D15)="No aplica",B15,CONCATENATE(B15," ",D15)) -> Pepsi 400 ml
A16: 9 | B16: Monster 473 ml | C16: =HYPERLINK("#'M-TipoProducto'!B9", 'M-TipoProducto'!B9) -> Bebida | D16: =HYPERLINK("#'M-Tamaño'!B11", 'M-Tamaño'!B11) -> No aplica | E16: =IF(F16="Sin insumo","No","Si") -> Si | F16: =HYPERLINK("#'M-ProductoInterno'!B18", 'M-ProductoInterno'!B18) -> Monster 473 ml | G16: {=_xlfn.XLOOKUP(1,('M-HistoricoPrecio'!$B:$B=I16)*('M-HistoricoPrecio'!$E:$E="01/01/1000"),'M-HistoricoPrecio'!$C:$C,"")} -> 5200 | H16: Si | I16: =IF(TRIM(D16)="No aplica",B16,CONCATENATE(B16," ",D16)) -> Monster 473 ml
A17: 10 | B17: Colombiana 400 ml | C17: =HYPERLINK("#'M-TipoProducto'!B9", 'M-TipoProducto'!B9) -> Bebida | D17: =HYPERLINK("#'M-Tamaño'!B11", 'M-Tamaño'!B11) -> No aplica | E17: =IF(F17="Sin insumo","No","Si") -> Si | F17: =HYPERLINK("#'M-ProductoInterno'!B19", 'M-ProductoInterno'!B19) -> Colombiana 400 ml | G17: {=_xlfn.XLOOKUP(1,('M-HistoricoPrecio'!$B:$B=I17)*('M-HistoricoPrecio'!$E:$E="01/01/1000"),'M-HistoricoPrecio'!$C:$C,"")} -> 4500 | H17: Si | I17: =IF(TRIM(D17)="No aplica",B17,CONCATENATE(B17," ",D17)) -> Colombiana 400 ml
A18: 11 | B18: Mr tea 300 ml | C18: =HYPERLINK("#'M-TipoProducto'!B9", 'M-TipoProducto'!B9) -> Bebida | D18: =HYPERLINK("#'M-Tamaño'!B11", 'M-Tamaño'!B11) -> No aplica | E18: =IF(F18="Sin insumo","No","Si") -> Si | F18: =HYPERLINK("#'M-ProductoInterno'!B20", 'M-ProductoInterno'!B20) -> Mr tea 300 ml | G18: {=_xlfn.XLOOKUP(1,('M-HistoricoPrecio'!$B:$B=I18)*('M-HistoricoPrecio'!$E:$E="01/01/1000"),'M-HistoricoPrecio'!$C:$C,"")} -> 4500 | H18: Si | I18: =IF(TRIM(D18)="No aplica",B18,CONCATENATE(B18," ",D18)) -> Mr tea 300 ml
A19: 12 | B19: Hawaiana | C19: =HYPERLINK("#'M-TipoProducto'!B8", 'M-TipoProducto'!B8) -> Pizza | D19: =HYPERLINK("#'M-Tamaño'!B8", 'M-Tamaño'!B8) -> Grande | E19: =IF(F19="Sin insumo","No","Si") -> No | F19: =HYPERLINK("#'M-ProductoInterno'!B22", 'M-ProductoInterno'!B22) -> Sin insumo | G19: {=_xlfn.XLOOKUP(1,('M-HistoricoPrecio'!$B:$B=I19)*('M-HistoricoPrecio'!$E:$E="01/01/1000"),'M-HistoricoPrecio'!$C:$C,"")} -> 35000 | H19: Si | I19: =IF(TRIM(D19)="No aplica",B19,CONCATENATE(B19," ",D19)) -> Hawaiana Grande

Sheet C-Producto
A1: <<<Modelo de Dominio | B1: <<<Objetos de Dominio
A2: Nombre | B2: Producto
A3: Descripción | B3: =HYPERLINK("#'Objetos de dominio'!B12", 'Objetos de dominio'!B14) -> Son los productos que la pizzería vende, como las pizzas, las bebidas y las adiciones.
A4: Nombre atributo | B4: Descripción atributo | C4: Identificador del objeto de dominio | D4: Tipo de dato | E4: Obligatorio | F4: Longitud mínima (si aplica) | G4: Longitud máxima (si aplica) | H4: Precisión (si aplica) | I4: Rendondeo (si aplica) | J4: Rango inicial (si aplica) | K4: Rango final (si aplica) | L4: Formato (si aplica) | M4: Reglas especiales (si aplica) | N4: Dato calculado | O4: Aplica ajuste del dato (si aplica) | P4: Carácter de ajuste (si aplica) | Q4: Quitar espacios en blanco al inicio (si aplica) | R4: Quitar espacios en blanco al fin (si aplica) | S4: Dato sensible (si aplica) | T4: Valor por defecto (si aplica) | U4: Auto generado | V4: =HYPERLINK("#'C-Producto'!A21", 'C-Producto'!A21) -> Registrar producto | W4: =HYPERLINK("#'C-Producto'!A28", 'C-Producto'!A28) -> Inactivar producto | X4: =HYPERLINK("#'C-Producto'!A31", 'C-Producto'!A31) -> Consultar productos activos
A5: =HYPERLINK("#'M-Producto'!A7", 'M-Producto'!A7) -> Id | B5: =HYPERLINK("#'M-Producto'!A2", 'M-Producto'!A2) -> Identificador unico de cada producto que vende la pizzeria | C5: Si | D5: Identificador único universal | E5: Si | N5: No | O5: No | Q5: No | R5: No | S5: No | U5: Si | V5: Requerido | W5: Requerido | X5: No Mostrar
A6: =HYPERLINK("#'M-Producto'!B7", 'M-Producto'!B7) -> Nombre | B6: =HYPERLINK("#'M-Producto'!B2", 'M-Producto'!B2) -> Nombre del prodcuto , si es un producto interno entonces el nombre debe coincidir con uno ya existente | C6: No | D6: Alfanumerico | E6: Si | F6: 1 | G6: 40 | M6: El usuario lo registra. Si el producto es un producto interno, debe existir un producto interno con el mismo nombre. | N6: No | O6: No | Q6: Si | R6: Si | S6: No | U6: No | V6: Requerido | W6: No Requerido | X6: Mostrar
A7: =HYPERLINK("#'M-Producto'!C7", 'M-Producto'!C7) -> TipoProducto | B7: =HYPERLINK("#'M-Producto'!C2", 'M-Producto'!C2) -> Tipo de producto al que pertenece (Pizza, Bebida o Adicion) | C7: No | D7: TipoProducto | E7: Si | M7: Referenciado en vivo (HYPERLINK) al catálogo M-TipoProducto. | N7: No | O7: No | Q7: No | R7: No | S7: No | U7: No | V7: Requerido | W7: No Requerido | X7: Mostrar
A8: =HYPERLINK("#'M-Producto'!D7", 'M-Producto'!D7) -> Tamaño | B8: =HYPERLINK("#'M-Producto'!D2", 'M-Producto'!D2) -> Tamaño del producto (Grande, Mediana o Pequeña) para productos que no son pizza el valor es No aplica | C8: No | D8: Tamaño | E8: Si | M8: Referenciado en vivo (HYPERLINK) al catálogo M-Tamaño. Para productos que no son pizza, el valor es No aplica. | N8: No | O8: No | Q8: No | R8: No | S8: No | U8: No | V8: Requerido | W8: No Requerido | X8: Mostrar
A9: =HYPERLINK("#'M-Producto'!E7", 'M-Producto'!E7) -> ProductoInterno | B9: =HYPERLINK("#'M-Producto'!E2", 'M-Producto'!E2) -> Dato calculado: indica si el producto se vende directamente desde el inventario (por ejemplo una bebida). Es Si cuando tiene un ProductoInternoAsociado y No cuando el asociado es "Sin insumo" | C9: No | D9: Tipo Logico | E9: Si | M9: El usuario indica si el producto se vende directo del inventario. Si es Si, se asocia el producto interno con el mismo nombre. En la base de datos se calcula a partir del ProductoInternoAsociado. | N9: Si | O9: No | Q9: No | R9: No | S9: No | U9: No | V9: Requerido | W9: No Requerido | X9: Mostrar
A10: =HYPERLINK("#'M-Producto'!F7", 'M-Producto'!F7) -> ProductoInternoAsociado | B10: =HYPERLINK("#'M-Producto'!F2", 'M-Producto'!F2) -> Producto interno asociado al producto. Si ProductoInterno es Si, es el producto interno con el mismo nombre; si no, es el registro "Sin insumo" | C10: No | D10: ProductoInterno | E10: Si | M10: Se asigna automaticamente: si ProductoInterno es Si, el producto interno con el mismo nombre (debe existir); si es No, el registro "Sin insumo". | N10: Si | O10: No | Q10: No | R10: No | S10: No | T10: Sin insumo | U10: No | V10: No Requerido | W10: No Requerido | X10: No Mostrar
A11: =HYPERLINK("#'M-Producto'!G7", 'M-Producto'!G7) -> Precio | B11: =HYPERLINK("#'M-Producto'!G2", 'M-Producto'!G2) -> Contiene el precio de venta publico del producto | C11: No | D11: Decimal Europeo | E11: Si | H11: 2 | I11: A la unidad (0) | J11: >0 | K11: 1000000 | M11: Lo registra el usuario al crear el producto. Debe coincidir con el precio vigente en HistoricoPrecio (FechaFin = 01/01/1000). | N11: No | O11: No | Q11: No | R11: No | S11: No | U11: No | V11: Requerido | W11: No Requerido | X11: Mostrar
A12: =HYPERLINK("#'M-Producto'!H7", 'M-Producto'!H7) -> Activo | B12: =HYPERLINK("#'M-Producto'!H2", 'M-Producto'!H2) -> Indica si el producto esta activo y disponible para la venta | C12: No | D12: Tipo Logico | E12: Si | M12: Se registra como activo (Si). Solo los productos activos se muestran al consultar los productos. | N12: No | O12: No | Q12: No | R12: No | S12: No | T12: Si | U12: No | V12: No Requerido | W12: No Requerido | X12: No Mostrar
A15: Nombre combinación única | B15: Descripción | C15: Atributos involucrados
A16: Combinación única 1 | B16: No pueden existir dos productos con el mismo Nombre y el mismo Tamaño. | C16: =HYPERLINK("#'C-Producto'!A6", 'C-Producto'!A6) -> Nombre
C17: =HYPERLINK("#'C-Producto'!A8", 'C-Producto'!A8) -> Tamaño
A19: Responsabilidad | C19: Descripción | G19: Entradas | J19: Salida | O19: Políticas (Reglas de Negocio) | Q19: Excepción
G20: Parámetro | H20: Tipo de dato | I20: Descripción | J20: Tipo de Dato | K20: Descripción | O20: Política | P20: Descripción | Q20: Detalle | R20: ¿Qué hago?
A21: =HYPERLINK("#'C-Producto'!V4", 'E-Producto'!B7) -> Registrar producto | C21: ='E-Producto'!C7 -> Permite incorporar un nuevo producto a la oferta comercial de la pizzería, definiendo la información necesaria para su identificación y comercialización. | G21: Datos | H21: Producto | I21: Información propia necesaria para registrar el producto. | J21: Producto | K21: Producto registrado con la información proporcionada. | O21: =HYPERLINK("#'P-Producto'!A5", 'P-Producto'!A5) -> P-PRO-001 | P21: ='P-Producto'!B5 -> Asegurar que los datos requeridos para registrar un producto sean validos: nombre de 1 a 40 caracteres, tipo de producto y tamano diligenciados, y precio mayor que 0 y como maximo 1.000.000. | Q21: Los datos ingresados para registrar el producto no cumplen las reglas establecidas. | R21: Rechazar el registro e informar cual dato no es valido.
O22: =HYPERLINK("#'P-Producto'!A6", 'P-Producto'!A6) -> P-PRO-002 | P22: ='P-Producto'!B6 -> Asegurar que el identificador generado para el producto no esté siendo utilizado por otro producto. | Q22: El identificador generado ya esta siendo utilizado por otro producto. | R22: Generar un nuevo identificador hasta garantizar que no exista.
O23: =HYPERLINK("#'P-Producto'!A7", 'P-Producto'!A7) -> P-PRO-003 | P23: ='P-Producto'!B7 -> Asegurar que no exista otro producto con el mismo Nombre y el mismo Tamaño al registrar el producto. | Q23: Ya existe otro producto con el mismo Nombre y el mismo Tamaño. | R23: Rechazar el registro e informar que ya existe un producto igual registrado.
O24: =HYPERLINK("#'P-Producto'!A8", 'P-Producto'!A8) -> P-PRO-004 | P24: ='P-Producto'!B8 -> Asegurar que el tipo de producto utilizado para registrar el producto corresponda a un tipo válido definido por la pizzería. | Q24: El tipo de producto utilizado no corresponde a un tipo valido definido por la pizzeria. | R24: Rechazar el registro e informar que el tipo de producto no es valido.
O25: =HYPERLINK("#'P-Producto'!A9", 'P-Producto'!A9) -> P-PRO-005 | P25: ='P-Producto'!B9 -> Asegurar que, cuando el producto sea un producto interno, exista un producto interno con el mismo nombre y se asocie como ProductoInternoAsociado; si no es producto interno, se asocia el registro "Sin insumo". | Q25: No existe un producto interno con el mismo nombre del producto. | R25: Rechazar el registro e informar que primero debe registrarse el producto interno.
O26: =HYPERLINK("#'P-Producto'!A10", 'P-Producto'!A10) -> P-PRO-006 | P26: ='P-Producto'!B10 -> Asegurar que el tamaño utilizado para registrar el producto corresponda a un tamaño válido definido por la pizzería. | Q26: El tamaño utilizado no corresponde a un tamaño valido definido por la pizzeria. | R26: Rechazar el registro e informar que el tamaño no es valido.
O27: =HYPERLINK("#'P-Producto'!A14", 'P-Producto'!A14) -> P-PRO-010 | P27: ='P-Producto'!B14 -> Al registrar un producto, su precio queda registrado en HistoricoPrecio como precio vigente desde la fecha de registro (FechaFin 01/01/1000). | Q27: No fue posible registrar el precio inicial en el historico de precios. | R27: Rechazar el registro completo para que el producto no quede sin precio vigente.
A28: =HYPERLINK("#'C-Producto'!W4", 'E-Producto'!B14) -> Inactivar producto | C28: ='E-Producto'!C14 -> Permite inactivar un producto que la pizzeria ya no ofrece: no se puede vender, pero se conserva su historial de precios, ventas y recetas. | G28: Id | H28: UUID | I28: Identificador del producto que se desea eliminar. | J28: Producto | K28: Producto inactivado. | O28: =HYPERLINK("#'P-Producto'!A11", 'P-Producto'!A11) -> P-PRO-007 | P28: ='P-Producto'!B11 -> Asegurar que el producto que se quiere inactivar se encuentre registrado en el sistema. | Q28: El producto no existe con el identificador indicado. | R28: Rechazar la eliminación e informar que el producto no existe.
O29: =HYPERLINK("#'P-Producto'!A16", 'P-Producto'!A16) -> P-PRO-012 | P29: ='P-Producto'!B16 -> Asegurar que el producto que se desea inactivar no se encuentre ya inactivo. | Q29: El producto ya se encuentra inactivo. | R29: Informar que el producto ya esta inactivo.
O30: =HYPERLINK("#'P-Producto'!A12", 'P-Producto'!A12) -> P-PRO-008 | P30: ='P-Producto'!B12 -> Asegurar que al inactivar un producto se conserve su informacion historica (precios, ventas y recetas), aunque ya no se ofrezca en la pizzeria. | Q30: El producto tiene precios, ventas o recetas registradas. | R30: Inactivar el producto sin borrar su historial.
A31: =HYPERLINK("#'C-Producto'!X4", 'E-Producto'!B17) -> Consultar productos activos | C31: ='E-Producto'!C17 -> Permite consultar los productos activos que la pizzeria ofrece, por ejemplo para registrar una venta o armar una receta. | G31: Ninguno | H31: - | I31: No requiere datos de entrada. | J31: Lista de Producto | K31: Productos activos con su tipo, tamano y precio. | O31: =HYPERLINK("#'P-Producto'!A17", 'P-Producto'!A17) -> P-PRO-013 | P31: ='P-Producto'!B17 -> Asegurar que solo se consulten los productos activos. | Q31: No existen productos activos. | R31: Informar que no hay productos activos.

Sheet E-Producto
A1: <<<Modelo de Dominio | B1: <<<Objetos de Dominio
A2: Objeto de Dominio: | B2: Producto
A3: Descripción: | B3: ='C-Producto'!B3 -> Son los productos que la pizzería vende, como las pizzas, las bebidas y las adiciones.
A4: Actor | B4: Action/Command | D4: Entity/Aggregate/Object domain | E4: Read Model | G4: Business Rule/Policy | H4: External System | I4: Domain Event | J4: Hotspot/questions/Risk
A5: Actor | B5: Acción | C5: Descripción | D5: Objeto de dominio | E5: Información externa | G5: Políticas | H5: Sistema Externo | I5: Evento | J5: Aspectos por solucionar
E6: Información | F6: Descripción | G6: Número
A7: Administrador | B7: Registrar producto | C7: Permite incorporar un nuevo producto a la oferta comercial de la pizzería, definiendo la información necesaria para su identificación y comercialización. | D7: Producto | E7: Tipo de producto | F7: Permite determinar el tipo de producto que se desea registrar y consultar la información necesaria para su creación. | G7: =HYPERLINK("#'P-Producto'!A5", "P-PRO-001") -> P-PRO-001 | I7: Producto registrado
G8: =HYPERLINK("#'P-Producto'!A6", "P-PRO-002") -> P-PRO-002
G9: =HYPERLINK("#'P-Producto'!A7", "P-PRO-003") -> P-PRO-003
G10: =HYPERLINK("#'P-Producto'!A8", "P-PRO-004") -> P-PRO-004
G11: =HYPERLINK("#'P-Producto'!A9", "P-PRO-005") -> P-PRO-005
G12: =HYPERLINK("#'P-Producto'!A10", "P-PRO-006") -> P-PRO-006
G13: =HYPERLINK("#'P-Producto'!A14", "P-PRO-010") -> P-PRO-010
A14: Administrador | B14: Inactivar producto | C14: Permite inactivar un producto que la pizzeria ya no ofrece: no se puede vender, pero se conserva su historial de precios, ventas y recetas. | D14: Producto | E14: Identificador del prodcuto e historio de precio de ese producto | F14: Identificar el producto que se quiere eliminar y cual es su informacion historica asociada | G14: =HYPERLINK("#'P-Producto'!A11", "P-PRO-007") -> P-PRO-007 | I14: Producto inactivado
G15: =HYPERLINK("#'P-Producto'!A16", "P-PRO-012") -> P-PRO-012
G16: =HYPERLINK("#'P-Producto'!A12", "P-PRO-008") -> P-PRO-008
A17: Administrador | B17: Consultar productos activos | C17: Permite consultar los productos activos que la pizzeria ofrece, por ejemplo para registrar una venta o armar una receta. | E17: Productos registrados | F17: Productos con estado activo. | G17: =HYPERLINK("#'P-Producto'!A17", "P-PRO-013") -> P-PRO-013 | I17: Productos activos consultados

Sheet P-Producto
A1: <<<Modelo de Dominio | B1: <<<Objetos de Dominio
A2: Objeto de Dominio | B2: Producto
A3: Descripcion | B3: ='C-Producto'!B3 -> Son los productos que la pizzería vende, como las pizzas, las bebidas y las adiciones.
A4: Numero politica | B4: Descripcion Politica | C4: Objeto Responsable | D4: Regla Referenciada
A5: P-PRO-001 | B5: Asegurar que los datos requeridos para registrar un producto sean validos: nombre de 1 a 40 caracteres, tipo de producto y tamano diligenciados, y precio mayor que 0 y como maximo 1.000.000. | C5: Producto
A6: P-PRO-002 | B6: Asegurar que el identificador generado para el producto no esté siendo utilizado por otro producto. | C6: Producto
A7: P-PRO-003 | B7: Asegurar que no exista otro producto con el mismo Nombre y el mismo Tamaño al registrar el producto. | C7: Producto
A8: P-PRO-004 | B8: Asegurar que el tipo de producto utilizado para registrar el producto corresponda a un tipo válido definido por la pizzería. | C8: TipoProducto | D8: =HYPERLINK("#'P-TipoProducto'!A5", 'P-TipoProducto'!A5) -> P-TP-001
A9: P-PRO-005 | B9: Asegurar que, cuando el producto sea un producto interno, exista un producto interno con el mismo nombre y se asocie como ProductoInternoAsociado; si no es producto interno, se asocia el registro "Sin insumo". | C9: ProductoInterno | D9: =HYPERLINK("#'P-ProductoInterno'!A11", 'P-ProductoInterno'!A11) -> P-PI-007
A10: P-PRO-006 | B10: Asegurar que el tamaño utilizado para registrar el producto corresponda a un tamaño válido definido por la pizzería. | C10: Tamaño | D10: =HYPERLINK("#'P-Tamaño'!A5", 'P-Tamaño'!A5) -> P-TAM-001
A11: P-PRO-007 | B11: Asegurar que el producto que se quiere inactivar se encuentre registrado en el sistema. | C11: Producto
A12: P-PRO-008 | B12: Asegurar que al inactivar un producto se conserve su informacion historica (precios, ventas y recetas), aunque ya no se ofrezca en la pizzeria. | C12: HistoricoPrecio | D12: =HYPERLINK("#'P-HistoricoPrecio'!A15", 'P-HistoricoPrecio'!A15) -> P-HP-011
A13: P-PRO-009 | B13: Asegurar que el producto exista con el identificador indicado. | C13: Producto
A14: P-PRO-010 | B14: Al registrar un producto, su precio queda registrado en HistoricoPrecio como precio vigente desde la fecha de registro (FechaFin 01/01/1000). | C14: HistoricoPrecio | D14: =HYPERLINK("#'P-HistoricoPrecio'!A5", 'P-HistoricoPrecio'!A5) -> P-HP-001
A15: P-PRO-011 | B15: Asegurar que un producto inactivo no pueda venderse ni recibir nuevos ingredientes en su receta. | C15: Producto
A16: P-PRO-012 | B16: Asegurar que el producto que se desea inactivar no se encuentre ya inactivo. | C16: Producto
A17: P-PRO-013 | B17: Asegurar que solo se consulten los productos activos. | C17: Producto

Sheet M-Venta
A1: <<<Modelo de Dominio | B1: <<<Objetos de Dominio
A2: Identificador de cada venta dentro del sistema | B2: Fecha en la que se realizo la venta | C2: Hora en la que se realizo la venta | D2: Número de la factura de venta. El sistema lo asigna solo en el momento en que la venta se hace | E2: Indicativo de a que cliente le pertenece la venta | F2: Total de la venta
A3: Tipo de dato | B3: Fecha | C3: Time | D3: Alfanumerico(max 9 caracteres) | E3: Alfanumerico(max 10 caracteres) | F3: Decimal Europeo (2)
A4: Obligatorio | B4: Si | C4: Si | D4: Si | E4: No | F4: Si
A5: Id | B5: Fecha | C5: Hora | D5: Factura | E5: Cliente | F5: Total | G5: CombinacionUnica
A6: 1 | B6: 46268 | C6: 11:30:00 Pm | D6: FV-000001 | E6: 1036456892 | F6: =SUMIF('M-DetalleVenta'!$B:$B,D6,'M-DetalleVenta'!$F:$F) -> 25000 | G6: =D6 -> FV-000001
A7: 2 | B7: 46268 | C7: 11:45:00 Pm | D7: FV-000002 | E7: 1030789345 | F7: =SUMIF('M-DetalleVenta'!$B:$B,D7,'M-DetalleVenta'!$F:$F) -> 106000 | G7: =D7 -> FV-000002
A8: 3 | B8: 46227 | C8: 1:00:00 Pm | D8: FV-000003 | E8: 1040875813 | F8: =SUMIF('M-DetalleVenta'!$B:$B,D8,'M-DetalleVenta'!$F:$F) -> 5000 | G8: =D8 -> FV-000003
A9: 4 | B9: 46297 | C9: 12:30:00 Pm | D9: FV-000004 | E9: 2222222222 | F9: =SUMIF('M-DetalleVenta'!$B:$B,D9,'M-DetalleVenta'!$F:$F) -> 35000 | G9: =D9 -> FV-000004

Sheet C-Venta
A1: <<<Modelo de Dominio | B1: <<<Objetos de Dominio
A2: Nombre | B2: Venta
A3: Descripción | B3: =HYPERLINK("#'Objetos de dominio'!B13", 'Objetos de dominio'!B15) -> Es cuando un cliente compra productos en la pizzería.
A4: Nombre atributo | B4: Descripción atributo | C4: Identificador del objeto de dominio | D4: Tipo de dato | E4: Obligatorio | F4: Longitud mínima (si aplica) | G4: Longitud máxima (si aplica) | H4: Precisión (si aplica) | I4: Rendondeo (si aplica) | J4: Rango inicial (si aplica) | K4: Rango final (si aplica) | L4: Formato (si aplica) | M4: Reglas especiales (si aplica) | N4: Dato calculado | O4: Aplica ajuste del dato (si aplica) | P4: Carácter de ajuste (si aplica) | Q4: Quitar espacios en blanco al inicio (si aplica) | R4: Quitar espacios en blanco al fin (si aplica) | S4: Dato sensible (si aplica) | T4: Valor por defecto (si aplica) | U4: Auto generado | V4: =HYPERLINK("#'C-Venta'!A22", 'C-Venta'!A22) -> Registrar venta | W4: =HYPERLINK("#'C-Venta'!A25", 'C-Venta'!A25) -> Confirmar venta | Y4: =HYPERLINK("#'C-Venta'!A34", 'C-Venta'!A34) -> Eliminar venta | Z4: =HYPERLINK("#'C-Venta'!A37", 'C-Venta'!A37) -> Consultar venta
A5: =HYPERLINK("#'M-Venta'!A5", 'M-Venta'!A5) -> Id | B5: =HYPERLINK("#'M-Venta'!A2", 'M-Venta'!A2) -> Identificador de cada venta dentro del sistema | C5: Si | D5: Identificador unico universal | E5: Si | N5: No | O5: No | Q5: No | R5: No | S5: No | U5: Si | V5: Requerido | W5: Requerido | X5: No Modificable | Y5: Requerido | Z5: No Mostrar
A6: =HYPERLINK("#'M-Venta'!B5", 'M-Venta'!B5) -> Fecha | B6: =HYPERLINK("#'M-Venta'!B2", 'M-Venta'!B2) -> Fecha en la que se realizo la venta | C6: No | D6: Fecha | E6: Si | L6: dd/mm/yyyy | N6: No | O6: No | Q6: No | R6: No | S6: No | U6: Si | V6: Requerido | W6: No Requerido | X6: No Modificable | Y6: No Requerido | Z6: Mostrar
A7: =HYPERLINK("#'M-Venta'!C5", 'M-Venta'!C5) -> Hora | B7: =HYPERLINK("#'M-Venta'!C2", 'M-Venta'!C2) -> Hora en la que se realizo la venta | C7: No | D7: Time | E7: Si | L7: HH:mm:ss | M7: Se registra con precision de segundos para evitar que dos ventas del mismo dia choquen en la combinacion unica. | N7: No | O7: No | Q7: No | R7: No | S7: No | U7: Si | V7: Requerido | W7: No Requerido | X7: No Modificable | Y7: No Requerido | Z7: Mostrar
A8: =HYPERLINK("#'M-Venta'!D5", 'M-Venta'!D5) -> Factura | B8: =HYPERLINK("#'M-Venta'!D2", 'M-Venta'!D2) -> Número de la factura de venta. El sistema lo asigna solo en el momento en que la venta se hace | C8: No | D8: Alfanumerico | E8: Si | F8: 9 | G8: 9 | L8: FV-###### | M8: No lo escribe nadie a mano: el sistema lo asigna en el momento en que la venta se confirma. Formato FV- seguido de 6 digitos (por ejemplo FV-000001) y no se puede repetir. | N8: No | O8: No | Q8: No | R8: No | S8: No | U8: Si | V8: No Requerido | W8: No Requerido | X8: No Modificable | Y8: No Requerido | Z8: Mostrar
A9: =HYPERLINK("#'M-Venta'!E5", 'M-Venta'!E5) -> Cliente | B9: =HYPERLINK("#'M-Venta'!E2", 'M-Venta'!E2) -> Indicativo de a que cliente le pertenece la venta | C9: No | D9: Alfanumerico | E9: No | F9: 1 | G9: 10 | M9: Documento del cliente. Si no se indica, se registra 2222222222 (consumidor final). | N9: No | O9: No | Q9: Si | R9: Si | S9: No | T9: 2222222222 | U9: No | V9: No Requerido | W9: No Requerido | X9: No Modificable | Y9: No Requerido | Z9: Mostrar
A10: =HYPERLINK("#'M-Venta'!F5", 'M-Venta'!F5) -> Total | B10: =HYPERLINK("#'M-Venta'!F2", 'M-Venta'!F2) -> Total de la venta | C10: No | D10: Decimal Europeo | E10: Si | H10: 2 | I10: A la unidad (0) | J10: >0 | K10: 1000000 | M10: El valor total de una venta corresponde a la suma de los Subtotal de todos los DetalleVenta asociados a la misma. | N10: Si | O10: No | Q10: No | R10: No | S10: Si | U10: No | V10: No Requerido | W10: No Requerido | X10: No Modificable | Y10: No Requerido | Z10: Mostrar
A13: Nombre combinación única | B13: Descripción | C13: Atributos involucrados
A14: Combinación única 1 | B14: No pueden existir dos ventas con la misma Fecha y la misma Hora (a precision de segundos). | C14: =HYPERLINK("#'C-Venta'!A6", 'C-Venta'!A6) -> Fecha
C15: =HYPERLINK("#'C-Venta'!A7", 'C-Venta'!A7) -> Hora
A16: Combinación única 2 | B16: No pueden existir dos ventas con el mismo número de factura. | C16: =HYPERLINK("#'C-Venta'!A8", 'C-Venta'!A8) -> Factura
A20: Responsabilidad | C20: Descripción | G20: Entradas | J20: Salida | O20: Políticas (Reglas de Negocio) | Q20: Excepción
G21: Parámetro | H21: Tipo de dato | I21: Descripción | J21: Tipo de Dato | K21: Descripción | O21: Política | P21: Descripción | Q21: Detalle | R21: ¿Qué hago?
A22: =HYPERLINK("#'C-Venta'!V4", 'E-Venta'!B7) -> Registrar venta | C22: ='E-Venta'!C7 -> Permite registrar una venta realizada en el establecimiento, asociando los productos solicitados y la información correspondiente. | G22: Datos | H22: Venta | I22: Información necesaria para registrar la venta. | J22: Venta | K22: Venta registrada con la información proporcionada. | O22: =HYPERLINK("#'P-Venta'!A5", 'P-Venta'!A5) -> P-VEN-001 | P22: ='P-Venta'!B5 -> Asegurar que los datos requeridos para registrar una venta sean válidos de acuerdo con el tipo de dato, obligatoriedad, formato y rango correspondiente. | Q22: Los datos ingresados para registrar la venta no son validos. | R22: Rechazar el registro e informar cual dato no es valido.
O23: =HYPERLINK("#'P-Venta'!A6", 'P-Venta'!A6) -> P-VEN-002 | P23: ='P-Venta'!B6 -> Asegurar que no exista otra venta registrada con la misma Fecha y la misma Hora. | Q23: Ya existe otra venta registrada con la misma Fecha y la misma Hora. | R23: Rechazar el registro e informar que ya existe una venta en ese mismo momento.
O24: =HYPERLINK("#'P-Venta'!A15", 'P-Venta'!A15) -> P-VEN-011 | P24: ='P-Venta'!B15 -> Si no se indica el cliente de la venta, se registra 2222222222 (consumidor final). | Q24: No se indico el cliente de la venta. | R24: Registrar la venta con el cliente 2222222222 (consumidor final).
A25: =HYPERLINK("#'C-Venta'!W4", 'E-Venta'!B10) -> Confirmar venta | C25: ='E-Venta'!C10 -> Permite confirmar una venta: se calcula el total, se asigna el numero de factura, se registran los consumos y se descuenta el inventario por FIFO. Una venta confirmada ya no se puede modificar. | G25: Id | H25: UUID | I25: Identificador de la venta que se desea confirmar. | J25: Venta | K25: Venta confirmada, con el consumo de inventario registrado y su número de factura asignado. | O25: =HYPERLINK("#'P-Venta'!A11", 'P-Venta'!A11) -> P-VEN-007 | P25: ='P-Venta'!B11 -> Asegurar que la venta exista con el identificador indicado | Q25: La venta que se desea confirmar no existe. | R25: Rechazar la confirmacion e informar que la venta no existe.
O26: =HYPERLINK("#'P-Venta'!A13", 'P-Venta'!A13) -> P-VEN-009 | P26: ='P-Venta'!B13 -> Asegurar que una venta confirmada no pueda ser modificada o eliminada. | Q26: La venta ya se encuentra confirmada. | R26: Informar que la venta ya fue confirmada y no puede modificarse.
O27: =HYPERLINK("#'P-Venta'!A7", 'P-Venta'!A7) -> P-VEN-003 | P27: ='P-Venta'!B7 -> Asegurar que una venta contenga al menos un detalle de venta antes de ser confirmada. | Q27: La venta no contiene ningun detalle de venta. | R27: Rechazar la confirmacion e informar que la venta debe tener al menos un detalle.
O28: =HYPERLINK("#'P-Venta'!A8", 'P-Venta'!A8) -> P-VEN-004 | P28: ='P-Venta'!B8 -> Asegurar que todos los detalles asociados a una venta sean válidos antes de confirmar la operación. | Q28: Alguno de los detalles asociados a la venta no es valido. | R28: Rechazar la confirmacion e informar que hay un detalle no valido.
O29: =HYPERLINK("#'P-Venta'!A9", 'P-Venta'!A9) -> P-VEN-005 | P29: ='P-Venta'!B9 -> Asegurar que antes de confirmar una venta exista disponibilidad suficiente para atender los productos que requieren consumo de inventario. | Q29: No existe disponibilidad suficiente de inventario para atender los productos que requieren consumo. | R29: Rechazar la confirmacion e informar que no hay disponibilidad suficiente en el inventario.
O30: =HYPERLINK("#'P-Venta'!A10", 'P-Venta'!A10) -> P-VEN-006 | P30: ='P-Venta'!B10 -> Asegurar que el total de la venta corresponda a la suma de los subtotales de sus detalles y no supere 1.000.000. | Q30: El total no corresponde a la suma de los subtotales o supera 1.000.000. | R30: Rechazar la confirmacion e informar el total calculado.
O31: =HYPERLINK("#'P-Venta'!A14", 'P-Venta'!A14) -> P-VEN-010 | P31: ='P-Venta'!B14 -> Asegurar que al confirmar una venta se le asigne el siguiente numero de factura del consecutivo (FV- seguido de 6 digitos), sin repetir un numero que ya tenga otra venta. | Q31: El número de factura que le corresponde a la venta ya está asignado a otra venta. | R31: Rechazar la confirmación e informar que no se pudo asignar el número de factura.
O32: =HYPERLINK("#'P-Venta'!A16", 'P-Venta'!A16) -> P-VEN-012 | P32: ='P-Venta'!B16 -> Al confirmar una venta se registran los consumos de cada detalle de venta, segun la receta del producto vendido o su producto interno asociado. | Q32: No fue posible registrar los consumos de la venta. | R32: Rechazar la confirmacion completa para no dejar el inventario inconsistente.
O33: =HYPERLINK("#'P-Venta'!A17", 'P-Venta'!A17) -> P-VEN-013 | P33: ='P-Venta'!B17 -> Al confirmar una venta, cada producto interno consumido sale del inventario por FIFO: primero del lote mas antiguo con saldo disponible (el de menor numero de lote); se registra un movimiento de Salida por cada lote afectado y se actualiza el inventario. | Q33: No hay saldo suficiente en los lotes para descontar los productos internos. | R33: Rechazar la confirmacion e informar que producto interno no tiene existencias suficientes.
A34: =HYPERLINK("#'C-Venta'!Y4", 'E-Venta'!B19) -> Eliminar venta | C34: ='E-Venta'!C19 -> Permite eliminar una venta que no haya sido confirmada y que no tenga detalles de venta asociados que deban conservarse para mantener la trazabilidad. | G34: Id | H34: UUID | I34: Identificador de la venta que se desea eliminar. | J34: Venta | K34: Venta eliminada correctamente. | O34: =HYPERLINK("#'P-Venta'!A11", 'P-Venta'!A11) -> P-VEN-007 | P34: ='P-Venta'!B11 -> Asegurar que la venta exista con el identificador indicado | Q34: La venta que se desea eliminar no existe. | R34: Rechazar la eliminacion e informar que la venta no existe.
O35: =HYPERLINK("#'P-Venta'!A13", 'P-Venta'!A13) -> P-VEN-009 | P35: ='P-Venta'!B13 -> Asegurar que una venta confirmada no pueda ser modificada o eliminada. | Q35: La venta ya se encuentra confirmada. | R35: Rechazar la eliminacion e informar que una venta confirmada no puede eliminarse.
O36: =HYPERLINK("#'P-Venta'!A12", 'P-Venta'!A12) -> P-VEN-008 | P36: ='P-Venta'!B12 -> Asegurar que una venta no pueda eliminarse cuando tenga detalles de venta asociados que deban conservarse para mantener la trazabilidad. | Q36: La venta tiene detalles de venta asociados que deben conservarse. | R36: Rechazar la eliminacion e informar que la venta tiene detalles asociados.
A37: =HYPERLINK("#'C-Venta'!Z4", 'E-Venta'!B22) -> Consultar venta | C37: ='E-Venta'!C22 -> Permite consultar una venta con sus detalles, su total y su numero de factura. | G37: Id | H37: UUID | I37: Identificador de la venta. | J37: Venta | K37: Venta con sus detalles y su total. | O37: =HYPERLINK("#'P-Venta'!A11", 'P-Venta'!A11) -> P-VEN-007 | P37: ='P-Venta'!B11 -> Asegurar que la venta exista con el identificador indicado | Q37: No existe una venta con el identificador indicado. | R37: Informar que la venta no existe.

Sheet E-Venta
A1: <<<Modelo de Dominio | B1: <<<Objetos de Dominio
A2: Objeto de Dominio: | B2: Venta
A3: Descripción: | B3: ='C-Venta'!B3 -> Es cuando un cliente compra productos en la pizzería.
A4: Actor | B4: Action/Command | D4: Entity/Aggregate/Object domain | E4: Read Model | G4: Business Rule/Policy | H4: External System | I4: Domain Event | J4: Hotspot/questions/Risk
A5: Actor | B5: Acción | C5: Descripción | D5: Objeto de dominio | E5: Información externa | G5: Políticas | H5: Sistema Externo | I5: Evento | J5: Aspectos por solucionar
E6: Información | F6: Descripción | G6: Número
A7: Administrador | B7: Registrar venta | C7: Permite registrar una venta realizada en el establecimiento, asociando los productos solicitados y la información correspondiente. | D7: Venta | E7: Productos disponibles, precios vigentes, información del cliente | F7: Permite verificar que los productos puedan ser vendidos y que la información utilizada en la venta sea correcta. | G7: =HYPERLINK("#'P-Venta'!A5", "P-VEN-001") -> P-VEN-001 | I7: Venta registrada
G8: =HYPERLINK("#'P-Venta'!A6", "P-VEN-002") -> P-VEN-002
G9: =HYPERLINK("#'P-Venta'!A15", "P-VEN-011") -> P-VEN-011
A10: Administrador | B10: Confirmar venta | C10: Permite confirmar una venta: se calcula el total, se asigna el numero de factura, se registran los consumos y se descuenta el inventario por FIFO. Una venta confirmada ya no se puede modificar. | D10: Venta | E10: Detalles de venta, disponibilidad de inventario | F10: Permite comprobar que la venta contiene información válida y que puede ser atendida con las existencias disponibles. | G10: =HYPERLINK("#'P-Venta'!A11", "P-VEN-007") -> P-VEN-007 | I10: Venta confirmada
G11: =HYPERLINK("#'P-Venta'!A13", "P-VEN-009") -> P-VEN-009
G12: =HYPERLINK("#'P-Venta'!A7", "P-VEN-003") -> P-VEN-003
G13: =HYPERLINK("#'P-Venta'!A8", "P-VEN-004") -> P-VEN-004
G14: =HYPERLINK("#'P-Venta'!A9", "P-VEN-005") -> P-VEN-005
G15: =HYPERLINK("#'P-Venta'!A10", "P-VEN-006") -> P-VEN-006
G16: =HYPERLINK("#'P-Venta'!A14", "P-VEN-010") -> P-VEN-010
G17: =HYPERLINK("#'P-Venta'!A16", "P-VEN-012") -> P-VEN-012
G18: =HYPERLINK("#'P-Venta'!A17", "P-VEN-013") -> P-VEN-013
A19: Administrador | B19: Eliminar venta | C19: Permite eliminar una venta que no haya sido confirmada y que no tenga detalles de venta asociados que deban conservarse para mantener la trazabilidad. | D19: Venta | E19: Ventas registradas | F19: Permite identificar la venta existente antes de eliminarla. | G19: =HYPERLINK("#'P-Venta'!A11", "P-VEN-007") -> P-VEN-007 | I19: Venta eliminada
G20: =HYPERLINK("#'P-Venta'!A13", "P-VEN-009") -> P-VEN-009
G21: =HYPERLINK("#'P-Venta'!A12", "P-VEN-008") -> P-VEN-008
A22: Administrador | B22: Consultar venta | C22: Permite consultar una venta con sus detalles, su total y su numero de factura. | E22: Ventas registradas | F22: Identificador de la venta que se desea consultar. | G22: =HYPERLINK("#'P-Venta'!A11", "P-VEN-007") -> P-VEN-007 | I22: Venta consultada

Sheet P-Venta
A1: <<<Modelo de Dominio | B1: <<<Objetos de Dominio
A2: Objeto de Dominio | B2: Venta
A3: Descripcion | B3: ='C-Venta'!B3 -> Es cuando un cliente compra productos en la pizzería.
A4: Numero politica | B4: Descripcion Politica | C4: Objeto Responsable | D4: Regla Referenciada
A5: P-VEN-001 | B5: Asegurar que los datos requeridos para registrar una venta sean válidos de acuerdo con el tipo de dato, obligatoriedad, formato y rango correspondiente. | C5: Venta
A6: P-VEN-002 | B6: Asegurar que no exista otra venta registrada con la misma Fecha y la misma Hora. | C6: Venta
A7: P-VEN-003 | B7: Asegurar que una venta contenga al menos un detalle de venta antes de ser confirmada. | C7: DetalleVenta | D7: =HYPERLINK("#'P-DetalleVenta'!A16", 'P-DetalleVenta'!A16) -> P-DV-012
A8: P-VEN-004 | B8: Asegurar que todos los detalles asociados a una venta sean válidos antes de confirmar la operación. | C8: DetalleVenta | D8: =HYPERLINK("#'P-DetalleVenta'!A16", 'P-DetalleVenta'!A16) -> P-DV-012
A9: P-VEN-005 | B9: Asegurar que antes de confirmar una venta exista disponibilidad suficiente para atender los productos que requieren consumo de inventario. | C9: Lote | D9: =HYPERLINK("#'P-Lote'!A11", 'P-Lote'!A11) -> P-LOT-007
A10: P-VEN-006 | B10: Asegurar que el total de la venta corresponda a la suma de los subtotales de sus detalles y no supere 1.000.000. | C10: Venta
A11: P-VEN-007 | B11: Asegurar que la venta exista con el identificador indicado | C11: Venta
A12: P-VEN-008 | B12: Asegurar que una venta no pueda eliminarse cuando tenga detalles de venta asociados que deban conservarse para mantener la trazabilidad. | C12: DetalleVenta | D12: =HYPERLINK("#'P-DetalleVenta'!A16", 'P-DetalleVenta'!A16) -> P-DV-012
A13: P-VEN-009 | B13: Asegurar que una venta confirmada no pueda ser modificada o eliminada. | C13: Venta
A14: P-VEN-010 | B14: Asegurar que al confirmar una venta se le asigne el siguiente numero de factura del consecutivo (FV- seguido de 6 digitos), sin repetir un numero que ya tenga otra venta. | C14: Venta
A15: P-VEN-011 | B15: Si no se indica el cliente de la venta, se registra 2222222222 (consumidor final). | C15: Venta
A16: P-VEN-012 | B16: Al confirmar una venta se registran los consumos de cada detalle de venta, segun la receta del producto vendido o su producto interno asociado. | C16: ConsumoVenta | D16: =HYPERLINK("#'P-ConsumoVenta'!A5", 'P-ConsumoVenta'!A5) -> P-CV-001
A17: P-VEN-013 | B17: Al confirmar una venta, cada producto interno consumido sale del inventario por FIFO: primero del lote mas antiguo con saldo disponible (el de menor numero de lote); se registra un movimiento de Salida por cada lote afectado y se actualiza el inventario. | C17: MovimientoInventario | D17: =HYPERLINK("#'P-MovimientoInventario'!A5", 'P-MovimientoInventario'!A5) -> P-MI-001

Sheet M-MovimientoInventario
A1: <<<Modelo de Dominio | D1: <<<Objetos de Dominio
A2: Identificador unico de cada movimiento: una entrada o salida concreta de un lote | B2: Fecha en la que se registra el movimiento de inventario, correspondiente al momento en que se realiza la entrada o salida sobre el lote. | C2: Codigo de la operacion (TipoMovimiento) que genero el movimiento; a traves de el se conoce la CategoriaOrigen y el documento de origen | D2: Clase de movimiento: Entrada (suma al inventario) o Salida (resta del inventario) | E2: Lote sobre el que se realizo la entrada o salida. Por el lote se conoce el producto interno y la unidad de medida | F2: Cantidad que entro o salio del lote, expresada en la unidad de medida del lote (kg, l o und)
A3: Tipo de dato | B3: Fecha | C3: TipoMovimiento | D3: ClaseMovimiento | E3: Lote | F3: Decimal Europeo (4)
A4: Obligatorio | B4: Si | C4: Si | D4: Si | E4: Si | F4: Si
A5: Id | B5: FechaMovimiento | C5: TipoMovimiento | D5: ClaseMovimiento | E5: Lote | F5: Cantidad | G5: Combinacion unica 1
A6: 1 | B6: ='M-Compra'!C6 -> 46266 | C6: =HYPERLINK("#'M-TipoMovimiento'!A8", 'M-TipoMovimiento'!A8) -> 99 | D6: =HYPERLINK("#'M-ClaseMovimiento'!B8", 'M-ClaseMovimiento'!B8) -> Entrada | E6: =HYPERLINK("#'M-Lote'!I6", 'M-Lote'!I6) -> 1 Queso | F6: =IF(OR('M-DetalleCompra'!D7="g",'M-DetalleCompra'!D7="ml"),'M-DetalleCompra'!C7/1000,'M-DetalleCompra'!C7) -> 10.2 | G6: =C6&" "&E6 -> 99 1 Queso
A7: 2 | B7: ='M-Compra'!C6 -> 46266 | C7: =HYPERLINK("#'M-TipoMovimiento'!A9", 'M-TipoMovimiento'!A9) -> 100 | D7: =HYPERLINK("#'M-ClaseMovimiento'!B8", 'M-ClaseMovimiento'!B8) -> Entrada | E7: =HYPERLINK("#'M-Lote'!I7", 'M-Lote'!I7) -> 1 Albahaca | F7: =IF(OR('M-DetalleCompra'!D8="g",'M-DetalleCompra'!D8="ml"),'M-DetalleCompra'!C8/1000,'M-DetalleCompra'!C8) -> 10.3 | G7: =C7&" "&E7 -> 100 1 Albahaca
A8: 3 | B8: ='M-Compra'!C6 -> 46266 | C8: =HYPERLINK("#'M-TipoMovimiento'!A10", 'M-TipoMovimiento'!A10) -> 101 | D8: =HYPERLINK("#'M-ClaseMovimiento'!B8", 'M-ClaseMovimiento'!B8) -> Entrada | E8: =HYPERLINK("#'M-Lote'!I8", 'M-Lote'!I8) -> 1 Peperoni | F8: =IF(OR('M-DetalleCompra'!D9="g",'M-DetalleCompra'!D9="ml"),'M-DetalleCompra'!C9/1000,'M-DetalleCompra'!C9) -> 12.5 | G8: =C8&" "&E8 -> 101 1 Peperoni
A9: 4 | B9: ='M-Compra'!C7 -> 46144 | C9: =HYPERLINK("#'M-TipoMovimiento'!A11", 'M-TipoMovimiento'!A11) -> 102 | D9: =HYPERLINK("#'M-ClaseMovimiento'!B8", 'M-ClaseMovimiento'!B8) -> Entrada | E9: =HYPERLINK("#'M-Lote'!I9", 'M-Lote'!I9) -> 1 Aceite de oliva | F9: =IF(OR('M-DetalleCompra'!D10="g",'M-DetalleCompra'!D10="ml"),'M-DetalleCompra'!C10/1000,'M-DetalleCompra'!C10) -> 15.2 | G9: =C9&" "&E9 -> 102 1 Aceite de oliva
A10: 5 | B10: ='M-Compra'!C7 -> 46144 | C10: =HYPERLINK("#'M-TipoMovimiento'!A12", 'M-TipoMovimiento'!A12) -> 103 | D10: =HYPERLINK("#'M-ClaseMovimiento'!B8", 'M-ClaseMovimiento'!B8) -> Entrada | E10: =HYPERLINK("#'M-Lote'!I10", 'M-Lote'!I10) -> 2 Aceite de oliva | F10: =IF(OR('M-DetalleCompra'!D11="g",'M-DetalleCompra'!D11="ml"),'M-DetalleCompra'!C11/1000,'M-DetalleCompra'!C11) -> 3 | G10: =C10&" "&E10 -> 103 2 Aceite de oliva
A11: 6 | B11: ='M-Compra'!C7 -> 46144 | C11: =HYPERLINK("#'M-TipoMovimiento'!A13", 'M-TipoMovimiento'!A13) -> 104 | D11: =HYPERLINK("#'M-ClaseMovimiento'!B8", 'M-ClaseMovimiento'!B8) -> Entrada | E11: =HYPERLINK("#'M-Lote'!I11", 'M-Lote'!I11) -> 1 Masa de Pizza | F11: =IF(OR('M-DetalleCompra'!D12="g",'M-DetalleCompra'!D12="ml"),'M-DetalleCompra'!C12/1000,'M-DetalleCompra'!C12) -> 0.2 | G11: =C11&" "&E11 -> 104 1 Masa de Pizza
A12: 7 | B12: ='M-Compra'!C8 -> 46213 | C12: =HYPERLINK("#'M-TipoMovimiento'!A14", 'M-TipoMovimiento'!A14) -> 105 | D12: =HYPERLINK("#'M-ClaseMovimiento'!B8", 'M-ClaseMovimiento'!B8) -> Entrada | E12: =HYPERLINK("#'M-Lote'!I12", 'M-Lote'!I12) -> 1 Pepsi 400 ml | F12: =IF(OR('M-DetalleCompra'!D13="g",'M-DetalleCompra'!D13="ml"),'M-DetalleCompra'!C13/1000,'M-DetalleCompra'!C13) -> 24 | G12: =C12&" "&E12 -> 105 1 Pepsi 400 ml
A13: 8 | B13: ='M-Compra'!C9 -> 46249 | C13: =HYPERLINK("#'M-TipoMovimiento'!A15", 'M-TipoMovimiento'!A15) -> 106 | D13: =HYPERLINK("#'M-ClaseMovimiento'!B8", 'M-ClaseMovimiento'!B8) -> Entrada | E13: =HYPERLINK("#'M-Lote'!I13", 'M-Lote'!I13) -> 2 Masa de Pizza | F13: =IF(OR('M-DetalleCompra'!D14="g",'M-DetalleCompra'!D14="ml"),'M-DetalleCompra'!C14/1000,'M-DetalleCompra'!C14) -> 12 | G13: =C13&" "&E13 -> 106 2 Masa de Pizza
A14: 9 | B14: ='M-Compra'!C10 -> 46204 | C14: =HYPERLINK("#'M-TipoMovimiento'!A16", 'M-TipoMovimiento'!A16) -> 107 | D14: =HYPERLINK("#'M-ClaseMovimiento'!B8", 'M-ClaseMovimiento'!B8) -> Entrada | E14: =HYPERLINK("#'M-Lote'!I14", 'M-Lote'!I14) -> 2 Queso | F14: =IF(OR('M-DetalleCompra'!D15="g",'M-DetalleCompra'!D15="ml"),'M-DetalleCompra'!C15/1000,'M-DetalleCompra'!C15) -> 0.15 | G14: =C14&" "&E14 -> 107 2 Queso
A15: 10 | B15: ='M-Compra'!C11 -> 46188 | C15: =HYPERLINK("#'M-TipoMovimiento'!A17", 'M-TipoMovimiento'!A17) -> 108 | D15: =HYPERLINK("#'M-ClaseMovimiento'!B8", 'M-ClaseMovimiento'!B8) -> Entrada | E15: =HYPERLINK("#'M-Lote'!I15", 'M-Lote'!I15) -> 1 Salsa de Tomate | F15: =IF(OR('M-DetalleCompra'!D16="g",'M-DetalleCompra'!D16="ml"),'M-DetalleCompra'!C16/1000,'M-DetalleCompra'!C16) -> 10.5 | G15: =C15&" "&E15 -> 108 1 Salsa de Tomate
A16: 11 | B16: ='M-Venta'!B6 -> 46268 | C16: =HYPERLINK("#'M-TipoMovimiento'!A25", 'M-TipoMovimiento'!A25) -> 153 | D16: =HYPERLINK("#'M-ClaseMovimiento'!B9", 'M-ClaseMovimiento'!B9) -> Salida | E16: =HYPERLINK("#'M-Lote'!I11", 'M-Lote'!I11) -> 1 Masa de Pizza | F16: ='M-Lote'!E11 -> 0.2 | G16: =C16&" "&E16 -> 153 1 Masa de Pizza
A17: 12 | B17: ='M-Venta'!B6 -> 46268 | C17: =HYPERLINK("#'M-TipoMovimiento'!A25", 'M-TipoMovimiento'!A25) -> 153 | D17: =HYPERLINK("#'M-ClaseMovimiento'!B9", 'M-ClaseMovimiento'!B9) -> Salida | E17: =HYPERLINK("#'M-Lote'!I13", 'M-Lote'!I13) -> 2 Masa de Pizza | F17: ='M-DetalleReceta'!C6*'M-DetalleVenta'!C6/1000-F16 -> 0.15 | G17: =C17&" "&E17 -> 153 2 Masa de Pizza
A18: 13 | B18: ='M-Venta'!B6 -> 46268 | C18: =HYPERLINK("#'M-TipoMovimiento'!A26", 'M-TipoMovimiento'!A26) -> 154 | D18: =HYPERLINK("#'M-ClaseMovimiento'!B9", 'M-ClaseMovimiento'!B9) -> Salida | E18: =HYPERLINK("#'M-Lote'!I15", 'M-Lote'!I15) -> 1 Salsa de Tomate | F18: ='M-DetalleReceta'!C7*'M-DetalleVenta'!C6/1000 -> 0.3 | G18: =C18&" "&E18 -> 154 1 Salsa de Tomate
A19: 14 | B19: ='M-Venta'!B6 -> 46268 | C19: =HYPERLINK("#'M-TipoMovimiento'!A27", 'M-TipoMovimiento'!A27) -> 155 | D19: =HYPERLINK("#'M-ClaseMovimiento'!B9", 'M-ClaseMovimiento'!B9) -> Salida | E19: =HYPERLINK("#'M-Lote'!I9", 'M-Lote'!I9) -> 1 Aceite de oliva | F19: ='M-DetalleReceta'!C8*'M-DetalleVenta'!C6/1000 -> 0.002 | G19: =C19&" "&E19 -> 155 1 Aceite de oliva
A20: 15 | B20: ='M-Venta'!B6 -> 46268 | C20: =HYPERLINK("#'M-TipoMovimiento'!A28", 'M-TipoMovimiento'!A28) -> 156 | D20: =HYPERLINK("#'M-ClaseMovimiento'!B9", 'M-ClaseMovimiento'!B9) -> Salida | E20: =HYPERLINK("#'M-Lote'!I6", 'M-Lote'!I6) -> 1 Queso | F20: ='M-DetalleReceta'!C9*'M-DetalleVenta'!C6/1000 -> 0.1 | G20: =C20&" "&E20 -> 156 1 Queso
A21: 16 | B21: ='M-Venta'!B6 -> 46268 | C21: =HYPERLINK("#'M-TipoMovimiento'!A29", 'M-TipoMovimiento'!A29) -> 157 | D21: =HYPERLINK("#'M-ClaseMovimiento'!B9", 'M-ClaseMovimiento'!B9) -> Salida | E21: =HYPERLINK("#'M-Lote'!I7", 'M-Lote'!I7) -> 1 Albahaca | F21: ='M-DetalleReceta'!C10*'M-DetalleVenta'!C6/1000 -> 0.05 | G21: =C21&" "&E21 -> 157 1 Albahaca
A22: 17 | B22: ='M-Venta'!B7 -> 46268 | C22: =HYPERLINK("#'M-TipoMovimiento'!A30", 'M-TipoMovimiento'!A30) -> 158 | D22: =HYPERLINK("#'M-ClaseMovimiento'!B9", 'M-ClaseMovimiento'!B9) -> Salida | E22: =HYPERLINK("#'M-Lote'!I8", 'M-Lote'!I8) -> 1 Peperoni | F22: ='M-DetalleReceta'!C17*'M-DetalleVenta'!C7/1000 -> 0.16 | G22: =C22&" "&E22 -> 158 1 Peperoni
A23: 20 | B23: ='M-Cambio'!F7 -> 46274 | C23: =HYPERLINK("#'M-TipoMovimiento'!A31", 'M-TipoMovimiento'!A31) -> 200 | D23: =HYPERLINK("#'M-ClaseMovimiento'!B8", 'M-ClaseMovimiento'!B8) -> Entrada | E23: =HYPERLINK("#'M-Lote'!I16", 'M-Lote'!I16) -> 2 Pepsi 400 ml | F23: =IF(OR('M-Cambio'!D7="g",'M-Cambio'!D7="ml"),'M-Cambio'!C7/1000,'M-Cambio'!C7) -> 24 | G23: =C23&" "&E23 -> 200 2 Pepsi 400 ml
A24: 21 | B24: ='M-Cambio'!F8 -> 46274 | C24: =HYPERLINK("#'M-TipoMovimiento'!A32", 'M-TipoMovimiento'!A32) -> 201 | D24: =HYPERLINK("#'M-ClaseMovimiento'!B8", 'M-ClaseMovimiento'!B8) -> Entrada | E24: =HYPERLINK("#'M-Lote'!I17", 'M-Lote'!I17) -> 3 Aceite de oliva | F24: =IF(OR('M-Cambio'!D8="g",'M-Cambio'!D8="ml"),'M-Cambio'!C8/1000,'M-Cambio'!C8) -> 5 | G24: =C24&" "&E24 -> 201 3 Aceite de oliva
A25: 23 | B25: ='M-Compra'!C12 -> 46291 | C25: =HYPERLINK("#'M-TipoMovimiento'!A18", 'M-TipoMovimiento'!A18) -> 109 | D25: =HYPERLINK("#'M-ClaseMovimiento'!B8", 'M-ClaseMovimiento'!B8) -> Entrada | E25: =HYPERLINK("#'M-Lote'!I18", 'M-Lote'!I18) -> 3 Queso | F25: =IF(OR('M-DetalleCompra'!D17="g",'M-DetalleCompra'!D17="ml"),'M-DetalleCompra'!C17/1000,'M-DetalleCompra'!C17) -> 0.3 | G25: =C25&" "&E25 -> 109 3 Queso
A26: 24 | B26: ='M-Compra'!C13 -> 46293 | C26: =HYPERLINK("#'M-TipoMovimiento'!A19", 'M-TipoMovimiento'!A19) -> 110 | D26: =HYPERLINK("#'M-ClaseMovimiento'!B8", 'M-ClaseMovimiento'!B8) -> Entrada | E26: =HYPERLINK("#'M-Lote'!I19", 'M-Lote'!I19) -> 1 Jamón | F26: =IF(OR('M-DetalleCompra'!D18="g",'M-DetalleCompra'!D18="ml"),'M-DetalleCompra'!C18/1000,'M-DetalleCompra'!C18) -> 1 | G26: =C26&" "&E26 -> 110 1 Jamón
A27: 25 | B27: ='M-Compra'!C13 -> 46293 | C27: =HYPERLINK("#'M-TipoMovimiento'!A20", 'M-TipoMovimiento'!A20) -> 111 | D27: =HYPERLINK("#'M-ClaseMovimiento'!B8", 'M-ClaseMovimiento'!B8) -> Entrada | E27: =HYPERLINK("#'M-Lote'!I20", 'M-Lote'!I20) -> 1 Piña | F27: =IF(OR('M-DetalleCompra'!D19="g",'M-DetalleCompra'!D19="ml"),'M-DetalleCompra'!C19/1000,'M-DetalleCompra'!C19) -> 1 | G27: =C27&" "&E27 -> 111 1 Piña
A28: 26 | B28: ='M-Compra'!C14 -> 46295 | C28: =HYPERLINK("#'M-TipoMovimiento'!A21", 'M-TipoMovimiento'!A21) -> 112 | D28: =HYPERLINK("#'M-ClaseMovimiento'!B8", 'M-ClaseMovimiento'!B8) -> Entrada | E28: =HYPERLINK("#'M-Lote'!I21", 'M-Lote'!I21) -> 4 Queso | F28: =IF(OR('M-DetalleCompra'!D20="g",'M-DetalleCompra'!D20="ml"),'M-DetalleCompra'!C20/1000,'M-DetalleCompra'!C20) -> 0.5 | G28: =C28&" "&E28 -> 112 4 Queso
A29: 27 | B29: ='M-Venta'!B9 -> 46297 | C29: =HYPERLINK("#'M-TipoMovimiento'!A22", 'M-TipoMovimiento'!A22) -> 150 | D29: =HYPERLINK("#'M-ClaseMovimiento'!B9", 'M-ClaseMovimiento'!B9) -> Salida | E29: =HYPERLINK("#'M-Lote'!I18", 'M-Lote'!I18) -> 3 Queso | F29: ='M-Lote'!E18 -> 0.3 | G29: =C29&" "&E29 -> 150 3 Queso
A30: 28 | B30: ='M-Venta'!B9 -> 46297 | C30: =HYPERLINK("#'M-TipoMovimiento'!A22", 'M-TipoMovimiento'!A22) -> 150 | D30: =HYPERLINK("#'M-ClaseMovimiento'!B9", 'M-ClaseMovimiento'!B9) -> Salida | E30: =HYPERLINK("#'M-Lote'!I21", 'M-Lote'!I21) -> 4 Queso | F30: ='M-DetalleReceta'!C28*'M-DetalleVenta'!C10/1000-F29 -> 0.2 | G30: =C30&" "&E30 -> 150 4 Queso
A31: 29 | B31: ='M-Venta'!B9 -> 46297 | C31: =HYPERLINK("#'M-TipoMovimiento'!A23", 'M-TipoMovimiento'!A23) -> 151 | D31: =HYPERLINK("#'M-ClaseMovimiento'!B9", 'M-ClaseMovimiento'!B9) -> Salida | E31: =HYPERLINK("#'M-Lote'!I19", 'M-Lote'!I19) -> 1 Jamón | F31: ='M-DetalleReceta'!C29*'M-DetalleVenta'!C10/1000 -> 0.1 | G31: =C31&" "&E31 -> 151 1 Jamón
A32: 30 | B32: ='M-Venta'!B9 -> 46297 | C32: =HYPERLINK("#'M-TipoMovimiento'!A24", 'M-TipoMovimiento'!A24) -> 152 | D32: =HYPERLINK("#'M-ClaseMovimiento'!B9", 'M-ClaseMovimiento'!B9) -> Salida | E32: =HYPERLINK("#'M-Lote'!I20", 'M-Lote'!I20) -> 1 Piña | F32: ='M-DetalleReceta'!C30*'M-DetalleVenta'!C10/1000 -> 0.08 | G32: =C32&" "&E32 -> 152 1 Piña

Sheet C-MovimientoInventario
A1: <<<Modelo de Dominio | B1: <<<Objetos de Dominio
A2: Nombre | B2: MovimientoInventario
A3: Descripción | B3: =HYPERLINK("#'Objetos de dominio'!B14", 'Objetos de dominio'!B16) -> Es cada entrada o salida concreta de un lote, registrada en una fecha (FechaMovimiento). Lo genera una operación (TipoMovimiento), indica si suma o resta (ClaseMovimiento) y por el lote se sabe qué producto interno se movió. Si una operación usa varios lotes (FIFO), genera un movimiento por cada lote.
A4: Nombre atributo | B4: Descripción atributo | C4: Identificador del objeto de dominio | D4: Tipo de dato | E4: Obligatorio | F4: Longitud mínima (si aplica) | G4: Longitud máxima (si aplica) | H4: Precisión (si aplica) | I4: Rendondeo (si aplica) | J4: Rango inicial (si aplica) | K4: Rango final (si aplica) | L4: Formato (si aplica) | M4: Reglas especiales (si aplica) | N4: Dato calculado | O4: Aplica ajuste del dato (si aplica) | P4: Carácter de ajuste (si aplica) | Q4: Quitar espacios en blanco al inicio (si aplica) | R4: Quitar espacios en blanco al fin (si aplica) | S4: Dato sensible (si aplica) | T4: Valor por defecto (si aplica) | U4: Auto generado | V4: =HYPERLINK("#'C-MovimientoInventario'!A21", 'C-MovimientoInventario'!A21) -> Registrar entrada de inventario por compra | W4: =HYPERLINK("#'C-MovimientoInventario'!A30", 'C-MovimientoInventario'!A30) -> Registrar salida de inventario por venta | X4: =HYPERLINK("#'C-MovimientoInventario'!A40", 'C-MovimientoInventario'!A40) -> Registrar movimientos por cambio de producto | Y4: =HYPERLINK("#'C-MovimientoInventario'!A50", 'C-MovimientoInventario'!A50) -> Consultar movimientos de un lote
A5: =HYPERLINK("#'M-MovimientoInventario'!A5", 'M-MovimientoInventario'!A5) -> Id | B5: =HYPERLINK("#'M-MovimientoInventario'!A2", 'M-MovimientoInventario'!A2) -> Identificador unico de cada movimiento: una entrada o salida concreta de un lote | C5: Si | D5: Identificador único universal | E5: Si | N5: No | O5: No | Q5: No | R5: No | S5: No | U5: Si | V5: Requerido | W5: Requerido | X5: Requerido | Y5: No Mostrar
A6: =HYPERLINK("#'M-MovimientoInventario'!D5", 'M-MovimientoInventario'!D5) -> ClaseMovimiento | B6: =HYPERLINK("#'M-MovimientoInventario'!D2", 'M-MovimientoInventario'!D2) -> Clase de movimiento: Entrada (suma al inventario) o Salida (resta del inventario) | C6: No | D6: ClaseMovimiento | E6: Si | M6: Entrada (suma al inventario) o Salida (resta del inventario). Debe ser una clase de movimiento existente. | N6: No | O6: No | Q6: No | R6: No | S6: No | U6: No | V6: Requerido | W6: Requerido | X6: Requerido | Y6: Mostrar
A7: =HYPERLINK("#'M-MovimientoInventario'!C5", 'M-MovimientoInventario'!C5) -> TipoMovimiento | B7: =HYPERLINK("#'M-MovimientoInventario'!C2", 'M-MovimientoInventario'!C2) -> Codigo de la operacion (TipoMovimiento) que genero el movimiento; a traves de el se conoce la CategoriaOrigen y el documento de origen | C7: No | D7: TipoMovimiento | E7: Si | M7: Codigo de la operacion que genero el movimiento (detalle de compra, consumo de venta o cambio); a traves de el se conoce la categoria de origen. | N7: No | O7: No | Q7: No | R7: No | S7: No | U7: No | V7: Requerido | W7: Requerido | X7: Requerido | Y7: Mostrar
A8: =HYPERLINK("#'M-MovimientoInventario'!F5", 'M-MovimientoInventario'!F5) -> Cantidad | B8: =HYPERLINK("#'M-MovimientoInventario'!F2", 'M-MovimientoInventario'!F2) -> Cantidad que entro o salio del lote, expresada en la unidad de medida del lote (kg, l o und) | C8: No | D8: Decimal Europeo | E8: Si | H8: 4 | J8: >0 | K8: 10000 | M8: Cantidad que entra o sale del lote, en la unidad de medida del lote. Debe ser mayor a cero y como maximo 10.000. | N8: No | O8: No | Q8: No | R8: No | S8: No | U8: No | V8: Requerido | W8: Requerido | X8: Requerido | Y8: Mostrar
A9: =HYPERLINK("#'M-MovimientoInventario'!B5", 'M-MovimientoInventario'!B5) -> FechaMovimiento | B9: =HYPERLINK("#'M-MovimientoInventario'!B2", 'M-MovimientoInventario'!B2) -> Fecha en la que se registra el movimiento de inventario, correspondiente al momento en que se realiza la entrada o salida sobre el lote. | C9: No | D9: Fecha | E9: Si | L9: dd/mm/yyyy | M9: Fecha en la que se registra el movimiento. | N9: No | O9: No | Q9: No | R9: No | S9: No | U9: No | V9: Requerido | W9: Requerido | X9: Requerido | Y9: Mostrar
A10: =HYPERLINK("#'M-MovimientoInventario'!E5", 'M-MovimientoInventario'!E5) -> Lote | B10: =HYPERLINK("#'M-MovimientoInventario'!E2", 'M-MovimientoInventario'!E2) -> Lote sobre el que se realizo la entrada o salida. Por el lote se conoce el producto interno y la unidad de medida | C10: No | D10: Lote | E10: Si | M10: Lote sobre el que se realiza la entrada o salida. Es obligatorio en todos los movimientos. | N10: No | O10: No | Q10: No | R10: No | S10: No | U10: No | V10: Requerido | W10: Requerido | X10: Requerido | Y10: Mostrar
A13: Nombre combinación única | B13: Descripción | C13: Atributos involucrados
A14: Combinación única 1 | B14: No se puede registrar dos veces el mismo codigo de operacion (TipoMovimiento) sobre el mismo Lote. | C14: =HYPERLINK("#'C-MovimientoInventario'!A7", 'C-MovimientoInventario'!A7) -> TipoMovimiento
C15: =HYPERLINK("#'C-MovimientoInventario'!A10", 'C-MovimientoInventario'!A10) -> Lote
A19: Responsabilidad | C19: Descripción | G19: Entradas | J19: Salida | O19: Políticas (Reglas de Negocio) | Q19: Excepción
G20: Parámetro | H20: Tipo de dato | I20: Descripción | J20: Tipo de Dato | K20: Descripción | O20: Política | P20: Descripción | Q20: Detalle | R20: ¿Qué hago?
A21: =HYPERLINK("#'C-MovimientoInventario'!V4", 'E-MovimientoInventario'!B7) -> Registrar entrada de inventario por compra | C21: ='E-MovimientoInventario'!C7 -> Registrar el ingreso de las existencias recibidas como consecuencia de una compra válida, asociando la entrada con el lote correspondiente. | G21: Datos | H21: DetalleCompra | I21: Producto adquirido, cantidad recibida, unidad de medida, compra, detalle de compra y lote sobre el cual se registra la entrada. | J21: MovimientoInventario | K21: Entrada de inventario registrada | O21: =HYPERLINK("#'P-MovimientoInventario'!A5", 'P-MovimientoInventario'!A5) -> P-MI-001 | P21: ='P-MovimientoInventario'!B5 -> Asegurar que los datos requeridos para registrar un movimiento de inventario sean válidos de acuerdo con el tipo de movimiento, cantidad, fecha y demás información obligatoria. | Q21: Los datos requeridos para registrar el movimiento no son validos. | R21: Rechazar el registro e informar cual dato no es valido.
O22: =HYPERLINK("#'P-MovimientoInventario'!A6", 'P-MovimientoInventario'!A6) -> P-MI-002 | P22: ='P-MovimientoInventario'!B6 -> Asegurar que la clase de movimiento sea valida para la operacion: Entrada para compras y para el lote de reemplazo de un cambio; Salida para ventas y para el lote que se devuelve en un cambio. | Q22: La clase de movimiento no corresponde a la operacion. | R22: Rechazar el registro e informar la clase de movimiento esperada.
O23: =HYPERLINK("#'P-MovimientoInventario'!A19", 'P-MovimientoInventario'!A19) -> P-MI-015 | P23: ='P-MovimientoInventario'!B19 -> Asegurar que el TipoMovimiento del movimiento exista y pertenezca a una categoria de origen valida (Compra, Venta o Cambio). | Q23: El TipoMovimiento no existe o su categoria de origen no es valida. | R23: Rechazar el registro e informar que el codigo de operacion no es valido.
O24: =HYPERLINK("#'P-MovimientoInventario'!A12", 'P-MovimientoInventario'!A12) -> P-MI-008 | P24: ='P-MovimientoInventario'!B12 -> Asegurar que un movimiento de inventario relacionado con una compra corresponda a un detalle de compra valido y use su mismo TipoMovimiento. | Q24: El detalle de compra asociado no es valido. | R24: Rechazar el registro e informar que el detalle de compra no existe.
O25: =HYPERLINK("#'P-MovimientoInventario'!A7", 'P-MovimientoInventario'!A7) -> P-MI-003 | P25: ='P-MovimientoInventario'!B7 -> Asegurar que el lote sobre el cual se registra el movimiento exista en el sistema. | Q25: El lote sobre el cual se registra el movimiento no existe. | R25: Rechazar el registro e informar que el lote no existe.
O26: =HYPERLINK("#'P-MovimientoInventario'!A8", 'P-MovimientoInventario'!A8) -> P-MI-004 | P26: ='P-MovimientoInventario'!B8 -> Asegurar que la cantidad registrada en un movimiento de inventario sea mayor que cero y como maximo 10.000. | Q26: La cantidad no es mayor que cero o supera 10.000. | R26: Rechazar el registro e informar el rango permitido.
O27: =HYPERLINK("#'P-MovimientoInventario'!A17", 'P-MovimientoInventario'!A17) -> P-MI-013 | P27: ='P-MovimientoInventario'!B17 -> Asegurar que no exista otro movimiento de inventario con el mismo Codigo de operacion y el mismo Lote. | Q27: Ya existe un movimiento con el mismo TipoMovimiento sobre el mismo lote. | R27: Rechazar el registro e informar la duplicidad.
O28: =HYPERLINK("#'P-MovimientoInventario'!A15", 'P-MovimientoInventario'!A15) -> P-MI-011 | P28: ='P-MovimientoInventario'!B15 -> La Cantidad del movimiento se copia de la operacion que lo genera y queda fija: del DetalleCompra para Compra, del ConsumoVenta para Venta (repartida entre los lotes por FIFO) y del Cambio para Cambio. No se recalcula despues, aunque la receta cambie. | Q28: La cantidad no corresponde a la de la operacion que genera el movimiento. | R28: Copiar la cantidad de la operacion de origen y dejarla fija.
O29: =HYPERLINK("#'P-MovimientoInventario'!A21", 'P-MovimientoInventario'!A21) -> P-MI-017 | P29: ='P-MovimientoInventario'!B21 -> Al registrar un movimiento se actualiza el saldo del lote afectado y la cantidad total del inventario del producto interno. | Q29: No fue posible actualizar el saldo del lote o el inventario. | R29: Rechazar el registro completo para no dejar el inventario inconsistente.
A30: =HYPERLINK("#'C-MovimientoInventario'!W4", 'E-MovimientoInventario'!B16) -> Registrar salida de inventario por venta | C30: ='E-MovimientoInventario'!C16 -> Registra la salida de los productos internos consumidos en una venta confirmada, descontandolos de los lotes por FIFO. | G30: Datos | H30: ConsumoVenta | I30: Consumo de venta que origina la salida. | J30: MovimientoInventario | K30: Salida de inventario por venta registrada | O30: =HYPERLINK("#'P-MovimientoInventario'!A5", 'P-MovimientoInventario'!A5) -> P-MI-001 | P30: ='P-MovimientoInventario'!B5 -> Asegurar que los datos requeridos para registrar un movimiento de inventario sean válidos de acuerdo con el tipo de movimiento, cantidad, fecha y demás información obligatoria. | Q30: Los datos requeridos para registrar el movimiento no son validos. | R30: Rechazar el registro e informar cual dato no es valido.
O31: =HYPERLINK("#'P-MovimientoInventario'!A6", 'P-MovimientoInventario'!A6) -> P-MI-002 | P31: ='P-MovimientoInventario'!B6 -> Asegurar que la clase de movimiento sea valida para la operacion: Entrada para compras y para el lote de reemplazo de un cambio; Salida para ventas y para el lote que se devuelve en un cambio. | Q31: La clase de movimiento no corresponde a la operacion. | R31: Rechazar el registro e informar la clase de movimiento esperada.
O32: =HYPERLINK("#'P-MovimientoInventario'!A19", 'P-MovimientoInventario'!A19) -> P-MI-015 | P32: ='P-MovimientoInventario'!B19 -> Asegurar que el TipoMovimiento del movimiento exista y pertenezca a una categoria de origen valida (Compra, Venta o Cambio). | Q32: El TipoMovimiento no existe o su categoria de origen no es valida. | R32: Rechazar el registro e informar que el codigo de operacion no es valido.
O33: =HYPERLINK("#'P-MovimientoInventario'!A13", 'P-MovimientoInventario'!A13) -> P-MI-009 | P33: ='P-MovimientoInventario'!B13 -> Asegurar que un movimiento de Salida por venta corresponda a un consumo de venta valido y use su mismo TipoMovimiento. | Q33: El consumo de venta asociado no es valido. | R33: Rechazar el registro e informar que el consumo de venta no existe.
O34: =HYPERLINK("#'P-MovimientoInventario'!A20", 'P-MovimientoInventario'!A20) -> P-MI-016 | P34: ='P-MovimientoInventario'!B20 -> Asegurar que las salidas por venta se tomen por FIFO: primero del lote mas antiguo con saldo disponible del producto interno, pasando al siguiente lote cuando el saldo no alcance. | Q34: No hay lotes con saldo suficiente para cubrir la salida. | R34: Rechazar el registro e informar que no hay existencias suficientes.
O35: =HYPERLINK("#'P-MovimientoInventario'!A7", 'P-MovimientoInventario'!A7) -> P-MI-003 | P35: ='P-MovimientoInventario'!B7 -> Asegurar que el lote sobre el cual se registra el movimiento exista en el sistema. | Q35: El lote sobre el cual se registra el movimiento no existe. | R35: Rechazar el registro e informar que el lote no existe.
O36: =HYPERLINK("#'P-MovimientoInventario'!A8", 'P-MovimientoInventario'!A8) -> P-MI-004 | P36: ='P-MovimientoInventario'!B8 -> Asegurar que la cantidad registrada en un movimiento de inventario sea mayor que cero y como maximo 10.000. | Q36: La cantidad no es mayor que cero o supera 10.000. | R36: Rechazar el registro e informar el rango permitido.
O37: =HYPERLINK("#'P-MovimientoInventario'!A17", 'P-MovimientoInventario'!A17) -> P-MI-013 | P37: ='P-MovimientoInventario'!B17 -> Asegurar que no exista otro movimiento de inventario con el mismo Codigo de operacion y el mismo Lote. | Q37: Ya existe un movimiento con el mismo TipoMovimiento sobre el mismo lote. | R37: Rechazar el registro e informar la duplicidad.
O38: =HYPERLINK("#'P-MovimientoInventario'!A15", 'P-MovimientoInventario'!A15) -> P-MI-011 | P38: ='P-MovimientoInventario'!B15 -> La Cantidad del movimiento se copia de la operacion que lo genera y queda fija: del DetalleCompra para Compra, del ConsumoVenta para Venta (repartida entre los lotes por FIFO) y del Cambio para Cambio. No se recalcula despues, aunque la receta cambie. | Q38: La cantidad no corresponde a la de la operacion que genera el movimiento. | R38: Copiar la cantidad de la operacion de origen y dejarla fija.
O39: =HYPERLINK("#'P-MovimientoInventario'!A21", 'P-MovimientoInventario'!A21) -> P-MI-017 | P39: ='P-MovimientoInventario'!B21 -> Al registrar un movimiento se actualiza el saldo del lote afectado y la cantidad total del inventario del producto interno. | Q39: No fue posible actualizar el saldo del lote o el inventario. | R39: Rechazar el registro completo para no dejar el inventario inconsistente.
A40: =HYPERLINK("#'C-MovimientoInventario'!X4", 'E-MovimientoInventario'!B26) -> Registrar movimientos por cambio de producto | C40: ='E-MovimientoInventario'!C26 -> Cuando se registra el cambio de un producto no perecedero, registra la Salida del lote que se devuelve al proveedor y la Entrada del lote de reemplazo, con el TipoMovimiento del cambio. | G40: Datos | H40: Cambio, Lote | I40: Permite identificar el lote proximo a vencer y el registro de Cambio correspondiente al reemplazo. | J40: MovimientoInventario | K40: Salida por cambio y entrada de reemplazo registradas | O40: =HYPERLINK("#'P-MovimientoInventario'!A5", 'P-MovimientoInventario'!A5) -> P-MI-001 | P40: ='P-MovimientoInventario'!B5 -> Asegurar que los datos requeridos para registrar un movimiento de inventario sean válidos de acuerdo con el tipo de movimiento, cantidad, fecha y demás información obligatoria. | Q40: Los datos requeridos para registrar el movimiento no son validos. | R40: Rechazar el registro e informar cual dato no es valido.
O41: =HYPERLINK("#'P-MovimientoInventario'!A6", 'P-MovimientoInventario'!A6) -> P-MI-002 | P41: ='P-MovimientoInventario'!B6 -> Asegurar que la clase de movimiento sea valida para la operacion: Entrada para compras y para el lote de reemplazo de un cambio; Salida para ventas y para el lote que se devuelve en un cambio. | Q41: La clase de movimiento no corresponde a la operacion. | R41: Rechazar el registro e informar la clase de movimiento esperada.
O42: =HYPERLINK("#'P-MovimientoInventario'!A19", 'P-MovimientoInventario'!A19) -> P-MI-015 | P42: ='P-MovimientoInventario'!B19 -> Asegurar que el TipoMovimiento del movimiento exista y pertenezca a una categoria de origen valida (Compra, Venta o Cambio). | Q42: El TipoMovimiento no existe o su categoria de origen no es valida. | R42: Rechazar el registro e informar que el codigo de operacion no es valido.
O43: =HYPERLINK("#'P-MovimientoInventario'!A16", 'P-MovimientoInventario'!A16) -> P-MI-012 | P43: ='P-MovimientoInventario'!B16 -> Asegurar que un movimiento de inventario relacionado con un Cambio corresponda a un registro de Cambio valido y existente. | Q43: El cambio asociado no existe o no es valido. | R43: Rechazar el registro e informar que el cambio no existe.
